Workbook

Sheet Read Me & Glossary
A1: READ ME — how this model works
A2: Purpose | B2: Investor-facing model to sell 50% of a 3-property (+ tours) portfolio into NewCo. Shows independent property valuation, after-tax cash returns, total return and a leverage/growth path. DRAFT — accountant/attorney sign-off pending.
A3: Structure | B3: NewCo owns 100% of the included properties. The incoming Property Partner can hold a different % per property via Control share-offer inputs. Buy-in is consideration paid to the current owner (share sale), not retained as working capital in NewCo.
A4: How to use | B4: Edit only the shaded (yellow) input cells on the Control sheet. Every other sheet recalculates. Open in Excel or Google Sheets so formulas compute.
A5: Sheets | B5: Control (inputs) · 3 property P&Ls · Portfolio NewCo (consolidated) · Valuation (independent) · Investor KPIs · Property KPIs · Leverage & Growth · Change Log.
A7: TERMINOLOGY (SA hospitality standard):
A8: Unit | B8: One lettable villa/apartment (African Sky Villa, Remington, Winchester). Whole-unit lets, not per-room.
A9: Available unit-night | B9: One unit available for one night. Units × 365 = available unit-nights per year.
A10: Occupied unit-night | B10: One unit actually let for one night. Occupancy % = occupied ÷ available.
A11: ADR | B11: Average Daily Rate — the gross nightly rate per unit (base covers 2 guests; extra guests add per-guest).
A12: Guest-night | B12: One guest staying one night = occupied unit-nights × guests per unit. Drives meals.
A13: Meal cover | B13: One guest taking meals on one night. 75% of guest-nights take both breakfast + dinner.
A14: NOI | B14: Net Operating Income — revenue less operating expenses (incl. FF&E reserve), before tax and finance. Basis for income valuation.
A15: Cap rate | B15: Capitalisation rate — NOI ÷ property value. Lower cap rate = higher value. Used for residential income valuation.
A16: MOIC / IRR | B16: MOIC = money multiple (total received ÷ invested). IRR = annualised return accounting for timing.
A17: VALUATION METHOD | B17: Beachside & Menlyn are valued by income capitalisation (NOI ÷ market cap rate), which corroborates their cost basis. African Sky is valued on comparable/cost because its income is largely OPERATING (holiday-let + F&B + tours) — capitalising that at a property cap rate would massively overstate 3 villas. Adopted NAV is deliberately conservative; the income approach sits above it.
A18: OPEN FLAGS (gated) | B18: • VAT: combined revenue is over the R1m compulsory-registration threshold — short-term accommodation is taxable, long-term residential exempt (mixed supply). Default keeps the gross basis; confirm with the accountant. • Transfer of properties into NewCo triggers transfer duty / VAT / CGT, and a s42 asset-for-share roll-over carries an 18-month de-grouping clawback if 50% is sold at/near formation — attorney + accountant. • Selling 50% equity may engage Companies Act offer-to-public / FAIS rules. • Cap rates and the African Sky comparable value are assumptions to confirm with a registered valuer. • Winchester is not built — its revenue is phased from its online year and its R500k build is funded from NewCo cash.
A19: Status | B19: DRAFT · unaudited · ZAR · rebuilt 2026-07-10. Not an offer to the public; subject to MOI/shareholders agreement and professional sign-off. Nothing here is legal, tax or investment advice.
A20: TOURS (v3) | B20: African Sky tour income and supplier cost are now driven by the 'ASKY Tours Calcs' sheet — 14 experiences (safaris, day tours, river adventures, transfers) each with per-pax retail (fixed from the live site), supplier cost and take-up. The Control tour cells link to its totals (revenue O27, cost P27); edit tours on that sheet.

Sheet Key Assumptions Sources
A1: KEY ASSUMPTIONS & SOURCES
A2: Plain-English source sheet for proposal review. All model items are live linked where relevant.
A4: Category | B4: Assumption | C4: Value | D4: Source / explanation
A5: Scenario | B5: African Sky partner share % | C5: 0.5 | D5: 0% excludes property; >0% includes at selected share
A6: Scenario | B6: Winchester expansion option | C6: N | D6: Y/N; only active if African Sky share > 0%
A7: Scenario | B7: Beachside partner share % | C7: 0.5 | D7: 0% excludes property; >0% includes at selected share
A8: Scenario | B8: Menlyn partner share % | C8: 0.5 | D8: 0% excludes property; >0% includes at selected share
A9: Guests | B9: ASV avg guests per occupied unit-night | C9: 2.8 | D9: Control!B31
A10: Pricing | B10: ASV base ADR incl. 2 guests | C10: 4500 | D10: Control!B28
A11: Pricing | B11: ASV extra guest rate | C11: 1000 | D11: Control!B29
A12: Pricing | B12: Remington base ADR incl. 2 guests | C12: =Control!$B$32 -> 3700 | D12: Control!B32
A13: Pricing | B13: Remington extra guest rate | C13: =Control!$B$33 -> 750 | D13: Control!B33
A14: Tours | B14: Tour revenue Year 1 | C14: 2071762.4 | D14: Linked from ASKY Tours Calcs totals
A15: Tours | B15: Tour supplier cost Year 1 | C15: 1512882.8 | D15: Linked from ASKY Tours Calcs totals
A16: Stay duration | B16: ASV avg nights / booking | C16: 0 | D16: Realised booking analysis in ASKY Stay Calc
A17: Stay duration | B17: Remington avg nights / booking | C17: 0 | D17: Realised booking analysis in ASKY Stay Calc
A18: Valuation | B18: Adopted property value | C18: 12800000 | D18: Valuation!F9
A19: Valuation | B19: Partner NAV today | C19: 6400000 | D19: Valuation!F10
A20: Exit | B20: Property value growth p.a. | C20: 0.05 | D20: Control!B68 linked to Control!B74
A21: Tax / legal | B21: Open flags | C21: See Read Me & Glossary!B18 | D21: Accountant/attorney sign-off required
A22: Optional asset | B22: Winchester development expansion toggle | C22: N | D22: Y includes Winchester revenue, build capex and value; N excludes it. Only active if African Sky toggle is Y.

Sheet Control
A1: CONTROL — edit only the shaded (yellow) input cells
A2: ZAR · DRAFT · all sheets link here. Terminology follows SA hospitality/property convention — see 'Read Me & Glossary'.
A4: 0 · PARTNER SHARE OFFER | B4: Partner Offer Prop % | C4: Distribution allocation % | E4: INVESTOR KPI SNAPSHOT — ACTIVE PORTFOLIO
A5: African Sky partner share % | B5: 0.5 | C5: =B5 -> 0.5 | E5: KPI | F5: Value | G5: What it shows
A6: Winchester expansion? (Y/N; active if African Sky share > 0%) | B6: N | E6: =_xlfn.TEXTJOIN(", ",TRUE,IF($B$5>0,"African Sky",""),IF(AND($B$5>0,$B$6="Y"),"Winchester expansion",""),IF($B$7>0,"Beachside",""),IF($B$8>0,"Menlyn","")) -> African Sky, Beachside, Menlyn | G6: Properties with share % > 0 are included; Winchester is separate option
A7: Beachside partner share % | B7: 0.5 | C7: =B7 -> 0.5 | E7: Active portfolio value | F7: =Valuation!$F$9 -> 12900000 | G7: 100% adopted value of active properties
A8: Menlyn partner share % | B8: 0.5 | C8: =B8 -> 0.5 | E8: Partner buy-in | F8: =Control!$B$15 -> 6400000 | G8: Cash consideration based on active properties and property-specific partner %
E9: Partner NAV today | F9: =Valuation!$F$10 -> 6450000 | G9: Partner NAV using property-specific partner % by property
A10: 1 · DEAL & STRUCTURE | E10: Offer vs NAV | F10: =IFERROR(Control!$B$15/Valuation!$F$10,"") -> 0.99224806 | G10: 1.0x = buy-in equals NAV
A11: Reference % for listed buy-in pricing | B11: 0.5 | E11: Year 1 partner distribution | F11: ='Portfolio NewCo'!B16 -> 952520.4 | G11: Projected first-year cash distribution using Control distribution allocation %
A12: African Sky — buy-in at reference % (ZAR) | B12: 3000000 | E12: Year 1 cash yield | F12: =IFERROR('Portfolio NewCo'!B16/Control!$B$15,"") -> 0.14883131 | G12: Year 1 distribution ÷ partner buy-in
A13: Beachside — buy-in at reference % (ZAR) | B13: 2000000 | E13: Cash payback year | F13: ='INV - Investor KPIs'!B25 -> 6 | G13: Year cumulative distributions recover buy-in
A14: Menlyn — buy-in at reference % (ZAR) | B14: 1400000 | E14: 5Y Total Partner Distributions | F14: ='INV - Investor KPIs'!G7 -> 5263276.5 | G14: Cumulative partner distributions received through Year 5
A15: Total active partner buy-in (share-offer %) | B15: =IF($B$5>0,$B$12/$B$11*$B$5,0)+IF($B$7>0,$B$13/$B$11*$B$7,0)+IF($B$8>0,$B$14/$B$11*$B$8,0) -> 6400000 | E15: 5Y Total Partner Value if Exit in Year 5 | F15: ='INV - Investor KPIs'!G12 -> 13001372 | G15: Cumulative distributions + exit NAV — Total Partner Value if Exit in Year 5
A16: 2 · FORECAST DRIVERS | E16: 5Y Total IRR | F16: ='INV - Investor KPIs'!C18 -> 0.19036144 | G16: Includes cash distributions + exit NAV
A17: Room-rate (ADR) escalation p.a. | B17: 0.05 | E17: 5Y Total MOIC | F17: ='INV - Investor KPIs'!C20 -> 2.0314643 | G17: Total value received ÷ buy-in
A18: Expense inflation p.a. | B18: 0.05 | E18: 10Y Total Partner Distributions | F18: ='INV - Investor KPIs'!L7 -> 11980699 | G18: Cumulative partner distributions received through Year 10
A19: Occupancy — short-let units (%) — DEPRECATED: replaced by per-villa occupancy (B30 / B34 / B37) | B19: 0.75 | E19: 10Y Total Partner Value if Exit in Year 10 | F19: ='INV - Investor KPIs'!L12 -> 21856687 | G19: Cumulative distributions + exit NAV — Total Partner Value if Exit in Year 10
A20: Available nights per year | B20: 365 | E20: 10Y Total IRR | F20: ='INV - Investor KPIs'!D18 -> 0.19595828 | G20: Includes cash distributions + exit NAV
A21: Model horizon (years) — DISPLAY MEMO ONLY: projection is fixed at 20 years | B21: 20 | E21: 10Y Total MOIC | F21: ='INV - Investor KPIs'!D20 -> 3.4151074 | G21: Total value received ÷ buy-in
A22: 3 · TAX, VAT & RESERVES | E22: 15Y Total Partner Distributions | F22: ='INV - Investor KPIs'!Q7 -> 20554022 | G22: Cumulative partner distributions received through Year 15
A23: Corporate income tax rate | B23: 0.27 | E23: 15Y Total Partner Value if Exit in Year 15 | F23: ='INV - Investor KPIs'!Q12 -> 33158564 | G23: Cumulative distributions + exit NAV — Total Partner Value if Exit in Year 15
A24: Apply output VAT to short-let accommodation? (1=Yes/0=No) — PLACEHOLDER: VAT not yet wired; gated to accountant | B24: 0 | E24: 15Y Total IRR | F24: ='INV - Investor KPIs'!E18 -> 0.19757586 | G24: Includes cash distributions + exit NAV
A25: VAT rate — PLACEHOLDER: not yet wired | B25: 0.15 | E25: 15Y Total MOIC | F25: ='INV - Investor KPIs'!E20 -> 5.1810255 | G25: Total value received ÷ buy-in
A26: FF&E / capex reserve (% of accommodation revenue) | B26: 0.04 | E26: 20Y Total Partner Distributions | F26: ='INV - Investor KPIs'!V7 -> 31495996 | G26: Cumulative partner distributions received through Year 20
A27: 4 · AFRICAN SKY VILLAS — 3 units + meals + tours | E27: 20Y Total Partner Value if Exit in Year 20 | F27: ='INV - Investor KPIs'!V12 -> 47582940 | G27: Cumulative distributions + exit NAV — Total Partner Value if Exit in Year 20
A28: African Sky Villa — ADR incl. 2 guests (ZAR/night) | B28: 4500 | E28: 20Y Total IRR | F28: ='INV - Investor KPIs'!F18 -> 0.19823225 | G28: Includes cash distributions + exit NAV
A29: African Sky Villa — extra-guest rate (ZAR/guest/night) | B29: 1000 | E29: 20Y Total MOIC | F29: ='INV - Investor KPIs'!F20 -> 7.4348343 | G29: Total value received ÷ buy-in
A30: African Sky Villa — avg annual nights booked (%) | B30: ='ASKY Bookings'!C390 -> 0.68175583
A31: African Sky Villa — avg guests per occupied unit-night | B31: ='ASKY Bookings'!C409 -> 2.750503
A32: Remington Villa — ADR incl. 2 guests (ZAR/night) | B32: 3700
A33: Remington Villa — extra-guest rate (ZAR/guest/night) | B33: 750
A34: Remington Villa — avg annual nights booked (%) | B34: ='ASKY Bookings'!D390 -> 0.62328767
A35: Remington Villa — avg guests per occupied unit-night | B35: ='ASKY Bookings'!D409 -> 2.6879121
A36: Winchester (planned) — ADR, sleeps 2 (ZAR/night) | B36: 3500
A37: Winchester — avg annual nights booked (%) | B37: 0.52
A38: Winchester — avg guests per occupied unit-night | B38: 2
A39: Winchester — online from year | B39: 2
A40: Winchester — construction cost (ZAR, one-off) | B40: 500000
A41: Meal take-up — guests taking both meals (%) | B41: 0.75
A42: Breakfast price (ZAR/guest) | B42: 150
A43: Breakfast cost (ZAR/guest) | B43: 100
A44: Dinner price (ZAR/guest) | B44: 375
A45: Dinner cost (ZAR/guest) | B45: 200
A46: Tours & activities revenue (ZAR/yr) — linked from ASKY Tours Calcs | B46: ='ASKY Tours Calcs'!O27 -> 2045556.5
A47: Tours & activities cost (ZAR/yr) — linked from ASKY Tours Calcs | B47: ='ASKY Tours Calcs'!P27 -> 1493746.3
A48: African Sky — salaries & wages (ZAR/month) | B48: 30000
A49: African Sky — utilities & municipal (ZAR/month) | B49: 6800
A50: African Sky — repairs & maintenance (ZAR/month) | B50: 3500
A51: African Sky — other operating (ZAR/month) | B51: 5000
A52: African Sky — channel commission (% of accommodation) | B52: 0.2
A53: 5 · BEACHSIDE ESCAPE — Big Bay
A54: Long-term rent (ZAR/month) | B54: 30000
A55: Long-term months per year | B55: 10
A56: Long-term gross revenueY1 | B56: =B54*B55 -> 300000
A57: Peak holiday ADR (ZAR/night) | B57: 4500
A58: Peak months per year (Dec+Jan) | B58: 2
A59: Nights per peak month | B59: 30
A60: Peak-season occupancy (%) | B60: 0.9
A61: Peak holiday gross revenue Y1 | B61: =B57*B58*B59*B60 -> 243000
A62: TOTAL BEACHSIDE GROSS REVENUE Y1 | B62: =B56+B61 -> 543000
A63: Commission on nightly lets (%) | B63: 0.2
A64: Utilities & municipal (ZAR/month) | B64: 1000
A65: Repairs & maintenance (ZAR/month) | B65: 1000
A66: Levies (ZAR/month) | B66: 3800
A67: 6 · MENLYN MAIN — long-term rental
A68: Rental income (ZAR/month) | B68: 28000
A69: TOTAL MENLYN MAIN GROSS REVENUE Y1 | B69: =B68*12 -> 336000
A70: Utilities & municipal (ZAR/month) | B70: 900
A71: Repairs & maintenance (ZAR/month) | B71: 1000
A72: Levies / rates (ZAR/month) | B72: 3500
A73: 7 · VALUATION (independent — income & comparable)
A74: African Sky — hospitality cap rate (memo only) | B74: 0.1
A75: Beachside — residential cap rate | B75: 0.075
A76: Menlyn — residential cap rate | B76: 0.085
A77: African Sky — property value, 2 built units (comparable/cost, ZAR) | B77: 6000000
A78: Property value growth p.a. (exit) | B78: =B84 -> 0.05
A79: Sale friction / exit costs (%) | B79: 0.06
A80: 8 · LEVERAGE & GROWTH ENGINE
A81: Target loan-to-value on portfolio (%) | B81: 0.6
A82: Debt interest rate p.a. (%) | B82: 0.115
A83: Stabilised / acquisition income yield (%) | B83: 0.09
A84: Property appreciation p.a. (%) | B84: 0.05
A85: Share of free cashflow reinvested (%) | B85: 1
A87: Display note
A88: If a property share % is 0%, the property remains visible for context but numeric values/outputs are visually blanked. Underlying inputs/formulas are preserved and reappear when share % is above 0%.

Sheet African Sky P&L
A1: AFRICAN SKY VILLAS — P&L (annual, 20-year)
A2: 3 units (African Sky Villa · Remington · Winchester) + meals + tours. Winchester phases in from its online year. After FF&E reserve, after tax.
A4: Year | C4: 1 | D4: 2 | E4: 3 | F4: 4 | G4: 5 | H4: 6 | I4: 7 | J4: 8 | K4: 9 | L4: 10 | M4: 11 | N4: 12 | O4: 13 | P4: 14 | Q4: 15 | R4: 16 | S4: 17 | T4: 18 | U4: 19 | V4: 20
A6: Occupied unit-nights / unit | C6: =IF(Control!$B$5>0,Control!$B$20*(Control!$B$30+Control!$B$34+IF(Control!$B$6="Y",Control!$B$37,0))/(2+IF(Control!$B$6="Y",1,0)),0) -> 238.17044 | D6: =IF(Control!$B$5>0,Control!$B$20*(Control!$B$30+Control!$B$34+IF(Control!$B$6="Y",Control!$B$37,0))/(2+IF(Control!$B$6="Y",1,0)),0) -> 238.17044 | E6: =IF(Control!$B$5>0,Control!$B$20*(Control!$B$30+Control!$B$34+IF(Control!$B$6="Y",Control!$B$37,0))/(2+IF(Control!$B$6="Y",1,0)),0) -> 238.17044 | F6: =IF(Control!$B$5>0,Control!$B$20*(Control!$B$30+Control!$B$34+IF(Control!$B$6="Y",Control!$B$37,0))/(2+IF(Control!$B$6="Y",1,0)),0) -> 238.17044 | G6: =IF(Control!$B$5>0,Control!$B$20*(Control!$B$30+Control!$B$34+IF(Control!$B$6="Y",Control!$B$37,0))/(2+IF(Control!$B$6="Y",1,0)),0) -> 238.17044 | H6: =IF(Control!$B$5>0,Control!$B$20*(Control!$B$30+Control!$B$34+IF(Control!$B$6="Y",Control!$B$37,0))/(2+IF(Control!$B$6="Y",1,0)),0) -> 238.17044 | I6: =IF(Control!$B$5>0,Control!$B$20*(Control!$B$30+Control!$B$34+IF(Control!$B$6="Y",Control!$B$37,0))/(2+IF(Control!$B$6="Y",1,0)),0) -> 238.17044 | J6: =IF(Control!$B$5>0,Control!$B$20*(Control!$B$30+Control!$B$34+IF(Control!$B$6="Y",Control!$B$37,0))/(2+IF(Control!$B$6="Y",1,0)),0) -> 238.17044 | ... V6: =IF(Control!$B$5>0,Control!$B$20*(Control!$B$30+Control!$B$34+IF(Control!$B$6="Y",Control!$B$37,0))/(2+IF(Control!$B$6="Y",1,0)),0) -> 238.17044
A7: African Sky Villa — accommodation | C7: =IF(Control!$B$5>0,(Control!$B$20*Control!$B$30)*(Control!$B$28+Control!$B$29*MAX(0,Control!$B$31-2))*POWER(1+Control!$B$17,C$4-1),0) -> 1306539.8 | D7: =IF(Control!$B$5>0,(Control!$B$20*Control!$B$30)*(Control!$B$28+Control!$B$29*MAX(0,Control!$B$31-2))*POWER(1+Control!$B$17,D$4-1),0) -> 1371866.8 | E7: =IF(Control!$B$5>0,(Control!$B$20*Control!$B$30)*(Control!$B$28+Control!$B$29*MAX(0,Control!$B$31-2))*POWER(1+Control!$B$17,E$4-1),0) -> 1440460.1 | F7: =IF(Control!$B$5>0,(Control!$B$20*Control!$B$30)*(Control!$B$28+Control!$B$29*MAX(0,Control!$B$31-2))*POWER(1+Control!$B$17,F$4-1),0) -> 1512483.1 | G7: =IF(Control!$B$5>0,(Control!$B$20*Control!$B$30)*(Control!$B$28+Control!$B$29*MAX(0,Control!$B$31-2))*POWER(1+Control!$B$17,G$4-1),0) -> 1588107.3 | H7: =IF(Control!$B$5>0,(Control!$B$20*Control!$B$30)*(Control!$B$28+Control!$B$29*MAX(0,Control!$B$31-2))*POWER(1+Control!$B$17,H$4-1),0) -> 1667512.6 | I7: =IF(Control!$B$5>0,(Control!$B$20*Control!$B$30)*(Control!$B$28+Control!$B$29*MAX(0,Control!$B$31-2))*POWER(1+Control!$B$17,I$4-1),0) -> 1750888.3 | J7: =IF(Control!$B$5>0,(Control!$B$20*Control!$B$30)*(Control!$B$28+Control!$B$29*MAX(0,Control!$B$31-2))*POWER(1+Control!$B$17,J$4-1),0) -> 1838432.7 | ... V7: =IF(Control!$B$5>0,(Control!$B$20*Control!$B$30)*(Control!$B$28+Control!$B$29*MAX(0,Control!$B$31-2))*POWER(1+Control!$B$17,V$4-1),0) -> 3301561
A8: Remington Villa — accommodation | C8: =IF(Control!$B$5>0,(Control!$B$20*Control!$B$34)*(Control!$B$32+Control!$B$33*MAX(0,Control!$B$35-2))*POWER(1+Control!$B$17,C$4-1),0) -> 959125 | D8: =IF(Control!$B$5>0,(Control!$B$20*Control!$B$34)*(Control!$B$32+Control!$B$33*MAX(0,Control!$B$35-2))*POWER(1+Control!$B$17,D$4-1),0) -> 1007081.3 | E8: =IF(Control!$B$5>0,(Control!$B$20*Control!$B$34)*(Control!$B$32+Control!$B$33*MAX(0,Control!$B$35-2))*POWER(1+Control!$B$17,E$4-1),0) -> 1057435.3 | F8: =IF(Control!$B$5>0,(Control!$B$20*Control!$B$34)*(Control!$B$32+Control!$B$33*MAX(0,Control!$B$35-2))*POWER(1+Control!$B$17,F$4-1),0) -> 1110307.1 | G8: =IF(Control!$B$5>0,(Control!$B$20*Control!$B$34)*(Control!$B$32+Control!$B$33*MAX(0,Control!$B$35-2))*POWER(1+Control!$B$17,G$4-1),0) -> 1165822.4 | H8: =IF(Control!$B$5>0,(Control!$B$20*Control!$B$34)*(Control!$B$32+Control!$B$33*MAX(0,Control!$B$35-2))*POWER(1+Control!$B$17,H$4-1),0) -> 1224113.6 | I8: =IF(Control!$B$5>0,(Control!$B$20*Control!$B$34)*(Control!$B$32+Control!$B$33*MAX(0,Control!$B$35-2))*POWER(1+Control!$B$17,I$4-1),0) -> 1285319.2 | J8: =IF(Control!$B$5>0,(Control!$B$20*Control!$B$34)*(Control!$B$32+Control!$B$33*MAX(0,Control!$B$35-2))*POWER(1+Control!$B$17,J$4-1),0) -> 1349585.2 | ... V8: =IF(Control!$B$5>0,(Control!$B$20*Control!$B$34)*(Control!$B$32+Control!$B$33*MAX(0,Control!$B$35-2))*POWER(1+Control!$B$17,V$4-1),0) -> 2423661.1
A9: Winchester — accommodation | C9: =IF(AND(Control!$B$5>0,Control!$B$6="Y",C$4>=Control!$B$39),(Control!$B$20*Control!$B$37)*Control!$B$36*POWER(1+Control!$B$17,C$4-1),0) -> 0 | D9: =IF(AND(Control!$B$5>0,Control!$B$6="Y",D$4>=Control!$B$39),(Control!$B$20*Control!$B$37)*Control!$B$36*POWER(1+Control!$B$17,D$4-1),0) -> 0 | E9: =IF(AND(Control!$B$5>0,Control!$B$6="Y",E$4>=Control!$B$39),(Control!$B$20*Control!$B$37)*Control!$B$36*POWER(1+Control!$B$17,E$4-1),0) -> 0 | F9: =IF(AND(Control!$B$5>0,Control!$B$6="Y",F$4>=Control!$B$39),(Control!$B$20*Control!$B$37)*Control!$B$36*POWER(1+Control!$B$17,F$4-1),0) -> 0 | G9: =IF(AND(Control!$B$5>0,Control!$B$6="Y",G$4>=Control!$B$39),(Control!$B$20*Control!$B$37)*Control!$B$36*POWER(1+Control!$B$17,G$4-1),0) -> 0 | H9: =IF(AND(Control!$B$5>0,Control!$B$6="Y",H$4>=Control!$B$39),(Control!$B$20*Control!$B$37)*Control!$B$36*POWER(1+Control!$B$17,H$4-1),0) -> 0 | I9: =IF(AND(Control!$B$5>0,Control!$B$6="Y",I$4>=Control!$B$39),(Control!$B$20*Control!$B$37)*Control!$B$36*POWER(1+Control!$B$17,I$4-1),0) -> 0 | J9: =IF(AND(Control!$B$5>0,Control!$B$6="Y",J$4>=Control!$B$39),(Control!$B$20*Control!$B$37)*Control!$B$36*POWER(1+Control!$B$17,J$4-1),0) -> 0 | ... V9: =IF(AND(Control!$B$5>0,Control!$B$6="Y",V$4>=Control!$B$39),(Control!$B$20*Control!$B$37)*Control!$B$36*POWER(1+Control!$B$17,V$4-1),0) -> 0
A10: Accommodation revenue — all units | C10: =SUM(C7:C9) -> 2265664.8 | D10: =SUM(D7:D9) -> 2378948 | E10: =SUM(E7:E9) -> 2497895.4 | F10: =SUM(F7:F9) -> 2622790.2 | G10: =SUM(G7:G9) -> 2753929.7 | H10: =SUM(H7:H9) -> 2891626.2 | I10: =SUM(I7:I9) -> 3036207.5 | J10: =SUM(J7:J9) -> 3188017.9 | ... V10: =SUM(V7:V9) -> 5725222.1
A11: Guest-nights (meal base) | C11: =IF(Control!$B$5>0,Control!$B$20*(Control!$B$30*Control!$B$31+Control!$B$34*Control!$B$35+IF(AND(Control!$B$6="Y",C$4>=Control!$B$39),Control!$B$37*Control!$B$38,0)),0) -> 1295.9376 | D11: =IF(Control!$B$5>0,Control!$B$20*(Control!$B$30*Control!$B$31+Control!$B$34*Control!$B$35+IF(AND(Control!$B$6="Y",D$4>=Control!$B$39),Control!$B$37*Control!$B$38,0)),0) -> 1295.9376 | E11: =IF(Control!$B$5>0,Control!$B$20*(Control!$B$30*Control!$B$31+Control!$B$34*Control!$B$35+IF(AND(Control!$B$6="Y",E$4>=Control!$B$39),Control!$B$37*Control!$B$38,0)),0) -> 1295.9376 | F11: =IF(Control!$B$5>0,Control!$B$20*(Control!$B$30*Control!$B$31+Control!$B$34*Control!$B$35+IF(AND(Control!$B$6="Y",F$4>=Control!$B$39),Control!$B$37*Control!$B$38,0)),0) -> 1295.9376 | G11: =IF(Control!$B$5>0,Control!$B$20*(Control!$B$30*Control!$B$31+Control!$B$34*Control!$B$35+IF(AND(Control!$B$6="Y",G$4>=Control!$B$39),Control!$B$37*Control!$B$38,0)),0) -> 1295.9376 | H11: =IF(Control!$B$5>0,Control!$B$20*(Control!$B$30*Control!$B$31+Control!$B$34*Control!$B$35+IF(AND(Control!$B$6="Y",H$4>=Control!$B$39),Control!$B$37*Control!$B$38,0)),0) -> 1295.9376 | I11: =IF(Control!$B$5>0,Control!$B$20*(Control!$B$30*Control!$B$31+Control!$B$34*Control!$B$35+IF(AND(Control!$B$6="Y",I$4>=Control!$B$39),Control!$B$37*Control!$B$38,0)),0) -> 1295.9376 | J11: =IF(Control!$B$5>0,Control!$B$20*(Control!$B$30*Control!$B$31+Control!$B$34*Control!$B$35+IF(AND(Control!$B$6="Y",J$4>=Control!$B$39),Control!$B$37*Control!$B$38,0)),0) -> 1295.9376 | ... V11: =IF(Control!$B$5>0,Control!$B$20*(Control!$B$30*Control!$B$31+Control!$B$34*Control!$B$35+IF(AND(Control!$B$6="Y",V$4>=Control!$B$39),Control!$B$37*Control!$B$38,0)),0) -> 1295.9376
A12: Meal covers — both meals taken | C12: =C11*Control!$B$41 -> 971.95319 | D12: =D11*Control!$B$41 -> 971.95319 | E12: =E11*Control!$B$41 -> 971.95319 | F12: =F11*Control!$B$41 -> 971.95319 | G12: =G11*Control!$B$41 -> 971.95319 | H12: =H11*Control!$B$41 -> 971.95319 | I12: =I11*Control!$B$41 -> 971.95319 | J12: =J11*Control!$B$41 -> 971.95319 | ... V12: =V11*Control!$B$41 -> 971.95319
A13: Meals income (breakfast + dinner) | C13: =C12*(Control!$B$42+Control!$B$44)*POWER(1+Control!$B$17,C$4-1) -> 510275.42 | D13: =D12*(Control!$B$42+Control!$B$44)*POWER(1+Control!$B$17,D$4-1) -> 535789.2 | E13: =E12*(Control!$B$42+Control!$B$44)*POWER(1+Control!$B$17,E$4-1) -> 562578.66 | F13: =F12*(Control!$B$42+Control!$B$44)*POWER(1+Control!$B$17,F$4-1) -> 590707.59 | G13: =G12*(Control!$B$42+Control!$B$44)*POWER(1+Control!$B$17,G$4-1) -> 620242.97 | H13: =H12*(Control!$B$42+Control!$B$44)*POWER(1+Control!$B$17,H$4-1) -> 651255.12 | I13: =I12*(Control!$B$42+Control!$B$44)*POWER(1+Control!$B$17,I$4-1) -> 683817.87 | J13: =J12*(Control!$B$42+Control!$B$44)*POWER(1+Control!$B$17,J$4-1) -> 718008.77 | ... V13: =V12*(Control!$B$42+Control!$B$44)*POWER(1+Control!$B$17,V$4-1) -> 1289440.6
A14: Tours & activities income | C14: =IF(Control!$B$5>0,Control!$B$46*((Control!$B$20*(Control!$B$30*Control!$B$31+Control!$B$34*Control!$B$35+IF(AND(Control!$B$6="Y",C$4>=Control!$B$39),Control!$B$37*Control!$B$38,0)))/(Control!$B$20*(Control!$B$30*Control!$B$31+Control!$B$34*Control!$B$35+IF(AND(Control!$B$5>0,Control!$B$6="Y",1>=Control!$B$39),Control!$B$37*Control!$B$38,0))))*POWER(1+Control!$B$17,C$4-1),0) -> 2045556.5 | D14: =IF(Control!$B$5>0,Control!$B$46*((Control!$B$20*(Control!$B$30*Control!$B$31+Control!$B$34*Control!$B$35+IF(AND(Control!$B$6="Y",D$4>=Control!$B$39),Control!$B$37*Control!$B$38,0)))/(Control!$B$20*(Control!$B$30*Control!$B$31+Control!$B$34*Control!$B$35+IF(AND(Control!$B$5>0,Control!$B$6="Y",1>=Control!$B$39),Control!$B$37*Control!$B$38,0))))*POWER(1+Control!$B$17,D$4-1),0) -> 2147834.3 | E14: =IF(Control!$B$5>0,Control!$B$46*((Control!$B$20*(Control!$B$30*Control!$B$31+Control!$B$34*Control!$B$35+IF(AND(Control!$B$6="Y",E$4>=Control!$B$39),Control!$B$37*Control!$B$38,0)))/(Control!$B$20*(Control!$B$30*Control!$B$31+Control!$B$34*Control!$B$35+IF(AND(Control!$B$5>0,Control!$B$6="Y",1>=Control!$B$39),Control!$B$37*Control!$B$38,0))))*POWER(1+Control!$B$17,E$4-1),0) -> 2255226 | F14: =IF(Control!$B$5>0,Control!$B$46*((Control!$B$20*(Control!$B$30*Control!$B$31+Control!$B$34*Control!$B$35+IF(AND(Control!$B$6="Y",F$4>=Control!$B$39),Control!$B$37*Control!$B$38,0)))/(Control!$B$20*(Control!$B$30*Control!$B$31+Control!$B$34*Control!$B$35+IF(AND(Control!$B$5>0,Control!$B$6="Y",1>=Control!$B$39),Control!$B$37*Control!$B$38,0))))*POWER(1+Control!$B$17,F$4-1),0) -> 2367987.3 | G14: =IF(Control!$B$5>0,Control!$B$46*((Control!$B$20*(Control!$B$30*Control!$B$31+Control!$B$34*Control!$B$35+IF(AND(Control!$B$6="Y",G$4>=Control!$B$39),Control!$B$37*Control!$B$38,0)))/(Control!$B$20*(Control!$B$30*Control!$B$31+Control!$B$34*Control!$B$35+IF(AND(Control!$B$5>0,Control!$B$6="Y",1>=Control!$B$39),Control!$B$37*Control!$B$38,0))))*POWER(1+Control!$B$17,G$4-1),0) -> 2486386.7 | H14: =IF(Control!$B$5>0,Control!$B$46*((Control!$B$20*(Control!$B$30*Control!$B$31+Control!$B$34*Control!$B$35+IF(AND(Control!$B$6="Y",H$4>=Control!$B$39),Control!$B$37*Control!$B$38,0)))/(Control!$B$20*(Control!$B$30*Control!$B$31+Control!$B$34*Control!$B$35+IF(AND(Control!$B$5>0,Control!$B$6="Y",1>=Control!$B$39),Control!$B$37*Control!$B$38,0))))*POWER(1+Control!$B$17,H$4-1),0) -> 2610706 | I14: =IF(Control!$B$5>0,Control!$B$46*((Control!$B$20*(Control!$B$30*Control!$B$31+Control!$B$34*Control!$B$35+IF(AND(Control!$B$6="Y",I$4>=Control!$B$39),Control!$B$37*Control!$B$38,0)))/(Control!$B$20*(Control!$B$30*Control!$B$31+Control!$B$34*Control!$B$35+IF(AND(Control!$B$5>0,Control!$B$6="Y",1>=Control!$B$39),Control!$B$37*Control!$B$38,0))))*POWER(1+Control!$B$17,I$4-1),0) -> 2741241.3 | J14: =IF(Control!$B$5>0,Control!$B$46*((Control!$B$20*(Control!$B$30*Control!$B$31+Control!$B$34*Control!$B$35+IF(AND(Control!$B$6="Y",J$4>=Control!$B$39),Control!$B$37*Control!$B$38,0)))/(Control!$B$20*(Control!$B$30*Control!$B$31+Control!$B$34*Control!$B$35+IF(AND(Control!$B$5>0,Control!$B$6="Y",1>=Control!$B$39),Control!$B$37*Control!$B$38,0))))*POWER(1+Control!$B$17,J$4-1),0) -> 2878303.4 | ... V14: =IF(Control!$B$5>0,Control!$B$46*((Control!$B$20*(Control!$B$30*Control!$B$31+Control!$B$34*Control!$B$35+IF(AND(Control!$B$6="Y",V$4>=Control!$B$39),Control!$B$37*Control!$B$38,0)))/(Control!$B$20*(Control!$B$30*Control!$B$31+Control!$B$34*Control!$B$35+IF(AND(Control!$B$5>0,Control!$B$6="Y",1>=Control!$B$39),Control!$B$37*Control!$B$38,0))))*POWER(1+Control!$B$17,V$4-1),0) -> 5169019.4
A15: GROSS REVENUE | C15: =C10+C13+C14 -> 4821496.7 | D15: =D10+D13+D14 -> 5062571.5 | E15: =E10+E13+E14 -> 5315700.1 | F15: =F10+F13+F14 -> 5581485.1 | G15: =G10+G13+G14 -> 5860559.4 | H15: =H10+H13+H14 -> 6153587.3 | I15: =I10+I13+I14 -> 6461266.7 | J15: =J10+J13+J14 -> 6784330 | ... V15: =V10+V13+V14 -> 12183682
A16: OPERATING EXPENSES
A17: Channel commission | C17: =C10*Control!$B$52 -> 453132.96 | D17: =D10*Control!$B$52 -> 475789.6 | E17: =E10*Control!$B$52 -> 499579.08 | F17: =F10*Control!$B$52 -> 524558.04 | G17: =G10*Control!$B$52 -> 550785.94 | H17: =H10*Control!$B$52 -> 578325.24 | I17: =I10*Control!$B$52 -> 607241.5 | J17: =J10*Control!$B$52 -> 637603.57 | ... V17: =V10*Control!$B$52 -> 1145044.4
A18: Meals & provisions cost | C18: =IF(Control!$B$5>0,C12*(Control!$B$43+Control!$B$45)*POWER(1+Control!$B$18,C$4-1),0) -> 291585.96 | D18: =IF(Control!$B$5>0,D12*(Control!$B$43+Control!$B$45)*POWER(1+Control!$B$18,D$4-1),0) -> 306165.25 | E18: =IF(Control!$B$5>0,E12*(Control!$B$43+Control!$B$45)*POWER(1+Control!$B$18,E$4-1),0) -> 321473.52 | F18: =IF(Control!$B$5>0,F12*(Control!$B$43+Control!$B$45)*POWER(1+Control!$B$18,F$4-1),0) -> 337547.19 | G18: =IF(Control!$B$5>0,G12*(Control!$B$43+Control!$B$45)*POWER(1+Control!$B$18,G$4-1),0) -> 354424.55 | H18: =IF(Control!$B$5>0,H12*(Control!$B$43+Control!$B$45)*POWER(1+Control!$B$18,H$4-1),0) -> 372145.78 | I18: =IF(Control!$B$5>0,I12*(Control!$B$43+Control!$B$45)*POWER(1+Control!$B$18,I$4-1),0) -> 390753.07 | J18: =IF(Control!$B$5>0,J12*(Control!$B$43+Control!$B$45)*POWER(1+Control!$B$18,J$4-1),0) -> 410290.72 | ... V18: =IF(Control!$B$5>0,V12*(Control!$B$43+Control!$B$45)*POWER(1+Control!$B$18,V$4-1),0) -> 736823.19
A19: Tours & activities cost | C19: =IF(Control!$B$5>0,Control!$B$47*((Control!$B$20*(Control!$B$30*Control!$B$31+Control!$B$34*Control!$B$35+IF(AND(Control!$B$6="Y",C$4>=Control!$B$39),Control!$B$37*Control!$B$38,0)))/(Control!$B$20*(Control!$B$30*Control!$B$31+Control!$B$34*Control!$B$35+IF(AND(Control!$B$5>0,Control!$B$6="Y",1>=Control!$B$39),Control!$B$37*Control!$B$38,0))))*POWER(1+Control!$B$18,C$4-1),0) -> 1493746.3 | D19: =IF(Control!$B$5>0,Control!$B$47*((Control!$B$20*(Control!$B$30*Control!$B$31+Control!$B$34*Control!$B$35+IF(AND(Control!$B$6="Y",D$4>=Control!$B$39),Control!$B$37*Control!$B$38,0)))/(Control!$B$20*(Control!$B$30*Control!$B$31+Control!$B$34*Control!$B$35+IF(AND(Control!$B$5>0,Control!$B$6="Y",1>=Control!$B$39),Control!$B$37*Control!$B$38,0))))*POWER(1+Control!$B$18,D$4-1),0) -> 1568433.6 | E19: =IF(Control!$B$5>0,Control!$B$47*((Control!$B$20*(Control!$B$30*Control!$B$31+Control!$B$34*Control!$B$35+IF(AND(Control!$B$6="Y",E$4>=Control!$B$39),Control!$B$37*Control!$B$38,0)))/(Control!$B$20*(Control!$B$30*Control!$B$31+Control!$B$34*Control!$B$35+IF(AND(Control!$B$5>0,Control!$B$6="Y",1>=Control!$B$39),Control!$B$37*Control!$B$38,0))))*POWER(1+Control!$B$18,E$4-1),0) -> 1646855.3 | F19: =IF(Control!$B$5>0,Control!$B$47*((Control!$B$20*(Control!$B$30*Control!$B$31+Control!$B$34*Control!$B$35+IF(AND(Control!$B$6="Y",F$4>=Control!$B$39),Control!$B$37*Control!$B$38,0)))/(Control!$B$20*(Control!$B$30*Control!$B$31+Control!$B$34*Control!$B$35+IF(AND(Control!$B$5>0,Control!$B$6="Y",1>=Control!$B$39),Control!$B$37*Control!$B$38,0))))*POWER(1+Control!$B$18,F$4-1),0) -> 1729198 | G19: =IF(Control!$B$5>0,Control!$B$47*((Control!$B$20*(Control!$B$30*Control!$B$31+Control!$B$34*Control!$B$35+IF(AND(Control!$B$6="Y",G$4>=Control!$B$39),Control!$B$37*Control!$B$38,0)))/(Control!$B$20*(Control!$B$30*Control!$B$31+Control!$B$34*Control!$B$35+IF(AND(Control!$B$5>0,Control!$B$6="Y",1>=Control!$B$39),Control!$B$37*Control!$B$38,0))))*POWER(1+Control!$B$18,G$4-1),0) -> 1815657.9 | H19: =IF(Control!$B$5>0,Control!$B$47*((Control!$B$20*(Control!$B$30*Control!$B$31+Control!$B$34*Control!$B$35+IF(AND(Control!$B$6="Y",H$4>=Control!$B$39),Control!$B$37*Control!$B$38,0)))/(Control!$B$20*(Control!$B$30*Control!$B$31+Control!$B$34*Control!$B$35+IF(AND(Control!$B$5>0,Control!$B$6="Y",1>=Control!$B$39),Control!$B$37*Control!$B$38,0))))*POWER(1+Control!$B$18,H$4-1),0) -> 1906440.8 | I19: =IF(Control!$B$5>0,Control!$B$47*((Control!$B$20*(Control!$B$30*Control!$B$31+Control!$B$34*Control!$B$35+IF(AND(Control!$B$6="Y",I$4>=Control!$B$39),Control!$B$37*Control!$B$38,0)))/(Control!$B$20*(Control!$B$30*Control!$B$31+Control!$B$34*Control!$B$35+IF(AND(Control!$B$5>0,Control!$B$6="Y",1>=Control!$B$39),Control!$B$37*Control!$B$38,0))))*POWER(1+Control!$B$18,I$4-1),0) -> 2001762.8 | J19: =IF(Control!$B$5>0,Control!$B$47*((Control!$B$20*(Control!$B$30*Control!$B$31+Control!$B$34*Control!$B$35+IF(AND(Control!$B$6="Y",J$4>=Control!$B$39),Control!$B$37*Control!$B$38,0)))/(Control!$B$20*(Control!$B$30*Control!$B$31+Control!$B$34*Control!$B$35+IF(AND(Control!$B$5>0,Control!$B$6="Y",1>=Control!$B$39),Control!$B$37*Control!$B$38,0))))*POWER(1+Control!$B$18,J$4-1),0) -> 2101851 | ... V19: =IF(Control!$B$5>0,Control!$B$47*((Control!$B$20*(Control!$B$30*Control!$B$31+Control!$B$34*Control!$B$35+IF(AND(Control!$B$6="Y",V$4>=Control!$B$39),Control!$B$37*Control!$B$38,0)))/(Control!$B$20*(Control!$B$30*Control!$B$31+Control!$B$34*Control!$B$35+IF(AND(Control!$B$5>0,Control!$B$6="Y",1>=Control!$B$39),Control!$B$37*Control!$B$38,0))))*POWER(1+Control!$B$18,V$4-1),0) -> 3774622.4
A20: Salaries & wages | C20: =IF(Control!$B$5>0,Control!$B$48*12*POWER(1+Control!$B$18,C$4-1),0) -> 360000 | D20: =IF(Control!$B$5>0,Control!$B$48*12*POWER(1+Control!$B$18,D$4-1),0) -> 378000 | E20: =IF(Control!$B$5>0,Control!$B$48*12*POWER(1+Control!$B$18,E$4-1),0) -> 396900 | F20: =IF(Control!$B$5>0,Control!$B$48*12*POWER(1+Control!$B$18,F$4-1),0) -> 416745 | G20: =IF(Control!$B$5>0,Control!$B$48*12*POWER(1+Control!$B$18,G$4-1),0) -> 437582.25 | H20: =IF(Control!$B$5>0,Control!$B$48*12*POWER(1+Control!$B$18,H$4-1),0) -> 459461.36 | I20: =IF(Control!$B$5>0,Control!$B$48*12*POWER(1+Control!$B$18,I$4-1),0) -> 482434.43 | J20: =IF(Control!$B$5>0,Control!$B$48*12*POWER(1+Control!$B$18,J$4-1),0) -> 506556.15 | ... V20: =IF(Control!$B$5>0,Control!$B$48*12*POWER(1+Control!$B$18,V$4-1),0) -> 909702.07
A21: Utilities & municipal | C21: =IF(Control!$B$5>0,Control!$B$49*12*POWER(1+Control!$B$18,C$4-1),0) -> 81600 | D21: =IF(Control!$B$5>0,Control!$B$49*12*POWER(1+Control!$B$18,D$4-1),0) -> 85680 | E21: =IF(Control!$B$5>0,Control!$B$49*12*POWER(1+Control!$B$18,E$4-1),0) -> 89964 | F21: =IF(Control!$B$5>0,Control!$B$49*12*POWER(1+Control!$B$18,F$4-1),0) -> 94462.2 | G21: =IF(Control!$B$5>0,Control!$B$49*12*POWER(1+Control!$B$18,G$4-1),0) -> 99185.31 | H21: =IF(Control!$B$5>0,Control!$B$49*12*POWER(1+Control!$B$18,H$4-1),0) -> 104144.58 | I21: =IF(Control!$B$5>0,Control!$B$49*12*POWER(1+Control!$B$18,I$4-1),0) -> 109351.8 | J21: =IF(Control!$B$5>0,Control!$B$49*12*POWER(1+Control!$B$18,J$4-1),0) -> 114819.39 | ... V21: =IF(Control!$B$5>0,Control!$B$49*12*POWER(1+Control!$B$18,V$4-1),0) -> 206199.14
A22: Repairs & maintenance | C22: =IF(Control!$B$5>0,Control!$B$50*12*POWER(1+Control!$B$18,C$4-1),0) -> 42000 | D22: =IF(Control!$B$5>0,Control!$B$50*12*POWER(1+Control!$B$18,D$4-1),0) -> 44100 | E22: =IF(Control!$B$5>0,Control!$B$50*12*POWER(1+Control!$B$18,E$4-1),0) -> 46305 | F22: =IF(Control!$B$5>0,Control!$B$50*12*POWER(1+Control!$B$18,F$4-1),0) -> 48620.25 | G22: =IF(Control!$B$5>0,Control!$B$50*12*POWER(1+Control!$B$18,G$4-1),0) -> 51051.262 | H22: =IF(Control!$B$5>0,Control!$B$50*12*POWER(1+Control!$B$18,H$4-1),0) -> 53603.826 | I22: =IF(Control!$B$5>0,Control!$B$50*12*POWER(1+Control!$B$18,I$4-1),0) -> 56284.017 | J22: =IF(Control!$B$5>0,Control!$B$50*12*POWER(1+Control!$B$18,J$4-1),0) -> 59098.218 | ... V22: =IF(Control!$B$5>0,Control!$B$50*12*POWER(1+Control!$B$18,V$4-1),0) -> 106131.91
A23: Other operating | C23: =IF(Control!$B$5>0,Control!$B$51*12*POWER(1+Control!$B$18,C$4-1),0) -> 60000 | D23: =IF(Control!$B$5>0,Control!$B$51*12*POWER(1+Control!$B$18,D$4-1),0) -> 63000 | E23: =IF(Control!$B$5>0,Control!$B$51*12*POWER(1+Control!$B$18,E$4-1),0) -> 66150 | F23: =IF(Control!$B$5>0,Control!$B$51*12*POWER(1+Control!$B$18,F$4-1),0) -> 69457.5 | G23: =IF(Control!$B$5>0,Control!$B$51*12*POWER(1+Control!$B$18,G$4-1),0) -> 72930.375 | H23: =IF(Control!$B$5>0,Control!$B$51*12*POWER(1+Control!$B$18,H$4-1),0) -> 76576.894 | I23: =IF(Control!$B$5>0,Control!$B$51*12*POWER(1+Control!$B$18,I$4-1),0) -> 80405.738 | J23: =IF(Control!$B$5>0,Control!$B$51*12*POWER(1+Control!$B$18,J$4-1),0) -> 84426.025 | ... V23: =IF(Control!$B$5>0,Control!$B$51*12*POWER(1+Control!$B$18,V$4-1),0) -> 151617.01
A24: FF&E / capex reserve | C24: =C10*Control!$B$26 -> 90626.591 | D24: =D10*Control!$B$26 -> 95157.921 | E24: =E10*Control!$B$26 -> 99915.817 | F24: =F10*Control!$B$26 -> 104911.61 | G24: =G10*Control!$B$26 -> 110157.19 | H24: =H10*Control!$B$26 -> 115665.05 | I24: =I10*Control!$B$26 -> 121448.3 | J24: =J10*Control!$B$26 -> 127520.71 | ... V24: =V10*Control!$B$26 -> 229008.88
A25: TOTAL EXPENSES | C25: =SUM(C17:C24) -> 2872691.8 | D25: =SUM(D17:D24) -> 3016326.4 | E25: =SUM(E17:E24) -> 3167142.7 | F25: =SUM(F17:F24) -> 3325499.8 | G25: =SUM(G17:G24) -> 3491774.8 | H25: =SUM(H17:H24) -> 3666363.5 | I25: =SUM(I17:I24) -> 3849681.7 | J25: =SUM(J17:J24) -> 4042165.8 | ... V25: =SUM(V17:V24) -> 7259149
A26: NET OPERATING INCOME (NOI, pre-tax) | C26: =C15-C25 -> 1948804.9 | D26: =D15-D25 -> 2046245.2 | E26: =E15-E25 -> 2148557.4 | F26: =F15-F25 -> 2255985.3 | G26: =G15-G25 -> 2368784.6 | H26: =H15-H25 -> 2487223.8 | I26: =I15-I25 -> 2611585 | J26: =J15-J25 -> 2742164.2 | ... V26: =V15-V25 -> 4924533
A27: Income tax | C27: =-C26*Control!$B$23 -> -526177.33 | D27: =-D26*Control!$B$23 -> -552486.2 | E27: =-E26*Control!$B$23 -> -580110.51 | F27: =-F26*Control!$B$23 -> -609116.03 | G27: =-G26*Control!$B$23 -> -639571.83 | H27: =-H26*Control!$B$23 -> -671550.42 | I27: =-I26*Control!$B$23 -> -705127.95 | J27: =-J26*Control!$B$23 -> -740384.34 | ... V27: =-V26*Control!$B$23 -> -1329623.9
A28: NET PROFIT AFTER TAX | C28: =C26+C27 -> 1422627.6 | D28: =D26+D27 -> 1493759 | E28: =E26+E27 -> 1568446.9 | F28: =F26+F27 -> 1646869.3 | G28: =G26+G27 -> 1729212.7 | H28: =H26+H27 -> 1815673.4 | I28: =I26+I27 -> 1906457 | J28: =J26+J27 -> 2001779.9 | ... V28: =V26+V27 -> 3594909.1

Sheet Beachside P&L
A1: BEACHSIDE ESCAPE — P&L (annual, 20-year)
A2: Big Bay. 10 months long-term + Dec/Jan peak nightly (90% occupancy). After reserve, after tax.
A4: Year | C4: 1 | D4: 2 | E4: 3 | F4: 4 | G4: 5 | H4: 6 | I4: 7 | J4: 8 | K4: 9 | L4: 10 | M4: 11 | N4: 12 | O4: 13 | P4: 14 | Q4: 15 | R4: 16 | S4: 17 | T4: 18 | U4: 19 | V4: 20
A6: Long-term rental income | C6: =IF(Control!$B$7>0,Control!$B$54*Control!$B$55*POWER(1+Control!$B$17,C$4-1),0) -> 300000 | D6: =IF(Control!$B$7>0,Control!$B$54*Control!$B$55*POWER(1+Control!$B$17,D$4-1),0) -> 315000 | E6: =IF(Control!$B$7>0,Control!$B$54*Control!$B$55*POWER(1+Control!$B$17,E$4-1),0) -> 330750 | F6: =IF(Control!$B$7>0,Control!$B$54*Control!$B$55*POWER(1+Control!$B$17,F$4-1),0) -> 347287.5 | G6: =IF(Control!$B$7>0,Control!$B$54*Control!$B$55*POWER(1+Control!$B$17,G$4-1),0) -> 364651.88 | H6: =IF(Control!$B$7>0,Control!$B$54*Control!$B$55*POWER(1+Control!$B$17,H$4-1),0) -> 382884.47 | I6: =IF(Control!$B$7>0,Control!$B$54*Control!$B$55*POWER(1+Control!$B$17,I$4-1),0) -> 402028.69 | J6: =IF(Control!$B$7>0,Control!$B$54*Control!$B$55*POWER(1+Control!$B$17,J$4-1),0) -> 422130.13 | ... V6: =IF(Control!$B$7>0,Control!$B$54*Control!$B$55*POWER(1+Control!$B$17,V$4-1),0) -> 758085.06
A7: Peak nightly income (Dec+Jan) | C7: =IF(Control!$B$7>0,Control!$B$57*Control!$B$58*Control!$B$59*Control!$B$60*POWER(1+Control!$B$17,C$4-1),0) -> 243000 | D7: =IF(Control!$B$7>0,Control!$B$57*Control!$B$58*Control!$B$59*Control!$B$60*POWER(1+Control!$B$17,D$4-1),0) -> 255150 | E7: =IF(Control!$B$7>0,Control!$B$57*Control!$B$58*Control!$B$59*Control!$B$60*POWER(1+Control!$B$17,E$4-1),0) -> 267907.5 | F7: =IF(Control!$B$7>0,Control!$B$57*Control!$B$58*Control!$B$59*Control!$B$60*POWER(1+Control!$B$17,F$4-1),0) -> 281302.88 | G7: =IF(Control!$B$7>0,Control!$B$57*Control!$B$58*Control!$B$59*Control!$B$60*POWER(1+Control!$B$17,G$4-1),0) -> 295368.02 | H7: =IF(Control!$B$7>0,Control!$B$57*Control!$B$58*Control!$B$59*Control!$B$60*POWER(1+Control!$B$17,H$4-1),0) -> 310136.42 | I7: =IF(Control!$B$7>0,Control!$B$57*Control!$B$58*Control!$B$59*Control!$B$60*POWER(1+Control!$B$17,I$4-1),0) -> 325643.24 | J7: =IF(Control!$B$7>0,Control!$B$57*Control!$B$58*Control!$B$59*Control!$B$60*POWER(1+Control!$B$17,J$4-1),0) -> 341925.4 | ... V7: =IF(Control!$B$7>0,Control!$B$57*Control!$B$58*Control!$B$59*Control!$B$60*POWER(1+Control!$B$17,V$4-1),0) -> 614048.9
A8: GROSS REVENUE | C8: =SUM(C6:C7) -> 543000 | D8: =SUM(D6:D7) -> 570150 | E8: =SUM(E6:E7) -> 598657.5 | F8: =SUM(F6:F7) -> 628590.38 | G8: =SUM(G6:G7) -> 660019.89 | H8: =SUM(H6:H7) -> 693020.89 | I8: =SUM(I6:I7) -> 727671.93 | J8: =SUM(J6:J7) -> 764055.53 | ... V8: =SUM(V6:V7) -> 1372134
A9: OPERATING EXPENSES
A10: Channel commission (nightly only) | C10: =C7*Control!$B$63 -> 48600 | D10: =D7*Control!$B$63 -> 51030 | E10: =E7*Control!$B$63 -> 53581.5 | F10: =F7*Control!$B$63 -> 56260.575 | G10: =G7*Control!$B$63 -> 59073.604 | H10: =H7*Control!$B$63 -> 62027.284 | I10: =I7*Control!$B$63 -> 65128.648 | J10: =J7*Control!$B$63 -> 68385.081 | ... V10: =V7*Control!$B$63 -> 122809.78
A11: Utilities & municipal | C11: =IF(Control!$B$7>0,Control!$B$64*12*POWER(1+Control!$B$18,C$4-1),0) -> 12000 | D11: =IF(Control!$B$7>0,Control!$B$64*12*POWER(1+Control!$B$18,D$4-1),0) -> 12600 | E11: =IF(Control!$B$7>0,Control!$B$64*12*POWER(1+Control!$B$18,E$4-1),0) -> 13230 | F11: =IF(Control!$B$7>0,Control!$B$64*12*POWER(1+Control!$B$18,F$4-1),0) -> 13891.5 | G11: =IF(Control!$B$7>0,Control!$B$64*12*POWER(1+Control!$B$18,G$4-1),0) -> 14586.075 | H11: =IF(Control!$B$7>0,Control!$B$64*12*POWER(1+Control!$B$18,H$4-1),0) -> 15315.379 | I11: =IF(Control!$B$7>0,Control!$B$64*12*POWER(1+Control!$B$18,I$4-1),0) -> 16081.148 | J11: =IF(Control!$B$7>0,Control!$B$64*12*POWER(1+Control!$B$18,J$4-1),0) -> 16885.205 | ... V11: =IF(Control!$B$7>0,Control!$B$64*12*POWER(1+Control!$B$18,V$4-1),0) -> 30323.402
A12: Repairs & maintenance | C12: =IF(Control!$B$7>0,Control!$B$65*12*POWER(1+Control!$B$18,C$4-1),0) -> 12000 | D12: =IF(Control!$B$7>0,Control!$B$65*12*POWER(1+Control!$B$18,D$4-1),0) -> 12600 | E12: =IF(Control!$B$7>0,Control!$B$65*12*POWER(1+Control!$B$18,E$4-1),0) -> 13230 | F12: =IF(Control!$B$7>0,Control!$B$65*12*POWER(1+Control!$B$18,F$4-1),0) -> 13891.5 | G12: =IF(Control!$B$7>0,Control!$B$65*12*POWER(1+Control!$B$18,G$4-1),0) -> 14586.075 | H12: =IF(Control!$B$7>0,Control!$B$65*12*POWER(1+Control!$B$18,H$4-1),0) -> 15315.379 | I12: =IF(Control!$B$7>0,Control!$B$65*12*POWER(1+Control!$B$18,I$4-1),0) -> 16081.148 | J12: =IF(Control!$B$7>0,Control!$B$65*12*POWER(1+Control!$B$18,J$4-1),0) -> 16885.205 | ... V12: =IF(Control!$B$7>0,Control!$B$65*12*POWER(1+Control!$B$18,V$4-1),0) -> 30323.402
A13: Levies | C13: =IF(Control!$B$7>0,Control!$B$66*12*POWER(1+Control!$B$18,C$4-1),0) -> 45600 | D13: =IF(Control!$B$7>0,Control!$B$66*12*POWER(1+Control!$B$18,D$4-1),0) -> 47880 | E13: =IF(Control!$B$7>0,Control!$B$66*12*POWER(1+Control!$B$18,E$4-1),0) -> 50274 | F13: =IF(Control!$B$7>0,Control!$B$66*12*POWER(1+Control!$B$18,F$4-1),0) -> 52787.7 | G13: =IF(Control!$B$7>0,Control!$B$66*12*POWER(1+Control!$B$18,G$4-1),0) -> 55427.085 | H13: =IF(Control!$B$7>0,Control!$B$66*12*POWER(1+Control!$B$18,H$4-1),0) -> 58198.439 | I13: =IF(Control!$B$7>0,Control!$B$66*12*POWER(1+Control!$B$18,I$4-1),0) -> 61108.361 | J13: =IF(Control!$B$7>0,Control!$B$66*12*POWER(1+Control!$B$18,J$4-1),0) -> 64163.779 | ... V13: =IF(Control!$B$7>0,Control!$B$66*12*POWER(1+Control!$B$18,V$4-1),0) -> 115228.93
A14: FF&E / capex reserve | C14: =C8*Control!$B$26 -> 21720 | D14: =D8*Control!$B$26 -> 22806 | E14: =E8*Control!$B$26 -> 23946.3 | F14: =F8*Control!$B$26 -> 25143.615 | G14: =G8*Control!$B$26 -> 26400.796 | H14: =H8*Control!$B$26 -> 27720.836 | I14: =I8*Control!$B$26 -> 29106.877 | J14: =J8*Control!$B$26 -> 30562.221 | ... V14: =V8*Control!$B$26 -> 54885.358
A15: TOTAL EXPENSES | C15: =SUM(C10:C14) -> 139920 | D15: =SUM(D10:D14) -> 146916 | E15: =SUM(E10:E14) -> 154261.8 | F15: =SUM(F10:F14) -> 161974.89 | G15: =SUM(G10:G14) -> 170073.63 | H15: =SUM(H10:H14) -> 178577.32 | I15: =SUM(I10:I14) -> 187506.18 | J15: =SUM(J10:J14) -> 196881.49 | ... V15: =SUM(V10:V14) -> 353570.87
A16: NET OPERATING INCOME (NOI, pre-tax) | C16: =C8-C15 -> 403080 | D16: =D8-D15 -> 423234 | E16: =E8-E15 -> 444395.7 | F16: =F8-F15 -> 466615.49 | G16: =G8-G15 -> 489946.26 | H16: =H8-H15 -> 514443.57 | I16: =I8-I15 -> 540165.75 | J16: =J8-J15 -> 567174.04 | ... V16: =V8-V15 -> 1018563.1
A17: Income tax | C17: =-C16*Control!$B$23 -> -108831.6 | D17: =-D16*Control!$B$23 -> -114273.18 | E17: =-E16*Control!$B$23 -> -119986.84 | F17: =-F16*Control!$B$23 -> -125986.18 | G17: =-G16*Control!$B$23 -> -132285.49 | H17: =-H16*Control!$B$23 -> -138899.76 | I17: =-I16*Control!$B$23 -> -145844.75 | J17: =-J16*Control!$B$23 -> -153136.99 | ... V17: =-V16*Control!$B$23 -> -275012.03
A18: NET PROFIT AFTER TAX | C18: =C16+C17 -> 294248.4 | D18: =D16+D17 -> 308960.82 | E18: =E16+E17 -> 324408.86 | F18: =F16+F17 -> 340629.3 | G18: =G16+G17 -> 357660.77 | H18: =H16+H17 -> 375543.81 | I18: =I16+I17 -> 394321 | J18: =J16+J17 -> 414037.05 | ... V18: =V16+V17 -> 743551.05

Sheet Menlyn P&L
A1: MENLYN MAIN — P&L (annual, 20-year)
A2: Long-term residential rental only. After reserve, after tax.
A4: Year | C4: 1 | D4: 2 | E4: 3 | F4: 4 | G4: 5 | H4: 6 | I4: 7 | J4: 8 | K4: 9 | L4: 10 | M4: 11 | N4: 12 | O4: 13 | P4: 14 | Q4: 15 | R4: 16 | S4: 17 | T4: 18 | U4: 19 | V4: 20
A6: GROSS REVENUE (rental) | C6: =IF(Control!$B$8>0,Control!$B$68*12*POWER(1+Control!$B$17,C$4-1),0) -> 336000 | D6: =IF(Control!$B$8>0,Control!$B$68*12*POWER(1+Control!$B$17,D$4-1),0) -> 352800 | E6: =IF(Control!$B$8>0,Control!$B$68*12*POWER(1+Control!$B$17,E$4-1),0) -> 370440 | F6: =IF(Control!$B$8>0,Control!$B$68*12*POWER(1+Control!$B$17,F$4-1),0) -> 388962 | G6: =IF(Control!$B$8>0,Control!$B$68*12*POWER(1+Control!$B$17,G$4-1),0) -> 408410.1 | H6: =IF(Control!$B$8>0,Control!$B$68*12*POWER(1+Control!$B$17,H$4-1),0) -> 428830.61 | I6: =IF(Control!$B$8>0,Control!$B$68*12*POWER(1+Control!$B$17,I$4-1),0) -> 450272.14 | J6: =IF(Control!$B$8>0,Control!$B$68*12*POWER(1+Control!$B$17,J$4-1),0) -> 472785.74 | ... V6: =IF(Control!$B$8>0,Control!$B$68*12*POWER(1+Control!$B$17,V$4-1),0) -> 849055.27
A7: OPERATING EXPENSES
A8: Utilities & municipal | C8: =IF(Control!$B$8>0,Control!$B$70*12*POWER(1+Control!$B$18,C$4-1),0) -> 10800 | D8: =IF(Control!$B$8>0,Control!$B$70*12*POWER(1+Control!$B$18,D$4-1),0) -> 11340 | E8: =IF(Control!$B$8>0,Control!$B$70*12*POWER(1+Control!$B$18,E$4-1),0) -> 11907 | F8: =IF(Control!$B$8>0,Control!$B$70*12*POWER(1+Control!$B$18,F$4-1),0) -> 12502.35 | G8: =IF(Control!$B$8>0,Control!$B$70*12*POWER(1+Control!$B$18,G$4-1),0) -> 13127.468 | H8: =IF(Control!$B$8>0,Control!$B$70*12*POWER(1+Control!$B$18,H$4-1),0) -> 13783.841 | I8: =IF(Control!$B$8>0,Control!$B$70*12*POWER(1+Control!$B$18,I$4-1),0) -> 14473.033 | J8: =IF(Control!$B$8>0,Control!$B$70*12*POWER(1+Control!$B$18,J$4-1),0) -> 15196.685 | ... V8: =IF(Control!$B$8>0,Control!$B$70*12*POWER(1+Control!$B$18,V$4-1),0) -> 27291.062
A9: Repairs & maintenance | C9: =IF(Control!$B$8>0,Control!$B$71*12*POWER(1+Control!$B$18,C$4-1),0) -> 12000 | D9: =IF(Control!$B$8>0,Control!$B$71*12*POWER(1+Control!$B$18,D$4-1),0) -> 12600 | E9: =IF(Control!$B$8>0,Control!$B$71*12*POWER(1+Control!$B$18,E$4-1),0) -> 13230 | F9: =IF(Control!$B$8>0,Control!$B$71*12*POWER(1+Control!$B$18,F$4-1),0) -> 13891.5 | G9: =IF(Control!$B$8>0,Control!$B$71*12*POWER(1+Control!$B$18,G$4-1),0) -> 14586.075 | H9: =IF(Control!$B$8>0,Control!$B$71*12*POWER(1+Control!$B$18,H$4-1),0) -> 15315.379 | I9: =IF(Control!$B$8>0,Control!$B$71*12*POWER(1+Control!$B$18,I$4-1),0) -> 16081.148 | J9: =IF(Control!$B$8>0,Control!$B$71*12*POWER(1+Control!$B$18,J$4-1),0) -> 16885.205 | ... V9: =IF(Control!$B$8>0,Control!$B$71*12*POWER(1+Control!$B$18,V$4-1),0) -> 30323.402
A10: Levies / rates | C10: =IF(Control!$B$8>0,Control!$B$72*12*POWER(1+Control!$B$18,C$4-1),0) -> 42000 | D10: =IF(Control!$B$8>0,Control!$B$72*12*POWER(1+Control!$B$18,D$4-1),0) -> 44100 | E10: =IF(Control!$B$8>0,Control!$B$72*12*POWER(1+Control!$B$18,E$4-1),0) -> 46305 | F10: =IF(Control!$B$8>0,Control!$B$72*12*POWER(1+Control!$B$18,F$4-1),0) -> 48620.25 | G10: =IF(Control!$B$8>0,Control!$B$72*12*POWER(1+Control!$B$18,G$4-1),0) -> 51051.262 | H10: =IF(Control!$B$8>0,Control!$B$72*12*POWER(1+Control!$B$18,H$4-1),0) -> 53603.826 | I10: =IF(Control!$B$8>0,Control!$B$72*12*POWER(1+Control!$B$18,I$4-1),0) -> 56284.017 | J10: =IF(Control!$B$8>0,Control!$B$72*12*POWER(1+Control!$B$18,J$4-1),0) -> 59098.218 | ... V10: =IF(Control!$B$8>0,Control!$B$72*12*POWER(1+Control!$B$18,V$4-1),0) -> 106131.91
A11: FF&E / capex reserve | C11: =C6*Control!$B$26 -> 13440 | D11: =D6*Control!$B$26 -> 14112 | E11: =E6*Control!$B$26 -> 14817.6 | F11: =F6*Control!$B$26 -> 15558.48 | G11: =G6*Control!$B$26 -> 16336.404 | H11: =H6*Control!$B$26 -> 17153.224 | I11: =I6*Control!$B$26 -> 18010.885 | J11: =J6*Control!$B$26 -> 18911.43 | ... V11: =V6*Control!$B$26 -> 33962.211
A12: TOTAL EXPENSES | C12: =SUM(C8:C11) -> 78240 | D12: =SUM(D8:D11) -> 82152 | E12: =SUM(E8:E11) -> 86259.6 | F12: =SUM(F8:F11) -> 90572.58 | G12: =SUM(G8:G11) -> 95101.209 | H12: =SUM(H8:H11) -> 99856.269 | I12: =SUM(I8:I11) -> 104849.08 | J12: =SUM(J8:J11) -> 110091.54 | ... V12: =SUM(V8:V11) -> 197708.58
A13: NET OPERATING INCOME (NOI, pre-tax) | C13: =C6-C12 -> 257760 | D13: =D6-D12 -> 270648 | E13: =E6-E12 -> 284180.4 | F13: =F6-F12 -> 298389.42 | G13: =G6-G12 -> 313308.89 | H13: =H6-H12 -> 328974.34 | I13: =I6-I12 -> 345423.05 | J13: =J6-J12 -> 362694.2 | ... V13: =V6-V12 -> 651346.68
A14: Income tax | C14: =-C13*Control!$B$23 -> -69595.2 | D14: =-D13*Control!$B$23 -> -73074.96 | E14: =-E13*Control!$B$23 -> -76728.708 | F14: =-F13*Control!$B$23 -> -80565.143 | G14: =-G13*Control!$B$23 -> -84593.401 | H14: =-H13*Control!$B$23 -> -88823.071 | I14: =-I13*Control!$B$23 -> -93264.224 | J14: =-J13*Control!$B$23 -> -97927.435 | ... V14: =-V13*Control!$B$23 -> -175863.6
A15: NET PROFIT AFTER TAX | C15: =C13+C14 -> 188164.8 | D15: =D13+D14 -> 197573.04 | E15: =E13+E14 -> 207451.69 | F15: =F13+F14 -> 217824.28 | G15: =G13+G14 -> 228715.49 | H15: =H13+H14 -> 240151.26 | I15: =I13+I14 -> 252158.83 | J15: =J13+J14 -> 264766.77 | ... V15: =V13+V14 -> 475483.08

Sheet Valuation
A1: PROPERTY VALUATION — independent (income & comparable, NOT back-solved from buy-in)
A2: Two industry methods per asset. Partner share % inputs on Control include/exclude each property from investor economics; 0% excludes, >0% includes. Winchester is a development expansion option and only activates if African Sky share > 0%.
A4: Valuation basis | C4: African Sky | D4: Beachside | E4: Menlyn | F4: Portfolio
A5: In-place annual NOI (active properties only; AS reflects Winchester only if expansion is active) | C5: ='African Sky P&L'!D26 -> 2046245.2 | D5: ='Beachside P&L'!C16 -> 403080 | E5: ='Menlyn P&L'!C13 -> 257760 | F5: =SUM(C5:E5) -> 2707085.2
A6: Market cap rate (income approach) | C6: =Control!$B$74 -> 0.1 | D6: =Control!$B$75 -> 0.075 | E6: =Control!B76 -> 0.085
A7: Income-capitalised value (NOI ÷ cap rate) | C7: =IFERROR(C5/C6,0) -> 20462452 | D7: =IFERROR(D5/D6,0) -> 5374400 | E7: =IFERROR(E5/E6,0) -> 3032470.6
A8: Independent comparable value (CMA input — editable; income approach corroborates below) | C8: =IF(Control!$B$5>0,Control!$B$77+IF(AND(Control!$B$6="Y",Control!$B$5>0),Control!$B$40,0),0) -> 6000000 | D8: =IF(Control!$B$7>0,4000000,0) -> 4000000 | E8: =IF(Control!$B$8>0,2900000,0) -> 2900000 | F8: =SUM(C8:E8) -> 12900000
A9: ADOPTED property value (conservative) | C9: =C8 -> 6000000 | D9: =D8 -> 4000000 | E9: =E8 -> 2900000 | F9: =SUM(C9:E9) -> 12900000
A10: Partner NAV @ property-specific % | C10: =C9*Control!$B$5 -> 3000000 | D10: =D9*Control!$B$7 -> 2000000 | E10: =E9*Control!$B$8 -> 1450000 | F10: =SUM(C10:E10) -> 6450000
A11: Income approach vs adopted (×, >1 = conservative) | C11: =IFERROR(C7/C9,0) -> 3.4104086 | D11: =IFERROR(D7/D9,0) -> 1.3436 | E11: =IFERROR(E7/E9,0) -> 1.0456795
A12: NOI yield on adopted value | C12: =IFERROR(C5/C9,0) -> 0.34104086 | D12: =IFERROR(D5/D9,0) -> 0.10077 | E12: =IFERROR(E5/E9,0) -> 0.088882759
A13: Memo: African Sky operating-business value (meals+tours net × 3, indicative) | C13: =IF(Control!$B$5>0,(('African Sky P&L'!D13-'African Sky P&L'!D18)+('African Sky P&L'!D14-'African Sky P&L'!D19))*3,0) -> 2427074
A15: v7.8 note: Beachside & Menlyn adopted values are now independent CMA inputs (D8/E8), no longer buy-in×2. Income-capitalised values (row 7) corroborate higher. Internal estimates pending a registered (SACPVP) valuation.

Sheet Portfolio NewCo
A1: PORTFOLIO — NewCo consolidated (20-year)
A2: NewCo owns 100% of the three properties. Partner owns 50% of NewCo. Distributions = 50% of after-tax profit, less any capex funded from NewCo cash.
A4: Year | B4: 1 | C4: 2 | D4: 3 | E4: 4 | F4: 5 | G4: 6 | H4: 7 | I4: 8 | J4: 9 | K4: 10 | L4: 11 | M4: 12 | N4: 13 | O4: 14 | P4: 15 | Q4: 16 | R4: 17 | S4: 18 | T4: 19 | U4: 20
A6: African Sky NOI | B6: ='African Sky P&L'!C26 -> 1948804.9 | C6: ='African Sky P&L'!D26 -> 2046245.2 | D6: ='African Sky P&L'!E26 -> 2148557.4 | E6: ='African Sky P&L'!F26 -> 2255985.3 | F6: ='African Sky P&L'!G26 -> 2368784.6 | G6: ='African Sky P&L'!H26 -> 2487223.8 | H6: ='African Sky P&L'!I26 -> 2611585 | I6: ='African Sky P&L'!J26 -> 2742164.2 | ... U6: ='African Sky P&L'!V26 -> 4924533
A7: Beachside NOI | B7: ='Beachside P&L'!C16 -> 403080 | C7: ='Beachside P&L'!D16 -> 423234 | D7: ='Beachside P&L'!E16 -> 444395.7 | E7: ='Beachside P&L'!F16 -> 466615.49 | F7: ='Beachside P&L'!G16 -> 489946.26 | G7: ='Beachside P&L'!H16 -> 514443.57 | H7: ='Beachside P&L'!I16 -> 540165.75 | I7: ='Beachside P&L'!J16 -> 567174.04 | ... U7: ='Beachside P&L'!V16 -> 1018563.1
A8: Menlyn NOI | B8: ='Menlyn P&L'!C13 -> 257760 | C8: ='Menlyn P&L'!D13 -> 270648 | D8: ='Menlyn P&L'!E13 -> 284180.4 | E8: ='Menlyn P&L'!F13 -> 298389.42 | F8: ='Menlyn P&L'!G13 -> 313308.89 | G8: ='Menlyn P&L'!H13 -> 328974.34 | H8: ='Menlyn P&L'!I13 -> 345423.05 | I8: ='Menlyn P&L'!J13 -> 362694.2 | ... U8: ='Menlyn P&L'!V13 -> 651346.68
A9: PORTFOLIO NOI | B9: =SUM(B6:B8) -> 2609644.9 | C9: =SUM(C6:C8) -> 2740127.2 | D9: =SUM(D6:D8) -> 2877133.5 | E9: =SUM(E6:E8) -> 3020990.2 | F9: =SUM(F6:F8) -> 3172039.7 | G9: =SUM(G6:G8) -> 3330641.7 | H9: =SUM(H6:H8) -> 3497173.8 | I9: =SUM(I6:I8) -> 3672032.5 | ... U9: =SUM(U6:U8) -> 6594442.8
A10: African Sky NPAT | B10: ='African Sky P&L'!C28 -> 1422627.6 | C10: ='African Sky P&L'!D28 -> 1493759 | D10: ='African Sky P&L'!E28 -> 1568446.9 | E10: ='African Sky P&L'!F28 -> 1646869.3 | F10: ='African Sky P&L'!G28 -> 1729212.7 | G10: ='African Sky P&L'!H28 -> 1815673.4 | H10: ='African Sky P&L'!I28 -> 1906457 | I10: ='African Sky P&L'!J28 -> 2001779.9 | ... U10: ='African Sky P&L'!V28 -> 3594909.1
A11: Beachside NPAT | B11: ='Beachside P&L'!C18 -> 294248.4 | C11: ='Beachside P&L'!D18 -> 308960.82 | D11: ='Beachside P&L'!E18 -> 324408.86 | E11: ='Beachside P&L'!F18 -> 340629.3 | F11: ='Beachside P&L'!G18 -> 357660.77 | G11: ='Beachside P&L'!H18 -> 375543.81 | H11: ='Beachside P&L'!I18 -> 394321 | I11: ='Beachside P&L'!J18 -> 414037.05 | ... U11: ='Beachside P&L'!V18 -> 743551.05
A12: Menlyn NPAT | B12: ='Menlyn P&L'!C15 -> 188164.8 | C12: ='Menlyn P&L'!D15 -> 197573.04 | D12: ='Menlyn P&L'!E15 -> 207451.69 | E12: ='Menlyn P&L'!F15 -> 217824.28 | F12: ='Menlyn P&L'!G15 -> 228715.49 | G12: ='Menlyn P&L'!H15 -> 240151.26 | H12: ='Menlyn P&L'!I15 -> 252158.83 | I12: ='Menlyn P&L'!J15 -> 264766.77 | ... U12: ='Menlyn P&L'!V15 -> 475483.08
A13: PORTFOLIO NPAT | B13: =SUM(B10:B12) -> 1905040.8 | C13: =SUM(C10:C12) -> 2000292.8 | D13: =SUM(D10:D12) -> 2100307.5 | E13: =SUM(E10:E12) -> 2205322.9 | F13: =SUM(F10:F12) -> 2315589 | G13: =SUM(G10:G12) -> 2431368.4 | H13: =SUM(H10:H12) -> 2552936.9 | I13: =SUM(I10:I12) -> 2680583.7 | ... U13: =SUM(U10:U12) -> 4813943.2
A14: Less: Winchester construction capex | B14: =-IF(AND(Control!$B$5>0,Control!$B$6="Y",B$4=Control!$B$39-1),Control!$B$40,0) -> 0 | C14: =-IF(AND(Control!$B$5>0,Control!$B$6="Y",C$4=Control!$B$39-1),Control!$B$40,0) -> 0 | D14: =-IF(AND(Control!$B$5>0,Control!$B$6="Y",D$4=Control!$B$39-1),Control!$B$40,0) -> 0 | E14: =-IF(AND(Control!$B$5>0,Control!$B$6="Y",E$4=Control!$B$39-1),Control!$B$40,0) -> 0 | F14: =-IF(AND(Control!$B$5>0,Control!$B$6="Y",F$4=Control!$B$39-1),Control!$B$40,0) -> 0 | G14: =-IF(AND(Control!$B$5>0,Control!$B$6="Y",G$4=Control!$B$39-1),Control!$B$40,0) -> 0 | H14: =-IF(AND(Control!$B$5>0,Control!$B$6="Y",H$4=Control!$B$39-1),Control!$B$40,0) -> 0 | I14: =-IF(AND(Control!$B$5>0,Control!$B$6="Y",I$4=Control!$B$39-1),Control!$B$40,0) -> 0 | ... U14: =-IF(AND(Control!$B$5>0,Control!$B$6="Y",U$4=Control!$B$39-1),Control!$B$40,0) -> 0
A15: Distributable profit | B15: =B13+B14 -> 1905040.8 | C15: =C13+C14 -> 2000292.8 | D15: =D13+D14 -> 2100307.5 | E15: =E13+E14 -> 2205322.9 | F15: =F13+F14 -> 2315589 | G15: =G13+G14 -> 2431368.4 | H15: =H13+H14 -> 2552936.9 | I15: =I13+I14 -> 2680583.7 | ... U15: =U13+U14 -> 4813943.2
A16: Partner distribution (property-specific %) | B16: =SUM(B24:B26) -> 952520.4 | C16: =SUM(C24:C26) -> 1000146.4 | D16: =SUM(D24:D26) -> 1050153.7 | E16: =SUM(E24:E26) -> 1102661.4 | F16: =SUM(F24:F26) -> 1157794.5 | G16: =SUM(G24:G26) -> 1215684.2 | H16: =SUM(H24:H26) -> 1276468.4 | I16: =SUM(I24:I26) -> 1340291.9 | ... U16: =SUM(U24:U26) -> 2406971.6
A17: Cumulative partner distribution | B17: =B16 -> 952520.4 | C17: =B17+C16 -> 1952666.8 | D17: =C17+D16 -> 3002820.6 | E17: =D17+E16 -> 4105482 | F17: =E17+F16 -> 5263276.5 | G17: =F17+G16 -> 6478960.7 | H17: =G17+H16 -> 7755429.1 | I17: =H17+I16 -> 9095721 | J17: =I17+J16 -> 10503027 | ... U17: =T17+U16 -> 31495996
A18: Partner cash yield (on total buy-in) | B18: =B16/Control!$B$15 -> 0.14883131 | C18: =C16/Control!$B$15 -> 0.15627288 | D18: =D16/Control!$B$15 -> 0.16408652 | E18: =E16/Control!$B$15 -> 0.17229085 | F18: =F16/Control!$B$15 -> 0.18090539 | G18: =G16/Control!$B$15 -> 0.18995066 | H18: =H16/Control!$B$15 -> 0.19944819 | I18: =I16/Control!$B$15 -> 0.2094206 | ... U18: =U16/Control!$B$15 -> 0.37608931
A19: Average annual cash yield (on buy-in) | B19: =AVERAGE(B18:U18) -> 0.24606247
A20: DISTRIBUTION ALLOCATION HELPER — driven by Control column C
A21: African Sky distributable cash | B21: =B10+B14 -> 1422627.6 | C21: =C10+C14 -> 1493759 | D21: =D10+D14 -> 1568446.9 | E21: =E10+E14 -> 1646869.3 | F21: =F10+F14 -> 1729212.7 | G21: =G10+G14 -> 1815673.4 | H21: =H10+H14 -> 1906457 | I21: =I10+I14 -> 2001779.9 | ... U21: =U10+U14 -> 3594909.1
A22: Beachside distributable cash | B22: =B11 -> 294248.4 | C22: =C11 -> 308960.82 | D22: =D11 -> 324408.86 | E22: =E11 -> 340629.3 | F22: =F11 -> 357660.77 | G22: =G11 -> 375543.81 | H22: =H11 -> 394321 | I22: =I11 -> 414037.05 | ... U22: =U11 -> 743551.05
A23: Menlyn distributable cash | B23: =B12 -> 188164.8 | C23: =C12 -> 197573.04 | D23: =D12 -> 207451.69 | E23: =E12 -> 217824.28 | F23: =F12 -> 228715.49 | G23: =G12 -> 240151.26 | H23: =H12 -> 252158.83 | I23: =I12 -> 264766.77 | ... U23: =U12 -> 475483.08
A24: African Sky partner distribution | B24: =B21*Control!$C$5 -> 711313.8 | C24: =C21*Control!$C$5 -> 746879.49 | D24: =D21*Control!$C$5 -> 784223.46 | E24: =E21*Control!$C$5 -> 823434.63 | F24: =F21*Control!$C$5 -> 864606.37 | G24: =G21*Control!$C$5 -> 907836.68 | H24: =H21*Control!$C$5 -> 953228.52 | I24: =I21*Control!$C$5 -> 1000889.9 | ... U24: =U21*Control!$C$5 -> 1797454.5
A25: Beachside partner distribution | B25: =B22*Control!$C$7 -> 147124.2 | C25: =C22*Control!$C$7 -> 154480.41 | D25: =D22*Control!$C$7 -> 162204.43 | E25: =E22*Control!$C$7 -> 170314.65 | F25: =F22*Control!$C$7 -> 178830.38 | G25: =G22*Control!$C$7 -> 187771.9 | H25: =H22*Control!$C$7 -> 197160.5 | I25: =I22*Control!$C$7 -> 207018.52 | ... U25: =U22*Control!$C$7 -> 371775.53
A26: Menlyn partner distribution | B26: =B23*Control!$C$8 -> 94082.4 | C26: =C23*Control!$C$8 -> 98786.52 | D26: =D23*Control!$C$8 -> 103725.85 | E26: =E23*Control!$C$8 -> 108912.14 | F26: =F23*Control!$C$8 -> 114357.75 | G26: =G23*Control!$C$8 -> 120075.63 | H26: =H23*Control!$C$8 -> 126079.41 | I26: =I23*Control!$C$8 -> 132383.38 | ... U26: =U23*Control!$C$8 -> 237741.54
A27: African Sky cumulative distribution | B27: =B24 -> 711313.8 | C27: =B27+C24 -> 1458193.3 | D27: =C27+D24 -> 2242416.7 | E27: =D27+E24 -> 3065851.4 | F27: =E27+F24 -> 3930457.7 | G27: =F27+G24 -> 4838294.4 | H27: =G27+H24 -> 5791523 | I27: =H27+I24 -> 6792412.9 | J27: =I27+J24 -> 7843347.3 | ... U27: =T27+U24 -> 23520269
A28: Beachside cumulative distribution | B28: =B25 -> 147124.2 | C28: =B28+C25 -> 301604.61 | D28: =C28+D25 -> 463809.04 | E28: =D28+E25 -> 634123.69 | F28: =E28+F25 -> 812954.08 | G28: =F28+G25 -> 1000726 | H28: =G28+H25 -> 1197886.5 | I28: =H28+I25 -> 1404905 | J28: =I28+J25 -> 1622274.5 | ... U28: =T28+U25 -> 4864802
A29: Menlyn cumulative distribution | B29: =B26 -> 94082.4 | C29: =B29+C26 -> 192868.92 | D29: =C29+D26 -> 296594.77 | E29: =D29+E26 -> 405506.9 | F29: =E29+F26 -> 519864.65 | G29: =F29+G26 -> 639940.28 | H29: =G29+H26 -> 766019.7 | I29: =H29+I26 -> 898403.08 | J29: =I29+J26 -> 1037405.6 | ... U29: =T29+U26 -> 3110924.3

Sheet INV - Property Breakdown
A1: PROPERTY OVERVIEW + PROPERTY-SPECIFIC PARTNER ECONOMICS
A2: Scenario share inputs include/exclude each property: 0% excludes, >0% includes at selected partner share. Winchester follows African Sky and its expansion option.
A4: TABLE 1 — PROPERTY / ASSET METRICS
A5: Metric | B5: African Sky Villas | C5: Beachside Escape | D5: Menlyn Main | E5: Portfolio
A6: Description | B6: 3-villa short-let / hospitality asset: African Sky Villa, Remington Villa and planned Winchester, with meals plus tours & activities. | C6: Big Bay property with mixed long-term rental plus peak holiday letting during Dec/Jan. | D6: Long-term residential rental apartment with recurring monthly rental income. | E6: Combined NewCo property portfolio.
A7: Revenue basis | B7: Accommodation + meals + tours & activities. | C7: 10 months long-term rent + 2 peak holiday months. | D7: Monthly long-term rental. | E7: All property revenue streams consolidated.
A8: Adopted property value (100%) | B8: =Valuation!C9 -> 6000000 | C8: =Valuation!D9 -> 4000000 | D8: =Valuation!E9 -> 2900000 | E8: =Valuation!F9 -> 12900000
A9: Year 1 NOI | B9: ='Portfolio NewCo'!B6 -> 1948804.9 | C9: ='Portfolio NewCo'!B7 -> 403080 | D9: ='Portfolio NewCo'!B8 -> 257760 | E9: ='Portfolio NewCo'!B9 -> 2609644.9
A10: NOI yield on adopted value | B10: ='INV - Property KPIs'!B9 -> 0.34131153 | C10: ='INV - Property KPIs'!C9 -> 0.10589247 | D10: ='INV - Property KPIs'!D9 -> 0.093400966 | E10: ='INV - Property KPIs'!F9 -> 0.21258154
A11: Implied value / NOI multiple | B11: ='INV - Property KPIs'!B10 -> 2.9298747 | C11: ='INV - Property KPIs'!C10 -> 9.4435417 | D11: ='INV - Property KPIs'!D10 -> 10.706527 | E11: ='INV - Property KPIs'!F10 -> 4.7040773
A13: TABLE 2 — PROPERTY-SPECIFIC PARTNER / INVESTOR ECONOMICS
A14: Metric | B14: African Sky Villas | C14: Beachside Escape | D14: Menlyn Main | E14: Portfolio
A15: Partner share / NAV @ property-specific % | B15: =Valuation!C10 -> 3000000 | C15: =Valuation!D10 -> 2000000 | D15: =Valuation!E10 -> 1450000 | E15: =Valuation!F10 -> 6450000
A16: Partner buy-in component | B16: ='INV - Property KPIs'!B5 -> 3000000 | C16: ='INV - Property KPIs'!C5 -> 2000000 | D16: ='INV - Property KPIs'!D5 -> 1400000 | E16: ='INV - Property KPIs'!F5 -> 6400000
A17: 5-year total IRR | B17: ='INV - Property KPIs'!B13 -> 0.27893316 | C17: ='INV - Property KPIs'!C13 -> 0.11237279 | D17: ='INV - Property KPIs'!D13 -> 0.11227215 | E17: ='INV - Property KPIs'!F13 -> 0.19036144
A18: Year-1 cash yield | B18: ='African Sky P&L'!C28*Control!$B$5/Control!$B$12 -> 0.2371046 | C18: ='Beachside P&L'!C18*Control!$B$7/Control!$B$13 -> 0.0735621 | D18: =IFERROR('Menlyn P&L'!C15*Control!$B$8/Control!$B$14,0) -> 0.067201714 | E18: ='Portfolio NewCo'!B16/Control!$B$15 -> 0.14883131
A19: 5-year total MOIC | B19: ='INV - Property KPIs'!B12 -> 2.5098573 | C19: ='INV - Property KPIs'!C12 -> 1.6061817 | D19: ='INV - Property KPIs'!D12 -> 1.6138832 | E19: ='INV - Property KPIs'!F12 -> 2.0314643
A20: 10-year total IRR | B20: ='INV - Property KPIs'!B16 -> 0.28494676 | C20: ='INV - Property KPIs'!C16 -> 0.11890725 | D20: ='INV - Property KPIs'!D16 -> 0.11511622 | E20: ='INV - Property KPIs'!F16 -> 0.19595828
A21: 10-year total MOIC | B21: ='INV - Property KPIs'!B15 -> 4.5134371 | C21: ='INV - Property KPIs'!C15 -> 2.4564171 | D21: ='INV - Property KPIs'!D15 -> 2.4311012 | E21: ='INV - Property KPIs'!F15 -> 3.4151074
A22: 15-year total IRR | B22: ='INV - Property KPIs'!B19 -> 0.28639638 | C22: ='INV - Property KPIs'!C19 -> 0.12100886 | D22: ='INV - Property KPIs'!D19 -> 0.11603551 | E22: ='INV - Property KPIs'!F19 -> 0.19757586
A23: 15-year total MOIC | B23: ='INV - Property KPIs'!B18 -> 7.0705692 | C23: ='INV - Property KPIs'!C18 -> 3.5415569 | D23: ='INV - Property KPIs'!D18 -> 3.4741015 | E23: ='INV - Property KPIs'!F18 -> 5.1810255
A24: 20-year total IRR
A25: 20-year total MOIC | B25: ='INV - Property KPIs'!B21 -> 10.33419 | C25: ='INV - Property KPIs'!C21 -> 4.9265009 | D25: ='INV - Property KPIs'!D21 -> 4.8052636 | E25: ='INV - Property KPIs'!F21 -> 7.4348343
A26: African Sky Villa accommodation | B26: Occupied unit-nights × ADR incl. extra guests | C26: ='African Sky P&L'!C7 -> 1306539.8 | D26: ='African Sky P&L'!D7 -> 1371866.8 | E26: Short-let villa revenue
A27: Remington Villa accommodation | B27: Occupied unit-nights × ADR incl. extra guests | C27: ='African Sky P&L'!C8 -> 959125 | D27: ='African Sky P&L'!D8 -> 1007081.3 | E27: Short-let villa revenue
A28: Winchester accommodation | B28: Online-from-year × ADR | C28: ='African Sky P&L'!C9 -> 0 | D28: ='African Sky P&L'!D9 -> 0 | E28: Planned unit online from model year
A29: Meals income | B29: Guest-nights × meal take-up × breakfast/dinner pricing | C29: ='African Sky P&L'!C13 -> 510275.42 | D29: ='African Sky P&L'!D13 -> 535789.2 | E29: Breakfast + dinner income
A30: Tours & activities income | B30: Linked tour revenue assumptions | C30: ='African Sky P&L'!C14 -> 2045556.5 | D30: ='African Sky P&L'!D14 -> 2147834.3 | E30: Linked from ASKY Tours Calcs
A31: Total gross revenue | B31: Sum of above streams | C31: ='African Sky P&L'!C15 -> 4821496.7 | D31: ='African Sky P&L'!D15 -> 5062571.5 | E31: Before operating expenses
A33: BEACHSIDE ESCAPE — revenue streams
A34: Revenue stream / driver | B34: Basis | C34: Year 1 | D34: Year 2 | E34: Notes
A35: Long-term rent | B35: Monthly rent × long-term months | C35: =Control!B54*Control!B55 -> 300000 | D35: =C35*(1+Control!B17) -> 315000 | E35: 10 long-term months per year
A36: Peak holiday lets | B36: Peak ADR × peak months × nights/month × occupancy | C36: =Control!B57*Control!B58*Control!B59*Control!B60 -> 243000 | D36: =C36*(1+Control!B17) -> 255150 | E36: Dec/Jan holiday letting
A37: Estimated gross revenue | B37: Long-term rent + peak holiday lets | C37: =SUM(C35:C36) -> 543000 | D37: =SUM(D35:D36) -> 570150 | E37: Before commission and operating expenses
A38: Year 1 NOI | B38: Portfolio NewCo Beachside NOI | C38: ='Portfolio NewCo'!B7 -> 403080 | D38: ='Portfolio NewCo'!C7 -> 423234 | E38: After model operating costs
A40: MENLYN MAIN — revenue streams
A41: Revenue stream / driver
A42: Long-term rental income | B42: Monthly rent × 12 | E42: Recurring monthly rental
A43: Estimated gross revenue | B43: Long-term rental income | C43: =Control!B68*12 -> 336000 | D43: =C43*(1+Control!B17) -> 352800 | E43: Before operating expenses
A44: Year 1 NOI | B44: Portfolio NewCo Menlyn NOI | C44: =C43 -> 336000 | D44: =D43 -> 352800 | E44: After model operating costs
C45: ='Portfolio NewCo'!B8 -> 257760 | D45: ='Portfolio NewCo'!C8 -> 270648

Sheet INV - 3-Statement Model
A1: 3-STATEMENT MODEL — NewCo consolidated + investor tracking
A2: Integrated model linked to Control, property P&Ls, Portfolio NewCo, Valuation, and Investor KPIs. Formation column shows today; Year 1–20 columns are live-linked forecast periods.
A3: Currency: ZAR. Base case: no external debt; distributable post-tax profit is paid out after Winchester construction capex is funded from NewCo cash.
A5: Year | B5: Formation / Today | C5: 1 | D5: 2 | E5: 3 | F5: 4 | G5: 5 | H5: 6 | I5: 7 | J5: 8 | K5: 9 | L5: 10 | M5: 11 | N5: 12 | O5: 13 | P5: 14 | Q5: 15 | R5: 16 | S5: 17 | T5: 18 | U5: 19 | V5: 20
A7: CONSOLIDATED INCOME STATEMENT
A8: Gross revenue | B8: =0 -> 0 | C8: =SUM('African Sky P&L'!C15,'Beachside P&L'!C8,'Menlyn P&L'!C6) -> 5700496.7 | D8: =SUM('African Sky P&L'!D15,'Beachside P&L'!D8,'Menlyn P&L'!D6) -> 5985521.5 | E8: =SUM('African Sky P&L'!E15,'Beachside P&L'!E8,'Menlyn P&L'!E6) -> 6284797.6 | F8: =SUM('African Sky P&L'!F15,'Beachside P&L'!F8,'Menlyn P&L'!F6) -> 6599037.5 | G8: =SUM('African Sky P&L'!G15,'Beachside P&L'!G8,'Menlyn P&L'!G6) -> 6928989.4 | H8: =SUM('African Sky P&L'!H15,'Beachside P&L'!H8,'Menlyn P&L'!H6) -> 7275438.8 | I8: =SUM('African Sky P&L'!I15,'Beachside P&L'!I8,'Menlyn P&L'!I6) -> 7639210.8 | J8: =SUM('African Sky P&L'!J15,'Beachside P&L'!J8,'Menlyn P&L'!J6) -> 8021171.3 | ... V8: =SUM('African Sky P&L'!V15,'Beachside P&L'!V8,'Menlyn P&L'!V6) -> 14404871
A9: Operating expenses | B9: =0 -> 0 | C9: =C8-C10 -> 3090851.8 | D9: =D8-D10 -> 3245394.4 | E9: =E8-E10 -> 3407664.1 | F9: =F8-F10 -> 3578047.3 | G9: =G8-G10 -> 3756949.6 | H9: =H8-H10 -> 3944797.1 | I9: =I8-I10 -> 4142037 | J9: =J8-J10 -> 4349138.8 | ... V9: =V8-V10 -> 7810428.5
A10: NET OPERATING INCOME (NOI) | B10: =0 -> 0 | C10: ='Portfolio NewCo'!B9 -> 2609644.9 | D10: ='Portfolio NewCo'!C9 -> 2740127.2 | E10: ='Portfolio NewCo'!D9 -> 2877133.5 | F10: ='Portfolio NewCo'!E9 -> 3020990.2 | G10: ='Portfolio NewCo'!F9 -> 3172039.7 | H10: ='Portfolio NewCo'!G9 -> 3330641.7 | I10: ='Portfolio NewCo'!H9 -> 3497173.8 | J10: ='Portfolio NewCo'!I9 -> 3672032.5 | ... V10: ='Portfolio NewCo'!U9 -> 6594442.8
A11: Income tax | B11: =0 -> 0 | C11: =C12-C10 -> -704604.13 | D11: =D12-D10 -> -739834.34 | E11: =E12-E10 -> -776826.05 | F11: =F12-F10 -> -815667.36 | G11: =G12-G10 -> -856450.72 | H11: =H12-H10 -> -899273.26 | I11: =I12-I10 -> -944236.92 | J11: =J12-J10 -> -991448.77 | ... V11: =V12-V10 -> -1780499.5
A12: NET PROFIT AFTER TAX (NPAT) | B12: =0 -> 0 | C12: ='Portfolio NewCo'!B13 -> 1905040.8 | D12: ='Portfolio NewCo'!C13 -> 2000292.8 | E12: ='Portfolio NewCo'!D13 -> 2100307.5 | F12: ='Portfolio NewCo'!E13 -> 2205322.9 | G12: ='Portfolio NewCo'!F13 -> 2315589 | H12: ='Portfolio NewCo'!G13 -> 2431368.4 | I12: ='Portfolio NewCo'!H13 -> 2552936.9 | J12: ='Portfolio NewCo'!I13 -> 2680583.7 | ... V12: ='Portfolio NewCo'!U13 -> 4813943.2
A13: NPAT margin | B13: ="" | C13: =IFERROR(C12/C8,0) -> 0.33418856 | D13: =IFERROR(D12/D8,0) -> 0.33418856 | E13: =IFERROR(E12/E8,0) -> 0.33418856 | F13: =IFERROR(F12/F8,0) -> 0.33418856 | G13: =IFERROR(G12/G8,0) -> 0.33418856 | H13: =IFERROR(H12/H8,0) -> 0.33418856 | I13: =IFERROR(I12/I8,0) -> 0.33418856 | J13: =IFERROR(J12/J8,0) -> 0.33418856 | ... V13: =IFERROR(V12/V8,0) -> 0.33418856
A15: INVESTOR — INCOME STATEMENT VIEW
A16: Blended partner ownership % | B16: =IFERROR(Valuation!$F$10/Valuation!$F$9,0) -> 0.5 | C16: =IFERROR(Valuation!$F$10/Valuation!$F$9,0) -> 0.5 | D16: =IFERROR(Valuation!$F$10/Valuation!$F$9,0) -> 0.5 | E16: =IFERROR(Valuation!$F$10/Valuation!$F$9,0) -> 0.5 | F16: =IFERROR(Valuation!$F$10/Valuation!$F$9,0) -> 0.5 | G16: =IFERROR(Valuation!$F$10/Valuation!$F$9,0) -> 0.5 | H16: =IFERROR(Valuation!$F$10/Valuation!$F$9,0) -> 0.5 | I16: =IFERROR(Valuation!$F$10/Valuation!$F$9,0) -> 0.5 | ... V16: =IFERROR(Valuation!$F$10/Valuation!$F$9,0) -> 0.5
A17: Investor share of NOI | B17: =0 -> 0 | C17: =C10*C16 -> 1304822.5 | D17: =D10*D16 -> 1370063.6 | E17: =E10*E16 -> 1438566.8 | F17: =F10*F16 -> 1510495.1 | G17: =G10*G16 -> 1586019.9 | H17: =H10*H16 -> 1665320.9 | I17: =I10*I16 -> 1748586.9 | J17: =J10*J16 -> 1836016.2 | ... V17: =V10*V16 -> 3297221.4
A18: Investor share of NPAT | B18: =0 -> 0 | C18: =C12*C16 -> 952520.4 | D18: =D12*D16 -> 1000146.4 | E18: =E12*E16 -> 1050153.7 | F18: =F12*F16 -> 1102661.4 | G18: =G12*G16 -> 1157794.5 | H18: =H12*H16 -> 1215684.2 | I18: =I12*I16 -> 1276468.4 | J18: =J12*J16 -> 1340291.9 | ... V18: =V12*V16 -> 2406971.6
A19: Cash-on-cash yield | B19: ="" | C19: ='INV - Investor KPIs'!C9 -> 0.14883131 | D19: ='INV - Investor KPIs'!D9 -> 0.15627288 | E19: ='INV - Investor KPIs'!E9 -> 0.16408652 | F19: ='INV - Investor KPIs'!F9 -> 0.17229085 | G19: ='INV - Investor KPIs'!G9 -> 0.18090539 | H19: ='INV - Investor KPIs'!H9 -> 0.18995066 | I19: ='INV - Investor KPIs'!I9 -> 0.19944819 | J19: ='INV - Investor KPIs'!J9 -> 0.2094206 | ... V19: ='INV - Investor KPIs'!V9 -> 0.37608931
A21: CONSOLIDATED BALANCE SHEET
A22: Cash | B22: =0 -> 0 | C22: =C46 -> 0 | D22: =D46 -> 0 | E22: =E46 -> 0 | F22: =F46 -> 0 | G22: =G46 -> 0 | H22: =H46 -> 0 | I22: =I46 -> 0 | J22: =J46 -> 0 | ... V22: =V46 -> 0
A23: Property assets / portfolio fair value | B23: =Valuation!$F$9 -> 12900000 | C23: =Valuation!$F$9*POWER(1+Control!$B$78,C$5) -> 13545000 | D23: =Valuation!$F$9*POWER(1+Control!$B$78,D$5) -> 14222250 | E23: =Valuation!$F$9*POWER(1+Control!$B$78,E$5) -> 14933363 | F23: =Valuation!$F$9*POWER(1+Control!$B$78,F$5) -> 15680031 | G23: =Valuation!$F$9*POWER(1+Control!$B$78,G$5) -> 16464032 | H23: =Valuation!$F$9*POWER(1+Control!$B$78,H$5) -> 17287234 | I23: =Valuation!$F$9*POWER(1+Control!$B$78,I$5) -> 18151595 | J23: =Valuation!$F$9*POWER(1+Control!$B$78,J$5) -> 19059175 | ... V23: =Valuation!$F$9*POWER(1+Control!$B$78,V$5) -> 34227540
A24: TOTAL ASSETS | B24: =SUM(B22:B23) -> 12900000 | C24: =SUM(C22:C23) -> 13545000 | D24: =SUM(D22:D23) -> 14222250 | E24: =SUM(E22:E23) -> 14933363 | F24: =SUM(F22:F23) -> 15680031 | G24: =SUM(G22:G23) -> 16464032 | H24: =SUM(H22:H23) -> 17287234 | I24: =SUM(I22:I23) -> 18151595 | ... V24: =SUM(V22:V23) -> 34227540
A25: Debt | B25: =0 -> 0 | C25: =0 -> 0 | D25: =0 -> 0 | E25: =0 -> 0 | F25: =0 -> 0 | G25: =0 -> 0 | H25: =0 -> 0 | I25: =0 -> 0 | ... V25: =0 -> 0
A26: TOTAL LIABILITIES | B26: =B25 -> 0 | C26: =C25 -> 0 | D26: =D25 -> 0 | E26: =E25 -> 0 | F26: =F25 -> 0 | G26: =G25 -> 0 | H26: =H25 -> 0 | I26: =I25 -> 0 | ... V26: =V25 -> 0
A27: Opening contributed property equity | B27: =Valuation!$F$9 -> 12900000 | C27: =Valuation!$F$9 -> 12900000 | D27: =Valuation!$F$9 -> 12900000 | E27: =Valuation!$F$9 -> 12900000 | F27: =Valuation!$F$9 -> 12900000 | G27: =Valuation!$F$9 -> 12900000 | H27: =Valuation!$F$9 -> 12900000 | I27: =Valuation!$F$9 -> 12900000 | ... V27: =Valuation!$F$9 -> 12900000
A28: Cumulative retained earnings | B28: =0 -> 0 | C28: =B28+C42+C44 -> 0 | D28: =C28+D42+D44 -> 0 | E28: =D28+E42+E44 -> 0 | F28: =E28+F42+F44 -> 0 | G28: =F28+G42+G44 -> 0 | H28: =G28+H42+H44 -> 0 | I28: =H28+I42+I44 -> 0 | J28: =I28+J42+J44 -> 0 | ... V28: =U28+V42+V44 -> 0
A29: Fair value / revaluation reserve | B29: =B30-B27-B28 -> 0 | C29: =C30-C27-C28 -> 645000 | D29: =D30-D27-D28 -> 1322250 | E29: =E30-E27-E28 -> 2033362.5 | F29: =F30-F27-F28 -> 2780030.6 | G29: =G30-G27-G28 -> 3564032.2 | H29: =H30-H27-H28 -> 4387233.8 | I29: =I30-I27-I28 -> 5251595.5 | ... V29: =V30-V27-V28 -> 21327540
A30: TOTAL EQUITY | B30: =B24-B26 -> 12900000 | C30: =C24-C26 -> 13545000 | D30: =D24-D26 -> 14222250 | E30: =E24-E26 -> 14933363 | F30: =F24-F26 -> 15680031 | G30: =G24-G26 -> 16464032 | H30: =H24-H26 -> 17287234 | I30: =I24-I26 -> 18151595 | ... V30: =V24-V26 -> 34227540
A31: TOTAL LIABILITIES + EQUITY | B31: =B26+B30 -> 12900000 | C31: =C26+C30 -> 13545000 | D31: =D26+D30 -> 14222250 | E31: =E26+E30 -> 14933363 | F31: =F26+F30 -> 15680031 | G31: =G26+G30 -> 16464032 | H31: =H26+H30 -> 17287234 | I31: =I26+I30 -> 18151595 | ... V31: =V26+V30 -> 34227540
A32: Balance sheet check | B32: =B24-B31 -> 0 | C32: =C24-C31 -> 0 | D32: =D24-D31 -> 0 | E32: =E24-E31 -> 0 | F32: =F24-F31 -> 0 | G32: =G24-G31 -> 0 | H32: =H24-H31 -> 0 | I32: =I24-I31 -> 0 | ... V32: =V24-V31 -> 0
A34: INVESTOR — BALANCE SHEET VIEW
A35: Partner NAV if exit this year | B35: =Valuation!$F$10 -> 6450000 | C35: ='INV - Investor KPIs'!C11 -> 6366150 | D35: ='INV - Investor KPIs'!D11 -> 6684457.5 | E35: ='INV - Investor KPIs'!E11 -> 7018680.4 | F35: ='INV - Investor KPIs'!F11 -> 7369614.4 | G35: ='INV - Investor KPIs'!G11 -> 7738095.1 | H35: ='INV - Investor KPIs'!H11 -> 8124999.9 | I35: ='INV - Investor KPIs'!I11 -> 8531249.9 | J35: ='INV - Investor KPIs'!J11 -> 8957812.4 | ... V35: ='INV - Investor KPIs'!V11 -> 16086944
A36: Unrecovered capital | B36: =Control!$B$15 -> 6400000 | C36: ='INV - Investor KPIs'!C8 -> 5447479.6 | D36: ='INV - Investor KPIs'!D8 -> 4447333.2 | E36: ='INV - Investor KPIs'!E8 -> 3397179.4 | F36: ='INV - Investor KPIs'!F8 -> 2294518 | G36: ='INV - Investor KPIs'!G8 -> 1136723.5 | H36: ='INV - Investor KPIs'!H8 -> 0 | I36: ='INV - Investor KPIs'!I8 -> 0 | J36: ='INV - Investor KPIs'!J8 -> 0 | ... V36: ='INV - Investor KPIs'!V8 -> 0
A37: Total value if exit this year | B37: =B35 -> 6450000 | C37: ='INV - Investor KPIs'!C12 -> 7318670.4 | D37: ='INV - Investor KPIs'!D12 -> 8637124.3 | E37: ='INV - Investor KPIs'!E12 -> 10021501 | F37: ='INV - Investor KPIs'!F12 -> 11475096 | G37: ='INV - Investor KPIs'!G12 -> 13001372 | H37: ='INV - Investor KPIs'!H12 -> 14603961 | I37: ='INV - Investor KPIs'!I12 -> 16286679 | J37: ='INV - Investor KPIs'!J12 -> 18053533 | ... V37: ='INV - Investor KPIs'!V12 -> 47582940
A38: Total MOIC if exit | B38: =B37/Control!$B$15 -> 1.0078125 | C38: ='INV - Investor KPIs'!C13 -> 1.1435422 | D38: ='INV - Investor KPIs'!D13 -> 1.3495507 | E38: ='INV - Investor KPIs'!E13 -> 1.5658595 | F38: ='INV - Investor KPIs'!F13 -> 1.7929838 | G38: ='INV - Investor KPIs'!G13 -> 2.0314643 | H38: ='INV - Investor KPIs'!H13 -> 2.2818688 | I38: ='INV - Investor KPIs'!I13 -> 2.5447936 | J38: ='INV - Investor KPIs'!J13 -> 2.8208646 | ... V38: ='INV - Investor KPIs'!V13 -> 7.4348343
A40: CONSOLIDATED CASH FLOW STATEMENT
A41: Beginning cash | B41: =0 -> 0 | C41: =B46 -> 0 | D41: =C46 -> 0 | E41: =D46 -> 0 | F41: =E46 -> 0 | G41: =F46 -> 0 | H41: =G46 -> 0 | I41: =H46 -> 0 | J41: =I46 -> 0 | ... V41: =U46 -> 0
A42: NPAT | B42: =0 -> 0 | C42: =C12 -> 1905040.8 | D42: =D12 -> 2000292.8 | E42: =E12 -> 2100307.5 | F42: =F12 -> 2205322.9 | G42: =G12 -> 2315589 | H42: =H12 -> 2431368.4 | I42: =I12 -> 2552936.9 | J42: =J12 -> 2680583.7 | ... V42: =V12 -> 4813943.2
A43: Winchester construction capex | B43: =0 -> 0 | C43: ='Portfolio NewCo'!B14 -> 0 | D43: ='Portfolio NewCo'!C14 -> 0 | E43: ='Portfolio NewCo'!D14 -> 0 | F43: ='Portfolio NewCo'!E14 -> 0 | G43: ='Portfolio NewCo'!F14 -> 0 | H43: ='Portfolio NewCo'!G14 -> 0 | I43: ='Portfolio NewCo'!H14 -> 0 | J43: ='Portfolio NewCo'!I14 -> 0 | ... V43: ='Portfolio NewCo'!U14 -> 0
A44: Shareholder distributions | B44: =0 -> 0 | C44: =-'Portfolio NewCo'!B15 -> -1905040.8 | D44: =-'Portfolio NewCo'!C15 -> -2000292.8 | E44: =-'Portfolio NewCo'!D15 -> -2100307.5 | F44: =-'Portfolio NewCo'!E15 -> -2205322.9 | G44: =-'Portfolio NewCo'!F15 -> -2315589 | H44: =-'Portfolio NewCo'!G15 -> -2431368.4 | I44: =-'Portfolio NewCo'!H15 -> -2552936.9 | J44: =-'Portfolio NewCo'!I15 -> -2680583.7 | ... V44: =-'Portfolio NewCo'!U15 -> -4813943.2
A45: Net change in cash | B45: =SUM(B42:B44) -> 0 | C45: =SUM(C42:C44) -> 0 | D45: =SUM(D42:D44) -> 0 | E45: =SUM(E42:E44) -> 0 | F45: =SUM(F42:F44) -> 0 | G45: =SUM(G42:G44) -> 0 | H45: =SUM(H42:H44) -> 0 | I45: =SUM(I42:I44) -> 0 | ... V45: =SUM(V42:V44) -> 0
A46: ENDING CASH | B46: =B41+B45 -> 0 | C46: =C41+C45 -> 0 | D46: =D41+D45 -> 0 | E46: =E41+E45 -> 0 | F46: =F41+F45 -> 0 | G46: =G41+G45 -> 0 | H46: =H41+H45 -> 0 | I46: =I41+I45 -> 0 | ... V46: =V41+V45 -> 0
A47: Cash tie-out check | B47: =B46-B22 -> 0 | C47: =C46-C22 -> 0 | D47: =D46-D22 -> 0 | E47: =E46-E22 -> 0 | F47: =F46-F22 -> 0 | G47: =G46-G22 -> 0 | H47: =H46-H22 -> 0 | I47: =I46-I22 -> 0 | ... V47: =V46-V22 -> 0
A49: INVESTOR — CASH FLOW VIEW
A50: Partner initial investment | B50: =-Control!$B$15 -> -6400000 | C50: =0 -> 0 | D50: =0 -> 0 | E50: =0 -> 0 | F50: =0 -> 0 | G50: =0 -> 0 | H50: =0 -> 0 | I50: =0 -> 0 | J50: =0 -> 0 | ... V50: =0 -> 0
A51: Partner cash distribution | B51: =0 -> 0 | C51: ='INV - Investor KPIs'!C6 -> 952520.4 | D51: ='INV - Investor KPIs'!D6 -> 1000146.4 | E51: ='INV - Investor KPIs'!E6 -> 1050153.7 | F51: ='INV - Investor KPIs'!F6 -> 1102661.4 | G51: ='INV - Investor KPIs'!G6 -> 1157794.5 | H51: ='INV - Investor KPIs'!H6 -> 1215684.2 | I51: ='INV - Investor KPIs'!I6 -> 1276468.4 | J51: ='INV - Investor KPIs'!J6 -> 1340291.9 | ... V51: ='INV - Investor KPIs'!V6 -> 2406971.6
A52: Cumulative partner distributions | B52: =0 -> 0 | C52: ='INV - Investor KPIs'!C7 -> 952520.4 | D52: ='INV - Investor KPIs'!D7 -> 1952666.8 | E52: ='INV - Investor KPIs'!E7 -> 3002820.6 | F52: ='INV - Investor KPIs'!F7 -> 4105482 | G52: ='INV - Investor KPIs'!G7 -> 5263276.5 | H52: ='INV - Investor KPIs'!H7 -> 6478960.7 | I52: ='INV - Investor KPIs'!I7 -> 7755429.1 | J52: ='INV - Investor KPIs'!J7 -> 9095721 | ... V52: ='INV - Investor KPIs'!V7 -> 31495996
A53: Cash MOIC | B53: =0 -> 0 | C53: ='INV - Investor KPIs'!C10 -> 0.14883131 | D53: ='INV - Investor KPIs'!D10 -> 0.30510419 | E53: ='INV - Investor KPIs'!E10 -> 0.46919071 | F53: ='INV - Investor KPIs'!F10 -> 0.64148156 | G53: ='INV - Investor KPIs'!G10 -> 0.82238695 | H53: ='INV - Investor KPIs'!H10 -> 1.0123376 | I53: ='INV - Investor KPIs'!I10 -> 1.2117858 | J53: ='INV - Investor KPIs'!J10 -> 1.4212064 | ... V53: ='INV - Investor KPIs'!V10 -> 4.9212493
A54: Cash payback achieved? | B54: ="No" -> No | C54: =IF(C52>=Control!$B$15,"Yes","No") -> No | D54: =IF(D52>=Control!$B$15,"Yes","No") -> No | E54: =IF(E52>=Control!$B$15,"Yes","No") -> No | F54: =IF(F52>=Control!$B$15,"Yes","No") -> No | G54: =IF(G52>=Control!$B$15,"Yes","No") -> No | H54: =IF(H52>=Control!$B$15,"Yes","No") -> Yes | I54: =IF(I52>=Control!$B$15,"Yes","No") -> Yes | J54: =IF(J52>=Control!$B$15,"Yes","No") -> Yes | ... V54: =IF(V52>=Control!$B$15,"Yes","No") -> Yes
A56: MODEL CHECKS
A57: BS balances? | B57: =IF(ABS(B32)<1,"OK","ERROR") -> OK | C57: =IF(ABS(C32)<1,"OK","ERROR") -> OK | D57: =IF(ABS(D32)<1,"OK","ERROR") -> OK | E57: =IF(ABS(E32)<1,"OK","ERROR") -> OK | F57: =IF(ABS(F32)<1,"OK","ERROR") -> OK | G57: =IF(ABS(G32)<1,"OK","ERROR") -> OK | H57: =IF(ABS(H32)<1,"OK","ERROR") -> OK | I57: =IF(ABS(I32)<1,"OK","ERROR") -> OK | ... V57: =IF(ABS(V32)<1,"OK","ERROR") -> OK
A58: Ending cash ties to BS cash? | B58: =IF(ABS(B47)<1,"OK","ERROR") -> OK | C58: =IF(ABS(C47)<1,"OK","ERROR") -> OK | D58: =IF(ABS(D47)<1,"OK","ERROR") -> OK | E58: =IF(ABS(E47)<1,"OK","ERROR") -> OK | F58: =IF(ABS(F47)<1,"OK","ERROR") -> OK | G58: =IF(ABS(G47)<1,"OK","ERROR") -> OK | H58: =IF(ABS(H47)<1,"OK","ERROR") -> OK | I58: =IF(ABS(I47)<1,"OK","ERROR") -> OK | ... V58: =IF(ABS(V47)<1,"OK","ERROR") -> OK
A59: NPAT links to cash flow? | B59: =IF(ABS(B12-B42)<1,"OK","ERROR") -> OK | C59: =IF(ABS(C12-C42)<1,"OK","ERROR") -> OK | D59: =IF(ABS(D12-D42)<1,"OK","ERROR") -> OK | E59: =IF(ABS(E12-E42)<1,"OK","ERROR") -> OK | F59: =IF(ABS(F12-F42)<1,"OK","ERROR") -> OK | G59: =IF(ABS(G12-G42)<1,"OK","ERROR") -> OK | H59: =IF(ABS(H12-H42)<1,"OK","ERROR") -> OK | I59: =IF(ABS(I12-I42)<1,"OK","ERROR") -> OK | ... V59: =IF(ABS(V12-V42)<1,"OK","ERROR") -> OK
A60: Master check | B60: =IF(COUNTIF(B57:V59,"ERROR")=0,"✓ ALL CHECKS PASS","✗ REVIEW CHECKS") -> ✓ ALL CHECKS PASS

Sheet INV - Property KPIs
A1: PROPERTY RETURNS & KPIs — per asset (property-specific partner %)
A2: Each property uses its own partner ownership %. Distributions, NAV, buy-in, IRR and MOIC are calculated from the property-specific partner %.
A4: Metric | B4: African Sky | C4: Beachside | D4: Menlyn | F4: Portfolio Total
A5: Partner buy-in component | B5: =IF(Control!$B$5>0,Control!$B$12/Control!$B$11*Control!$B$5,0) -> 3000000 | C5: =IF(Control!$B$7>0,Control!$B$13/Control!$B$11*Control!$B$7,0) -> 2000000 | D5: =IF(Control!$B$8>0,Control!$B$14/Control!$B$11*Control!$B$8,0) -> 1400000 | F5: =Control!$B$15 -> 6400000
A6: Adopted property value (100%) | B6: =Valuation!C9 -> 6000000 | C6: =Valuation!D9 -> 4000000 | D6: =Valuation!E9 -> 2900000 | F6: =Valuation!$F$9 -> 12900000
A7: Partner NAV @ property-specific % | B7: =Valuation!C10 -> 3000000 | C7: =Valuation!D10 -> 2000000 | D7: =Valuation!E10 -> 1450000 | F7: =Valuation!$F$10 -> 6450000
A8: Average annual NOI (Yr 1-3) | B8: =AVERAGE('African Sky P&L'!C26:E26) -> 2047869.2 | C8: =AVERAGE('Beachside P&L'!C16:E16) -> 423569.9 | D8: =AVERAGE('Menlyn P&L'!C13:E13) -> 270862.8 | F8: =AVERAGE('Portfolio NewCo'!B9:D9) -> 2742301.9
A9: NOI yield on adopted value | B9: =IFERROR(B8/B6,"") -> 0.34131153 | C9: =IFERROR(C8/C6,"") -> 0.10589247 | D9: =IFERROR(D8/D6,"") -> 0.093400966 | F9: =IFERROR(F8/F6,"") -> 0.21258154
A10: Implied earnings multiple (value ÷ NOI) | B10: =IFERROR(B6/B8,"") -> 2.9298747 | C10: =IFERROR(C6/C8,"") -> 9.4435417 | D10: =IFERROR(D6/D8,"") -> 10.706527 | F10: =IFERROR(F6/F8,"") -> 4.7040773
A11: 5-year Cash MOIC | B11: =IF(B5=0,"",INDEX($B$28:$U$28,1,5)/B5) -> 1.3101526 | C11: =IF(C5=0,"",INDEX($B$29:$U$29,1,5)/C5) -> 0.40647704 | D11: =IF(D5=0,"",INDEX($B$30:$U$30,1,5)/D5) -> 0.37133189 | F11: =IFERROR(INDEX('INV - Investor KPIs'!$C$10:$V$10,1,5),"") -> 0.82238695
A12: 5-year Total MOIC | B12: =IF(B5=0,"",(INDEX($B$28:$U$28,1,5)+B7*POWER(1+Control!$B$78,5)*(1-Control!$B$79))/B5) -> 2.5098573 | C12: =IF(C5=0,"",(INDEX($B$29:$U$29,1,5)+C7*POWER(1+Control!$B$78,5)*(1-Control!$B$79))/C5) -> 1.6061817 | D12: =IF(D5=0,"",(INDEX($B$30:$U$30,1,5)+D7*POWER(1+Control!$B$78,5)*(1-Control!$B$79))/D5) -> 1.6138832 | F12: =IFERROR(INDEX('INV - Investor KPIs'!$C$13:$V$13,1,5),"") -> 2.0314643
A13: 5-year Total IRR | B13: =IF(B5=0,"",IFERROR(IRR(B32:G32),"")) -> 0.27893316 | C13: =IF(C5=0,"",IFERROR(IRR(B33:G33),"")) -> 0.11237279 | D13: =IF(D5=0,"",IFERROR(IRR(B34:G34),"")) -> 0.11227215 | F13: ='INV - Investor KPIs'!C18 -> 0.19036144
A14: 10-year Cash MOIC | B14: =IF(B5=0,"",INDEX($B$28:$U$28,1,10)/B5) -> 2.9822762 | C14: =IF(C5=0,"",INDEX($B$29:$U$29,1,10)/C5) -> 0.92525619 | D14: =IF(D5=0,"",INDEX($B$30:$U$30,1,10)/D5) -> 0.84525594 | F14: =IFERROR(INDEX('INV - Investor KPIs'!$C$10:$V$10,1,10),"") -> 1.8719842
A15: 10-year Total MOIC | B15: =IF(B5=0,"",(INDEX($B$28:$U$28,1,10)+B7*POWER(1+Control!$B$78,10)*(1-Control!$B$79))/B5) -> 4.5134371 | C15: =IF(C5=0,"",(INDEX($B$29:$U$29,1,10)+C7*POWER(1+Control!$B$78,10)*(1-Control!$B$79))/C5) -> 2.4564171 | D15: =IF(D5=0,"",(INDEX($B$30:$U$30,1,10)+D7*POWER(1+Control!$B$78,10)*(1-Control!$B$79))/D5) -> 2.4311012 | F15: =IFERROR(INDEX('INV - Investor KPIs'!$C$13:$V$13,1,10),"") -> 3.4151074
A16: 10-year Total IRR | B16: =IF(B5=0,"",IFERROR(IRR(B35:L35),"")) -> 0.28494676 | C16: =IF(C5=0,"",IFERROR(IRR(B36:L36),"")) -> 0.11890725 | D16: =IF(D5=0,"",IFERROR(IRR(B37:L37),"")) -> 0.11511622 | F16: ='INV - Investor KPIs'!D18 -> 0.19595828
A17: 15-year Cash MOIC | B17: =IF(B5=0,"",INDEX($B$28:$U$28,1,15)/B5) -> 5.1163767 | C17: =IF(C5=0,"",INDEX($B$29:$U$29,1,15)/C5) -> 1.5873645 | D17: =IF(D5=0,"",INDEX($B$30:$U$30,1,15)/D5) -> 1.4501165 | F17: =IFERROR(INDEX('INV - Investor KPIs'!$C$10:$V$10,1,15),"") -> 3.2115659
A18: 15-year Total MOIC | B18: =IF(B5=0,"",(INDEX($B$28:$U$28,1,15)+B7*POWER(1+Control!$B$78,15)*(1-Control!$B$79))/B5) -> 7.0705692 | C18: =IF(C5=0,"",(INDEX($B$29:$U$29,1,15)+C7*POWER(1+Control!$B$78,15)*(1-Control!$B$79))/C5) -> 3.5415569 | D18: =IF(D5=0,"",(INDEX($B$30:$U$30,1,15)+D7*POWER(1+Control!$B$78,15)*(1-Control!$B$79))/D5) -> 3.4741015 | F18: =IFERROR(INDEX('INV - Investor KPIs'!$C$13:$V$13,1,15),"") -> 5.1810255
A19: 15-year Total IRR | B19: =IF(B5=0,"",IFERROR(IRR(B38:Q38),"")) -> 0.28639638 | C19: =IF(C5=0,"",IFERROR(IRR(B39:Q39),"")) -> 0.12100886 | D19: =IF(D5=0,"",IFERROR(IRR(B40:Q40),"")) -> 0.11603551 | F19: ='INV - Investor KPIs'!E18 -> 0.19757586
A20: 20-year Cash MOIC | B20: =IF(B5=0,"",INDEX($B$28:$U$28,1,20)/B5) -> 7.8400898 | C20: =IF(C5=0,"",INDEX($B$29:$U$29,1,20)/C5) -> 2.432401 | D20: =IF(D5=0,"",INDEX($B$30:$U$30,1,20)/D5) -> 2.2220888 | F20: =IFERROR(INDEX('INV - Investor KPIs'!$C$10:$V$10,1,20),"") -> 4.9212493
A21: 20-year Total MOIC | B21: =IF(B5=0,"",(INDEX($B$28:$U$28,1,20)+B7*POWER(1+Control!$B$78,20)*(1-Control!$B$79))/B5) -> 10.33419 | C21: =IF(C5=0,"",(INDEX($B$29:$U$29,1,20)+C7*POWER(1+Control!$B$78,20)*(1-Control!$B$79))/C5) -> 4.9265009 | D21: =IF(D5=0,"",(INDEX($B$30:$U$30,1,20)+D7*POWER(1+Control!$B$78,20)*(1-Control!$B$79))/D5) -> 4.8052636 | F21: =IFERROR(INDEX('INV - Investor KPIs'!$C$13:$V$13,1,20),"") -> 7.4348343
A22: 20-year Total IRR | B22: =IF(B5=0,"",IFERROR(IRR(B41:V41),"")) -> 0.28685725 | C22: =IF(C5=0,"",IFERROR(IRR(B42:V42),"")) -> 0.12200123 | D22: =IF(D5=0,"",IFERROR(IRR(B43:V43),"")) -> 0.11647377 | F22: ='INV - Investor KPIs'!F18 -> 0.19823225
A24: 50% PARTNER DISTRIBUTION HELPERS — by property
A25: AS partner dist | B25: ='Portfolio NewCo'!B24 -> 711313.8 | C25: ='Portfolio NewCo'!C24 -> 746879.49 | D25: ='Portfolio NewCo'!D24 -> 784223.46 | E25: ='Portfolio NewCo'!E24 -> 823434.63 | F25: ='Portfolio NewCo'!F24 -> 864606.37 | G25: ='Portfolio NewCo'!G24 -> 907836.68 | H25: ='Portfolio NewCo'!H24 -> 953228.52 | I25: ='Portfolio NewCo'!I24 -> 1000889.9 | ... U25: ='Portfolio NewCo'!U24 -> 1797454.5
A26: BS partner dist | B26: ='Portfolio NewCo'!B25 -> 147124.2 | C26: ='Portfolio NewCo'!C25 -> 154480.41 | D26: ='Portfolio NewCo'!D25 -> 162204.43 | E26: ='Portfolio NewCo'!E25 -> 170314.65 | F26: ='Portfolio NewCo'!F25 -> 178830.38 | G26: ='Portfolio NewCo'!G25 -> 187771.9 | H26: ='Portfolio NewCo'!H25 -> 197160.5 | I26: ='Portfolio NewCo'!I25 -> 207018.52 | ... U26: ='Portfolio NewCo'!U25 -> 371775.53
A27: MN partner dist | B27: ='Portfolio NewCo'!B26 -> 94082.4 | C27: ='Portfolio NewCo'!C26 -> 98786.52 | D27: ='Portfolio NewCo'!D26 -> 103725.85 | E27: ='Portfolio NewCo'!E26 -> 108912.14 | F27: ='Portfolio NewCo'!F26 -> 114357.75 | G27: ='Portfolio NewCo'!G26 -> 120075.63 | H27: ='Portfolio NewCo'!H26 -> 126079.41 | I27: ='Portfolio NewCo'!I26 -> 132383.38 | ... U27: ='Portfolio NewCo'!U26 -> 237741.54
A28: AS cumulative | B28: ='Portfolio NewCo'!B27 -> 711313.8 | C28: ='Portfolio NewCo'!C27 -> 1458193.3 | D28: ='Portfolio NewCo'!D27 -> 2242416.7 | E28: ='Portfolio NewCo'!E27 -> 3065851.4 | F28: ='Portfolio NewCo'!F27 -> 3930457.7 | G28: ='Portfolio NewCo'!G27 -> 4838294.4 | H28: ='Portfolio NewCo'!H27 -> 5791523 | I28: ='Portfolio NewCo'!I27 -> 6792412.9 | ... U28: ='Portfolio NewCo'!U27 -> 23520269
A29: BS cumulative | B29: ='Portfolio NewCo'!B28 -> 147124.2 | C29: ='Portfolio NewCo'!C28 -> 301604.61 | D29: ='Portfolio NewCo'!D28 -> 463809.04 | E29: ='Portfolio NewCo'!E28 -> 634123.69 | F29: ='Portfolio NewCo'!F28 -> 812954.08 | G29: ='Portfolio NewCo'!G28 -> 1000726 | H29: ='Portfolio NewCo'!H28 -> 1197886.5 | I29: ='Portfolio NewCo'!I28 -> 1404905 | ... U29: ='Portfolio NewCo'!U28 -> 4864802
A30: MN cumulative | B30: ='Portfolio NewCo'!B29 -> 94082.4 | C30: ='Portfolio NewCo'!C29 -> 192868.92 | D30: ='Portfolio NewCo'!D29 -> 296594.77 | E30: ='Portfolio NewCo'!E29 -> 405506.9 | F30: ='Portfolio NewCo'!F29 -> 519864.65 | G30: ='Portfolio NewCo'!G29 -> 639940.28 | H30: ='Portfolio NewCo'!H29 -> 766019.7 | I30: ='Portfolio NewCo'!I29 -> 898403.08 | ... U30: ='Portfolio NewCo'!U29 -> 3110924.3
A32: AS total-exit 5y | B32: =-B5 -> -3000000 | C32: =INDEX($B$25:$U$25,1,1) -> 711313.8 | D32: =INDEX($B$25:$U$25,1,2) -> 746879.49 | E32: =INDEX($B$25:$U$25,1,3) -> 784223.46 | F32: =INDEX($B$25:$U$25,1,4) -> 823434.63 | G32: =INDEX($B$25:$U$25,1,5)+B7*POWER(1+Control!$B$78,5)*(1-Control!$B$79) -> 4463720.4
A33: BS total-exit 5y | B33: =-C5 -> -2000000 | C33: =INDEX($B$26:$U$26,1,1) -> 147124.2 | D33: =INDEX($B$26:$U$26,1,2) -> 154480.41 | E33: =INDEX($B$26:$U$26,1,3) -> 162204.43 | F33: =INDEX($B$26:$U$26,1,4) -> 170314.65 | G33: =INDEX($B$26:$U$26,1,5)+C7*POWER(1+Control!$B$78,5)*(1-Control!$B$79) -> 2578239.7
A34: MN total-exit 5y | B34: =-D5 -> -1400000 | C34: =INDEX($B$27:$U$27,1,1) -> 94082.4 | D34: =INDEX($B$27:$U$27,1,2) -> 98786.52 | E34: =INDEX($B$27:$U$27,1,3) -> 103725.85 | F34: =INDEX($B$27:$U$27,1,4) -> 108912.14 | G34: =INDEX($B$27:$U$27,1,5)+D7*POWER(1+Control!$B$78,5)*(1-Control!$B$79) -> 1853929.5
A35: AS total-exit 10y | B35: =-B5 -> -3000000 | C35: =INDEX($B$25:$U$25,1,1) -> 711313.8 | D35: =INDEX($B$25:$U$25,1,2) -> 746879.49 | E35: =INDEX($B$25:$U$25,1,3) -> 784223.46 | F35: =INDEX($B$25:$U$25,1,4) -> 823434.63 | G35: =INDEX($B$25:$U$25,1,5) -> 864606.37 | H35: =INDEX($B$25:$U$25,1,6) -> 907836.68 | I35: =INDEX($B$25:$U$25,1,7) -> 953228.52 | J35: =INDEX($B$25:$U$25,1,8) -> 1000889.9 | K35: =INDEX($B$25:$U$25,1,9) -> 1050934.4 | L35: =INDEX($B$25:$U$25,1,10)+B7*POWER(1+Control!$B$78,10)*(1-Control!$B$79) -> 5696964
A36: BS total-exit 10y | B36: =-C5 -> -2000000 | C36: =INDEX($B$26:$U$26,1,1) -> 147124.2 | D36: =INDEX($B$26:$U$26,1,2) -> 154480.41 | E36: =INDEX($B$26:$U$26,1,3) -> 162204.43 | F36: =INDEX($B$26:$U$26,1,4) -> 170314.65 | G36: =INDEX($B$26:$U$26,1,5) -> 178830.38 | H36: =INDEX($B$26:$U$26,1,6) -> 187771.9 | I36: =INDEX($B$26:$U$26,1,7) -> 197160.5 | J36: =INDEX($B$26:$U$26,1,8) -> 207018.52 | K36: =INDEX($B$26:$U$26,1,9) -> 217369.45 | L36: =INDEX($B$26:$U$26,1,10)+C7*POWER(1+Control!$B$78,10)*(1-Control!$B$79) -> 3290559.8
A37: MN total-exit 10y | B37: =-D5 -> -1400000 | C37: =INDEX($B$27:$U$27,1,1) -> 94082.4 | D37: =INDEX($B$27:$U$27,1,2) -> 98786.52 | E37: =INDEX($B$27:$U$27,1,3) -> 103725.85 | F37: =INDEX($B$27:$U$27,1,4) -> 108912.14 | G37: =INDEX($B$27:$U$27,1,5) -> 114357.75 | H37: =INDEX($B$27:$U$27,1,6) -> 120075.63 | I37: =INDEX($B$27:$U$27,1,7) -> 126079.41 | J37: =INDEX($B$27:$U$27,1,8) -> 132383.38 | K37: =INDEX($B$27:$U$27,1,9) -> 139002.55 | L37: =INDEX($B$27:$U$27,1,10)+D7*POWER(1+Control!$B$78,10)*(1-Control!$B$79) -> 2366136.1
A38: AS total-exit 15y | B38: =-B5 -> -3000000 | C38: =INDEX($B$25:$U$25,1,1) -> 711313.8 | D38: =INDEX($B$25:$U$25,1,2) -> 746879.49 | E38: =INDEX($B$25:$U$25,1,3) -> 784223.46 | F38: =INDEX($B$25:$U$25,1,4) -> 823434.63 | G38: =INDEX($B$25:$U$25,1,5) -> 864606.37 | H38: =INDEX($B$25:$U$25,1,6) -> 907836.68 | I38: =INDEX($B$25:$U$25,1,7) -> 953228.52 | J38: =INDEX($B$25:$U$25,1,8) -> 1000889.9 | K38: =INDEX($B$25:$U$25,1,9) -> 1050934.4 | L38: =INDEX($B$25:$U$25,1,10) -> 1103481.2 | M38: =INDEX($B$25:$U$25,1,11) -> 1158655.2 | N38: =INDEX($B$25:$U$25,1,12) -> 1216588 | O38: =INDEX($B$25:$U$25,1,13) -> 1277417.4 | P38: =INDEX($B$25:$U$25,1,14) -> 1341288.3 | Q38: =INDEX($B$25:$U$25,1,15)+B7*POWER(1+Control!$B$78,15)*(1-Control!$B$79) -> 7270930.1
A39: BS total-exit 15y | B39: =-C5 -> -2000000 | C39: =INDEX($B$26:$U$26,1,1) -> 147124.2 | D39: =INDEX($B$26:$U$26,1,2) -> 154480.41 | E39: =INDEX($B$26:$U$26,1,3) -> 162204.43 | F39: =INDEX($B$26:$U$26,1,4) -> 170314.65 | G39: =INDEX($B$26:$U$26,1,5) -> 178830.38 | H39: =INDEX($B$26:$U$26,1,6) -> 187771.9 | I39: =INDEX($B$26:$U$26,1,7) -> 197160.5 | J39: =INDEX($B$26:$U$26,1,8) -> 207018.52 | K39: =INDEX($B$26:$U$26,1,9) -> 217369.45 | L39: =INDEX($B$26:$U$26,1,10) -> 228237.92 | M39: =INDEX($B$26:$U$26,1,11) -> 239649.82 | N39: =INDEX($B$26:$U$26,1,12) -> 251632.31 | O39: =INDEX($B$26:$U$26,1,13) -> 264213.93 | P39: =INDEX($B$26:$U$26,1,14) -> 277424.62 | Q39: =INDEX($B$26:$U$26,1,15)+C7*POWER(1+Control!$B$78,15)*(1-Control!$B$79) -> 4199680.8
A40: MN total-exit 15y | B40: =-D5 -> -1400000 | C40: =INDEX($B$27:$U$27,1,1) -> 94082.4 | D40: =INDEX($B$27:$U$27,1,2) -> 98786.52 | E40: =INDEX($B$27:$U$27,1,3) -> 103725.85 | F40: =INDEX($B$27:$U$27,1,4) -> 108912.14 | G40: =INDEX($B$27:$U$27,1,5) -> 114357.75 | H40: =INDEX($B$27:$U$27,1,6) -> 120075.63 | I40: =INDEX($B$27:$U$27,1,7) -> 126079.41 | J40: =INDEX($B$27:$U$27,1,8) -> 132383.38 | K40: =INDEX($B$27:$U$27,1,9) -> 139002.55 | L40: =INDEX($B$27:$U$27,1,10) -> 145952.68 | M40: =INDEX($B$27:$U$27,1,11) -> 153250.32 | N40: =INDEX($B$27:$U$27,1,12) -> 160912.83 | O40: =INDEX($B$27:$U$27,1,13) -> 168958.47 | P40: =INDEX($B$27:$U$27,1,14) -> 177406.4 | Q40: =INDEX($B$27:$U$27,1,15)+D7*POWER(1+Control!$B$78,15)*(1-Control!$B$79) -> 3019855.8
A41: AS total-exit 20y | B41: =-B5 -> -3000000 | C41: =INDEX($B$25:$U$25,1,1) -> 711313.8 | D41: =INDEX($B$25:$U$25,1,2) -> 746879.49 | E41: =INDEX($B$25:$U$25,1,3) -> 784223.46 | F41: =INDEX($B$25:$U$25,1,4) -> 823434.63 | G41: =INDEX($B$25:$U$25,1,5) -> 864606.37 | H41: =INDEX($B$25:$U$25,1,6) -> 907836.68 | I41: =INDEX($B$25:$U$25,1,7) -> 953228.52 | J41: =INDEX($B$25:$U$25,1,8) -> 1000889.9 | K41: =INDEX($B$25:$U$25,1,9) -> 1050934.4 | L41: =INDEX($B$25:$U$25,1,10) -> 1103481.2 | M41: =INDEX($B$25:$U$25,1,11) -> 1158655.2 | N41: =INDEX($B$25:$U$25,1,12) -> 1216588 | O41: =INDEX($B$25:$U$25,1,13) -> 1277417.4 | P41: =INDEX($B$25:$U$25,1,14) -> 1341288.3 | Q41: =INDEX($B$25:$U$25,1,15) -> 1408352.7 | R41: =INDEX($B$25:$U$25,1,16) -> 1478770.3 | S41: =INDEX($B$25:$U$25,1,17) -> 1552708.8 | T41: =INDEX($B$25:$U$25,1,18) -> 1630344.3 | U41: =INDEX($B$25:$U$25,1,19) -> 1711861.5 | V41: =INDEX($B$25:$U$25,1,20)+B7*POWER(1+Control!$B$78,20)*(1-Control!$B$79) -> 9279754.1
A42: BS total-exit 20y | B42: =-C5 -> -2000000 | C42: =INDEX($B$26:$U$26,1,1) -> 147124.2 | D42: =INDEX($B$26:$U$26,1,2) -> 154480.41 | E42: =INDEX($B$26:$U$26,1,3) -> 162204.43 | F42: =INDEX($B$26:$U$26,1,4) -> 170314.65 | G42: =INDEX($B$26:$U$26,1,5) -> 178830.38 | H42: =INDEX($B$26:$U$26,1,6) -> 187771.9 | I42: =INDEX($B$26:$U$26,1,7) -> 197160.5 | J42: =INDEX($B$26:$U$26,1,8) -> 207018.52 | K42: =INDEX($B$26:$U$26,1,9) -> 217369.45 | L42: =INDEX($B$26:$U$26,1,10) -> 228237.92 | M42: =INDEX($B$26:$U$26,1,11) -> 239649.82 | N42: =INDEX($B$26:$U$26,1,12) -> 251632.31 | O42: =INDEX($B$26:$U$26,1,13) -> 264213.93 | P42: =INDEX($B$26:$U$26,1,14) -> 277424.62 | Q42: =INDEX($B$26:$U$26,1,15) -> 291295.85 | R42: =INDEX($B$26:$U$26,1,16) -> 305860.65 | S42: =INDEX($B$26:$U$26,1,17) -> 321153.68 | T42: =INDEX($B$26:$U$26,1,18) -> 337211.36 | U42: =INDEX($B$26:$U$26,1,19) -> 354071.93 | V42: =INDEX($B$26:$U$26,1,20)+C7*POWER(1+Control!$B$78,20)*(1-Control!$B$79) -> 5359975.2
A43: MN total-exit 20y | B43: =-D5 -> -1400000 | C43: =INDEX($B$27:$U$27,1,1) -> 94082.4 | D43: =INDEX($B$27:$U$27,1,2) -> 98786.52 | E43: =INDEX($B$27:$U$27,1,3) -> 103725.85 | F43: =INDEX($B$27:$U$27,1,4) -> 108912.14 | G43: =INDEX($B$27:$U$27,1,5) -> 114357.75 | H43: =INDEX($B$27:$U$27,1,6) -> 120075.63 | I43: =INDEX($B$27:$U$27,1,7) -> 126079.41 | J43: =INDEX($B$27:$U$27,1,8) -> 132383.38 | K43: =INDEX($B$27:$U$27,1,9) -> 139002.55 | L43: =INDEX($B$27:$U$27,1,10) -> 145952.68 | M43: =INDEX($B$27:$U$27,1,11) -> 153250.32 | N43: =INDEX($B$27:$U$27,1,12) -> 160912.83 | O43: =INDEX($B$27:$U$27,1,13) -> 168958.47 | P43: =INDEX($B$27:$U$27,1,14) -> 177406.4 | Q43: =INDEX($B$27:$U$27,1,15) -> 186276.72 | R43: =INDEX($B$27:$U$27,1,16) -> 195590.55 | S43: =INDEX($B$27:$U$27,1,17) -> 205370.08 | T43: =INDEX($B$27:$U$27,1,18) -> 215638.58 | U43: =INDEX($B$27:$U$27,1,19) -> 226420.51 | V43: =INDEX($B$27:$U$27,1,20)+D7*POWER(1+Control!$B$78,20)*(1-Control!$B$79) -> 3854186.3

Sheet INV - Investor KPIs
A1: INVESTOR RETURNS & KPIs — property-specific partner %
A2: Cash = property-specific partner distributions. Total = distributions + property-specific partner share of property value at exit.
A4: Year | C4: 1 | D4: 2 | E4: 3 | F4: 4 | G4: 5 | H4: 6 | I4: 7 | J4: 8 | K4: 9 | L4: 10 | M4: 11 | N4: 12 | O4: 13 | P4: 14 | Q4: 15 | R4: 16 | S4: 17 | T4: 18 | U4: 19 | V4: 20
A6: Partner distribution | C6: ='Portfolio NewCo'!B16 -> 952520.4 | D6: ='Portfolio NewCo'!C16 -> 1000146.4 | E6: ='Portfolio NewCo'!D16 -> 1050153.7 | F6: ='Portfolio NewCo'!E16 -> 1102661.4 | G6: ='Portfolio NewCo'!F16 -> 1157794.5 | H6: ='Portfolio NewCo'!G16 -> 1215684.2 | I6: ='Portfolio NewCo'!H16 -> 1276468.4 | J6: ='Portfolio NewCo'!I16 -> 1340291.9 | ... V6: ='Portfolio NewCo'!U16 -> 2406971.6
A7: Cumulative distribution | C7: ='Portfolio NewCo'!B17 -> 952520.4 | D7: ='Portfolio NewCo'!C17 -> 1952666.8 | E7: ='Portfolio NewCo'!D17 -> 3002820.6 | F7: ='Portfolio NewCo'!E17 -> 4105482 | G7: ='Portfolio NewCo'!F17 -> 5263276.5 | H7: ='Portfolio NewCo'!G17 -> 6478960.7 | I7: ='Portfolio NewCo'!H17 -> 7755429.1 | J7: ='Portfolio NewCo'!I17 -> 9095721 | ... V7: ='Portfolio NewCo'!U17 -> 31495996
A8: Unrecovered capital | C8: =MAX(0,Control!$B$15-C7) -> 5447479.6 | D8: =MAX(0,Control!$B$15-D7) -> 4447333.2 | E8: =MAX(0,Control!$B$15-E7) -> 3397179.4 | F8: =MAX(0,Control!$B$15-F7) -> 2294518 | G8: =MAX(0,Control!$B$15-G7) -> 1136723.5 | H8: =MAX(0,Control!$B$15-H7) -> 0 | I8: =MAX(0,Control!$B$15-I7) -> 0 | J8: =MAX(0,Control!$B$15-J7) -> 0 | ... V8: =MAX(0,Control!$B$15-V7) -> 0
A9: Cash-on-cash yield | C9: =IF(Control!$B$15=0,"",C6/Control!$B$15) -> 0.14883131 | D9: =IF(Control!$B$15=0,"",D6/Control!$B$15) -> 0.15627288 | E9: =IF(Control!$B$15=0,"",E6/Control!$B$15) -> 0.16408652 | F9: =IF(Control!$B$15=0,"",F6/Control!$B$15) -> 0.17229085 | G9: =IF(Control!$B$15=0,"",G6/Control!$B$15) -> 0.18090539 | H9: =IF(Control!$B$15=0,"",H6/Control!$B$15) -> 0.18995066 | I9: =IF(Control!$B$15=0,"",I6/Control!$B$15) -> 0.19944819 | J9: =IF(Control!$B$15=0,"",J6/Control!$B$15) -> 0.2094206 | ... V9: =IF(Control!$B$15=0,"",V6/Control!$B$15) -> 0.37608931
A10: Cash MOIC | C10: =IF(Control!$B$15=0,"",C7/Control!$B$15) -> 0.14883131 | D10: =IF(Control!$B$15=0,"",D7/Control!$B$15) -> 0.30510419 | E10: =IF(Control!$B$15=0,"",E7/Control!$B$15) -> 0.46919071 | F10: =IF(Control!$B$15=0,"",F7/Control!$B$15) -> 0.64148156 | G10: =IF(Control!$B$15=0,"",G7/Control!$B$15) -> 0.82238695 | H10: =IF(Control!$B$15=0,"",H7/Control!$B$15) -> 1.0123376 | I10: =IF(Control!$B$15=0,"",I7/Control!$B$15) -> 1.2117858 | J10: =IF(Control!$B$15=0,"",J7/Control!$B$15) -> 1.4212064 | ... V10: =IF(Control!$B$15=0,"",V7/Control!$B$15) -> 4.9212493
A11: Partner NAV if exit this year | C11: =Valuation!$F$10*POWER(1+Control!$B$78,C$4)*(1-Control!$B$79) -> 6366150 | D11: =Valuation!$F$10*POWER(1+Control!$B$78,D$4)*(1-Control!$B$79) -> 6684457.5 | E11: =Valuation!$F$10*POWER(1+Control!$B$78,E$4)*(1-Control!$B$79) -> 7018680.4 | F11: =Valuation!$F$10*POWER(1+Control!$B$78,F$4)*(1-Control!$B$79) -> 7369614.4 | G11: =Valuation!$F$10*POWER(1+Control!$B$78,G$4)*(1-Control!$B$79) -> 7738095.1 | H11: =Valuation!$F$10*POWER(1+Control!$B$78,H$4)*(1-Control!$B$79) -> 8124999.9 | I11: =Valuation!$F$10*POWER(1+Control!$B$78,I$4)*(1-Control!$B$79) -> 8531249.9 | J11: =Valuation!$F$10*POWER(1+Control!$B$78,J$4)*(1-Control!$B$79) -> 8957812.4 | ... V11: =Valuation!$F$10*POWER(1+Control!$B$78,V$4)*(1-Control!$B$79) -> 16086944
A12: Total value if exit (cash + NAV) | C12: =C7+C11 -> 7318670.4 | D12: =D7+D11 -> 8637124.3 | E12: =E7+E11 -> 10021501 | F12: =F7+F11 -> 11475096 | G12: =G7+G11 -> 13001372 | H12: =H7+H11 -> 14603961 | I12: =I7+I11 -> 16286679 | J12: =J7+J11 -> 18053533 | ... V12: =V7+V11 -> 47582940
A13: Total MOIC (incl. property value) | C13: =IF(Control!$B$15=0,"",C12/Control!$B$15) -> 1.1435422 | D13: =IF(Control!$B$15=0,"",D12/Control!$B$15) -> 1.3495507 | E13: =IF(Control!$B$15=0,"",E12/Control!$B$15) -> 1.5658595 | F13: =IF(Control!$B$15=0,"",F12/Control!$B$15) -> 1.7929838 | G13: =IF(Control!$B$15=0,"",G12/Control!$B$15) -> 2.0314643 | H13: =IF(Control!$B$15=0,"",H12/Control!$B$15) -> 2.2818688 | I13: =IF(Control!$B$15=0,"",I12/Control!$B$15) -> 2.5447936 | J13: =IF(Control!$B$15=0,"",J12/Control!$B$15) -> 2.8208646 | ... V13: =IF(Control!$B$15=0,"",V12/Control!$B$15) -> 7.4348343
A15: HOLD-PERIOD KPIs
A16: Hold period | B16: 3-year | C16: 5-year | D16: 10-year | E16: 15-year | F16: 20-year
A17: Cash IRR | B17: =IF(Control!$B$15=0,"",IFERROR(IRR(C30:F30),"")) -> -0.29693627 | C17: =IF(Control!$B$15=0,"",IFERROR(IRR(C31:H31),"")) -> -0.06002416 | D17: =IF(Control!$B$15=0,"",IFERROR(IRR(C32:M32),"")) -> 0.12248842 | E17: =IF(Control!$B$15=0,"",IFERROR(IRR(C33:R33),"")) -> 0.16915031 | F17: =IF(Control!$B$15=0,"",IFERROR(IRR(C34:W34),"")) -> 0.1857513
A18: Total IRR (incl. property value) | B18: =IF(Control!$B$15=0,"",IFERROR(IRR(C35:F35),"")) -> 0.18254411 | C18: =IF(Control!$B$15=0,"",IFERROR(IRR(C36:H36),"")) -> 0.19036144 | D18: =IF(Control!$B$15=0,"",IFERROR(IRR(C37:M37),"")) -> 0.19595828 | E18: =IF(Control!$B$15=0,"",IFERROR(IRR(C38:R38),"")) -> 0.19757586 | F18: =IF(Control!$B$15=0,"",IFERROR(IRR(C39:W39),"")) -> 0.19823225
A19: Cash MOIC | B19: =IF(Control!$B$15=0,"",INDEX($C$10:$V$10,1,3)) -> 0.46919071 | C19: =IF(Control!$B$15=0,"",INDEX($C$10:$V$10,1,5)) -> 0.82238695 | D19: =IF(Control!$B$15=0,"",INDEX($C$10:$V$10,1,10)) -> 1.8719842 | E19: =IF(Control!$B$15=0,"",INDEX($C$10:$V$10,1,15)) -> 3.2115659 | F19: =IF(Control!$B$15=0,"",INDEX($C$10:$V$10,1,20)) -> 4.9212493
A20: Total MOIC | B20: =IF(Control!$B$15=0,"",INDEX($C$13:$V$13,1,3)) -> 1.5658595 | C20: =IF(Control!$B$15=0,"",INDEX($C$13:$V$13,1,5)) -> 2.0314643 | D20: =IF(Control!$B$15=0,"",INDEX($C$13:$V$13,1,10)) -> 3.4151074 | E20: =IF(Control!$B$15=0,"",INDEX($C$13:$V$13,1,15)) -> 5.1810255 | F20: =IF(Control!$B$15=0,"",INDEX($C$13:$V$13,1,20)) -> 7.4348343
A22: 50% PARTNER VIEW — key investor context
A23: Buy-in paid by 50% partner | B23: =Control!$B$15 -> 6400000
A24: Partner NAV today @ 50% | B24: =Valuation!$F$10 -> 6450000
A25: Cash payback year | B25: =IF(Control!$B$15=0,"No active properties",COUNTIF('Portfolio NewCo'!B17:U17,"<"&Control!$B$15)+1) -> 6
A29: — exit cashflow helpers (t0 col C … t20 col W) —
A30: cash 3y | C30: =-Control!$B$15 -> -6400000 | D30: =INDEX($C$6:$V$6,1,1) -> 952520.4 | E30: =INDEX($C$6:$V$6,1,2) -> 1000146.4 | F30: =INDEX($C$6:$V$6,1,3) -> 1050153.7
A31: cash 5y | C31: =-Control!$B$15 -> -6400000 | D31: =INDEX($C$6:$V$6,1,1) -> 952520.4 | E31: =INDEX($C$6:$V$6,1,2) -> 1000146.4 | F31: =INDEX($C$6:$V$6,1,3) -> 1050153.7 | G31: =INDEX($C$6:$V$6,1,4) -> 1102661.4 | H31: =INDEX($C$6:$V$6,1,5) -> 1157794.5
A32: cash 10y | C32: =-Control!$B$15 -> -6400000 | D32: =INDEX($C$6:$V$6,1,1) -> 952520.4 | E32: =INDEX($C$6:$V$6,1,2) -> 1000146.4 | F32: =INDEX($C$6:$V$6,1,3) -> 1050153.7 | G32: =INDEX($C$6:$V$6,1,4) -> 1102661.4 | H32: =INDEX($C$6:$V$6,1,5) -> 1157794.5 | I32: =INDEX($C$6:$V$6,1,6) -> 1215684.2 | J32: =INDEX($C$6:$V$6,1,7) -> 1276468.4 | K32: =INDEX($C$6:$V$6,1,8) -> 1340291.9 | L32: =INDEX($C$6:$V$6,1,9) -> 1407306.4 | M32: =INDEX($C$6:$V$6,1,10) -> 1477671.8
A33: cash 15y | C33: =-Control!$B$15 -> -6400000 | D33: =INDEX($C$6:$V$6,1,1) -> 952520.4 | E33: =INDEX($C$6:$V$6,1,2) -> 1000146.4 | F33: =INDEX($C$6:$V$6,1,3) -> 1050153.7 | G33: =INDEX($C$6:$V$6,1,4) -> 1102661.4 | H33: =INDEX($C$6:$V$6,1,5) -> 1157794.5 | I33: =INDEX($C$6:$V$6,1,6) -> 1215684.2 | J33: =INDEX($C$6:$V$6,1,7) -> 1276468.4 | K33: =INDEX($C$6:$V$6,1,8) -> 1340291.9 | L33: =INDEX($C$6:$V$6,1,9) -> 1407306.4 | M33: =INDEX($C$6:$V$6,1,10) -> 1477671.8 | N33: =INDEX($C$6:$V$6,1,11) -> 1551555.4 | O33: =INDEX($C$6:$V$6,1,12) -> 1629133.1 | P33: =INDEX($C$6:$V$6,1,13) -> 1710589.8 | Q33: =INDEX($C$6:$V$6,1,14) -> 1796119.3 | R33: =INDEX($C$6:$V$6,1,15) -> 1885925.2
A34: cash 20y | C34: =-Control!$B$15 -> -6400000 | D34: =INDEX($C$6:$V$6,1,1) -> 952520.4 | E34: =INDEX($C$6:$V$6,1,2) -> 1000146.4 | F34: =INDEX($C$6:$V$6,1,3) -> 1050153.7 | G34: =INDEX($C$6:$V$6,1,4) -> 1102661.4 | H34: =INDEX($C$6:$V$6,1,5) -> 1157794.5 | I34: =INDEX($C$6:$V$6,1,6) -> 1215684.2 | J34: =INDEX($C$6:$V$6,1,7) -> 1276468.4 | K34: =INDEX($C$6:$V$6,1,8) -> 1340291.9 | L34: =INDEX($C$6:$V$6,1,9) -> 1407306.4 | M34: =INDEX($C$6:$V$6,1,10) -> 1477671.8 | N34: =INDEX($C$6:$V$6,1,11) -> 1551555.4 | O34: =INDEX($C$6:$V$6,1,12) -> 1629133.1 | P34: =INDEX($C$6:$V$6,1,13) -> 1710589.8 | Q34: =INDEX($C$6:$V$6,1,14) -> 1796119.3 | R34: =INDEX($C$6:$V$6,1,15) -> 1885925.2 | S34: =INDEX($C$6:$V$6,1,16) -> 1980221.5 | T34: =INDEX($C$6:$V$6,1,17) -> 2079232.6 | U34: =INDEX($C$6:$V$6,1,18) -> 2183194.2 | V34: =INDEX($C$6:$V$6,1,19) -> 2292353.9 | W34: =INDEX($C$6:$V$6,1,20) -> 2406971.6
A35: total 3y | C35: =-Control!$B$15 -> -6400000 | D35: =INDEX($C$6:$V$6,1,1) -> 952520.4 | E35: =INDEX($C$6:$V$6,1,2) -> 1000146.4 | F35: =INDEX($C$6:$V$6,1,3)+Valuation!$F$10*POWER(1+Control!$B$78,3)*(1-Control!$B$79) -> 8068834.1
A36: total 5y | C36: =-Control!$B$15 -> -6400000 | D36: =INDEX($C$6:$V$6,1,1) -> 952520.4 | E36: =INDEX($C$6:$V$6,1,2) -> 1000146.4 | F36: =INDEX($C$6:$V$6,1,3) -> 1050153.7 | G36: =INDEX($C$6:$V$6,1,4) -> 1102661.4 | H36: =INDEX($C$6:$V$6,1,5)+Valuation!$F$10*POWER(1+Control!$B$78,5)*(1-Control!$B$79) -> 8895889.6
A37: total 10y | C37: =-Control!$B$15 -> -6400000 | D37: =INDEX($C$6:$V$6,1,1) -> 952520.4 | E37: =INDEX($C$6:$V$6,1,2) -> 1000146.4 | F37: =INDEX($C$6:$V$6,1,3) -> 1050153.7 | G37: =INDEX($C$6:$V$6,1,4) -> 1102661.4 | H37: =INDEX($C$6:$V$6,1,5) -> 1157794.5 | I37: =INDEX($C$6:$V$6,1,6) -> 1215684.2 | J37: =INDEX($C$6:$V$6,1,7) -> 1276468.4 | K37: =INDEX($C$6:$V$6,1,8) -> 1340291.9 | L37: =INDEX($C$6:$V$6,1,9) -> 1407306.4 | M37: =INDEX($C$6:$V$6,1,10)+Valuation!$F$10*POWER(1+Control!$B$78,10)*(1-Control!$B$79) -> 11353660
A38: total 15y | C38: =-Control!$B$15 -> -6400000 | D38: =INDEX($C$6:$V$6,1,1) -> 952520.4 | E38: =INDEX($C$6:$V$6,1,2) -> 1000146.4 | F38: =INDEX($C$6:$V$6,1,3) -> 1050153.7 | G38: =INDEX($C$6:$V$6,1,4) -> 1102661.4 | H38: =INDEX($C$6:$V$6,1,5) -> 1157794.5 | I38: =INDEX($C$6:$V$6,1,6) -> 1215684.2 | J38: =INDEX($C$6:$V$6,1,7) -> 1276468.4 | K38: =INDEX($C$6:$V$6,1,8) -> 1340291.9 | L38: =INDEX($C$6:$V$6,1,9) -> 1407306.4 | M38: =INDEX($C$6:$V$6,1,10) -> 1477671.8 | N38: =INDEX($C$6:$V$6,1,11) -> 1551555.4 | O38: =INDEX($C$6:$V$6,1,12) -> 1629133.1 | P38: =INDEX($C$6:$V$6,1,13) -> 1710589.8 | Q38: =INDEX($C$6:$V$6,1,14) -> 1796119.3 | R38: =INDEX($C$6:$V$6,1,15)+Valuation!$F$10*POWER(1+Control!$B$78,15)*(1-Control!$B$79) -> 14490467
A39: total 20y | C39: =-Control!$B$15 -> -6400000 | D39: =INDEX($C$6:$V$6,1,1) -> 952520.4 | E39: =INDEX($C$6:$V$6,1,2) -> 1000146.4 | F39: =INDEX($C$6:$V$6,1,3) -> 1050153.7 | G39: =INDEX($C$6:$V$6,1,4) -> 1102661.4 | H39: =INDEX($C$6:$V$6,1,5) -> 1157794.5 | I39: =INDEX($C$6:$V$6,1,6) -> 1215684.2 | J39: =INDEX($C$6:$V$6,1,7) -> 1276468.4 | K39: =INDEX($C$6:$V$6,1,8) -> 1340291.9 | L39: =INDEX($C$6:$V$6,1,9) -> 1407306.4 | M39: =INDEX($C$6:$V$6,1,10) -> 1477671.8 | N39: =INDEX($C$6:$V$6,1,11) -> 1551555.4 | O39: =INDEX($C$6:$V$6,1,12) -> 1629133.1 | P39: =INDEX($C$6:$V$6,1,13) -> 1710589.8 | Q39: =INDEX($C$6:$V$6,1,14) -> 1796119.3 | R39: =INDEX($C$6:$V$6,1,15) -> 1885925.2 | S39: =INDEX($C$6:$V$6,1,16) -> 1980221.5 | T39: =INDEX($C$6:$V$6,1,17) -> 2079232.6 | U39: =INDEX($C$6:$V$6,1,18) -> 2183194.2 | V39: =INDEX($C$6:$V$6,1,19) -> 2292353.9 | W39: =INDEX($C$6:$V$6,1,20)+Valuation!$F$10*POWER(1+Control!$B$78,20)*(1-Control!$B$79) -> 18493916

Sheet INV - Sensitivity Risks
A1: SENSITIVITY & RISKS — live one-way IRR data-tables
A2: Each row recomputes the FULL 20-year partner return with one input changed (all other Control inputs held live). Base row is highlighted and equals the main model. Scenario input cells are yellow — edit them freely.
A4: Note: scenarios recompute the full 20-year return. 5-, 10-, and 15-year base-case partner KPIs are now shown on Investor KPIs and Investor Close Summary to avoid mixing base hold periods with scenario sensitivities.
A6: Occupancy | B6: 20-yr Total IRR | C6: 20-yr Total MOIC | D6: Payback (yr)
A7: 0.65 | B7: =IRR(C51:W51) -> 0.18088609 | C7: =SUM(D51:W51)/Control!$B$15 -> 6.8654966 | D7: =COUNTIF(D52:V52,"<"&Control!$B$15)+1 -> 7
A8: 0.7 | B8: =IRR(C53:W53) -> 0.18813128 | C8: =SUM(D53:W53)/Control!$B$15 -> 7.103206 | D8: =COUNTIF(D54:V54,"<"&Control!$B$15)+1 -> 7
A9: 0.75 | B9: =IRR(C55:W55) -> 0.19537237 | C9: =SUM(D55:W55)/Control!$B$15 -> 7.3409153 | D9: =COUNTIF(D56:V56,"<"&Control!$B$15)+1 -> 7
A10: 0.8 | B10: =IRR(C57:W57) -> 0.20260961 | C10: =SUM(D57:W57)/Control!$B$15 -> 7.5786247 | D10: =COUNTIF(D58:V58,"<"&Control!$B$15)+1 -> 6
A11: 0.85 | B11: =IRR(C59:W59) -> 0.20984325 | C11: =SUM(D59:W59)/Control!$B$15 -> 7.8163341 | D11: =COUNTIF(D60:V60,"<"&Control!$B$15)+1 -> 6
A13: ADR / RATE ESCALATION p.a. (Control!B11)
A14: ADR escalation | B14: 20-yr Total IRR | C14: 20-yr Total MOIC | D14: Payback (yr)
A15: 0.03 | B15: =IRR(C63:W63) -> 0.16654116 | C15: =SUM(D63:W63)/Control!$B$15 -> 5.6423402 | D15: =COUNTIF(D64:V64,"<"&Control!$B$15)+1 -> 7
A16: 0.04 | B16: =IRR(C65:W65) -> 0.18261767 | C16: =SUM(D65:W65)/Control!$B$15 -> 6.483592 | D16: =COUNTIF(D66:V66,"<"&Control!$B$15)+1 -> 7
A17: 0.05 | B17: =IRR(C67:W67) -> 0.19823225 | C17: =SUM(D67:W67)/Control!$B$15 -> 7.4348343 | D17: =COUNTIF(D68:V68,"<"&Control!$B$15)+1 -> 6
A18: 0.06 | B18: =IRR(C69:W69) -> 0.21341167 | C18: =SUM(D69:W69)/Control!$B$15 -> 8.5109931 | D18: =COUNTIF(D70:V70,"<"&Control!$B$15)+1 -> 6
A19: 0.07 | B19: =IRR(C71:W71) -> 0.22818885 | C19: =SUM(D71:W71)/Control!$B$15 -> 9.7289943 | D19: =COUNTIF(D72:V72,"<"&Control!$B$15)+1 -> 6
A21: TOUR GROSS PROFIT (× base, via ASKY Tours Calcs)
A22: Tour GP (× base) | B22: 20-yr Total IRR | C22: 20-yr Total MOIC | D22: Payback (yr)
A23: 0.6 | B23: =IRR(C75:W75) -> 0.18555288 | C23: =SUM(D75:W75)/Control!$B$15 -> 7.0185945 | D23: =COUNTIF(D76:V76,"<"&Control!$B$15)+1 -> 7
A24: 0.8 | B24: =IRR(C77:W77) -> 0.19189408 | C24: =SUM(D77:W77)/Control!$B$15 -> 7.2267144 | D24: =COUNTIF(D78:V78,"<"&Control!$B$15)+1 -> 7
A25: 1 | B25: =IRR(C79:W79) -> 0.19823225 | C25: =SUM(D79:W79)/Control!$B$15 -> 7.4348343 | D25: =COUNTIF(D80:V80,"<"&Control!$B$15)+1 -> 6
A26: 1.2 | B26: =IRR(C81:W81) -> 0.20456754 | C26: =SUM(D81:W81)/Control!$B$15 -> 7.6429543 | D26: =COUNTIF(D82:V82,"<"&Control!$B$15)+1 -> 6
A27: 1.4 | B27: =IRR(C83:W83) -> 0.21090013 | C27: =SUM(D83:W83)/Control!$B$15 -> 7.8510742 | D27: =COUNTIF(D84:V84,"<"&Control!$B$15)+1 -> 6
A29: EXIT PROPERTY GROWTH p.a. (Control!B70)
A30: Exit growth | B30: 20-yr Total IRR | C30: 20-yr Total MOIC | D30: Payback (yr)
A31: 0 | B31: =IRR(C87:W87) -> 0.19088961 | C31: =SUM(D87:W87)/Control!$B$15 -> 5.8685931 | D31: =COUNTIF(D88:V88,"<"&Control!$B$15)+1 -> 6
A32: 0.03 | B32: =IRR(C89:W89) -> 0.19462413 | C32: =SUM(D89:W89)/Control!$B$15 -> 6.6322575 | D32: =COUNTIF(D90:V90,"<"&Control!$B$15)+1 -> 6
A33: 0.05 | B33: =IRR(C91:W91) -> 0.19823225 | C33: =SUM(D91:W91)/Control!$B$15 -> 7.4348343 | D33: =COUNTIF(D92:V92,"<"&Control!$B$15)+1 -> 6
A34: 0.07 | B34: =IRR(C93:W93) -> 0.202949 | C34: =SUM(D93:W93)/Control!$B$15 -> 8.5871707 | D34: =COUNTIF(D94:V94,"<"&Control!$B$15)+1 -> 6
A35: 0.09 | B35: =IRR(C95:W95) -> 0.20892722 | C35: =SUM(D95:W95)/Control!$B$15 -> 10.230553 | D35: =COUNTIF(D96:V96,"<"&Control!$B$15)+1 -> 6
A38: RISK REGISTER & MITIGANTS
A39: Risk | B39: Why it matters | E39: Mitigant / response
A40: VAT / tax treatment | B40: Can affect net cashflows and transaction structure; turnover (incl. tours) is well over the R1m threshold. | E40: Keep flagged; obtain accountant sign-off before closing.
A41: Property transfer / legal structuring | B41: Transfer duty, VAT, CGT, s42 roll-over and shareholder docs affect execution. | E41: Attorney review and final deal structure before signature.
A42: African Sky operating income vs property value | B42: Operating NOI implies a high value if capitalised directly. | E42: Model adopts a conservative property value; operating upside shown separately.
A43: Tour take-up / supplier cost | B43: Tours materially contribute gross profit (see Tour GP table above). | E43: ASKY Tours Calcs is the source; update supplier costs/take-up as quotes firm up.
A44: Occupancy vs realised history | B44: Model runs 75%; realised bookings imply ~67-71% (see ASKY Stay Calc). | E44: Occupancy table above shows the return at 65-85%.
A45: Winchester expansion optional | B45: Timing/cost risk affects Year 1/2 cashflow only when Winchester expansion is set to Y on Control. | E45: Construction capex and revenue are gated by Control!B7; if N, sensitivity engine excludes Winchester.
A46: Exit growth assumption | B46: Exit NAV grows at the property value growth p.a. assumption (Control!B70); a large part of total return. | E46: Exit-growth table above shows the return at 0-9%.
A49: — live calculation engine below (safe to ignore / can be hidden) —
A51: [calc] Occupancy 0.65 dist | C51: =-Control!$B$15 -> -6400000 | D51: =Control!$B$11*(((((((Control!$B$20*$A$7)*((Control!$B$28+Control!$B$29*(Control!$B$38-2))+(Control!$B$32+Control!$B$33*(Control!$B$38-2))+IF(AND(Control!$B$5>0,Control!$B$6="Y",1>=Control!$B$39),Control!$B$36,0))*POWER(1+Control!$B$17,0))+((((Control!$B$20*$A$7)*Control!$B$38*2+IF(AND(Control!$B$5>0,Control!$B$6="Y",1>=Control!$B$39),(Control!$B$20*$A$7)*2,0))*Control!$B$41)*(Control!$B$42+Control!$B$44)*POWER(1+Control!$B$17,0))+(Control!$B$46*POWER(1+Control!$B$17,0)))-(((Control!$B$20*$A$7)*((Control!$B$28+Control!$B$29*(Control!$B$38-2))+(Control!$B$32+Control!$B$33*(Control!$B$38-2))+IF(AND(Control!$B$5>0,Control!$B$6="Y",1>=Control!$B$39),Control!$B$36,0))*POWER(1+Control!$B$17,0))*Control!$B$52+(((Control!$B$20*$A$7)*Control!$B$38*2+IF(AND(Control!$B$5>0,Control!$B$6="Y",1>=Control!$B$39),(Control!$B$20*$A$7)*2,0))*Control!$B$41)*(Control!$B$43+Control!$B$45)*POWER(1+Control!$B$18,0)+Control!$B$47*POWER(1+Control!$B$18,0)+(Control!$B$48+Control!$B$49+Control!$B$50+Control!$B$51)*12*POWER(1+Control!$B$18,0)+((Control!$B$20*$A$7)*((Control!$B$28+Control!$B$29*(Control!$B$38-2))+(Control!$B$32+Control!$B$33*(Control!$B$38-2))+IF(AND(Control!$B$5>0,Control!$B$6="Y",1>=Control!$B$39),Control!$B$36,0))*POWER(1+Control!$B$17,0))*Control!$B$26))+(((Control!$B$54*Control!$B$55+Control!$B$57*Control!$B$58*Control!$B$59*Control!$B$60)*POWER(1+Control!$B$17,0))-((Control!$B$57*Control!$B$58*Control!$B$59*Control!$B$60*POWER(1+Control!$B$17,0))*Control!$B$63+(Control!$B$64+Control!$B$65+Control!$B$66)*12*POWER(1+Control!$B$18,0)+((Control!$B$54*Control!$B$55+Control!$B$57*Control!$B$58*Control!$B$59*Control!$B$60)*POWER(1+Control!$B$17,0))*Control!$B$26))+((Control!$B$68*12*POWER(1+Control!$B$17,0))-((Control!$B$70+Control!$B$71+Control!$B$72)*12*POWER(1+Control!$B$18,0)+(Control!$B$68*12*POWER(1+Control!$B$17,0))*Control!$B$26)))*(1-Control!$B$23))-IF(AND(Control!$B$5>0,Control!$B$6="Y",1=Control!$B$39-1),Control!$B$40,0)) -> 842323.63 | E51: =Control!$B$11*(((((((Control!$B$20*$A$7)*((Control!$B$28+Control!$B$29*(Control!$B$38-2))+(Control!$B$32+Control!$B$33*(Control!$B$38-2))+IF(AND(Control!$B$5>0,Control!$B$6="Y",2>=Control!$B$39),Control!$B$36,0))*POWER(1+Control!$B$17,1))+((((Control!$B$20*$A$7)*Control!$B$38*2+IF(AND(Control!$B$5>0,Control!$B$6="Y",2>=Control!$B$39),(Control!$B$20*$A$7)*2,0))*Control!$B$41)*(Control!$B$42+Control!$B$44)*POWER(1+Control!$B$17,1))+(Control!$B$46*POWER(1+Control!$B$17,1)))-(((Control!$B$20*$A$7)*((Control!$B$28+Control!$B$29*(Control!$B$38-2))+(Control!$B$32+Control!$B$33*(Control!$B$38-2))+IF(AND(Control!$B$5>0,Control!$B$6="Y",2>=Control!$B$39),Control!$B$36,0))*POWER(1+Control!$B$17,1))*Control!$B$52+(((Control!$B$20*$A$7)*Control!$B$38*2+IF(AND(Control!$B$5>0,Control!$B$6="Y",2>=Control!$B$39),(Control!$B$20*$A$7)*2,0))*Control!$B$41)*(Control!$B$43+Control!$B$45)*POWER(1+Control!$B$18,1)+Control!$B$47*POWER(1+Control!$B$18,1)+(Control!$B$48+Control!$B$49+Control!$B$50+Control!$B$51)*12*POWER(1+Control!$B$18,1)+((Control!$B$20*$A$7)*((Control!$B$28+Control!$B$29*(Control!$B$38-2))+(Control!$B$32+Control!$B$33*(Control!$B$38-2))+IF(AND(Control!$B$5>0,Control!$B$6="Y",2>=Control!$B$39),Control!$B$36,0))*POWER(1+Control!$B$17,1))*Control!$B$26))+(((Control!$B$54*Control!$B$55+Control!$B$57*Control!$B$58*Control!$B$59*Control!$B$60)*POWER(1+Control!$B$17,1))-((Control!$B$57*Control!$B$58*Control!$B$59*Control!$B$60*POWER(1+Control!$B$17,1))*Control!$B$63+(Control!$B$64+Control!$B$65+Control!$B$66)*12*POWER(1+Control!$B$18,1)+((Control!$B$54*Control!$B$55+Control!$B$57*Control!$B$58*Control!$B$59*Control!$B$60)*POWER(1+Control!$B$17,1))*Control!$B$26))+((Control!$B$68*12*POWER(1+Control!$B$17,1))-((Control!$B$70+Control!$B$71+Control!$B$72)*12*POWER(1+Control!$B$18,1)+(Control!$B$68*12*POWER(1+Control!$B$17,1))*Control!$B$26)))*(1-Control!$B$23))-IF(AND(Control!$B$5>0,Control!$B$6="Y",2=Control!$B$39-1),Control!$B$40,0)) -> 884439.81 | F51: =Control!$B$11*(((((((Control!$B$20*$A$7)*((Control!$B$28+Control!$B$29*(Control!$B$38-2))+(Control!$B$32+Control!$B$33*(Control!$B$38-2))+IF(AND(Control!$B$5>0,Control!$B$6="Y",3>=Control!$B$39),Control!$B$36,0))*POWER(1+Control!$B$17,2))+((((Control!$B$20*$A$7)*Control!$B$38*2+IF(AND(Control!$B$5>0,Control!$B$6="Y",3>=Control!$B$39),(Control!$B$20*$A$7)*2,0))*Control!$B$41)*(Control!$B$42+Control!$B$44)*POWER(1+Control!$B$17,2))+(Control!$B$46*POWER(1+Control!$B$17,2)))-(((Control!$B$20*$A$7)*((Control!$B$28+Control!$B$29*(Control!$B$38-2))+(Control!$B$32+Control!$B$33*(Control!$B$38-2))+IF(AND(Control!$B$5>0,Control!$B$6="Y",3>=Control!$B$39),Control!$B$36,0))*POWER(1+Control!$B$17,2))*Control!$B$52+(((Control!$B$20*$A$7)*Control!$B$38*2+IF(AND(Control!$B$5>0,Control!$B$6="Y",3>=Control!$B$39),(Control!$B$20*$A$7)*2,0))*Control!$B$41)*(Control!$B$43+Control!$B$45)*POWER(1+Control!$B$18,2)+Control!$B$47*POWER(1+Control!$B$18,2)+(Control!$B$48+Control!$B$49+Control!$B$50+Control!$B$51)*12*POWER(1+Control!$B$18,2)+((Control!$B$20*$A$7)*((Control!$B$28+Control!$B$29*(Control!$B$38-2))+(Control!$B$32+Control!$B$33*(Control!$B$38-2))+IF(AND(Control!$B$5>0,Control!$B$6="Y",3>=Control!$B$39),Control!$B$36,0))*POWER(1+Control!$B$17,2))*Control!$B$26))+(((Control!$B$54*Control!$B$55+Control!$B$57*Control!$B$58*Control!$B$59*Control!$B$60)*POWER(1+Control!$B$17,2))-((Control!$B$57*Control!$B$58*Control!$B$59*Control!$B$60*POWER(1+Control!$B$17,2))*Control!$B$63+(Control!$B$64+Control!$B$65+Control!$B$66)*12*POWER(1+Control!$B$18,2)+((Control!$B$54*Control!$B$55+Control!$B$57*Control!$B$58*Control!$B$59*Control!$B$60)*POWER(1+Control!$B$17,2))*Control!$B$26))+((Control!$B$68*12*POWER(1+Control!$B$17,2))-((Control!$B$70+Control!$B$71+Control!$B$72)*12*POWER(1+Control!$B$18,2)+(Control!$B$68*12*POWER(1+Control!$B$17,2))*Control!$B$26)))*(1-Control!$B$23))-IF(AND(Control!$B$5>0,Control!$B$6="Y",3=Control!$B$39-1),Control!$B$40,0)) -> 928661.8 | G51: =Control!$B$11*(((((((Control!$B$20*$A$7)*((Control!$B$28+Control!$B$29*(Control!$B$38-2))+(Control!$B$32+Control!$B$33*(Control!$B$38-2))+IF(AND(Control!$B$5>0,Control!$B$6="Y",4>=Control!$B$39),Control!$B$36,0))*POWER(1+Control!$B$17,3))+((((Control!$B$20*$A$7)*Control!$B$38*2+IF(AND(Control!$B$5>0,Control!$B$6="Y",4>=Control!$B$39),(Control!$B$20*$A$7)*2,0))*Control!$B$41)*(Control!$B$42+Control!$B$44)*POWER(1+Control!$B$17,3))+(Control!$B$46*POWER(1+Control!$B$17,3)))-(((Control!$B$20*$A$7)*((Control!$B$28+Control!$B$29*(Control!$B$38-2))+(Control!$B$32+Control!$B$33*(Control!$B$38-2))+IF(AND(Control!$B$5>0,Control!$B$6="Y",4>=Control!$B$39),Control!$B$36,0))*POWER(1+Control!$B$17,3))*Control!$B$52+(((Control!$B$20*$A$7)*Control!$B$38*2+IF(AND(Control!$B$5>0,Control!$B$6="Y",4>=Control!$B$39),(Control!$B$20*$A$7)*2,0))*Control!$B$41)*(Control!$B$43+Control!$B$45)*POWER(1+Control!$B$18,3)+Control!$B$47*POWER(1+Control!$B$18,3)+(Control!$B$48+Control!$B$49+Control!$B$50+Control!$B$51)*12*POWER(1+Control!$B$18,3)+((Control!$B$20*$A$7)*((Control!$B$28+Control!$B$29*(Control!$B$38-2))+(Control!$B$32+Control!$B$33*(Control!$B$38-2))+IF(AND(Control!$B$5>0,Control!$B$6="Y",4>=Control!$B$39),Control!$B$36,0))*POWER(1+Control!$B$17,3))*Control!$B$26))+(((Control!$B$54*Control!$B$55+Control!$B$57*Control!$B$58*Control!$B$59*Control!$B$60)*POWER(1+Control!$B$17,3))-((Control!$B$57*Control!$B$58*Control!$B$59*Control!$B$60*POWER(1+Control!$B$17,3))*Control!$B$63+(Control!$B$64+Control!$B$65+Control!$B$66)*12*POWER(1+Control!$B$18,3)+((Control!$B$54*Control!$B$55+Control!$B$57*Control!$B$58*Control!$B$59*Control!$B$60)*POWER(1+Control!$B$17,3))*Control!$B$26))+((Control!$B$68*12*POWER(1+Control!$B$17,3))-((Control!$B$70+Control!$B$71+Control!$B$72)*12*POWER(1+Control!$B$18,3)+(Control!$B$68*12*POWER(1+Control!$B$17,3))*Control!$B$26)))*(1-Control!$B$23))-IF(AND(Control!$B$5>0,Control!$B$6="Y",4=Control!$B$39-1),Control!$B$40,0)) -> 975094.89 | H51: =Control!$B$11*(((((((Control!$B$20*$A$7)*((Control!$B$28+Control!$B$29*(Control!$B$38-2))+(Control!$B$32+Control!$B$33*(Control!$B$38-2))+IF(AND(Control!$B$5>0,Control!$B$6="Y",5>=Control!$B$39),Control!$B$36,0))*POWER(1+Control!$B$17,4))+((((Control!$B$20*$A$7)*Control!$B$38*2+IF(AND(Control!$B$5>0,Control!$B$6="Y",5>=Control!$B$39),(Control!$B$20*$A$7)*2,0))*Control!$B$41)*(Control!$B$42+Control!$B$44)*POWER(1+Control!$B$17,4))+(Control!$B$46*POWER(1+Control!$B$17,4)))-(((Control!$B$20*$A$7)*((Control!$B$28+Control!$B$29*(Control!$B$38-2))+(Control!$B$32+Control!$B$33*(Control!$B$38-2))+IF(AND(Control!$B$5>0,Control!$B$6="Y",5>=Control!$B$39),Control!$B$36,0))*POWER(1+Control!$B$17,4))*Control!$B$52+(((Control!$B$20*$A$7)*Control!$B$38*2+IF(AND(Control!$B$5>0,Control!$B$6="Y",5>=Control!$B$39),(Control!$B$20*$A$7)*2,0))*Control!$B$41)*(Control!$B$43+Control!$B$45)*POWER(1+Control!$B$18,4)+Control!$B$47*POWER(1+Control!$B$18,4)+(Control!$B$48+Control!$B$49+Control!$B$50+Control!$B$51)*12*POWER(1+Control!$B$18,4)+((Control!$B$20*$A$7)*((Control!$B$28+Control!$B$29*(Control!$B$38-2))+(Control!$B$32+Control!$B$33*(Control!$B$38-2))+IF(AND(Control!$B$5>0,Control!$B$6="Y",5>=Control!$B$39),Control!$B$36,0))*POWER(1+Control!$B$17,4))*Control!$B$26))+(((Control!$B$54*Control!$B$55+Control!$B$57*Control!$B$58*Control!$B$59*Control!$B$60)*POWER(1+Control!$B$17,4))-((Control!$B$57*Control!$B$58*Control!$B$59*Control!$B$60*POWER(1+Control!$B$17,4))*Control!$B$63+(Control!$B$64+Control!$B$65+Control!$B$66)*12*POWER(1+Control!$B$18,4)+((Control!$B$54*Control!$B$55+Control!$B$57*Control!$B$58*Control!$B$59*Control!$B$60)*POWER(1+Control!$B$17,4))*Control!$B$26))+((Control!$B$68*12*POWER(1+Control!$B$17,4))-((Control!$B$70+Control!$B$71+Control!$B$72)*12*POWER(1+Control!$B$18,4)+(Control!$B$68*12*POWER(1+Control!$B$17,4))*Control!$B$26)))*(1-Control!$B$23))-IF(AND(Control!$B$5>0,Control!$B$6="Y",5=Control!$B$39-1),Control!$B$40,0)) -> 1023849.6 | I51: =Control!$B$11*(((((((Control!$B$20*$A$7)*((Control!$B$28+Control!$B$29*(Control!$B$38-2))+(Control!$B$32+Control!$B$33*(Control!$B$38-2))+IF(AND(Control!$B$5>0,Control!$B$6="Y",6>=Control!$B$39),Control!$B$36,0))*POWER(1+Control!$B$17,5))+((((Control!$B$20*$A$7)*Control!$B$38*2+IF(AND(Control!$B$5>0,Control!$B$6="Y",6>=Control!$B$39),(Control!$B$20*$A$7)*2,0))*Control!$B$41)*(Control!$B$42+Control!$B$44)*POWER(1+Control!$B$17,5))+(Control!$B$46*POWER(1+Control!$B$17,5)))-(((Control!$B$20*$A$7)*((Control!$B$28+Control!$B$29*(Control!$B$38-2))+(Control!$B$32+Control!$B$33*(Control!$B$38-2))+IF(AND(Control!$B$5>0,Control!$B$6="Y",6>=Control!$B$39),Control!$B$36,0))*POWER(1+Control!$B$17,5))*Control!$B$52+(((Control!$B$20*$A$7)*Control!$B$38*2+IF(AND(Control!$B$5>0,Control!$B$6="Y",6>=Control!$B$39),(Control!$B$20*$A$7)*2,0))*Control!$B$41)*(Control!$B$43+Control!$B$45)*POWER(1+Control!$B$18,5)+Control!$B$47*POWER(1+Control!$B$18,5)+(Control!$B$48+Control!$B$49+Control!$B$50+Control!$B$51)*12*POWER(1+Control!$B$18,5)+((Control!$B$20*$A$7)*((Control!$B$28+Control!$B$29*(Control!$B$38-2))+(Control!$B$32+Control!$B$33*(Control!$B$38-2))+IF(AND(Control!$B$5>0,Control!$B$6="Y",6>=Control!$B$39),Control!$B$36,0))*POWER(1+Control!$B$17,5))*Control!$B$26))+(((Control!$B$54*Control!$B$55+Control!$B$57*Control!$B$58*Control!$B$59*Control!$B$60)*POWER(1+Control!$B$17,5))-((Control!$B$57*Control!$B$58*Control!$B$59*Control!$B$60*POWER(1+Control!$B$17,5))*Control!$B$63+(Control!$B$64+Control!$B$65+Control!$B$66)*12*POWER(1+Control!$B$18,5)+((Control!$B$54*Control!$B$55+Control!$B$57*Control!$B$58*Control!$B$59*Control!$B$60)*POWER(1+Control!$B$17,5))*Control!$B$26))+((Control!$B$68*12*POWER(1+Control!$B$17,5))-((Control!$B$70+Control!$B$71+Control!$B$72)*12*POWER(1+Control!$B$18,5)+(Control!$B$68*12*POWER(1+Control!$B$17,5))*Control!$B$26)))*(1-Control!$B$23))-IF(AND(Control!$B$5>0,Control!$B$6="Y",6=Control!$B$39-1),Control!$B$40,0)) -> 1075042.1 | J51: =Control!$B$11*(((((((Control!$B$20*$A$7)*((Control!$B$28+Control!$B$29*(Control!$B$38-2))+(Control!$B$32+Control!$B$33*(Control!$B$38-2))+IF(AND(Control!$B$5>0,Control!$B$6="Y",7>=Control!$B$39),Control!$B$36,0))*POWER(1+Control!$B$17,6))+((((Control!$B$20*$A$7)*Control!$B$38*2+IF(AND(Control!$B$5>0,Control!$B$6="Y",7>=Control!$B$39),(Control!$B$20*$A$7)*2,0))*Control!$B$41)*(Control!$B$42+Control!$B$44)*POWER(1+Control!$B$17,6))+(Control!$B$46*POWER(1+Control!$B$17,6)))-(((Control!$B$20*$A$7)*((Control!$B$28+Control!$B$29*(Control!$B$38-2))+(Control!$B$32+Control!$B$33*(Control!$B$38-2))+IF(AND(Control!$B$5>0,Control!$B$6="Y",7>=Control!$B$39),Control!$B$36,0))*POWER(1+Control!$B$17,6))*Control!$B$52+(((Control!$B$20*$A$7)*Control!$B$38*2+IF(AND(Control!$B$5>0,Control!$B$6="Y",7>=Control!$B$39),(Control!$B$20*$A$7)*2,0))*Control!$B$41)*(Control!$B$43+Control!$B$45)*POWER(1+Control!$B$18,6)+Control!$B$47*POWER(1+Control!$B$18,6)+(Control!$B$48+Control!$B$49+Control!$B$50+Control!$B$51)*12*POWER(1+Control!$B$18,6)+((Control!$B$20*$A$7)*((Control!$B$28+Control!$B$29*(Control!$B$38-2))+(Control!$B$32+Control!$B$33*(Control!$B$38-2))+IF(AND(Control!$B$5>0,Control!$B$6="Y",7>=Control!$B$39),Control!$B$36,0))*POWER(1+Control!$B$17,6))*Control!$B$26))+(((Control!$B$54*Control!$B$55+Control!$B$57*Control!$B$58*Control!$B$59*Control!$B$60)*POWER(1+Control!$B$17,6))-((Control!$B$57*Control!$B$58*Control!$B$59*Control!$B$60*POWER(1+Control!$B$17,6))*Control!$B$63+(Control!$B$64+Control!$B$65+Control!$B$66)*12*POWER(1+Control!$B$18,6)+((Control!$B$54*Control!$B$55+Control!$B$57*Control!$B$58*Control!$B$59*Control!$B$60)*POWER(1+Control!$B$17,6))*Control!$B$26))+((Control!$B$68*12*POWER(1+Control!$B$17,6))-((Control!$B$70+Control!$B$71+Control!$B$72)*12*POWER(1+Control!$B$18,6)+(Control!$B$68*12*POWER(1+Control!$B$17,6))*Control!$B$26)))*(1-Control!$B$23))-IF(AND(Control!$B$5>0,Control!$B$6="Y",7=Control!$B$39-1),Control!$B$40,0)) -> 1128794.2 | K51: =Control!$B$11*(((((((Control!$B$20*$A$7)*((Control!$B$28+Control!$B$29*(Control!$B$38-2))+(Control!$B$32+Control!$B$33*(Control!$B$38-2))+IF(AND(Control!$B$5>0,Control!$B$6="Y",8>=Control!$B$39),Control!$B$36,0))*POWER(1+Control!$B$17,7))+((((Control!$B$20*$A$7)*Control!$B$38*2+IF(AND(Control!$B$5>0,Control!$B$6="Y",8>=Control!$B$39),(Control!$B$20*$A$7)*2,0))*Control!$B$41)*(Control!$B$42+Control!$B$44)*POWER(1+Control!$B$17,7))+(Control!$B$46*POWER(1+Control!$B$17,7)))-(((Control!$B$20*$A$7)*((Control!$B$28+Control!$B$29*(Control!$B$38-2))+(Control!$B$32+Control!$B$33*(Control!$B$38-2))+IF(AND(Control!$B$5>0,Control!$B$6="Y",8>=Control!$B$39),Control!$B$36,0))*POWER(1+Control!$B$17,7))*Control!$B$52+(((Control!$B$20*$A$7)*Control!$B$38*2+IF(AND(Control!$B$5>0,Control!$B$6="Y",8>=Control!$B$39),(Control!$B$20*$A$7)*2,0))*Control!$B$41)*(Control!$B$43+Control!$B$45)*POWER(1+Control!$B$18,7)+Control!$B$47*POWER(1+Control!$B$18,7)+(Control!$B$48+Control!$B$49+Control!$B$50+Control!$B$51)*12*POWER(1+Control!$B$18,7)+((Control!$B$20*$A$7)*((Control!$B$28+Control!$B$29*(Control!$B$38-2))+(Control!$B$32+Control!$B$33*(Control!$B$38-2))+IF(AND(Control!$B$5>0,Control!$B$6="Y",8>=Control!$B$39),Control!$B$36,0))*POWER(1+Control!$B$17,7))*Control!$B$26))+(((Control!$B$54*Control!$B$55+Control!$B$57*Control!$B$58*Control!$B$59*Control!$B$60)*POWER(1+Control!$B$17,7))-((Control!$B$57*Control!$B$58*Control!$B$59*Control!$B$60*POWER(1+Control!$B$17,7))*Control!$B$63+(Control!$B$64+Control!$B$65+Control!$B$66)*12*POWER(1+Control!$B$18,7)+((Control!$B$54*Control!$B$55+Control!$B$57*Control!$B$58*Control!$B$59*Control!$B$60)*POWER(1+Control!$B$17,7))*Control!$B$26))+((Control!$B$68*12*POWER(1+Control!$B$17,7))-((Control!$B$70+Control!$B$71+Control!$B$72)*12*POWER(1+Control!$B$18,7)+(Control!$B$68*12*POWER(1+Control!$B$17,7))*Control!$B$26)))*(1-Control!$B$23))-IF(AND(Control!$B$5>0,Control!$B$6="Y",8=Control!$B$39-1),Control!$B$40,0)) -> 1185233.9 | L51: =Control!$B$11*(((((((Control!$B$20*$A$7)*((Control!$B$28+Control!$B$29*(Control!$B$38-2))+(Control!$B$32+Control!$B$33*(Control!$B$38-2))+IF(AND(Control!$B$5>0,Control!$B$6="Y",9>=Control!$B$39),Control!$B$36,0))*POWER(1+Control!$B$17,8))+((((Control!$B$20*$A$7)*Control!$B$38*2+IF(AND(Control!$B$5>0,Control!$B$6="Y",9>=Control!$B$39),(Control!$B$20*$A$7)*2,0))*Control!$B$41)*(Control!$B$42+Control!$B$44)*POWER(1+Control!$B$17,8))+(Control!$B$46*POWER(1+Control!$B$17,8)))-(((Control!$B$20*$A$7)*((Control!$B$28+Control!$B$29*(Control!$B$38-2))+(Control!$B$32+Control!$B$33*(Control!$B$38-2))+IF(AND(Control!$B$5>0,Control!$B$6="Y",9>=Control!$B$39),Control!$B$36,0))*POWER(1+Control!$B$17,8))*Control!$B$52+(((Control!$B$20*$A$7)*Control!$B$38*2+IF(AND(Control!$B$5>0,Control!$B$6="Y",9>=Control!$B$39),(Control!$B$20*$A$7)*2,0))*Control!$B$41)*(Control!$B$43+Control!$B$45)*POWER(1+Control!$B$18,8)+Control!$B$47*POWER(1+Control!$B$18,8)+(Control!$B$48+Control!$B$49+Control!$B$50+Control!$B$51)*12*POWER(1+Control!$B$18,8)+((Control!$B$20*$A$7)*((Control!$B$28+Control!$B$29*(Control!$B$38-2))+(Control!$B$32+Control!$B$33*(Control!$B$38-2))+IF(AND(Control!$B$5>0,Control!$B$6="Y",9>=Control!$B$39),Control!$B$36,0))*POWER(1+Control!$B$17,8))*Control!$B$26))+(((Control!$B$54*Control!$B$55+Control!$B$57*Control!$B$58*Control!$B$59*Control!$B$60)*POWER(1+Control!$B$17,8))-((Control!$B$57*Control!$B$58*Control!$B$59*Control!$B$60*POWER(1+Control!$B$17,8))*Control!$B$63+(Control!$B$64+Control!$B$65+Control!$B$66)*12*POWER(1+Control!$B$18,8)+((Control!$B$54*Control!$B$55+Control!$B$57*Control!$B$58*Control!$B$59*Control!$B$60)*POWER(1+Control!$B$17,8))*Control!$B$26))+((Control!$B$68*12*POWER(1+Control!$B$17,8))-((Control!$B$70+Control!$B$71+Control!$B$72)*12*POWER(1+Control!$B$18,8)+(Control!$B$68*12*POWER(1+Control!$B$17,8))*Control!$B$26)))*(1-Control!$B$23))-IF(AND(Control!$B$5>0,Control!$B$6="Y",9=Control!$B$39-1),Control!$B$40,0)) -> 1244495.6 | M51: =Control!$B$11*(((((((Control!$B$20*$A$7)*((Control!$B$28+Control!$B$29*(Control!$B$38-2))+(Control!$B$32+Control!$B$33*(Control!$B$38-2))+IF(AND(Control!$B$5>0,Control!$B$6="Y",10>=Control!$B$39),Control!$B$36,0))*POWER(1+Control!$B$17,9))+((((Control!$B$20*$A$7)*Control!$B$38*2+IF(AND(Control!$B$5>0,Control!$B$6="Y",10>=Control!$B$39),(Control!$B$20*$A$7)*2,0))*Control!$B$41)*(Control!$B$42+Control!$B$44)*POWER(1+Control!$B$17,9))+(Control!$B$46*POWER(1+Control!$B$17,9)))-(((Control!$B$20*$A$7)*((Control!$B$28+Control!$B$29*(Control!$B$38-2))+(Control!$B$32+Control!$B$33*(Control!$B$38-2))+IF(AND(Control!$B$5>0,Control!$B$6="Y",10>=Control!$B$39),Control!$B$36,0))*POWER(1+Control!$B$17,9))*Control!$B$52+(((Control!$B$20*$A$7)*Control!$B$38*2+IF(AND(Control!$B$5>0,Control!$B$6="Y",10>=Control!$B$39),(Control!$B$20*$A$7)*2,0))*Control!$B$41)*(Control!$B$43+Control!$B$45)*POWER(1+Control!$B$18,9)+Control!$B$47*POWER(1+Control!$B$18,9)+(Control!$B$48+Control!$B$49+Control!$B$50+Control!$B$51)*12*POWER(1+Control!$B$18,9)+((Control!$B$20*$A$7)*((Control!$B$28+Control!$B$29*(Control!$B$38-2))+(Control!$B$32+Control!$B$33*(Control!$B$38-2))+IF(AND(Control!$B$5>0,Control!$B$6="Y",10>=Control!$B$39),Control!$B$36,0))*POWER(1+Control!$B$17,9))*Control!$B$26))+(((Control!$B$54*Control!$B$55+Control!$B$57*Control!$B$58*Control!$B$59*Control!$B$60)*POWER(1+Control!$B$17,9))-((Control!$B$57*Control!$B$58*Control!$B$59*Control!$B$60*POWER(1+Control!$B$17,9))*Control!$B$63+(Control!$B$64+Control!$B$65+Control!$B$66)*12*POWER(1+Control!$B$18,9)+((Control!$B$54*Control!$B$55+Control!$B$57*Control!$B$58*Control!$B$59*Control!$B$60)*POWER(1+Control!$B$17,9))*Control!$B$26))+((Control!$B$68*12*POWER(1+Control!$B$17,9))-((Control!$B$70+Control!$B$71+Control!$B$72)*12*POWER(1+Control!$B$18,9)+(Control!$B$68*12*POWER(1+Control!$B$17,9))*Control!$B$26)))*(1-Control!$B$23))-IF(AND(Control!$B$5>0,Control!$B$6="Y",10=Control!$B$39-1),Control!$B$40,0)) -> 1306720.4 | N51: =Control!$B$11*(((((((Control!$B$20*$A$7)*((Control!$B$28+Control!$B$29*(Control!$B$38-2))+(Control!$B$32+Control!$B$33*(Control!$B$38-2))+IF(AND(Control!$B$5>0,Control!$B$6="Y",11>=Control!$B$39),Control!$B$36,0))*POWER(1+Control!$B$17,10))+((((Control!$B$20*$A$7)*Control!$B$38*2+IF(AND(Control!$B$5>0,Control!$B$6="Y",11>=Control!$B$39),(Control!$B$20*$A$7)*2,0))*Control!$B$41)*(Control!$B$42+Control!$B$44)*POWER(1+Control!$B$17,10))+(Control!$B$46*POWER(1+Control!$B$17,10)))-(((Control!$B$20*$A$7)*((Control!$B$28+Control!$B$29*(Control!$B$38-2))+(Control!$B$32+Control!$B$33*(Control!$B$38-2))+IF(AND(Control!$B$5>0,Control!$B$6="Y",11>=Control!$B$39),Control!$B$36,0))*POWER(1+Control!$B$17,10))*Control!$B$52+(((Control!$B$20*$A$7)*Control!$B$38*2+IF(AND(Control!$B$5>0,Control!$B$6="Y",11>=Control!$B$39),(Control!$B$20*$A$7)*2,0))*Control!$B$41)*(Control!$B$43+Control!$B$45)*POWER(1+Control!$B$18,10)+Control!$B$47*POWER(1+Control!$B$18,10)+(Control!$B$48+Control!$B$49+Control!$B$50+Control!$B$51)*12*POWER(1+Control!$B$18,10)+((Control!$B$20*$A$7)*((Control!$B$28+Control!$B$29*(Control!$B$38-2))+(Control!$B$32+Control!$B$33*(Control!$B$38-2))+IF(AND(Control!$B$5>0,Control!$B$6="Y",11>=Control!$B$39),Control!$B$36,0))*POWER(1+Control!$B$17,10))*Control!$B$26))+(((Control!$B$54*Control!$B$55+Control!$B$57*Control!$B$58*Control!$B$59*Control!$B$60)*POWER(1+Control!$B$17,10))-((Control!$B$57*Control!$B$58*Control!$B$59*Control!$B$60*POWER(1+Control!$B$17,10))*Control!$B$63+(Control!$B$64+Control!$B$65+Control!$B$66)*12*POWER(1+Control!$B$18,10)+((Control!$B$54*Control!$B$55+Control!$B$57*Control!$B$58*Control!$B$59*Control!$B$60)*POWER(1+Control!$B$17,10))*Control!$B$26))+((Control!$B$68*12*POWER(1+Control!$B$17,10))-((Control!$B$70+Control!$B$71+Control!$B$72)*12*POWER(1+Control!$B$18,10)+(Control!$B$68*12*POWER(1+Control!$B$17,10))*Control!$B$26)))*(1-Control!$B$23))-IF(AND(Control!$B$5>0,Control!$B$6="Y",11=Control!$B$39-1),Control!$B$40,0)) -> 1372056.4 | O51: =Control!$B$11*(((((((Control!$B$20*$A$7)*((Control!$B$28+Control!$B$29*(Control!$B$38-2))+(Control!$B$32+Control!$B$33*(Control!$B$38-2))+IF(AND(Control!$B$5>0,Control!$B$6="Y",12>=Control!$B$39),Control!$B$36,0))*POWER(1+Control!$B$17,11))+((((Control!$B$20*$A$7)*Control!$B$38*2+IF(AND(Control!$B$5>0,Control!$B$6="Y",12>=Control!$B$39),(Control!$B$20*$A$7)*2,0))*Control!$B$41)*(Control!$B$42+Control!$B$44)*POWER(1+Control!$B$17,11))+(Control!$B$46*POWER(1+Control!$B$17,11)))-(((Control!$B$20*$A$7)*((Control!$B$28+Control!$B$29*(Control!$B$38-2))+(Control!$B$32+Control!$B$33*(Control!$B$38-2))+IF(AND(Control!$B$5>0,Control!$B$6="Y",12>=Control!$B$39),Control!$B$36,0))*POWER(1+Control!$B$17,11))*Control!$B$52+(((Control!$B$20*$A$7)*Control!$B$38*2+IF(AND(Control!$B$5>0,Control!$B$6="Y",12>=Control!$B$39),(Control!$B$20*$A$7)*2,0))*Control!$B$41)*(Control!$B$43+Control!$B$45)*POWER(1+Control!$B$18,11)+Control!$B$47*POWER(1+Control!$B$18,11)+(Control!$B$48+Control!$B$49+Control!$B$50+Control!$B$51)*12*POWER(1+Control!$B$18,11)+((Control!$B$20*$A$7)*((Control!$B$28+Control!$B$29*(Control!$B$38-2))+(Control!$B$32+Control!$B$33*(Control!$B$38-2))+IF(AND(Control!$B$5>0,Control!$B$6="Y",12>=Control!$B$39),Control!$B$36,0))*POWER(1+Control!$B$17,11))*Control!$B$26))+(((Control!$B$54*Control!$B$55+Control!$B$57*Control!$B$58*Control!$B$59*Control!$B$60)*POWER(1+Control!$B$17,11))-((Control!$B$57*Control!$B$58*Control!$B$59*Control!$B$60*POWER(1+Control!$B$17,11))*Control!$B$63+(Control!$B$64+Control!$B$65+Control!$B$66)*12*POWER(1+Control!$B$18,11)+((Control!$B$54*Control!$B$55+Control!$B$57*Control!$B$58*Control!$B$59*Control!$B$60)*POWER(1+Control!$B$17,11))*Control!$B$26))+((Control!$B$68*12*POWER(1+Control!$B$17,11))-((Control!$B$70+Control!$B$71+Control!$B$72)*12*POWER(1+Control!$B$18,11)+(Control!$B$68*12*POWER(1+Control!$B$17,11))*Control!$B$26)))*(1-Control!$B$23))-IF(AND(Control!$B$5>0,Control!$B$6="Y",12=Control!$B$39-1),Control!$B$40,0)) -> 1440659.3 | P51: =Control!$B$11*(((((((Control!$B$20*$A$7)*((Control!$B$28+Control!$B$29*(Control!$B$38-2))+(Control!$B$32+Control!$B$33*(Control!$B$38-2))+IF(AND(Control!$B$5>0,Control!$B$6="Y",13>=Control!$B$39),Control!$B$36,0))*POWER(1+Control!$B$17,12))+((((Control!$B$20*$A$7)*Control!$B$38*2+IF(AND(Control!$B$5>0,Control!$B$6="Y",13>=Control!$B$39),(Control!$B$20*$A$7)*2,0))*Control!$B$41)*(Control!$B$42+Control!$B$44)*POWER(1+Control!$B$17,12))+(Control!$B$46*POWER(1+Control!$B$17,12)))-(((Control!$B$20*$A$7)*((Control!$B$28+Control!$B$29*(Control!$B$38-2))+(Control!$B$32+Control!$B$33*(Control!$B$38-2))+IF(AND(Control!$B$5>0,Control!$B$6="Y",13>=Control!$B$39),Control!$B$36,0))*POWER(1+Control!$B$17,12))*Control!$B$52+(((Control!$B$20*$A$7)*Control!$B$38*2+IF(AND(Control!$B$5>0,Control!$B$6="Y",13>=Control!$B$39),(Control!$B$20*$A$7)*2,0))*Control!$B$41)*(Control!$B$43+Control!$B$45)*POWER(1+Control!$B$18,12)+Control!$B$47*POWER(1+Control!$B$18,12)+(Control!$B$48+Control!$B$49+Control!$B$50+Control!$B$51)*12*POWER(1+Control!$B$18,12)+((Control!$B$20*$A$7)*((Control!$B$28+Control!$B$29*(Control!$B$38-2))+(Control!$B$32+Control!$B$33*(Control!$B$38-2))+IF(AND(Control!$B$5>0,Control!$B$6="Y",13>=Control!$B$39),Control!$B$36,0))*POWER(1+Control!$B$17,12))*Control!$B$26))+(((Control!$B$54*Control!$B$55+Control!$B$57*Control!$B$58*Control!$B$59*Control!$B$60)*POWER(1+Control!$B$17,12))-((Control!$B$57*Control!$B$58*Control!$B$59*Control!$B$60*POWER(1+Control!$B$17,12))*Control!$B$63+(Control!$B$64+Control!$B$65+Control!$B$66)*12*POWER(1+Control!$B$18,12)+((Control!$B$54*Control!$B$55+Control!$B$57*Control!$B$58*Control!$B$59*Control!$B$60)*POWER(1+Control!$B$17,12))*Control!$B$26))+((Control!$B$68*12*POWER(1+Control!$B$17,12))-((Control!$B$70+Control!$B$71+Control!$B$72)*12*POWER(1+Control!$B$18,12)+(Control!$B$68*12*POWER(1+Control!$B$17,12))*Control!$B$26)))*(1-Control!$B$23))-IF(AND(Control!$B$5>0,Control!$B$6="Y",13=Control!$B$39-1),Control!$B$40,0)) -> 1512692.2 | Q51: =Control!$B$11*(((((((Control!$B$20*$A$7)*((Control!$B$28+Control!$B$29*(Control!$B$38-2))+(Control!$B$32+Control!$B$33*(Control!$B$38-2))+IF(AND(Control!$B$5>0,Control!$B$6="Y",14>=Control!$B$39),Control!$B$36,0))*POWER(1+Control!$B$17,13))+((((Control!$B$20*$A$7)*Control!$B$38*2+IF(AND(Control!$B$5>0,Control!$B$6="Y",14>=Control!$B$39),(Control!$B$20*$A$7)*2,0))*Control!$B$41)*(Control!$B$42+Control!$B$44)*POWER(1+Control!$B$17,13))+(Control!$B$46*POWER(1+Control!$B$17,13)))-(((Control!$B$20*$A$7)*((Control!$B$28+Control!$B$29*(Control!$B$38-2))+(Control!$B$32+Control!$B$33*(Control!$B$38-2))+IF(AND(Control!$B$5>0,Control!$B$6="Y",14>=Control!$B$39),Control!$B$36,0))*POWER(1+Control!$B$17,13))*Control!$B$52+(((Control!$B$20*$A$7)*Control!$B$38*2+IF(AND(Control!$B$5>0,Control!$B$6="Y",14>=Control!$B$39),(Control!$B$20*$A$7)*2,0))*Control!$B$41)*(Control!$B$43+Control!$B$45)*POWER(1+Control!$B$18,13)+Control!$B$47*POWER(1+Control!$B$18,13)+(Control!$B$48+Control!$B$49+Control!$B$50+Control!$B$51)*12*POWER(1+Control!$B$18,13)+((Control!$B$20*$A$7)*((Control!$B$28+Control!$B$29*(Control!$B$38-2))+(Control!$B$32+Control!$B$33*(Control!$B$38-2))+IF(AND(Control!$B$5>0,Control!$B$6="Y",14>=Control!$B$39),Control!$B$36,0))*POWER(1+Control!$B$17,13))*Control!$B$26))+(((Control!$B$54*Control!$B$55+Control!$B$57*Control!$B$58*Control!$B$59*Control!$B$60)*POWER(1+Control!$B$17,13))-((Control!$B$57*Control!$B$58*Control!$B$59*Control!$B$60*POWER(1+Control!$B$17,13))*Control!$B$63+(Control!$B$64+Control!$B$65+Control!$B$66)*12*POWER(1+Control!$B$18,13)+((Control!$B$54*Control!$B$55+Control!$B$57*Control!$B$58*Control!$B$59*Control!$B$60)*POWER(1+Control!$B$17,13))*Control!$B$26))+((Control!$B$68*12*POWER(1+Control!$B$17,13))-((Control!$B$70+Control!$B$71+Control!$B$72)*12*POWER(1+Control!$B$18,13)+(Control!$B$68*12*POWER(1+Control!$B$17,13))*Control!$B$26)))*(1-Control!$B$23))-IF(AND(Control!$B$5>0,Control!$B$6="Y",14=Control!$B$39-1),Control!$B$40,0)) -> 1588326.8 | R51: =Control!$B$11*(((((((Control!$B$20*$A$7)*((Control!$B$28+Control!$B$29*(Control!$B$38-2))+(Control!$B$32+Control!$B$33*(Control!$B$38-2))+IF(AND(Control!$B$5>0,Control!$B$6="Y",15>=Control!$B$39),Control!$B$36,0))*POWER(1+Control!$B$17,14))+((((Control!$B$20*$A$7)*Control!$B$38*2+IF(AND(Control!$B$5>0,Control!$B$6="Y",15>=Control!$B$39),(Control!$B$20*$A$7)*2,0))*Control!$B$41)*(Control!$B$42+Control!$B$44)*POWER(1+Control!$B$17,14))+(Control!$B$46*POWER(1+Control!$B$17,14)))-(((Control!$B$20*$A$7)*((Control!$B$28+Control!$B$29*(Control!$B$38-2))+(Control!$B$32+Control!$B$33*(Control!$B$38-2))+IF(AND(Control!$B$5>0,Control!$B$6="Y",15>=Control!$B$39),Control!$B$36,0))*POWER(1+Control!$B$17,14))*Control!$B$52+(((Control!$B$20*$A$7)*Control!$B$38*2+IF(AND(Control!$B$5>0,Control!$B$6="Y",15>=Control!$B$39),(Control!$B$20*$A$7)*2,0))*Control!$B$41)*(Control!$B$43+Control!$B$45)*POWER(1+Control!$B$18,14)+Control!$B$47*POWER(1+Control!$B$18,14)+(Control!$B$48+Control!$B$49+Control!$B$50+Control!$B$51)*12*POWER(1+Control!$B$18,14)+((Control!$B$20*$A$7)*((Control!$B$28+Control!$B$29*(Control!$B$38-2))+(Control!$B$32+Control!$B$33*(Control!$B$38-2))+IF(AND(Control!$B$5>0,Control!$B$6="Y",15>=Control!$B$39),Control!$B$36,0))*POWER(1+Control!$B$17,14))*Control!$B$26))+(((Control!$B$54*Control!$B$55+Control!$B$57*Control!$B$58*Control!$B$59*Control!$B$60)*POWER(1+Control!$B$17,14))-((Control!$B$57*Control!$B$58*Control!$B$59*Control!$B$60*POWER(1+Control!$B$17,14))*Control!$B$63+(Control!$B$64+Control!$B$65+Control!$B$66)*12*POWER(1+Control!$B$18,14)+((Control!$B$54*Control!$B$55+Control!$B$57*Control!$B$58*Control!$B$59*Control!$B$60)*POWER(1+Control!$B$17,14))*Control!$B$26))+((Control!$B$68*12*POWER(1+Control!$B$17,14))-((Control!$B$70+Control!$B$71+Control!$B$72)*12*POWER(1+Control!$B$18,14)+(Control!$B$68*12*POWER(1+Control!$B$17,14))*Control!$B$26)))*(1-Control!$B$23))-IF(AND(Control!$B$5>0,Control!$B$6="Y",15=Control!$B$39-1),Control!$B$40,0)) -> 1667743.2 | S51: =Control!$B$11*(((((((Control!$B$20*$A$7)*((Control!$B$28+Control!$B$29*(Control!$B$38-2))+(Control!$B$32+Control!$B$33*(Control!$B$38-2))+IF(AND(Control!$B$5>0,Control!$B$6="Y",16>=Control!$B$39),Control!$B$36,0))*POWER(1+Control!$B$17,15))+((((Control!$B$20*$A$7)*Control!$B$38*2+IF(AND(Control!$B$5>0,Control!$B$6="Y",16>=Control!$B$39),(Control!$B$20*$A$7)*2,0))*Control!$B$41)*(Control!$B$42+Control!$B$44)*POWER(1+Control!$B$17,15))+(Control!$B$46*POWER(1+Control!$B$17,15)))-(((Control!$B$20*$A$7)*((Control!$B$28+Control!$B$29*(Control!$B$38-2))+(Control!$B$32+Control!$B$33*(Control!$B$38-2))+IF(AND(Control!$B$5>0,Control!$B$6="Y",16>=Control!$B$39),Control!$B$36,0))*POWER(1+Control!$B$17,15))*Control!$B$52+(((Control!$B$20*$A$7)*Control!$B$38*2+IF(AND(Control!$B$5>0,Control!$B$6="Y",16>=Control!$B$39),(Control!$B$20*$A$7)*2,0))*Control!$B$41)*(Control!$B$43+Control!$B$45)*POWER(1+Control!$B$18,15)+Control!$B$47*POWER(1+Control!$B$18,15)+(Control!$B$48+Control!$B$49+Control!$B$50+Control!$B$51)*12*POWER(1+Control!$B$18,15)+((Control!$B$20*$A$7)*((Control!$B$28+Control!$B$29*(Control!$B$38-2))+(Control!$B$32+Control!$B$33*(Control!$B$38-2))+IF(AND(Control!$B$5>0,Control!$B$6="Y",16>=Control!$B$39),Control!$B$36,0))*POWER(1+Control!$B$17,15))*Control!$B$26))+(((Control!$B$54*Control!$B$55+Control!$B$57*Control!$B$58*Control!$B$59*Control!$B$60)*POWER(1+Control!$B$17,15))-((Control!$B$57*Control!$B$58*Control!$B$59*Control!$B$60*POWER(1+Control!$B$17,15))*Control!$B$63+(Control!$B$64+Control!$B$65+Control!$B$66)*12*POWER(1+Control!$B$18,15)+((Control!$B$54*Control!$B$55+Control!$B$57*Control!$B$58*Control!$B$59*Control!$B$60)*POWER(1+Control!$B$17,15))*Control!$B$26))+((Control!$B$68*12*POWER(1+Control!$B$17,15))-((Control!$B$70+Control!$B$71+Control!$B$72)*12*POWER(1+Control!$B$18,15)+(Control!$B$68*12*POWER(1+Control!$B$17,15))*Control!$B$26)))*(1-Control!$B$23))-IF(AND(Control!$B$5>0,Control!$B$6="Y",16=Control!$B$39-1),Control!$B$40,0)) -> 1751130.3 | T51: =Control!$B$11*(((((((Control!$B$20*$A$7)*((Control!$B$28+Control!$B$29*(Control!$B$38-2))+(Control!$B$32+Control!$B$33*(Control!$B$38-2))+IF(AND(Control!$B$5>0,Control!$B$6="Y",17>=Control!$B$39),Control!$B$36,0))*POWER(1+Control!$B$17,16))+((((Control!$B$20*$A$7)*Control!$B$38*2+IF(AND(Control!$B$5>0,Control!$B$6="Y",17>=Control!$B$39),(Control!$B$20*$A$7)*2,0))*Control!$B$41)*(Control!$B$42+Control!$B$44)*POWER(1+Control!$B$17,16))+(Control!$B$46*POWER(1+Control!$B$17,16)))-(((Control!$B$20*$A$7)*((Control!$B$28+Control!$B$29*(Control!$B$38-2))+(Control!$B$32+Control!$B$33*(Control!$B$38-2))+IF(AND(Control!$B$5>0,Control!$B$6="Y",17>=Control!$B$39),Control!$B$36,0))*POWER(1+Control!$B$17,16))*Control!$B$52+(((Control!$B$20*$A$7)*Control!$B$38*2+IF(AND(Control!$B$5>0,Control!$B$6="Y",17>=Control!$B$39),(Control!$B$20*$A$7)*2,0))*Control!$B$41)*(Control!$B$43+Control!$B$45)*POWER(1+Control!$B$18,16)+Control!$B$47*POWER(1+Control!$B$18,16)+(Control!$B$48+Control!$B$49+Control!$B$50+Control!$B$51)*12*POWER(1+Control!$B$18,16)+((Control!$B$20*$A$7)*((Control!$B$28+Control!$B$29*(Control!$B$38-2))+(Control!$B$32+Control!$B$33*(Control!$B$38-2))+IF(AND(Control!$B$5>0,Control!$B$6="Y",17>=Control!$B$39),Control!$B$36,0))*POWER(1+Control!$B$17,16))*Control!$B$26))+(((Control!$B$54*Control!$B$55+Control!$B$57*Control!$B$58*Control!$B$59*Control!$B$60)*POWER(1+Control!$B$17,16))-((Control!$B$57*Control!$B$58*Control!$B$59*Control!$B$60*POWER(1+Control!$B$17,16))*Control!$B$63+(Control!$B$64+Control!$B$65+Control!$B$66)*12*POWER(1+Control!$B$18,16)+((Control!$B$54*Control!$B$55+Control!$B$57*Control!$B$58*Control!$B$59*Control!$B$60)*POWER(1+Control!$B$17,16))*Control!$B$26))+((Control!$B$68*12*POWER(1+Control!$B$17,16))-((Control!$B$70+Control!$B$71+Control!$B$72)*12*POWER(1+Control!$B$18,16)+(Control!$B$68*12*POWER(1+Control!$B$17,16))*Control!$B$26)))*(1-Control!$B$23))-IF(AND(Control!$B$5>0,Control!$B$6="Y",17=Control!$B$39-1),Control!$B$40,0)) -> 1838686.8 | U51: =Control!$B$11*(((((((Control!$B$20*$A$7)*((Control!$B$28+Control!$B$29*(Control!$B$38-2))+(Control!$B$32+Control!$B$33*(Control!$B$38-2))+IF(AND(Control!$B$5>0,Control!$B$6="Y",18>=Control!$B$39),Control!$B$36,0))*POWER(1+Control!$B$17,17))+((((Control!$B$20*$A$7)*Control!$B$38*2+IF(AND(Control!$B$5>0,Control!$B$6="Y",18>=Control!$B$39),(Control!$B$20*$A$7)*2,0))*Control!$B$41)*(Control!$B$42+Control!$B$44)*POWER(1+Control!$B$17,17))+(Control!$B$46*POWER(1+Control!$B$17,17)))-(((Control!$B$20*$A$7)*((Control!$B$28+Control!$B$29*(Control!$B$38-2))+(Control!$B$32+Control!$B$33*(Control!$B$38-2))+IF(AND(Control!$B$5>0,Control!$B$6="Y",18>=Control!$B$39),Control!$B$36,0))*POWER(1+Control!$B$17,17))*Control!$B$52+(((Control!$B$20*$A$7)*Control!$B$38*2+IF(AND(Control!$B$5>0,Control!$B$6="Y",18>=Control!$B$39),(Control!$B$20*$A$7)*2,0))*Control!$B$41)*(Control!$B$43+Control!$B$45)*POWER(1+Control!$B$18,17)+Control!$B$47*POWER(1+Control!$B$18,17)+(Control!$B$48+Control!$B$49+Control!$B$50+Control!$B$51)*12*POWER(1+Control!$B$18,17)+((Control!$B$20*$A$7)*((Control!$B$28+Control!$B$29*(Control!$B$38-2))+(Control!$B$32+Control!$B$33*(Control!$B$38-2))+IF(AND(Control!$B$5>0,Control!$B$6="Y",18>=Control!$B$39),Control!$B$36,0))*POWER(1+Control!$B$17,17))*Control!$B$26))+(((Control!$B$54*Control!$B$55+Control!$B$57*Control!$B$58*Control!$B$59*Control!$B$60)*POWER(1+Control!$B$17,17))-((Control!$B$57*Control!$B$58*Control!$B$59*Control!$B$60*POWER(1+Control!$B$17,17))*Control!$B$63+(Control!$B$64+Control!$B$65+Control!$B$66)*12*POWER(1+Control!$B$18,17)+((Control!$B$54*Control!$B$55+Control!$B$57*Control!$B$58*Control!$B$59*Control!$B$60)*POWER(1+Control!$B$17,17))*Control!$B$26))+((Control!$B$68*12*POWER(1+Control!$B$17,17))-((Control!$B$70+Control!$B$71+Control!$B$72)*12*POWER(1+Control!$B$18,17)+(Control!$B$68*12*POWER(1+Control!$B$17,17))*Control!$B$26)))*(1-Control!$B$23))-IF(AND(Control!$B$5>0,Control!$B$6="Y",18=Control!$B$39-1),Control!$B$40,0)) -> 1930621.2 | V51: =Control!$B$11*(((((((Control!$B$20*$A$7)*((Control!$B$28+Control!$B$29*(Control!$B$38-2))+(Control!$B$32+Control!$B$33*(Control!$B$38-2))+IF(AND(Control!$B$5>0,Control!$B$6="Y",19>=Control!$B$39),Control!$B$36,0))*POWER(1+Control!$B$17,18))+((((Control!$B$20*$A$7)*Control!$B$38*2+IF(AND(Control!$B$5>0,Control!$B$6="Y",19>=Control!$B$39),(Control!$B$20*$A$7)*2,0))*Control!$B$41)*(Control!$B$42+Control!$B$44)*POWER(1+Control!$B$17,18))+(Control!$B$46*POWER(1+Control!$B$17,18)))-(((Control!$B$20*$A$7)*((Control!$B$28+Control!$B$29*(Control!$B$38-2))+(Control!$B$32+Control!$B$33*(Control!$B$38-2))+IF(AND(Control!$B$5>0,Control!$B$6="Y",19>=Control!$B$39),Control!$B$36,0))*POWER(1+Control!$B$17,18))*Control!$B$52+(((Control!$B$20*$A$7)*Control!$B$38*2+IF(AND(Control!$B$5>0,Control!$B$6="Y",19>=Control!$B$39),(Control!$B$20*$A$7)*2,0))*Control!$B$41)*(Control!$B$43+Control!$B$45)*POWER(1+Control!$B$18,18)+Control!$B$47*POWER(1+Control!$B$18,18)+(Control!$B$48+Control!$B$49+Control!$B$50+Control!$B$51)*12*POWER(1+Control!$B$18,18)+((Control!$B$20*$A$7)*((Control!$B$28+Control!$B$29*(Control!$B$38-2))+(Control!$B$32+Control!$B$33*(Control!$B$38-2))+IF(AND(Control!$B$5>0,Control!$B$6="Y",19>=Control!$B$39),Control!$B$36,0))*POWER(1+Control!$B$17,18))*Control!$B$26))+(((Control!$B$54*Control!$B$55+Control!$B$57*Control!$B$58*Control!$B$59*Control!$B$60)*POWER(1+Control!$B$17,18))-((Control!$B$57*Control!$B$58*Control!$B$59*Control!$B$60*POWER(1+Control!$B$17,18))*Control!$B$63+(Control!$B$64+Control!$B$65+Control!$B$66)*12*POWER(1+Control!$B$18,18)+((Control!$B$54*Control!$B$55+Control!$B$57*Control!$B$58*Control!$B$59*Control!$B$60)*POWER(1+Control!$B$17,18))*Control!$B$26))+((Control!$B$68*12*POWER(1+Control!$B$17,18))-((Control!$B$70+Control!$B$71+Control!$B$72)*12*POWER(1+Control!$B$18,18)+(Control!$B$68*12*POWER(1+Control!$B$17,18))*Control!$B$26)))*(1-Control!$B$23))-IF(AND(Control!$B$5>0,Control!$B$6="Y",19=Control!$B$39-1),Control!$B$40,0)) -> 2027152.3 | W51: =Control!$B$11*(((((((Control!$B$20*$A$7)*((Control!$B$28+Control!$B$29*(Control!$B$38-2))+(Control!$B$32+Control!$B$33*(Control!$B$38-2))+IF(AND(Control!$B$5>0,Control!$B$6="Y",20>=Control!$B$39),Control!$B$36,0))*POWER(1+Control!$B$17,19))+((((Control!$B$20*$A$7)*Control!$B$38*2+IF(AND(Control!$B$5>0,Control!$B$6="Y",20>=Control!$B$39),(Control!$B$20*$A$7)*2,0))*Control!$B$41)*(Control!$B$42+Control!$B$44)*POWER(1+Control!$B$17,19))+(Control!$B$46*POWER(1+Control!$B$17,19)))-(((Control!$B$20*$A$7)*((Control!$B$28+Control!$B$29*(Control!$B$38-2))+(Control!$B$32+Control!$B$33*(Control!$B$38-2))+IF(AND(Control!$B$5>0,Control!$B$6="Y",20>=Control!$B$39),Control!$B$36,0))*POWER(1+Control!$B$17,19))*Control!$B$52+(((Control!$B$20*$A$7)*Control!$B$38*2+IF(AND(Control!$B$5>0,Control!$B$6="Y",20>=Control!$B$39),(Control!$B$20*$A$7)*2,0))*Control!$B$41)*(Control!$B$43+Control!$B$45)*POWER(1+Control!$B$18,19)+Control!$B$47*POWER(1+Control!$B$18,19)+(Control!$B$48+Control!$B$49+Control!$B$50+Control!$B$51)*12*POWER(1+Control!$B$18,19)+((Control!$B$20*$A$7)*((Control!$B$28+Control!$B$29*(Control!$B$38-2))+(Control!$B$32+Control!$B$33*(Control!$B$38-2))+IF(AND(Control!$B$5>0,Control!$B$6="Y",20>=Control!$B$39),Control!$B$36,0))*POWER(1+Control!$B$17,19))*Control!$B$26))+(((Control!$B$54*Control!$B$55+Control!$B$57*Control!$B$58*Control!$B$59*Control!$B$60)*POWER(1+Control!$B$17,19))-((Control!$B$57*Control!$B$58*Control!$B$59*Control!$B$60*POWER(1+Control!$B$17,19))*Control!$B$63+(Control!$B$64+Control!$B$65+Control!$B$66)*12*POWER(1+Control!$B$18,19)+((Control!$B$54*Control!$B$55+Control!$B$57*Control!$B$58*Control!$B$59*Control!$B$60)*POWER(1+Control!$B$17,19))*Control!$B$26))+((Control!$B$68*12*POWER(1+Control!$B$17,19))-((Control!$B$70+Control!$B$71+Control!$B$72)*12*POWER(1+Control!$B$18,19)+(Control!$B$68*12*POWER(1+Control!$B$17,19))*Control!$B$26)))*(1-Control!$B$23))-IF(AND(Control!$B$5>0,Control!$B$6="Y",20=Control!$B$39-1),Control!$B$40,0))+Valuation!$F$10*POWER(1+Control!$B$78,20)*(1-Control!$B$79) -> 18215454
A52: [calc] Occupancy 0.65 cum | D52: =D51 -> 842323.63 | E52: =D52+E51 -> 1726763.4 | F52: =E52+F51 -> 2655425.2 | G52: =F52+G51 -> 3630520.1 | H52: =G52+H51 -> 4654369.8 | I52: =H52+I51 -> 5729411.9 | J52: =I52+J51 -> 6858206.1 | K52: =J52+K51 -> 8043440.1 | L52: =K52+L51 -> 9287935.7 | ... V52: =U52+V51 -> 25723725
A53: [calc] Occupancy 0.7 dist | C53: =-Control!$B$15 -> -6400000 | D53: =Control!$B$11*(((((((Control!$B$20*$A$8)*((Control!$B$28+Control!$B$29*(Control!$B$38-2))+(Control!$B$32+Control!$B$33*(Control!$B$38-2))+IF(AND(Control!$B$5>0,Control!$B$6="Y",1>=Control!$B$39),Control!$B$36,0))*POWER(1+Control!$B$17,0))+((((Control!$B$20*$A$8)*Control!$B$38*2+IF(AND(Control!$B$5>0,Control!$B$6="Y",1>=Control!$B$39),(Control!$B$20*$A$8)*2,0))*Control!$B$41)*(Control!$B$42+Control!$B$44)*POWER(1+Control!$B$17,0))+(Control!$B$46*POWER(1+Control!$B$17,0)))-(((Control!$B$20*$A$8)*((Control!$B$28+Control!$B$29*(Control!$B$38-2))+(Control!$B$32+Control!$B$33*(Control!$B$38-2))+IF(AND(Control!$B$5>0,Control!$B$6="Y",1>=Control!$B$39),Control!$B$36,0))*POWER(1+Control!$B$17,0))*Control!$B$52+(((Control!$B$20*$A$8)*Control!$B$38*2+IF(AND(Control!$B$5>0,Control!$B$6="Y",1>=Control!$B$39),(Control!$B$20*$A$8)*2,0))*Control!$B$41)*(Control!$B$43+Control!$B$45)*POWER(1+Control!$B$18,0)+Control!$B$47*POWER(1+Control!$B$18,0)+(Control!$B$48+Control!$B$49+Control!$B$50+Control!$B$51)*12*POWER(1+Control!$B$18,0)+((Control!$B$20*$A$8)*((Control!$B$28+Control!$B$29*(Control!$B$38-2))+(Control!$B$32+Control!$B$33*(Control!$B$38-2))+IF(AND(Control!$B$5>0,Control!$B$6="Y",1>=Control!$B$39),Control!$B$36,0))*POWER(1+Control!$B$17,0))*Control!$B$26))+(((Control!$B$54*Control!$B$55+Control!$B$57*Control!$B$58*Control!$B$59*Control!$B$60)*POWER(1+Control!$B$17,0))-((Control!$B$57*Control!$B$58*Control!$B$59*Control!$B$60*POWER(1+Control!$B$17,0))*Control!$B$63+(Control!$B$64+Control!$B$65+Control!$B$66)*12*POWER(1+Control!$B$18,0)+((Control!$B$54*Control!$B$55+Control!$B$57*Control!$B$58*Control!$B$59*Control!$B$60)*POWER(1+Control!$B$17,0))*Control!$B$26))+((Control!$B$68*12*POWER(1+Control!$B$17,0))-((Control!$B$70+Control!$B$71+Control!$B$72)*12*POWER(1+Control!$B$18,0)+(Control!$B$68*12*POWER(1+Control!$B$17,0))*Control!$B$26)))*(1-Control!$B$23))-IF(AND(Control!$B$5>0,Control!$B$6="Y",1=Control!$B$39-1),Control!$B$40,0)) -> 888332.88 | E53: =Control!$B$11*(((((((Control!$B$20*$A$8)*((Control!$B$28+Control!$B$29*(Control!$B$38-2))+(Control!$B$32+Control!$B$33*(Control!$B$38-2))+IF(AND(Control!$B$5>0,Control!$B$6="Y",2>=Control!$B$39),Control!$B$36,0))*POWER(1+Control!$B$17,1))+((((Control!$B$20*$A$8)*Control!$B$38*2+IF(AND(Control!$B$5>0,Control!$B$6="Y",2>=Control!$B$39),(Control!$B$20*$A$8)*2,0))*Control!$B$41)*(Control!$B$42+Control!$B$44)*POWER(1+Control!$B$17,1))+(Control!$B$46*POWER(1+Control!$B$17,1)))-(((Control!$B$20*$A$8)*((Control!$B$28+Control!$B$29*(Control!$B$38-2))+(Control!$B$32+Control!$B$33*(Control!$B$38-2))+IF(AND(Control!$B$5>0,Control!$B$6="Y",2>=Control!$B$39),Control!$B$36,0))*POWER(1+Control!$B$17,1))*Control!$B$52+(((Control!$B$20*$A$8)*Control!$B$38*2+IF(AND(Control!$B$5>0,Control!$B$6="Y",2>=Control!$B$39),(Control!$B$20*$A$8)*2,0))*Control!$B$41)*(Control!$B$43+Control!$B$45)*POWER(1+Control!$B$18,1)+Control!$B$47*POWER(1+Control!$B$18,1)+(Control!$B$48+Control!$B$49+Control!$B$50+Control!$B$51)*12*POWER(1+Control!$B$18,1)+((Control!$B$20*$A$8)*((Control!$B$28+Control!$B$29*(Control!$B$38-2))+(Control!$B$32+Control!$B$33*(Control!$B$38-2))+IF(AND(Control!$B$5>0,Control!$B$6="Y",2>=Control!$B$39),Control!$B$36,0))*POWER(1+Control!$B$17,1))*Control!$B$26))+(((Control!$B$54*Control!$B$55+Control!$B$57*Control!$B$58*Control!$B$59*Control!$B$60)*POWER(1+Control!$B$17,1))-((Control!$B$57*Control!$B$58*Control!$B$59*Control!$B$60*POWER(1+Control!$B$17,1))*Control!$B$63+(Control!$B$64+Control!$B$65+Control!$B$66)*12*POWER(1+Control!$B$18,1)+((Control!$B$54*Control!$B$55+Control!$B$57*Control!$B$58*Control!$B$59*Control!$B$60)*POWER(1+Control!$B$17,1))*Control!$B$26))+((Control!$B$68*12*POWER(1+Control!$B$17,1))-((Control!$B$70+Control!$B$71+Control!$B$72)*12*POWER(1+Control!$B$18,1)+(Control!$B$68*12*POWER(1+Control!$B$17,1))*Control!$B$26)))*(1-Control!$B$23))-IF(AND(Control!$B$5>0,Control!$B$6="Y",2=Control!$B$39-1),Control!$B$40,0)) -> 932749.53 | F53: =Control!$B$11*(((((((Control!$B$20*$A$8)*((Control!$B$28+Control!$B$29*(Control!$B$38-2))+(Control!$B$32+Control!$B$33*(Control!$B$38-2))+IF(AND(Control!$B$5>0,Control!$B$6="Y",3>=Control!$B$39),Control!$B$36,0))*POWER(1+Control!$B$17,2))+((((Control!$B$20*$A$8)*Control!$B$38*2+IF(AND(Control!$B$5>0,Control!$B$6="Y",3>=Control!$B$39),(Control!$B$20*$A$8)*2,0))*Control!$B$41)*(Control!$B$42+Control!$B$44)*POWER(1+Control!$B$17,2))+(Control!$B$46*POWER(1+Control!$B$17,2)))-(((Control!$B$20*$A$8)*((Control!$B$28+Control!$B$29*(Control!$B$38-2))+(Control!$B$32+Control!$B$33*(Control!$B$38-2))+IF(AND(Control!$B$5>0,Control!$B$6="Y",3>=Control!$B$39),Control!$B$36,0))*POWER(1+Control!$B$17,2))*Control!$B$52+(((Control!$B$20*$A$8)*Control!$B$38*2+IF(AND(Control!$B$5>0,Control!$B$6="Y",3>=Control!$B$39),(Control!$B$20*$A$8)*2,0))*Control!$B$41)*(Control!$B$43+Control!$B$45)*POWER(1+Control!$B$18,2)+Control!$B$47*POWER(1+Control!$B$18,2)+(Control!$B$48+Control!$B$49+Control!$B$50+Control!$B$51)*12*POWER(1+Control!$B$18,2)+((Control!$B$20*$A$8)*((Control!$B$28+Control!$B$29*(Control!$B$38-2))+(Control!$B$32+Control!$B$33*(Control!$B$38-2))+IF(AND(Control!$B$5>0,Control!$B$6="Y",3>=Control!$B$39),Control!$B$36,0))*POWER(1+Control!$B$17,2))*Control!$B$26))+(((Control!$B$54*Control!$B$55+Control!$B$57*Control!$B$58*Control!$B$59*Control!$B$60)*POWER(1+Control!$B$17,2))-((Control!$B$57*Control!$B$58*Control!$B$59*Control!$B$60*POWER(1+Control!$B$17,2))*Control!$B$63+(Control!$B$64+Control!$B$65+Control!$B$66)*12*POWER(1+Control!$B$18,2)+((Control!$B$54*Control!$B$55+Control!$B$57*Control!$B$58*Control!$B$59*Control!$B$60)*POWER(1+Control!$B$17,2))*Control!$B$26))+((Control!$B$68*12*POWER(1+Control!$B$17,2))-((Control!$B$70+Control!$B$71+Control!$B$72)*12*POWER(1+Control!$B$18,2)+(Control!$B$68*12*POWER(1+Control!$B$17,2))*Control!$B$26)))*(1-Control!$B$23))-IF(AND(Control!$B$5>0,Control!$B$6="Y",3=Control!$B$39-1),Control!$B$40,0)) -> 979387 | G53: =Control!$B$11*(((((((Control!$B$20*$A$8)*((Control!$B$28+Control!$B$29*(Control!$B$38-2))+(Control!$B$32+Control!$B$33*(Control!$B$38-2))+IF(AND(Control!$B$5>0,Control!$B$6="Y",4>=Control!$B$39),Control!$B$36,0))*POWER(1+Control!$B$17,3))+((((Control!$B$20*$A$8)*Control!$B$38*2+IF(AND(Control!$B$5>0,Control!$B$6="Y",4>=Control!$B$39),(Control!$B$20*$A$8)*2,0))*Control!$B$41)*(Control!$B$42+Control!$B$44)*POWER(1+Control!$B$17,3))+(Control!$B$46*POWER(1+Control!$B$17,3)))-(((Control!$B$20*$A$8)*((Control!$B$28+Control!$B$29*(Control!$B$38-2))+(Control!$B$32+Control!$B$33*(Control!$B$38-2))+IF(AND(Control!$B$5>0,Control!$B$6="Y",4>=Control!$B$39),Control!$B$36,0))*POWER(1+Control!$B$17,3))*Control!$B$52+(((Control!$B$20*$A$8)*Control!$B$38*2+IF(AND(Control!$B$5>0,Control!$B$6="Y",4>=Control!$B$39),(Control!$B$20*$A$8)*2,0))*Control!$B$41)*(Control!$B$43+Control!$B$45)*POWER(1+Control!$B$18,3)+Control!$B$47*POWER(1+Control!$B$18,3)+(Control!$B$48+Control!$B$49+Control!$B$50+Control!$B$51)*12*POWER(1+Control!$B$18,3)+((Control!$B$20*$A$8)*((Control!$B$28+Control!$B$29*(Control!$B$38-2))+(Control!$B$32+Control!$B$33*(Control!$B$38-2))+IF(AND(Control!$B$5>0,Control!$B$6="Y",4>=Control!$B$39),Control!$B$36,0))*POWER(1+Control!$B$17,3))*Control!$B$26))+(((Control!$B$54*Control!$B$55+Control!$B$57*Control!$B$58*Control!$B$59*Control!$B$60)*POWER(1+Control!$B$17,3))-((Control!$B$57*Control!$B$58*Control!$B$59*Control!$B$60*POWER(1+Control!$B$17,3))*Control!$B$63+(Control!$B$64+Control!$B$65+Control!$B$66)*12*POWER(1+Control!$B$18,3)+((Control!$B$54*Control!$B$55+Control!$B$57*Control!$B$58*Control!$B$59*Control!$B$60)*POWER(1+Control!$B$17,3))*Control!$B$26))+((Control!$B$68*12*POWER(1+Control!$B$17,3))-((Control!$B$70+Control!$B$71+Control!$B$72)*12*POWER(1+Control!$B$18,3)+(Control!$B$68*12*POWER(1+Control!$B$17,3))*Control!$B$26)))*(1-Control!$B$23))-IF(AND(Control!$B$5>0,Control!$B$6="Y",4=Control!$B$39-1),Control!$B$40,0)) -> 1028356.4 | H53: =Control!$B$11*(((((((Control!$B$20*$A$8)*((Control!$B$28+Control!$B$29*(Control!$B$38-2))+(Control!$B$32+Control!$B$33*(Control!$B$38-2))+IF(AND(Control!$B$5>0,Control!$B$6="Y",5>=Control!$B$39),Control!$B$36,0))*POWER(1+Control!$B$17,4))+((((Control!$B$20*$A$8)*Control!$B$38*2+IF(AND(Control!$B$5>0,Control!$B$6="Y",5>=Control!$B$39),(Control!$B$20*$A$8)*2,0))*Control!$B$41)*(Control!$B$42+Control!$B$44)*POWER(1+Control!$B$17,4))+(Control!$B$46*POWER(1+Control!$B$17,4)))-(((Control!$B$20*$A$8)*((Control!$B$28+Control!$B$29*(Control!$B$38-2))+(Control!$B$32+Control!$B$33*(Control!$B$38-2))+IF(AND(Control!$B$5>0,Control!$B$6="Y",5>=Control!$B$39),Control!$B$36,0))*POWER(1+Control!$B$17,4))*Control!$B$52+(((Control!$B$20*$A$8)*Control!$B$38*2+IF(AND(Control!$B$5>0,Control!$B$6="Y",5>=Control!$B$39),(Control!$B$20*$A$8)*2,0))*Control!$B$41)*(Control!$B$43+Control!$B$45)*POWER(1+Control!$B$18,4)+Control!$B$47*POWER(1+Control!$B$18,4)+(Control!$B$48+Control!$B$49+Control!$B$50+Control!$B$51)*12*POWER(1+Control!$B$18,4)+((Control!$B$20*$A$8)*((Control!$B$28+Control!$B$29*(Control!$B$38-2))+(Control!$B$32+Control!$B$33*(Control!$B$38-2))+IF(AND(Control!$B$5>0,Control!$B$6="Y",5>=Control!$B$39),Control!$B$36,0))*POWER(1+Control!$B$17,4))*Control!$B$26))+(((Control!$B$54*Control!$B$55+Control!$B$57*Control!$B$58*Control!$B$59*Control!$B$60)*POWER(1+Control!$B$17,4))-((Control!$B$57*Control!$B$58*Control!$B$59*Control!$B$60*POWER(1+Control!$B$17,4))*Control!$B$63+(Control!$B$64+Control!$B$65+Control!$B$66)*12*POWER(1+Control!$B$18,4)+((Control!$B$54*Control!$B$55+Control!$B$57*Control!$B$58*Control!$B$59*Control!$B$60)*POWER(1+Control!$B$17,4))*Control!$B$26))+((Control!$B$68*12*POWER(1+Control!$B$17,4))-((Control!$B$70+Control!$B$71+Control!$B$72)*12*POWER(1+Control!$B$18,4)+(Control!$B$68*12*POWER(1+Control!$B$17,4))*Control!$B$26)))*(1-Control!$B$23))-IF(AND(Control!$B$5>0,Control!$B$6="Y",5=Control!$B$39-1),Control!$B$40,0)) -> 1079774.2 | I53: =Control!$B$11*(((((((Control!$B$20*$A$8)*((Control!$B$28+Control!$B$29*(Control!$B$38-2))+(Control!$B$32+Control!$B$33*(Control!$B$38-2))+IF(AND(Control!$B$5>0,Control!$B$6="Y",6>=Control!$B$39),Control!$B$36,0))*POWER(1+Control!$B$17,5))+((((Control!$B$20*$A$8)*Control!$B$38*2+IF(AND(Control!$B$5>0,Control!$B$6="Y",6>=Control!$B$39),(Control!$B$20*$A$8)*2,0))*Control!$B$41)*(Control!$B$42+Control!$B$44)*POWER(1+Control!$B$17,5))+(Control!$B$46*POWER(1+Control!$B$17,5)))-(((Control!$B$20*$A$8)*((Control!$B$28+Control!$B$29*(Control!$B$38-2))+(Control!$B$32+Control!$B$33*(Control!$B$38-2))+IF(AND(Control!$B$5>0,Control!$B$6="Y",6>=Control!$B$39),Control!$B$36,0))*POWER(1+Control!$B$17,5))*Control!$B$52+(((Control!$B$20*$A$8)*Control!$B$38*2+IF(AND(Control!$B$5>0,Control!$B$6="Y",6>=Control!$B$39),(Control!$B$20*$A$8)*2,0))*Control!$B$41)*(Control!$B$43+Control!$B$45)*POWER(1+Control!$B$18,5)+Control!$B$47*POWER(1+Control!$B$18,5)+(Control!$B$48+Control!$B$49+Control!$B$50+Control!$B$51)*12*POWER(1+Control!$B$18,5)+((Control!$B$20*$A$8)*((Control!$B$28+Control!$B$29*(Control!$B$38-2))+(Control!$B$32+Control!$B$33*(Control!$B$38-2))+IF(AND(Control!$B$5>0,Control!$B$6="Y",6>=Control!$B$39),Control!$B$36,0))*POWER(1+Control!$B$17,5))*Control!$B$26))+(((Control!$B$54*Control!$B$55+Control!$B$57*Control!$B$58*Control!$B$59*Control!$B$60)*POWER(1+Control!$B$17,5))-((Control!$B$57*Control!$B$58*Control!$B$59*Control!$B$60*POWER(1+Control!$B$17,5))*Control!$B$63+(Control!$B$64+Control!$B$65+Control!$B$66)*12*POWER(1+Control!$B$18,5)+((Control!$B$54*Control!$B$55+Control!$B$57*Control!$B$58*Control!$B$59*Control!$B$60)*POWER(1+Control!$B$17,5))*Control!$B$26))+((Control!$B$68*12*POWER(1+Control!$B$17,5))-((Control!$B$70+Control!$B$71+Control!$B$72)*12*POWER(1+Control!$B$18,5)+(Control!$B$68*12*POWER(1+Control!$B$17,5))*Control!$B$26)))*(1-Control!$B$23))-IF(AND(Control!$B$5>0,Control!$B$6="Y",6=Control!$B$39-1),Control!$B$40,0)) -> 1133762.9 | J53: =Control!$B$11*(((((((Control!$B$20*$A$8)*((Control!$B$28+Control!$B$29*(Control!$B$38-2))+(Control!$B$32+Control!$B$33*(Control!$B$38-2))+IF(AND(Control!$B$5>0,Control!$B$6="Y",7>=Control!$B$39),Control!$B$36,0))*POWER(1+Control!$B$17,6))+((((Control!$B$20*$A$8)*Control!$B$38*2+IF(AND(Control!$B$5>0,Control!$B$6="Y",7>=Control!$B$39),(Control!$B$20*$A$8)*2,0))*Control!$B$41)*(Control!$B$42+Control!$B$44)*POWER(1+Control!$B$17,6))+(Control!$B$46*POWER(1+Control!$B$17,6)))-(((Control!$B$20*$A$8)*((Control!$B$28+Control!$B$29*(Control!$B$38-2))+(Control!$B$32+Control!$B$33*(Control!$B$38-2))+IF(AND(Control!$B$5>0,Control!$B$6="Y",7>=Control!$B$39),Control!$B$36,0))*POWER(1+Control!$B$17,6))*Control!$B$52+(((Control!$B$20*$A$8)*Control!$B$38*2+IF(AND(Control!$B$5>0,Control!$B$6="Y",7>=Control!$B$39),(Control!$B$20*$A$8)*2,0))*Control!$B$41)*(Control!$B$43+Control!$B$45)*POWER(1+Control!$B$18,6)+Control!$B$47*POWER(1+Control!$B$18,6)+(Control!$B$48+Control!$B$49+Control!$B$50+Control!$B$51)*12*POWER(1+Control!$B$18,6)+((Control!$B$20*$A$8)*((Control!$B$28+Control!$B$29*(Control!$B$38-2))+(Control!$B$32+Control!$B$33*(Control!$B$38-2))+IF(AND(Control!$B$5>0,Control!$B$6="Y",7>=Control!$B$39),Control!$B$36,0))*POWER(1+Control!$B$17,6))*Control!$B$26))+(((Control!$B$54*Control!$B$55+Control!$B$57*Control!$B$58*Control!$B$59*Control!$B$60)*POWER(1+Control!$B$17,6))-((Control!$B$57*Control!$B$58*Control!$B$59*Control!$B$60*POWER(1+Control!$B$17,6))*Control!$B$63+(Control!$B$64+Control!$B$65+Control!$B$66)*12*POWER(1+Control!$B$18,6)+((Control!$B$54*Control!$B$55+Control!$B$57*Control!$B$58*Control!$B$59*Control!$B$60)*POWER(1+Control!$B$17,6))*Control!$B$26))+((Control!$B$68*12*POWER(1+Control!$B$17,6))-((Control!$B$70+Control!$B$71+Control!$B$72)*12*POWER(1+Control!$B$18,6)+(Control!$B$68*12*POWER(1+Control!$B$17,6))*Control!$B$26)))*(1-Control!$B$23))-IF(AND(Control!$B$5>0,Control!$B$6="Y",7=Control!$B$39-1),Control!$B$40,0)) -> 1190451 | K53: =Control!$B$11*(((((((Control!$B$20*$A$8)*((Control!$B$28+Control!$B$29*(Control!$B$38-2))+(Control!$B$32+Control!$B$33*(Control!$B$38-2))+IF(AND(Control!$B$5>0,Control!$B$6="Y",8>=Control!$B$39),Control!$B$36,0))*POWER(1+Control!$B$17,7))+((((Control!$B$20*$A$8)*Control!$B$38*2+IF(AND(Control!$B$5>0,Control!$B$6="Y",8>=Control!$B$39),(Control!$B$20*$A$8)*2,0))*Control!$B$41)*(Control!$B$42+Control!$B$44)*POWER(1+Control!$B$17,7))+(Control!$B$46*POWER(1+Control!$B$17,7)))-(((Control!$B$20*$A$8)*((Control!$B$28+Control!$B$29*(Control!$B$38-2))+(Control!$B$32+Control!$B$33*(Control!$B$38-2))+IF(AND(Control!$B$5>0,Control!$B$6="Y",8>=Control!$B$39),Control!$B$36,0))*POWER(1+Control!$B$17,7))*Control!$B$52+(((Control!$B$20*$A$8)*Control!$B$38*2+IF(AND(Control!$B$5>0,Control!$B$6="Y",8>=Control!$B$39),(Control!$B$20*$A$8)*2,0))*Control!$B$41)*(Control!$B$43+Control!$B$45)*POWER(1+Control!$B$18,7)+Control!$B$47*POWER(1+Control!$B$18,7)+(Control!$B$48+Control!$B$49+Control!$B$50+Control!$B$51)*12*POWER(1+Control!$B$18,7)+((Control!$B$20*$A$8)*((Control!$B$28+Control!$B$29*(Control!$B$38-2))+(Control!$B$32+Control!$B$33*(Control!$B$38-2))+IF(AND(Control!$B$5>0,Control!$B$6="Y",8>=Control!$B$39),Control!$B$36,0))*POWER(1+Control!$B$17,7))*Control!$B$26))+(((Control!$B$54*Control!$B$55+Control!$B$57*Control!$B$58*Control!$B$59*Control!$B$60)*POWER(1+Control!$B$17,7))-((Control!$B$57*Control!$B$58*Control!$B$59*Control!$B$60*POWER(1+Control!$B$17,7))*Control!$B$63+(Control!$B$64+Control!$B$65+Control!$B$66)*12*POWER(1+Control!$B$18,7)+((Control!$B$54*Control!$B$55+Control!$B$57*Control!$B$58*Control!$B$59*Control!$B$60)*POWER(1+Control!$B$17,7))*Control!$B$26))+((Control!$B$68*12*POWER(1+Control!$B$17,7))-((Control!$B$70+Control!$B$71+Control!$B$72)*12*POWER(1+Control!$B$18,7)+(Control!$B$68*12*POWER(1+Control!$B$17,7))*Control!$B$26)))*(1-Control!$B$23))-IF(AND(Control!$B$5>0,Control!$B$6="Y",8=Control!$B$39-1),Control!$B$40,0)) -> 1249973.6 | L53: =Control!$B$11*(((((((Control!$B$20*$A$8)*((Control!$B$28+Control!$B$29*(Control!$B$38-2))+(Control!$B$32+Control!$B$33*(Control!$B$38-2))+IF(AND(Control!$B$5>0,Control!$B$6="Y",9>=Control!$B$39),Control!$B$36,0))*POWER(1+Control!$B$17,8))+((((Control!$B$20*$A$8)*Control!$B$38*2+IF(AND(Control!$B$5>0,Control!$B$6="Y",9>=Control!$B$39),(Control!$B$20*$A$8)*2,0))*Control!$B$41)*(Control!$B$42+Control!$B$44)*POWER(1+Control!$B$17,8))+(Control!$B$46*POWER(1+Control!$B$17,8)))-(((Control!$B$20*$A$8)*((Control!$B$28+Control!$B$29*(Control!$B$38-2))+(Control!$B$32+Control!$B$33*(Control!$B$38-2))+IF(AND(Control!$B$5>0,Control!$B$6="Y",9>=Control!$B$39),Control!$B$36,0))*POWER(1+Control!$B$17,8))*Control!$B$52+(((Control!$B$20*$A$8)*Control!$B$38*2+IF(AND(Control!$B$5>0,Control!$B$6="Y",9>=Control!$B$39),(Control!$B$20*$A$8)*2,0))*Control!$B$41)*(Control!$B$43+Control!$B$45)*POWER(1+Control!$B$18,8)+Control!$B$47*POWER(1+Control!$B$18,8)+(Control!$B$48+Control!$B$49+Control!$B$50+Control!$B$51)*12*POWER(1+Control!$B$18,8)+((Control!$B$20*$A$8)*((Control!$B$28+Control!$B$29*(Control!$B$38-2))+(Control!$B$32+Control!$B$33*(Control!$B$38-2))+IF(AND(Control!$B$5>0,Control!$B$6="Y",9>=Control!$B$39),Control!$B$36,0))*POWER(1+Control!$B$17,8))*Control!$B$26))+(((Control!$B$54*Control!$B$55+Control!$B$57*Control!$B$58*Control!$B$59*Control!$B$60)*POWER(1+Control!$B$17,8))-((Control!$B$57*Control!$B$58*Control!$B$59*Control!$B$60*POWER(1+Control!$B$17,8))*Control!$B$63+(Control!$B$64+Control!$B$65+Control!$B$66)*12*POWER(1+Control!$B$18,8)+((Control!$B$54*Control!$B$55+Control!$B$57*Control!$B$58*Control!$B$59*Control!$B$60)*POWER(1+Control!$B$17,8))*Control!$B$26))+((Control!$B$68*12*POWER(1+Control!$B$17,8))-((Control!$B$70+Control!$B$71+Control!$B$72)*12*POWER(1+Control!$B$18,8)+(Control!$B$68*12*POWER(1+Control!$B$17,8))*Control!$B$26)))*(1-Control!$B$23))-IF(AND(Control!$B$5>0,Control!$B$6="Y",9=Control!$B$39-1),Control!$B$40,0)) -> 1312472.3 | M53: =Control!$B$11*(((((((Control!$B$20*$A$8)*((Control!$B$28+Control!$B$29*(Control!$B$38-2))+(Control!$B$32+Control!$B$33*(Control!$B$38-2))+IF(AND(Control!$B$5>0,Control!$B$6="Y",10>=Control!$B$39),Control!$B$36,0))*POWER(1+Control!$B$17,9))+((((Control!$B$20*$A$8)*Control!$B$38*2+IF(AND(Control!$B$5>0,Control!$B$6="Y",10>=Control!$B$39),(Control!$B$20*$A$8)*2,0))*Control!$B$41)*(Control!$B$42+Control!$B$44)*POWER(1+Control!$B$17,9))+(Control!$B$46*POWER(1+Control!$B$17,9)))-(((Control!$B$20*$A$8)*((Control!$B$28+Control!$B$29*(Control!$B$38-2))+(Control!$B$32+Control!$B$33*(Control!$B$38-2))+IF(AND(Control!$B$5>0,Control!$B$6="Y",10>=Control!$B$39),Control!$B$36,0))*POWER(1+Control!$B$17,9))*Control!$B$52+(((Control!$B$20*$A$8)*Control!$B$38*2+IF(AND(Control!$B$5>0,Control!$B$6="Y",10>=Control!$B$39),(Control!$B$20*$A$8)*2,0))*Control!$B$41)*(Control!$B$43+Control!$B$45)*POWER(1+Control!$B$18,9)+Control!$B$47*POWER(1+Control!$B$18,9)+(Control!$B$48+Control!$B$49+Control!$B$50+Control!$B$51)*12*POWER(1+Control!$B$18,9)+((Control!$B$20*$A$8)*((Control!$B$28+Control!$B$29*(Control!$B$38-2))+(Control!$B$32+Control!$B$33*(Control!$B$38-2))+IF(AND(Control!$B$5>0,Control!$B$6="Y",10>=Control!$B$39),Control!$B$36,0))*POWER(1+Control!$B$17,9))*Control!$B$26))+(((Control!$B$54*Control!$B$55+Control!$B$57*Control!$B$58*Control!$B$59*Control!$B$60)*POWER(1+Control!$B$17,9))-((Control!$B$57*Control!$B$58*Control!$B$59*Control!$B$60*POWER(1+Control!$B$17,9))*Control!$B$63+(Control!$B$64+Control!$B$65+Control!$B$66)*12*POWER(1+Control!$B$18,9)+((Control!$B$54*Control!$B$55+Control!$B$57*Control!$B$58*Control!$B$59*Control!$B$60)*POWER(1+Control!$B$17,9))*Control!$B$26))+((Control!$B$68*12*POWER(1+Control!$B$17,9))-((Control!$B$70+Control!$B$71+Control!$B$72)*12*POWER(1+Control!$B$18,9)+(Control!$B$68*12*POWER(1+Control!$B$17,9))*Control!$B$26)))*(1-Control!$B$23))-IF(AND(Control!$B$5>0,Control!$B$6="Y",10=Control!$B$39-1),Control!$B$40,0)) -> 1378095.9 | N53: =Control!$B$11*(((((((Control!$B$20*$A$8)*((Control!$B$28+Control!$B$29*(Control!$B$38-2))+(Control!$B$32+Control!$B$33*(Control!$B$38-2))+IF(AND(Control!$B$5>0,Control!$B$6="Y",11>=Control!$B$39),Control!$B$36,0))*POWER(1+Control!$B$17,10))+((((Control!$B$20*$A$8)*Control!$B$38*2+IF(AND(Control!$B$5>0,Control!$B$6="Y",11>=Control!$B$39),(Control!$B$20*$A$8)*2,0))*Control!$B$41)*(Control!$B$42+Control!$B$44)*POWER(1+Control!$B$17,10))+(Control!$B$46*POWER(1+Control!$B$17,10)))-(((Control!$B$20*$A$8)*((Control!$B$28+Control!$B$29*(Control!$B$38-2))+(Control!$B$32+Control!$B$33*(Control!$B$38-2))+IF(AND(Control!$B$5>0,Control!$B$6="Y",11>=Control!$B$39),Control!$B$36,0))*POWER(1+Control!$B$17,10))*Control!$B$52+(((Control!$B$20*$A$8)*Control!$B$38*2+IF(AND(Control!$B$5>0,Control!$B$6="Y",11>=Control!$B$39),(Control!$B$20*$A$8)*2,0))*Control!$B$41)*(Control!$B$43+Control!$B$45)*POWER(1+Control!$B$18,10)+Control!$B$47*POWER(1+Control!$B$18,10)+(Control!$B$48+Control!$B$49+Control!$B$50+Control!$B$51)*12*POWER(1+Control!$B$18,10)+((Control!$B$20*$A$8)*((Control!$B$28+Control!$B$29*(Control!$B$38-2))+(Control!$B$32+Control!$B$33*(Control!$B$38-2))+IF(AND(Control!$B$5>0,Control!$B$6="Y",11>=Control!$B$39),Control!$B$36,0))*POWER(1+Control!$B$17,10))*Control!$B$26))+(((Control!$B$54*Control!$B$55+Control!$B$57*Control!$B$58*Control!$B$59*Control!$B$60)*POWER(1+Control!$B$17,10))-((Control!$B$57*Control!$B$58*Control!$B$59*Control!$B$60*POWER(1+Control!$B$17,10))*Control!$B$63+(Control!$B$64+Control!$B$65+Control!$B$66)*12*POWER(1+Control!$B$18,10)+((Control!$B$54*Control!$B$55+Control!$B$57*Control!$B$58*Control!$B$59*Control!$B$60)*POWER(1+Control!$B$17,10))*Control!$B$26))+((Control!$B$68*12*POWER(1+Control!$B$17,10))-((Control!$B$70+Control!$B$71+Control!$B$72)*12*POWER(1+Control!$B$18,10)+(Control!$B$68*12*POWER(1+Control!$B$17,10))*Control!$B$26)))*(1-Control!$B$23))-IF(AND(Control!$B$5>0,Control!$B$6="Y",11=Control!$B$39-1),Control!$B$40,0)) -> 1447000.7 | O53: =Control!$B$11*(((((((Control!$B$20*$A$8)*((Control!$B$28+Control!$B$29*(Control!$B$38-2))+(Control!$B$32+Control!$B$33*(Control!$B$38-2))+IF(AND(Control!$B$5>0,Control!$B$6="Y",12>=Control!$B$39),Control!$B$36,0))*POWER(1+Control!$B$17,11))+((((Control!$B$20*$A$8)*Control!$B$38*2+IF(AND(Control!$B$5>0,Control!$B$6="Y",12>=Control!$B$39),(Control!$B$20*$A$8)*2,0))*Control!$B$41)*(Control!$B$42+Control!$B$44)*POWER(1+Control!$B$17,11))+(Control!$B$46*POWER(1+Control!$B$17,11)))-(((Control!$B$20*$A$8)*((Control!$B$28+Control!$B$29*(Control!$B$38-2))+(Control!$B$32+Control!$B$33*(Control!$B$38-2))+IF(AND(Control!$B$5>0,Control!$B$6="Y",12>=Control!$B$39),Control!$B$36,0))*POWER(1+Control!$B$17,11))*Control!$B$52+(((Control!$B$20*$A$8)*Control!$B$38*2+IF(AND(Control!$B$5>0,Control!$B$6="Y",12>=Control!$B$39),(Control!$B$20*$A$8)*2,0))*Control!$B$41)*(Control!$B$43+Control!$B$45)*POWER(1+Control!$B$18,11)+Control!$B$47*POWER(1+Control!$B$18,11)+(Control!$B$48+Control!$B$49+Control!$B$50+Control!$B$51)*12*POWER(1+Control!$B$18,11)+((Control!$B$20*$A$8)*((Control!$B$28+Control!$B$29*(Control!$B$38-2))+(Control!$B$32+Control!$B$33*(Control!$B$38-2))+IF(AND(Control!$B$5>0,Control!$B$6="Y",12>=Control!$B$39),Control!$B$36,0))*POWER(1+Control!$B$17,11))*Control!$B$26))+(((Control!$B$54*Control!$B$55+Control!$B$57*Control!$B$58*Control!$B$59*Control!$B$60)*POWER(1+Control!$B$17,11))-((Control!$B$57*Control!$B$58*Control!$B$59*Control!$B$60*POWER(1+Control!$B$17,11))*Control!$B$63+(Control!$B$64+Control!$B$65+Control!$B$66)*12*POWER(1+Control!$B$18,11)+((Control!$B$54*Control!$B$55+Control!$B$57*Control!$B$58*Control!$B$59*Control!$B$60)*POWER(1+Control!$B$17,11))*Control!$B$26))+((Control!$B$68*12*POWER(1+Control!$B$17,11))-((Control!$B$70+Control!$B$71+Control!$B$72)*12*POWER(1+Control!$B$18,11)+(Control!$B$68*12*POWER(1+Control!$B$17,11))*Control!$B$26)))*(1-Control!$B$23))-IF(AND(Control!$B$5>0,Control!$B$6="Y",12=Control!$B$39-1),Control!$B$40,0)) -> 1519350.7 | P53: =Control!$B$11*(((((((Control!$B$20*$A$8)*((Control!$B$28+Control!$B$29*(Control!$B$38-2))+(Control!$B$32+Control!$B$33*(Control!$B$38-2))+IF(AND(Control!$B$5>0,Control!$B$6="Y",13>=Control!$B$39),Control!$B$36,0))*POWER(1+Control!$B$17,12))+((((Control!$B$20*$A$8)*Control!$B$38*2+IF(AND(Control!$B$5>0,Control!$B$6="Y",13>=Control!$B$39),(Control!$B$20*$A$8)*2,0))*Control!$B$41)*(Control!$B$42+Control!$B$44)*POWER(1+Control!$B$17,12))+(Control!$B$46*POWER(1+Control!$B$17,12)))-(((Control!$B$20*$A$8)*((Control!$B$28+Control!$B$29*(Control!$B$38-2))+(Control!$B$32+Control!$B$33*(Control!$B$38-2))+IF(AND(Control!$B$5>0,Control!$B$6="Y",13>=Control!$B$39),Control!$B$36,0))*POWER(1+Control!$B$17,12))*Control!$B$52+(((Control!$B$20*$A$8)*Control!$B$38*2+IF(AND(Control!$B$5>0,Control!$B$6="Y",13>=Control!$B$39),(Control!$B$20*$A$8)*2,0))*Control!$B$41)*(Control!$B$43+Control!$B$45)*POWER(1+Control!$B$18,12)+Control!$B$47*POWER(1+Control!$B$18,12)+(Control!$B$48+Control!$B$49+Control!$B$50+Control!$B$51)*12*POWER(1+Control!$B$18,12)+((Control!$B$20*$A$8)*((Control!$B$28+Control!$B$29*(Control!$B$38-2))+(Control!$B$32+Control!$B$33*(Control!$B$38-2))+IF(AND(Control!$B$5>0,Control!$B$6="Y",13>=Control!$B$39),Control!$B$36,0))*POWER(1+Control!$B$17,12))*Control!$B$26))+(((Control!$B$54*Control!$B$55+Control!$B$57*Control!$B$58*Control!$B$59*Control!$B$60)*POWER(1+Control!$B$17,12))-((Control!$B$57*Control!$B$58*Control!$B$59*Control!$B$60*POWER(1+Control!$B$17,12))*Control!$B$63+(Control!$B$64+Control!$B$65+Control!$B$66)*12*POWER(1+Control!$B$18,12)+((Control!$B$54*Control!$B$55+Control!$B$57*Control!$B$58*Control!$B$59*Control!$B$60)*POWER(1+Control!$B$17,12))*Control!$B$26))+((Control!$B$68*12*POWER(1+Control!$B$17,12))-((Control!$B$70+Control!$B$71+Control!$B$72)*12*POWER(1+Control!$B$18,12)+(Control!$B$68*12*POWER(1+Control!$B$17,12))*Control!$B$26)))*(1-Control!$B$23))-IF(AND(Control!$B$5>0,Control!$B$6="Y",13=Control!$B$39-1),Control!$B$40,0)) -> 1595318.2 | Q53: =Control!$B$11*(((((((Control!$B$20*$A$8)*((Control!$B$28+Control!$B$29*(Control!$B$38-2))+(Control!$B$32+Control!$B$33*(Control!$B$38-2))+IF(AND(Control!$B$5>0,Control!$B$6="Y",14>=Control!$B$39),Control!$B$36,0))*POWER(1+Control!$B$17,13))+((((Control!$B$20*$A$8)*Control!$B$38*2+IF(AND(Control!$B$5>0,Control!$B$6="Y",14>=Control!$B$39),(Control!$B$20*$A$8)*2,0))*Control!$B$41)*(Control!$B$42+Control!$B$44)*POWER(1+Control!$B$17,13))+(Control!$B$46*POWER(1+Control!$B$17,13)))-(((Control!$B$20*$A$8)*((Control!$B$28+Control!$B$29*(Control!$B$38-2))+(Control!$B$32+Control!$B$33*(Control!$B$38-2))+IF(AND(Control!$B$5>0,Control!$B$6="Y",14>=Control!$B$39),Control!$B$36,0))*POWER(1+Control!$B$17,13))*Control!$B$52+(((Control!$B$20*$A$8)*Control!$B$38*2+IF(AND(Control!$B$5>0,Control!$B$6="Y",14>=Control!$B$39),(Control!$B$20*$A$8)*2,0))*Control!$B$41)*(Control!$B$43+Control!$B$45)*POWER(1+Control!$B$18,13)+Control!$B$47*POWER(1+Control!$B$18,13)+(Control!$B$48+Control!$B$49+Control!$B$50+Control!$B$51)*12*POWER(1+Control!$B$18,13)+((Control!$B$20*$A$8)*((Control!$B$28+Control!$B$29*(Control!$B$38-2))+(Control!$B$32+Control!$B$33*(Control!$B$38-2))+IF(AND(Control!$B$5>0,Control!$B$6="Y",14>=Control!$B$39),Control!$B$36,0))*POWER(1+Control!$B$17,13))*Control!$B$26))+(((Control!$B$54*Control!$B$55+Control!$B$57*Control!$B$58*Control!$B$59*Control!$B$60)*POWER(1+Control!$B$17,13))-((Control!$B$57*Control!$B$58*Control!$B$59*Control!$B$60*POWER(1+Control!$B$17,13))*Control!$B$63+(Control!$B$64+Control!$B$65+Control!$B$66)*12*POWER(1+Control!$B$18,13)+((Control!$B$54*Control!$B$55+Control!$B$57*Control!$B$58*Control!$B$59*Control!$B$60)*POWER(1+Control!$B$17,13))*Control!$B$26))+((Control!$B$68*12*POWER(1+Control!$B$17,13))-((Control!$B$70+Control!$B$71+Control!$B$72)*12*POWER(1+Control!$B$18,13)+(Control!$B$68*12*POWER(1+Control!$B$17,13))*Control!$B$26)))*(1-Control!$B$23))-IF(AND(Control!$B$5>0,Control!$B$6="Y",14=Control!$B$39-1),Control!$B$40,0)) -> 1675084.1 | R53: =Control!$B$11*(((((((Control!$B$20*$A$8)*((Control!$B$28+Control!$B$29*(Control!$B$38-2))+(Control!$B$32+Control!$B$33*(Control!$B$38-2))+IF(AND(Control!$B$5>0,Control!$B$6="Y",15>=Control!$B$39),Control!$B$36,0))*POWER(1+Control!$B$17,14))+((((Control!$B$20*$A$8)*Control!$B$38*2+IF(AND(Control!$B$5>0,Control!$B$6="Y",15>=Control!$B$39),(Control!$B$20*$A$8)*2,0))*Control!$B$41)*(Control!$B$42+Control!$B$44)*POWER(1+Control!$B$17,14))+(Control!$B$46*POWER(1+Control!$B$17,14)))-(((Control!$B$20*$A$8)*((Control!$B$28+Control!$B$29*(Control!$B$38-2))+(Control!$B$32+Control!$B$33*(Control!$B$38-2))+IF(AND(Control!$B$5>0,Control!$B$6="Y",15>=Control!$B$39),Control!$B$36,0))*POWER(1+Control!$B$17,14))*Control!$B$52+(((Control!$B$20*$A$8)*Control!$B$38*2+IF(AND(Control!$B$5>0,Control!$B$6="Y",15>=Control!$B$39),(Control!$B$20*$A$8)*2,0))*Control!$B$41)*(Control!$B$43+Control!$B$45)*POWER(1+Control!$B$18,14)+Control!$B$47*POWER(1+Control!$B$18,14)+(Control!$B$48+Control!$B$49+Control!$B$50+Control!$B$51)*12*POWER(1+Control!$B$18,14)+((Control!$B$20*$A$8)*((Control!$B$28+Control!$B$29*(Control!$B$38-2))+(Control!$B$32+Control!$B$33*(Control!$B$38-2))+IF(AND(Control!$B$5>0,Control!$B$6="Y",15>=Control!$B$39),Control!$B$36,0))*POWER(1+Control!$B$17,14))*Control!$B$26))+(((Control!$B$54*Control!$B$55+Control!$B$57*Control!$B$58*Control!$B$59*Control!$B$60)*POWER(1+Control!$B$17,14))-((Control!$B$57*Control!$B$58*Control!$B$59*Control!$B$60*POWER(1+Control!$B$17,14))*Control!$B$63+(Control!$B$64+Control!$B$65+Control!$B$66)*12*POWER(1+Control!$B$18,14)+((Control!$B$54*Control!$B$55+Control!$B$57*Control!$B$58*Control!$B$59*Control!$B$60)*POWER(1+Control!$B$17,14))*Control!$B$26))+((Control!$B$68*12*POWER(1+Control!$B$17,14))-((Control!$B$70+Control!$B$71+Control!$B$72)*12*POWER(1+Control!$B$18,14)+(Control!$B$68*12*POWER(1+Control!$B$17,14))*Control!$B$26)))*(1-Control!$B$23))-IF(AND(Control!$B$5>0,Control!$B$6="Y",15=Control!$B$39-1),Control!$B$40,0)) -> 1758838.3 | S53: =Control!$B$11*(((((((Control!$B$20*$A$8)*((Control!$B$28+Control!$B$29*(Control!$B$38-2))+(Control!$B$32+Control!$B$33*(Control!$B$38-2))+IF(AND(Control!$B$5>0,Control!$B$6="Y",16>=Control!$B$39),Control!$B$36,0))*POWER(1+Control!$B$17,15))+((((Control!$B$20*$A$8)*Control!$B$38*2+IF(AND(Control!$B$5>0,Control!$B$6="Y",16>=Control!$B$39),(Control!$B$20*$A$8)*2,0))*Control!$B$41)*(Control!$B$42+Control!$B$44)*POWER(1+Control!$B$17,15))+(Control!$B$46*POWER(1+Control!$B$17,15)))-(((Control!$B$20*$A$8)*((Control!$B$28+Control!$B$29*(Control!$B$38-2))+(Control!$B$32+Control!$B$33*(Control!$B$38-2))+IF(AND(Control!$B$5>0,Control!$B$6="Y",16>=Control!$B$39),Control!$B$36,0))*POWER(1+Control!$B$17,15))*Control!$B$52+(((Control!$B$20*$A$8)*Control!$B$38*2+IF(AND(Control!$B$5>0,Control!$B$6="Y",16>=Control!$B$39),(Control!$B$20*$A$8)*2,0))*Control!$B$41)*(Control!$B$43+Control!$B$45)*POWER(1+Control!$B$18,15)+Control!$B$47*POWER(1+Control!$B$18,15)+(Control!$B$48+Control!$B$49+Control!$B$50+Control!$B$51)*12*POWER(1+Control!$B$18,15)+((Control!$B$20*$A$8)*((Control!$B$28+Control!$B$29*(Control!$B$38-2))+(Control!$B$32+Control!$B$33*(Control!$B$38-2))+IF(AND(Control!$B$5>0,Control!$B$6="Y",16>=Control!$B$39),Control!$B$36,0))*POWER(1+Control!$B$17,15))*Control!$B$26))+(((Control!$B$54*Control!$B$55+Control!$B$57*Control!$B$58*Control!$B$59*Control!$B$60)*POWER(1+Control!$B$17,15))-((Control!$B$57*Control!$B$58*Control!$B$59*Control!$B$60*POWER(1+Control!$B$17,15))*Control!$B$63+(Control!$B$64+Control!$B$65+Control!$B$66)*12*POWER(1+Control!$B$18,15)+((Control!$B$54*Control!$B$55+Control!$B$57*Control!$B$58*Control!$B$59*Control!$B$60)*POWER(1+Control!$B$17,15))*Control!$B$26))+((Control!$B$68*12*POWER(1+Control!$B$17,15))-((Control!$B$70+Control!$B$71+Control!$B$72)*12*POWER(1+Control!$B$18,15)+(Control!$B$68*12*POWER(1+Control!$B$17,15))*Control!$B$26)))*(1-Control!$B$23))-IF(AND(Control!$B$5>0,Control!$B$6="Y",16=Control!$B$39-1),Control!$B$40,0)) -> 1846780.3 | T53: =Control!$B$11*(((((((Control!$B$20*$A$8)*((Control!$B$28+Control!$B$29*(Control!$B$38-2))+(Control!$B$32+Control!$B$33*(Control!$B$38-2))+IF(AND(Control!$B$5>0,Control!$B$6="Y",17>=Control!$B$39),Control!$B$36,0))*POWER(1+Control!$B$17,16))+((((Control!$B$20*$A$8)*Control!$B$38*2+IF(AND(Control!$B$5>0,Control!$B$6="Y",17>=Control!$B$39),(Control!$B$20*$A$8)*2,0))*Control!$B$41)*(Control!$B$42+Control!$B$44)*POWER(1+Control!$B$17,16))+(Control!$B$46*POWER(1+Control!$B$17,16)))-(((Control!$B$20*$A$8)*((Control!$B$28+Control!$B$29*(Control!$B$38-2))+(Control!$B$32+Control!$B$33*(Control!$B$38-2))+IF(AND(Control!$B$5>0,Control!$B$6="Y",17>=Control!$B$39),Control!$B$36,0))*POWER(1+Control!$B$17,16))*Control!$B$52+(((Control!$B$20*$A$8)*Control!$B$38*2+IF(AND(Control!$B$5>0,Control!$B$6="Y",17>=Control!$B$39),(Control!$B$20*$A$8)*2,0))*Control!$B$41)*(Control!$B$43+Control!$B$45)*POWER(1+Control!$B$18,16)+Control!$B$47*POWER(1+Control!$B$18,16)+(Control!$B$48+Control!$B$49+Control!$B$50+Control!$B$51)*12*POWER(1+Control!$B$18,16)+((Control!$B$20*$A$8)*((Control!$B$28+Control!$B$29*(Control!$B$38-2))+(Control!$B$32+Control!$B$33*(Control!$B$38-2))+IF(AND(Control!$B$5>0,Control!$B$6="Y",17>=Control!$B$39),Control!$B$36,0))*POWER(1+Control!$B$17,16))*Control!$B$26))+(((Control!$B$54*Control!$B$55+Control!$B$57*Control!$B$58*Control!$B$59*Control!$B$60)*POWER(1+Control!$B$17,16))-((Control!$B$57*Control!$B$58*Control!$B$59*Control!$B$60*POWER(1+Control!$B$17,16))*Control!$B$63+(Control!$B$64+Control!$B$65+Control!$B$66)*12*POWER(1+Control!$B$18,16)+((Control!$B$54*Control!$B$55+Control!$B$57*Control!$B$58*Control!$B$59*Control!$B$60)*POWER(1+Control!$B$17,16))*Control!$B$26))+((Control!$B$68*12*POWER(1+Control!$B$17,16))-((Control!$B$70+Control!$B$71+Control!$B$72)*12*POWER(1+Control!$B$18,16)+(Control!$B$68*12*POWER(1+Control!$B$17,16))*Control!$B$26)))*(1-Control!$B$23))-IF(AND(Control!$B$5>0,Control!$B$6="Y",17=Control!$B$39-1),Control!$B$40,0)) -> 1939119.3 | U53: =Control!$B$11*(((((((Control!$B$20*$A$8)*((Control!$B$28+Control!$B$29*(Control!$B$38-2))+(Control!$B$32+Control!$B$33*(Control!$B$38-2))+IF(AND(Control!$B$5>0,Control!$B$6="Y",18>=Control!$B$39),Control!$B$36,0))*POWER(1+Control!$B$17,17))+((((Control!$B$20*$A$8)*Control!$B$38*2+IF(AND(Control!$B$5>0,Control!$B$6="Y",18>=Control!$B$39),(Control!$B$20*$A$8)*2,0))*Control!$B$41)*(Control!$B$42+Control!$B$44)*POWER(1+Control!$B$17,17))+(Control!$B$46*POWER(1+Control!$B$17,17)))-(((Control!$B$20*$A$8)*((Control!$B$28+Control!$B$29*(Control!$B$38-2))+(Control!$B$32+Control!$B$33*(Control!$B$38-2))+IF(AND(Control!$B$5>0,Control!$B$6="Y",18>=Control!$B$39),Control!$B$36,0))*POWER(1+Control!$B$17,17))*Control!$B$52+(((Control!$B$20*$A$8)*Control!$B$38*2+IF(AND(Control!$B$5>0,Control!$B$6="Y",18>=Control!$B$39),(Control!$B$20*$A$8)*2,0))*Control!$B$41)*(Control!$B$43+Control!$B$45)*POWER(1+Control!$B$18,17)+Control!$B$47*POWER(1+Control!$B$18,17)+(Control!$B$48+Control!$B$49+Control!$B$50+Control!$B$51)*12*POWER(1+Control!$B$18,17)+((Control!$B$20*$A$8)*((Control!$B$28+Control!$B$29*(Control!$B$38-2))+(Control!$B$32+Control!$B$33*(Control!$B$38-2))+IF(AND(Control!$B$5>0,Control!$B$6="Y",18>=Control!$B$39),Control!$B$36,0))*POWER(1+Control!$B$17,17))*Control!$B$26))+(((Control!$B$54*Control!$B$55+Control!$B$57*Control!$B$58*Control!$B$59*Control!$B$60)*POWER(1+Control!$B$17,17))-((Control!$B$57*Control!$B$58*Control!$B$59*Control!$B$60*POWER(1+Control!$B$17,17))*Control!$B$63+(Control!$B$64+Control!$B$65+Control!$B$66)*12*POWER(1+Control!$B$18,17)+((Control!$B$54*Control!$B$55+Control!$B$57*Control!$B$58*Control!$B$59*Control!$B$60)*POWER(1+Control!$B$17,17))*Control!$B$26))+((Control!$B$68*12*POWER(1+Control!$B$17,17))-((Control!$B$70+Control!$B$71+Control!$B$72)*12*POWER(1+Control!$B$18,17)+(Control!$B$68*12*POWER(1+Control!$B$17,17))*Control!$B$26)))*(1-Control!$B$23))-IF(AND(Control!$B$5>0,Control!$B$6="Y",18=Control!$B$39-1),Control!$B$40,0)) -> 2036075.2 | V53: =Control!$B$11*(((((((Control!$B$20*$A$8)*((Control!$B$28+Control!$B$29*(Control!$B$38-2))+(Control!$B$32+Control!$B$33*(Control!$B$38-2))+IF(AND(Control!$B$5>0,Control!$B$6="Y",19>=Control!$B$39),Control!$B$36,0))*POWER(1+Control!$B$17,18))+((((Control!$B$20*$A$8)*Control!$B$38*2+IF(AND(Control!$B$5>0,Control!$B$6="Y",19>=Control!$B$39),(Control!$B$20*$A$8)*2,0))*Control!$B$41)*(Control!$B$42+Control!$B$44)*POWER(1+Control!$B$17,18))+(Control!$B$46*POWER(1+Control!$B$17,18)))-(((Control!$B$20*$A$8)*((Control!$B$28+Control!$B$29*(Control!$B$38-2))+(Control!$B$32+Control!$B$33*(Control!$B$38-2))+IF(AND(Control!$B$5>0,Control!$B$6="Y",19>=Control!$B$39),Control!$B$36,0))*POWER(1+Control!$B$17,18))*Control!$B$52+(((Control!$B$20*$A$8)*Control!$B$38*2+IF(AND(Control!$B$5>0,Control!$B$6="Y",19>=Control!$B$39),(Control!$B$20*$A$8)*2,0))*Control!$B$41)*(Control!$B$43+Control!$B$45)*POWER(1+Control!$B$18,18)+Control!$B$47*POWER(1+Control!$B$18,18)+(Control!$B$48+Control!$B$49+Control!$B$50+Control!$B$51)*12*POWER(1+Control!$B$18,18)+((Control!$B$20*$A$8)*((Control!$B$28+Control!$B$29*(Control!$B$38-2))+(Control!$B$32+Control!$B$33*(Control!$B$38-2))+IF(AND(Control!$B$5>0,Control!$B$6="Y",19>=Control!$B$39),Control!$B$36,0))*POWER(1+Control!$B$17,18))*Control!$B$26))+(((Control!$B$54*Control!$B$55+Control!$B$57*Control!$B$58*Control!$B$59*Control!$B$60)*POWER(1+Control!$B$17,18))-((Control!$B$57*Control!$B$58*Control!$B$59*Control!$B$60*POWER(1+Control!$B$17,18))*Control!$B$63+(Control!$B$64+Control!$B$65+Control!$B$66)*12*POWER(1+Control!$B$18,18)+((Control!$B$54*Control!$B$55+Control!$B$57*Control!$B$58*Control!$B$59*Control!$B$60)*POWER(1+Control!$B$17,18))*Control!$B$26))+((Control!$B$68*12*POWER(1+Control!$B$17,18))-((Control!$B$70+Control!$B$71+Control!$B$72)*12*POWER(1+Control!$B$18,18)+(Control!$B$68*12*POWER(1+Control!$B$17,18))*Control!$B$26)))*(1-Control!$B$23))-IF(AND(Control!$B$5>0,Control!$B$6="Y",19=Control!$B$39-1),Control!$B$40,0)) -> 2137879 | W53: =Control!$B$11*(((((((Control!$B$20*$A$8)*((Control!$B$28+Control!$B$29*(Control!$B$38-2))+(Control!$B$32+Control!$B$33*(Control!$B$38-2))+IF(AND(Control!$B$5>0,Control!$B$6="Y",20>=Control!$B$39),Control!$B$36,0))*POWER(1+Control!$B$17,19))+((((Control!$B$20*$A$8)*Control!$B$38*2+IF(AND(Control!$B$5>0,Control!$B$6="Y",20>=Control!$B$39),(Control!$B$20*$A$8)*2,0))*Control!$B$41)*(Control!$B$42+Control!$B$44)*POWER(1+Control!$B$17,19))+(Control!$B$46*POWER(1+Control!$B$17,19)))-(((Control!$B$20*$A$8)*((Control!$B$28+Control!$B$29*(Control!$B$38-2))+(Control!$B$32+Control!$B$33*(Control!$B$38-2))+IF(AND(Control!$B$5>0,Control!$B$6="Y",20>=Control!$B$39),Control!$B$36,0))*POWER(1+Control!$B$17,19))*Control!$B$52+(((Control!$B$20*$A$8)*Control!$B$38*2+IF(AND(Control!$B$5>0,Control!$B$6="Y",20>=Control!$B$39),(Control!$B$20*$A$8)*2,0))*Control!$B$41)*(Control!$B$43+Control!$B$45)*POWER(1+Control!$B$18,19)+Control!$B$47*POWER(1+Control!$B$18,19)+(Control!$B$48+Control!$B$49+Control!$B$50+Control!$B$51)*12*POWER(1+Control!$B$18,19)+((Control!$B$20*$A$8)*((Control!$B$28+Control!$B$29*(Control!$B$38-2))+(Control!$B$32+Control!$B$33*(Control!$B$38-2))+IF(AND(Control!$B$5>0,Control!$B$6="Y",20>=Control!$B$39),Control!$B$36,0))*POWER(1+Control!$B$17,19))*Control!$B$26))+(((Control!$B$54*Control!$B$55+Control!$B$57*Control!$B$58*Control!$B$59*Control!$B$60)*POWER(1+Control!$B$17,19))-((Control!$B$57*Control!$B$58*Control!$B$59*Control!$B$60*POWER(1+Control!$B$17,19))*Control!$B$63+(Control!$B$64+Control!$B$65+Control!$B$66)*12*POWER(1+Control!$B$18,19)+((Control!$B$54*Control!$B$55+Control!$B$57*Control!$B$58*Control!$B$59*Control!$B$60)*POWER(1+Control!$B$17,19))*Control!$B$26))+((Control!$B$68*12*POWER(1+Control!$B$17,19))-((Control!$B$70+Control!$B$71+Control!$B$72)*12*POWER(1+Control!$B$18,19)+(Control!$B$68*12*POWER(1+Control!$B$17,19))*Control!$B$26)))*(1-Control!$B$23))-IF(AND(Control!$B$5>0,Control!$B$6="Y",20=Control!$B$39-1),Control!$B$40,0))+Valuation!$F$10*POWER(1+Control!$B$78,20)*(1-Control!$B$79) -> 18331717
A54: [calc] Occupancy 0.7 cum | D54: =D53 -> 888332.88 | E54: =D54+E53 -> 1821082.4 | F54: =E54+F53 -> 2800469.4 | G54: =F54+G53 -> 3828825.8 | H54: =G54+H53 -> 4908599.9 | I54: =H54+I53 -> 6042362.8 | J54: =I54+J53 -> 7232813.9 | K54: =J54+K53 -> 8482787.4 | L54: =K54+L53 -> 9795259.7 | ... V54: =U54+V53 -> 27128801
