Workbook

Sheet Read Me & Glossary
A1: READ ME — how this model works
A2: Purpose | B2: Investor-facing model to sell 50% of a 3-property (+ tours) portfolio into NewCo. Shows independent property valuation, after-tax cash returns, total return and a leverage/growth path. DRAFT — accountant/attorney sign-off pending.
A3: Structure | B3: NewCo owns 100% of the included properties. The incoming Property Partner can hold a different % per property via Control share-offer inputs. Buy-in is consideration paid to the current owner (share sale), not retained as working capital in NewCo.
A4: How to use | B4: Edit only the shaded (yellow) input cells on the Control sheet. Every other sheet recalculates. Open in Excel or Google Sheets so formulas compute.
A5: Sheets | B5: Control (inputs) · 3 property P&Ls · Portfolio NewCo (consolidated) · Valuation (independent) · Investor KPIs · Property KPIs · Leverage & Growth · Change Log.
A7: TERMINOLOGY (SA hospitality standard):
A8: Unit | B8: One lettable villa/apartment (African Sky Villa, Remington, Winchester). Whole-unit lets, not per-room.
A9: Available unit-night | B9: One unit available for one night. Units × 365 = available unit-nights per year.
A10: Occupied unit-night | B10: One unit actually let for one night. Occupancy % = occupied ÷ available.
A11: ADR | B11: Average Daily Rate — the gross nightly rate per unit (base covers 2 guests; extra guests add per-guest).
A12: Guest-night | B12: One guest staying one night = occupied unit-nights × guests per unit. Drives meals.
A13: Meal cover | B13: One guest taking meals on one night. 75% of guest-nights take both breakfast + dinner.
A14: NOI | B14: Net Operating Income — revenue less operating expenses (incl. FF&E reserve), before tax and finance. Basis for income valuation.
A15: Cap rate | B15: Capitalisation rate — NOI ÷ property value. Lower cap rate = higher value. Used for residential income valuation.
A16: MOIC / IRR | B16: MOIC = money multiple (total received ÷ invested). IRR = annualised return accounting for timing.
A17: VALUATION METHOD | B17: Beachside & Menlyn are valued by income capitalisation (NOI ÷ market cap rate), which corroborates their cost basis. African Sky is valued on comparable/cost because its income is largely OPERATING (holiday-let + F&B + tours) — capitalising that at a property cap rate would massively overstate 3 villas. Adopted NAV is deliberately conservative; the income approach sits above it.
A18: OPEN FLAGS (gated) | B18: • VAT: combined revenue is over the R1m compulsory-registration threshold — short-term accommodation is taxable, long-term residential exempt (mixed supply). Default keeps the gross basis; confirm with the accountant. • Transfer of properties into NewCo triggers transfer duty / VAT / CGT, and a s42 asset-for-share roll-over carries an 18-month de-grouping clawback if 50% is sold at/near formation — attorney + accountant. • Selling 50% equity may engage Companies Act offer-to-public / FAIS rules. • Cap rates and the African Sky comparable value are assumptions to confirm with a registered valuer. • Winchester is not built — its revenue is phased from its online year and its R500k build is funded from NewCo cash.
A19: Status | B19: DRAFT · unaudited · ZAR · rebuilt 2026-07-10. Not an offer to the public; subject to MOI/shareholders agreement and professional sign-off. Nothing here is legal, tax or investment advice.
A20: TOURS (v3) | B20: African Sky tour income and supplier cost are now driven by the 'ASKY Tours Calcs' sheet — 14 experiences (safaris, day tours, river adventures, transfers) each with per-pax retail (fixed from the live site), supplier cost and take-up. The Control tour cells link to its totals (revenue O27, cost P27); edit tours on that sheet.

Sheet Key Assumptions Sources
A1: KEY ASSUMPTIONS & SOURCES
A2: Plain-English source sheet for proposal review. All model items are live linked where relevant.
A4: Category | B4: Assumption | C4: Value | D4: Source / explanation
A5: Scenario | B5: African Sky partner share % | C5: 0.5 | D5: 0% excludes property; >0% includes at selected share
A6: Scenario | B6: Winchester expansion option | C6: N | D6: Y/N; only active if African Sky share > 0%
A7: Scenario | B7: Beachside partner share % | C7: 0.5 | D7: 0% excludes property; >0% includes at selected share
A8: Scenario | B8: Menlyn partner share % | C8: 0.5 | D8: 0% excludes property; >0% includes at selected share
A9: Guests | B9: ASV avg guests per occupied unit-night | C9: 2.8 | D9: Control!B31
A10: Pricing | B10: ASV base ADR incl. 2 guests | C10: 4500 | D10: Control!B28
A11: Pricing | B11: ASV extra guest rate | C11: 1000 | D11: Control!B29
A12: Pricing | B12: Remington base ADR incl. 2 guests | C12: =Control!$B$32 | D12: Control!B32
A13: Pricing | B13: Remington extra guest rate | C13: =Control!$B$33 | D13: Control!B33
A14: Tours | B14: Tour revenue Year 1 | C14: 2071762.4 | D14: Linked from ASKY Tours Calcs totals
A15: Tours | B15: Tour supplier cost Year 1 | C15: 1512882.8 | D15: Linked from ASKY Tours Calcs totals
A16: Stay duration | B16: ASV avg nights / booking | C16: 0 | D16: Realised booking analysis in ASKY Stay Calc
A17: Stay duration | B17: Remington avg nights / booking | C17: 0 | D17: Realised booking analysis in ASKY Stay Calc
A18: Valuation | B18: Adopted property value | C18: 12800000 | D18: Valuation!F9
A19: Valuation | B19: Partner NAV today | C19: 6400000 | D19: Valuation!F10
A20: Exit | B20: Property value growth p.a. | C20: 0.05 | D20: Control!B68 linked to Control!B74
A21: Tax / legal | B21: Open flags | C21: See Read Me & Glossary!B18 | D21: Accountant/attorney sign-off required
A22: Optional asset | B22: Winchester development expansion toggle | C22: N | D22: Y includes Winchester revenue, build capex and value; N excludes it. Only active if African Sky toggle is Y.

Sheet Control
A1: CONTROL — edit only the shaded (yellow) input cells
A2: ZAR · DRAFT · all sheets link here. Terminology follows SA hospitality/property convention — see 'Read Me & Glossary'.
A4: 0 · PARTNER SHARE OFFER | B4: Partner Offer Prop % | C4: Distribution allocation % | E4: INVESTOR KPI SNAPSHOT — ACTIVE PORTFOLIO
A5: African Sky partner share % | B5: 0.5 | C5: =B5 | D5: follows Offer % (edit col B) | E5: KPI | F5: Value | G5: What it shows
A6: Winchester expansion? (Y/N; active if African Sky share > 0%) | B6: N | E6: =_xlfn.TEXTJOIN(", ",TRUE,IF($B$5>0,"African Sky",""),IF(AND($B$5>0,$B$6="Y"),"Winchester expansion",""),IF($B$7>0,"Beachside",""),IF($B$8>0,"Menlyn","")) | G6: Properties with share % > 0 are included; Winchester is separate option
A7: Beachside partner share % | B7: 0.5 | C7: =B7 | D7: follows Offer % (edit col B) | E7: Active portfolio value | F7: =Valuation!$F$9 | G7: 100% adopted value of active properties
A8: Menlyn partner share % | B8: 0.5 | C8: =B8 | D8: follows Offer % (edit col B) | E8: Partner buy-in | F8: =Control!$B$15 | G8: Cash consideration based on active properties and property-specific partner %
E9: Partner NAV today | F9: =Valuation!$F$10 | G9: Partner NAV using property-specific partner % by property
A10: 1 · DEAL & STRUCTURE | C10: 10Y Avg Annual Cash Yield | E10: Offer vs NAV | F10: =IFERROR(Control!$B$15/Valuation!$F$10,"") | G10: 1.0x = buy-in equals NAV
A11: Reference % for listed buy-in pricing | B11: 0.5 | E11: Year 1 partner distribution | F11: ='Portfolio NewCo'!B16 | G11: Projected first-year cash distribution using Control distribution allocation %
A12: African Sky — buy-in at reference % (ZAR) | B12: 3000000 | C12: =IFERROR(('Portfolio NewCo'!K25/10)/IF($B$5>0,$B$12/$B$11*$B$5,0),"") | E12: Year 1 cash yield | F12: =IFERROR('Portfolio NewCo'!B16/Control!$B$15,"") | G12: Year 1 distribution ÷ partner buy-in
A13: Beachside — buy-in at reference % (ZAR) | B13: 2000000 | C13: =IFERROR(('Portfolio NewCo'!K26/10)/IF($B$7>0,$B$13/$B$11*$B$7,0),"") | E13: Cash payback year | F13: ='INV - Investor KPIs'!B25 | G13: Year cumulative distributions recover buy-in
A14: Menlyn — buy-in at reference % (ZAR) | B14: 1400000 | C14: =IFERROR(('Portfolio NewCo'!K27/10)/IF($B$8>0,$B$14/$B$11*$B$8,0),"") | E14: 5Y Total Partner Distributions | F14: ='INV - Investor KPIs'!G7 | G14: Cumulative partner distributions received through Year 5
A15: Total active partner buy-in (share-offer %) | B15: =IF($B$5>0,$B$12/$B$11*$B$5,0)+IF($B$7>0,$B$13/$B$11*$B$7,0)+IF($B$8>0,$B$14/$B$11*$B$8,0) | C15: =IFERROR(('Portfolio NewCo'!K17/10)/$B$15,"") | E15: 5Y Total Partner Value if Exit in Year 5 | F15: ='INV - Investor KPIs'!G12 | G15: Cumulative distributions + exit NAV — Total Partner Value if Exit in Year 5
A16: 2 · FORECAST DRIVERS | E16: 5Y Total IRR | F16: ='INV - Investor KPIs'!C18 | G16: Includes cash distributions + exit NAV
A17: Room-rate (ADR) escalation p.a. | B17: 0.05 | E17: 5Y Total MOIC | F17: ='INV - Investor KPIs'!C20 | G17: Total value received ÷ buy-in
A18: Expense inflation p.a. | B18: 0.05 | E18: 10Y Total Partner Distributions | F18: ='INV - Investor KPIs'!L7 | G18: Cumulative partner distributions received through Year 10
A19: Occupancy — short-let units (%) — DEPRECATED: replaced by per-villa occupancy (B30 / B34 / B37) | B19: 0.75 | E19: 10Y Total Partner Value if Exit in Year 10 | F19: ='INV - Investor KPIs'!L12 | G19: Cumulative distributions + exit NAV — Total Partner Value if Exit in Year 10
A20: Available nights per year | B20: 365 | E20: 10Y Total IRR | F20: ='INV - Investor KPIs'!D18 | G20: Includes cash distributions + exit NAV
A21: Model horizon (years) — DISPLAY MEMO ONLY: projection is fixed at 20 years | B21: 20 | E21: 10Y Total MOIC | F21: ='INV - Investor KPIs'!D20 | G21: Total value received ÷ buy-in
A22: 3 · TAX, VAT & RESERVES | E22: 15Y Total Partner Distributions | F22: ='INV - Investor KPIs'!Q7 | G22: Cumulative partner distributions received through Year 15
A23: Corporate income tax rate | B23: 0.27 | E23: 15Y Total Partner Value if Exit in Year 15 | F23: ='INV - Investor KPIs'!Q12 | G23: Cumulative distributions + exit NAV — Total Partner Value if Exit in Year 15
A24: Apply output VAT to short-let accommodation? (1=Yes/0=No) — PLACEHOLDER: VAT not yet wired; gated to accountant | B24: 0 | E24: 15Y Total IRR | F24: ='INV - Investor KPIs'!E18 | G24: Includes cash distributions + exit NAV
A25: VAT rate — PLACEHOLDER: not yet wired | B25: 0.15 | E25: 15Y Total MOIC | F25: ='INV - Investor KPIs'!E20 | G25: Total value received ÷ buy-in
A26: FF&E / capex reserve (% of accommodation revenue) | B26: 0.04 | E26: 20Y Total Partner Distributions | F26: ='INV - Investor KPIs'!V7 | G26: Cumulative partner distributions received through Year 20
A27: 4 · AFRICAN SKY VILLAS — 3 units + meals + tours | E27: 20Y Total Partner Value if Exit in Year 20 | F27: ='INV - Investor KPIs'!V12 | G27: Cumulative distributions + exit NAV — Total Partner Value if Exit in Year 20
A28: African Sky Villa — ADR incl. 2 guests (ZAR/night) | B28: 4500 | E28: 20Y Total IRR | F28: ='INV - Investor KPIs'!F18 | G28: Includes cash distributions + exit NAV
A29: African Sky Villa — extra-guest rate (ZAR/guest/night) | B29: 1000 | E29: 20Y Total MOIC | F29: ='INV - Investor KPIs'!F20 | G29: Total value received ÷ buy-in
A30: African Sky Villa — avg annual nights booked (%) | B30: ='ASKY Bookings'!C390
A31: African Sky Villa — avg guests per occupied unit-night | B31: ='ASKY Bookings'!C409
A32: Remington Villa — ADR incl. 2 guests (ZAR/night) | B32: 3700
A33: Remington Villa — extra-guest rate (ZAR/guest/night) | B33: 750
A34: Remington Villa — avg annual nights booked (%) | B34: ='ASKY Bookings'!D390
A35: Remington Villa — avg guests per occupied unit-night | B35: ='ASKY Bookings'!D409
A36: Winchester (planned) — ADR, sleeps 2 (ZAR/night) | B36: 3500
A37: Winchester — avg annual nights booked (%) | B37: 0.52
A38: Winchester — avg guests per occupied unit-night | B38: 2
A39: Winchester — online from year | B39: 2
A40: Winchester — construction cost (ZAR, one-off) | B40: 500000
A41: Meal take-up — guests taking both meals (%) | B41: 0.75
A42: Breakfast price (ZAR/guest) | B42: 150
A43: Breakfast cost (ZAR/guest) | B43: 100
A44: Dinner price (ZAR/guest) | B44: 375
A45: Dinner cost (ZAR/guest) | B45: 200
A46: Tours & activities revenue (ZAR/yr) — linked from ASKY Tours Calcs | B46: ='ASKY Tours Calcs'!O27
A47: Tours & activities cost (ZAR/yr) — linked from ASKY Tours Calcs | B47: ='ASKY Tours Calcs'!P27
A48: African Sky — salaries & wages (ZAR/month) | B48: 30000
A49: African Sky — utilities & municipal (ZAR/month) | B49: 6800
A50: African Sky — repairs & maintenance (ZAR/month) | B50: 3500
A51: African Sky — other operating (ZAR/month) | B51: 5000
A52: African Sky — channel commission (% of accommodation) | B52: 0.2
A53: 5 · BEACHSIDE ESCAPE — Big Bay
A54: Long-term rent (ZAR/month) | B54: 30000
A55: Long-term months per year | B55: 10
A56: Peak holiday ADR (ZAR/night) | B56: 4500
A57: Peak months per year (Dec+Jan) | B57: 2
A58: Nights per peak month | B58: 30
A59: Peak-season occupancy (%) | B59: 0.9
A60: Commission on nightly lets (%) | B60: 0.2
A61: Utilities & municipal (ZAR/month) | B61: 1000
A62: Repairs & maintenance (ZAR/month) | B62: 1000
A63: Levies (ZAR/month) | B63: 3800
A64: 6 · MENLYN MAIN — long-term rental
A65: Rental income (ZAR/month) | B65: 28000
A66: Utilities & municipal (ZAR/month) | B66: 900
A67: Repairs & maintenance (ZAR/month) | B67: 1000
A68: Levies / rates (ZAR/month) | B68: 3500
A69: 7 · VALUATION (independent — income & comparable)
A70: African Sky — hospitality cap rate (memo only) | B70: 0.1
A71: Beachside — residential cap rate | B71: 0.075
A72: Menlyn — residential cap rate | B72: 0.085
A73: African Sky — property value, 2 built units (comparable/cost, ZAR) | B73: 6000000
A74: Property value growth p.a. (exit) | B74: =B80
A75: Sale friction / exit costs (%) | B75: 0.06
A76: 8 · LEVERAGE & GROWTH ENGINE
A77: Target loan-to-value on portfolio (%) | B77: 0.6
A78: Debt interest rate p.a. (%) | B78: 0.115
A79: Stabilised / acquisition income yield (%) | B79: 0.09
A80: Property appreciation p.a. (%) | B80: 0.05
A81: Share of free cashflow reinvested (%) | B81: 1
A83: Display note
A84: If a property share % is 0%, the property remains visible for context but numeric values/outputs are visually blanked. Underlying inputs/formulas are preserved and reappear when share % is above 0%.

Sheet INV - Property Breakdown
A1: PROPERTY OVERVIEW + PROPERTY-SPECIFIC PARTNER ECONOMICS
A2: Scenario share inputs include/exclude each property: 0% excludes, >0% includes at selected partner share. Winchester follows African Sky and its expansion option.
A4: TABLE 1 — PROPERTY / ASSET METRICS
A5: Metric | B5: African Sky Villas | C5: Beachside Escape | D5: Menlyn Main | E5: Portfolio
A6: Description | B6: 3-villa short-let / hospitality asset: African Sky Villa, Remington Villa and planned Winchester, with meals plus tours & activities. | C6: Big Bay property with mixed long-term rental plus peak holiday letting during Dec/Jan. | D6: Long-term residential rental apartment with recurring monthly rental income. | E6: Combined NewCo property portfolio.
A7: Revenue basis | B7: Accommodation + meals + tours & activities. | C7: 10 months long-term rent + 2 peak holiday months. | D7: Monthly long-term rental. | E7: All property revenue streams consolidated.
A8: Adopted property value (100%) | B8: =Valuation!C9 | C8: =Valuation!D9 | D8: =Valuation!E9 | E8: =Valuation!F9
A9: Year 1 NOI | B9: ='Portfolio NewCo'!B6 | C9: ='Portfolio NewCo'!B7 | D9: ='Portfolio NewCo'!B8 | E9: ='Portfolio NewCo'!B9
A10: NOI yield on adopted value | B10: ='INV - Property KPIs'!B9 | C10: ='INV - Property KPIs'!C9 | D10: ='INV - Property KPIs'!D9 | E10: ='INV - Property KPIs'!F9
A11: Implied value / NOI multiple | B11: ='INV - Property KPIs'!B10 | C11: ='INV - Property KPIs'!C10 | D11: ='INV - Property KPIs'!D10 | E11: ='INV - Property KPIs'!F10
A13: TABLE 2 — PROPERTY-SPECIFIC PARTNER / INVESTOR ECONOMICS
A14: Metric | B14: African Sky Villas | C14: Beachside Escape | D14: Menlyn Main | E14: Portfolio
A15: Partner share / NAV @ property-specific % | B15: =Valuation!C10 | C15: =Valuation!D10 | D15: =Valuation!E10 | E15: =Valuation!F10
A16: Partner buy-in component | B16: ='INV - Property KPIs'!B5 | C16: ='INV - Property KPIs'!C5 | D16: ='INV - Property KPIs'!D5 | E16: ='INV - Property KPIs'!F5
A17: 5-year total IRR | B17: ='INV - Property KPIs'!B13 | C17: ='INV - Property KPIs'!C13 | D17: ='INV - Property KPIs'!D13 | E17: ='INV - Property KPIs'!F13
A18: 5-year total MOIC | B18: ='INV - Property KPIs'!B12 | C18: ='INV - Property KPIs'!C12 | D18: ='INV - Property KPIs'!D12 | E18: ='INV - Property KPIs'!F12
A19: 10-year total IRR | B19: ='INV - Property KPIs'!B16 | C19: ='INV - Property KPIs'!C16 | D19: ='INV - Property KPIs'!D16 | E19: ='INV - Property KPIs'!F16
A20: 10-year total MOIC | B20: ='INV - Property KPIs'!B15 | C20: ='INV - Property KPIs'!C15 | D20: ='INV - Property KPIs'!D15 | E20: ='INV - Property KPIs'!F15
A21: 15-year total IRR | B21: ='INV - Property KPIs'!B19 | C21: ='INV - Property KPIs'!C19 | D21: ='INV - Property KPIs'!D19 | E21: ='INV - Property KPIs'!F19
A22: 15-year total MOIC | B22: ='INV - Property KPIs'!B18 | C22: ='INV - Property KPIs'!C18 | D22: ='INV - Property KPIs'!D18 | E22: ='INV - Property KPIs'!F18
A23: 20-year total IRR
A24: 20-year total MOIC | B24: ='INV - Property KPIs'!B21 | C24: ='INV - Property KPIs'!C21 | D24: ='INV - Property KPIs'!D21 | E24: ='INV - Property KPIs'!F21
A25: African Sky Villa accommodation | B25: Occupied unit-nights × ADR incl. extra guests | C25: ='African Sky P&L'!C7 | D25: ='African Sky P&L'!D7 | E25: Short-let villa revenue
A26: Remington Villa accommodation | B26: Occupied unit-nights × ADR incl. extra guests | C26: ='African Sky P&L'!C8 | D26: ='African Sky P&L'!D8 | E26: Short-let villa revenue
A27: Winchester accommodation | B27: Online-from-year × ADR | C27: ='African Sky P&L'!C9 | D27: ='African Sky P&L'!D9 | E27: Planned unit online from model year
A28: Meals income | B28: Guest-nights × meal take-up × breakfast/dinner pricing | C28: ='African Sky P&L'!C13 | D28: ='African Sky P&L'!D13 | E28: Breakfast + dinner income
A29: Tours & activities income | B29: Linked tour revenue assumptions | C29: ='African Sky P&L'!C14 | D29: ='African Sky P&L'!D14 | E29: Linked from ASKY Tours Calcs
A30: Total gross revenue | B30: Sum of above streams | C30: ='African Sky P&L'!C15 | D30: ='African Sky P&L'!D15 | E30: Before operating expenses
A32: BEACHSIDE ESCAPE — revenue streams
A33: Revenue stream / driver | B33: Basis | C33: Year 1 | D33: Year 2 | E33: Notes
A34: Long-term rent | B34: Monthly rent × long-term months | C34: =Control!B54*Control!B55 | D34: =C34*(1+Control!B17) | E34: 10 long-term months per year
A35: Peak holiday lets | B35: Peak ADR × peak months × nights/month × occupancy | C35: =Control!B56*Control!B57*Control!B58*Control!B59 | D35: =C35*(1+Control!B17) | E35: Dec/Jan holiday letting
A36: Estimated gross revenue | B36: Long-term rent + peak holiday lets | C36: =SUM(C34:C35) | D36: =SUM(D34:D35) | E36: Before commission and operating expenses
A37: Year 1 NOI | B37: Portfolio NewCo Beachside NOI | C37: ='Portfolio NewCo'!B7 | D37: ='Portfolio NewCo'!C7 | E37: After model operating costs
A39: MENLYN MAIN — revenue streams
A40: Revenue stream / driver
A41: Long-term rental income | B41: Monthly rent × 12 | E41: Recurring monthly rental
A42: Estimated gross revenue | B42: Long-term rental income | C42: =Control!B65*12 | D42: =C42*(1+Control!B17) | E42: Before operating expenses
A43: Year 1 NOI | B43: Portfolio NewCo Menlyn NOI | C43: =C42 | D43: =D42 | E43: After model operating costs
C44: ='Portfolio NewCo'!B8 | D44: ='Portfolio NewCo'!C8

Sheet Valuation
A1: PROPERTY VALUATION — independent (income & comparable, NOT back-solved from buy-in)
A2: Two industry methods per asset. Partner share % inputs on Control include/exclude each property from investor economics; 0% excludes, >0% includes. Winchester is a development expansion option and only activates if African Sky share > 0%.
A4: Valuation basis | C4: African Sky | D4: Beachside | E4: Menlyn | F4: Portfolio
A5: In-place annual NOI (active properties only; AS reflects Winchester only if expansion is active) | C5: ='African Sky P&L'!D26 | D5: ='Beachside P&L'!C16 | E5: ='Menlyn P&L'!C13 | F5: =SUM(C5:E5)
A6: Market cap rate (income approach) | C6: =Control!$B$70 | D6: =Control!$B$71 | E6: =Control!$B$72
A7: Income-capitalised value (NOI ÷ cap rate) | C7: =IFERROR(C5/C6,0) | D7: =IFERROR(D5/D6,0) | E7: =IFERROR(E5/E6,0)
A8: Independent comparable value (CMA input — editable; income approach corroborates below) | C8: =IF(Control!$B$5>0,Control!$B$73+IF(AND(Control!$B$6="Y",Control!$B$5>0),Control!$B$40,0),0) | D8: =IF(Control!$B$7>0,4000000,0) | E8: =IF(Control!$B$8>0,2900000,0) | F8: =SUM(C8:E8)
A9: ADOPTED property value (conservative) | C9: =C8 | D9: =D8 | E9: =E8 | F9: =SUM(C9:E9)
A10: Partner NAV @ property-specific % | C10: =C9*Control!$B$5 | D10: =D9*Control!$B$7 | E10: =E9*Control!$B$8 | F10: =SUM(C10:E10)
A11: Income approach vs adopted (×, >1 = conservative) | C11: =IFERROR(C7/C9,0) | D11: =IFERROR(D7/D9,0) | E11: =IFERROR(E7/E9,0)
A12: NOI yield on adopted value | C12: =IFERROR(C5/C9,0) | D12: =IFERROR(D5/D9,0) | E12: =IFERROR(E5/E9,0)
A13: Memo: African Sky operating-business value (meals+tours net × 3, indicative) | C13: =IF(Control!$B$5>0,(('African Sky P&L'!D13-'African Sky P&L'!D18)+('African Sky P&L'!D14-'African Sky P&L'!D19))*3,0)
A15: v7.8 note: Beachside & Menlyn adopted values are now independent CMA inputs (D8/E8), no longer buy-in×2. Income-capitalised values (row 7) corroborate higher. Internal estimates pending a registered (SACPVP) valuation.

Sheet African Sky P&L
A1: AFRICAN SKY VILLAS — P&L (annual, 20-year)
A2: 3 units (African Sky Villa · Remington · Winchester) + meals + tours. Winchester phases in from its online year. After FF&E reserve, after tax.
A4: Year | C4: 1 | D4: 2 | E4: 3 | F4: 4 | G4: 5 | H4: 6 | I4: 7 | J4: 8 | K4: 9 | L4: 10 | M4: 11 | N4: 12 | O4: 13 | P4: 14 | Q4: 15 | R4: 16 | S4: 17 | T4: 18 | U4: 19 | V4: 20
A6: Occupied unit-nights / unit | C6: =IF(Control!$B$5>0,Control!$B$20*(Control!$B$30+Control!$B$34+IF(Control!$B$6="Y",Control!$B$37,0))/(2+IF(Control!$B$6="Y",1,0)),0) | D6: =IF(Control!$B$5>0,Control!$B$20*(Control!$B$30+Control!$B$34+IF(Control!$B$6="Y",Control!$B$37,0))/(2+IF(Control!$B$6="Y",1,0)),0) | E6: =IF(Control!$B$5>0,Control!$B$20*(Control!$B$30+Control!$B$34+IF(Control!$B$6="Y",Control!$B$37,0))/(2+IF(Control!$B$6="Y",1,0)),0) | F6: =IF(Control!$B$5>0,Control!$B$20*(Control!$B$30+Control!$B$34+IF(Control!$B$6="Y",Control!$B$37,0))/(2+IF(Control!$B$6="Y",1,0)),0) | G6: =IF(Control!$B$5>0,Control!$B$20*(Control!$B$30+Control!$B$34+IF(Control!$B$6="Y",Control!$B$37,0))/(2+IF(Control!$B$6="Y",1,0)),0) | H6: =IF(Control!$B$5>0,Control!$B$20*(Control!$B$30+Control!$B$34+IF(Control!$B$6="Y",Control!$B$37,0))/(2+IF(Control!$B$6="Y",1,0)),0) | I6: =IF(Control!$B$5>0,Control!$B$20*(Control!$B$30+Control!$B$34+IF(Control!$B$6="Y",Control!$B$37,0))/(2+IF(Control!$B$6="Y",1,0)),0) | J6: =IF(Control!$B$5>0,Control!$B$20*(Control!$B$30+Control!$B$34+IF(Control!$B$6="Y",Control!$B$37,0))/(2+IF(Control!$B$6="Y",1,0)),0) | ... V6: =IF(Control!$B$5>0,Control!$B$20*(Control!$B$30+Control!$B$34+IF(Control!$B$6="Y",Control!$B$37,0))/(2+IF(Control!$B$6="Y",1,0)),0)
A7: African Sky Villa — accommodation | C7: =IF(Control!$B$5>0,(Control!$B$20*Control!$B$30)*(Control!$B$28+Control!$B$29*MAX(0,Control!$B$31-2))*POWER(1+Control!$B$17,C$4-1),0) | D7: =IF(Control!$B$5>0,(Control!$B$20*Control!$B$30)*(Control!$B$28+Control!$B$29*MAX(0,Control!$B$31-2))*POWER(1+Control!$B$17,D$4-1),0) | E7: =IF(Control!$B$5>0,(Control!$B$20*Control!$B$30)*(Control!$B$28+Control!$B$29*MAX(0,Control!$B$31-2))*POWER(1+Control!$B$17,E$4-1),0) | F7: =IF(Control!$B$5>0,(Control!$B$20*Control!$B$30)*(Control!$B$28+Control!$B$29*MAX(0,Control!$B$31-2))*POWER(1+Control!$B$17,F$4-1),0) | G7: =IF(Control!$B$5>0,(Control!$B$20*Control!$B$30)*(Control!$B$28+Control!$B$29*MAX(0,Control!$B$31-2))*POWER(1+Control!$B$17,G$4-1),0) | H7: =IF(Control!$B$5>0,(Control!$B$20*Control!$B$30)*(Control!$B$28+Control!$B$29*MAX(0,Control!$B$31-2))*POWER(1+Control!$B$17,H$4-1),0) | I7: =IF(Control!$B$5>0,(Control!$B$20*Control!$B$30)*(Control!$B$28+Control!$B$29*MAX(0,Control!$B$31-2))*POWER(1+Control!$B$17,I$4-1),0) | J7: =IF(Control!$B$5>0,(Control!$B$20*Control!$B$30)*(Control!$B$28+Control!$B$29*MAX(0,Control!$B$31-2))*POWER(1+Control!$B$17,J$4-1),0) | ... V7: =IF(Control!$B$5>0,(Control!$B$20*Control!$B$30)*(Control!$B$28+Control!$B$29*MAX(0,Control!$B$31-2))*POWER(1+Control!$B$17,V$4-1),0)
A8: Remington Villa — accommodation | C8: =IF(Control!$B$5>0,(Control!$B$20*Control!$B$34)*(Control!$B$32+Control!$B$33*MAX(0,Control!$B$35-2))*POWER(1+Control!$B$17,C$4-1),0) | D8: =IF(Control!$B$5>0,(Control!$B$20*Control!$B$34)*(Control!$B$32+Control!$B$33*MAX(0,Control!$B$35-2))*POWER(1+Control!$B$17,D$4-1),0) | E8: =IF(Control!$B$5>0,(Control!$B$20*Control!$B$34)*(Control!$B$32+Control!$B$33*MAX(0,Control!$B$35-2))*POWER(1+Control!$B$17,E$4-1),0) | F8: =IF(Control!$B$5>0,(Control!$B$20*Control!$B$34)*(Control!$B$32+Control!$B$33*MAX(0,Control!$B$35-2))*POWER(1+Control!$B$17,F$4-1),0) | G8: =IF(Control!$B$5>0,(Control!$B$20*Control!$B$34)*(Control!$B$32+Control!$B$33*MAX(0,Control!$B$35-2))*POWER(1+Control!$B$17,G$4-1),0) | H8: =IF(Control!$B$5>0,(Control!$B$20*Control!$B$34)*(Control!$B$32+Control!$B$33*MAX(0,Control!$B$35-2))*POWER(1+Control!$B$17,H$4-1),0) | I8: =IF(Control!$B$5>0,(Control!$B$20*Control!$B$34)*(Control!$B$32+Control!$B$33*MAX(0,Control!$B$35-2))*POWER(1+Control!$B$17,I$4-1),0) | J8: =IF(Control!$B$5>0,(Control!$B$20*Control!$B$34)*(Control!$B$32+Control!$B$33*MAX(0,Control!$B$35-2))*POWER(1+Control!$B$17,J$4-1),0) | ... V8: =IF(Control!$B$5>0,(Control!$B$20*Control!$B$34)*(Control!$B$32+Control!$B$33*MAX(0,Control!$B$35-2))*POWER(1+Control!$B$17,V$4-1),0)
A9: Winchester — accommodation | C9: =IF(AND(Control!$B$5>0,Control!$B$6="Y",C$4>=Control!$B$39),(Control!$B$20*Control!$B$37)*Control!$B$36*POWER(1+Control!$B$17,C$4-1),0) | D9: =IF(AND(Control!$B$5>0,Control!$B$6="Y",D$4>=Control!$B$39),(Control!$B$20*Control!$B$37)*Control!$B$36*POWER(1+Control!$B$17,D$4-1),0) | E9: =IF(AND(Control!$B$5>0,Control!$B$6="Y",E$4>=Control!$B$39),(Control!$B$20*Control!$B$37)*Control!$B$36*POWER(1+Control!$B$17,E$4-1),0) | F9: =IF(AND(Control!$B$5>0,Control!$B$6="Y",F$4>=Control!$B$39),(Control!$B$20*Control!$B$37)*Control!$B$36*POWER(1+Control!$B$17,F$4-1),0) | G9: =IF(AND(Control!$B$5>0,Control!$B$6="Y",G$4>=Control!$B$39),(Control!$B$20*Control!$B$37)*Control!$B$36*POWER(1+Control!$B$17,G$4-1),0) | H9: =IF(AND(Control!$B$5>0,Control!$B$6="Y",H$4>=Control!$B$39),(Control!$B$20*Control!$B$37)*Control!$B$36*POWER(1+Control!$B$17,H$4-1),0) | I9: =IF(AND(Control!$B$5>0,Control!$B$6="Y",I$4>=Control!$B$39),(Control!$B$20*Control!$B$37)*Control!$B$36*POWER(1+Control!$B$17,I$4-1),0) | J9: =IF(AND(Control!$B$5>0,Control!$B$6="Y",J$4>=Control!$B$39),(Control!$B$20*Control!$B$37)*Control!$B$36*POWER(1+Control!$B$17,J$4-1),0) | ... V9: =IF(AND(Control!$B$5>0,Control!$B$6="Y",V$4>=Control!$B$39),(Control!$B$20*Control!$B$37)*Control!$B$36*POWER(1+Control!$B$17,V$4-1),0)
A10: Accommodation revenue — all units | C10: =SUM(C7:C9) | D10: =SUM(D7:D9) | E10: =SUM(E7:E9) | F10: =SUM(F7:F9) | G10: =SUM(G7:G9) | H10: =SUM(H7:H9) | I10: =SUM(I7:I9) | J10: =SUM(J7:J9) | ... V10: =SUM(V7:V9)
A11: Guest-nights (meal base) | C11: =IF(Control!$B$5>0,Control!$B$20*(Control!$B$30*Control!$B$31+Control!$B$34*Control!$B$35+IF(AND(Control!$B$6="Y",C$4>=Control!$B$39),Control!$B$37*Control!$B$38,0)),0) | D11: =IF(Control!$B$5>0,Control!$B$20*(Control!$B$30*Control!$B$31+Control!$B$34*Control!$B$35+IF(AND(Control!$B$6="Y",D$4>=Control!$B$39),Control!$B$37*Control!$B$38,0)),0) | E11: =IF(Control!$B$5>0,Control!$B$20*(Control!$B$30*Control!$B$31+Control!$B$34*Control!$B$35+IF(AND(Control!$B$6="Y",E$4>=Control!$B$39),Control!$B$37*Control!$B$38,0)),0) | F11: =IF(Control!$B$5>0,Control!$B$20*(Control!$B$30*Control!$B$31+Control!$B$34*Control!$B$35+IF(AND(Control!$B$6="Y",F$4>=Control!$B$39),Control!$B$37*Control!$B$38,0)),0) | G11: =IF(Control!$B$5>0,Control!$B$20*(Control!$B$30*Control!$B$31+Control!$B$34*Control!$B$35+IF(AND(Control!$B$6="Y",G$4>=Control!$B$39),Control!$B$37*Control!$B$38,0)),0) | H11: =IF(Control!$B$5>0,Control!$B$20*(Control!$B$30*Control!$B$31+Control!$B$34*Control!$B$35+IF(AND(Control!$B$6="Y",H$4>=Control!$B$39),Control!$B$37*Control!$B$38,0)),0) | I11: =IF(Control!$B$5>0,Control!$B$20*(Control!$B$30*Control!$B$31+Control!$B$34*Control!$B$35+IF(AND(Control!$B$6="Y",I$4>=Control!$B$39),Control!$B$37*Control!$B$38,0)),0) | J11: =IF(Control!$B$5>0,Control!$B$20*(Control!$B$30*Control!$B$31+Control!$B$34*Control!$B$35+IF(AND(Control!$B$6="Y",J$4>=Control!$B$39),Control!$B$37*Control!$B$38,0)),0) | ... V11: =IF(Control!$B$5>0,Control!$B$20*(Control!$B$30*Control!$B$31+Control!$B$34*Control!$B$35+IF(AND(Control!$B$6="Y",V$4>=Control!$B$39),Control!$B$37*Control!$B$38,0)),0)
A12: Meal covers — both meals taken | C12: =C11*Control!$B$41 | D12: =D11*Control!$B$41 | E12: =E11*Control!$B$41 | F12: =F11*Control!$B$41 | G12: =G11*Control!$B$41 | H12: =H11*Control!$B$41 | I12: =I11*Control!$B$41 | J12: =J11*Control!$B$41 | ... V12: =V11*Control!$B$41
A13: Meals income (breakfast + dinner) | C13: =C12*(Control!$B$42+Control!$B$44)*POWER(1+Control!$B$17,C$4-1) | D13: =D12*(Control!$B$42+Control!$B$44)*POWER(1+Control!$B$17,D$4-1) | E13: =E12*(Control!$B$42+Control!$B$44)*POWER(1+Control!$B$17,E$4-1) | F13: =F12*(Control!$B$42+Control!$B$44)*POWER(1+Control!$B$17,F$4-1) | G13: =G12*(Control!$B$42+Control!$B$44)*POWER(1+Control!$B$17,G$4-1) | H13: =H12*(Control!$B$42+Control!$B$44)*POWER(1+Control!$B$17,H$4-1) | I13: =I12*(Control!$B$42+Control!$B$44)*POWER(1+Control!$B$17,I$4-1) | J13: =J12*(Control!$B$42+Control!$B$44)*POWER(1+Control!$B$17,J$4-1) | ... V13: =V12*(Control!$B$42+Control!$B$44)*POWER(1+Control!$B$17,V$4-1)
A14: Tours & activities income | C14: =IF(Control!$B$5>0,Control!$B$46*((Control!$B$20*(Control!$B$30*Control!$B$31+Control!$B$34*Control!$B$35+IF(AND(Control!$B$6="Y",C$4>=Control!$B$39),Control!$B$37*Control!$B$38,0)))/(Control!$B$20*(Control!$B$30*Control!$B$31+Control!$B$34*Control!$B$35+IF(AND(Control!$B$5>0,Control!$B$6="Y",1>=Control!$B$39),Control!$B$37*Control!$B$38,0))))*POWER(1+Control!$B$17,C$4-1),0) | D14: =IF(Control!$B$5>0,Control!$B$46*((Control!$B$20*(Control!$B$30*Control!$B$31+Control!$B$34*Control!$B$35+IF(AND(Control!$B$6="Y",D$4>=Control!$B$39),Control!$B$37*Control!$B$38,0)))/(Control!$B$20*(Control!$B$30*Control!$B$31+Control!$B$34*Control!$B$35+IF(AND(Control!$B$5>0,Control!$B$6="Y",1>=Control!$B$39),Control!$B$37*Control!$B$38,0))))*POWER(1+Control!$B$17,D$4-1),0) | E14: =IF(Control!$B$5>0,Control!$B$46*((Control!$B$20*(Control!$B$30*Control!$B$31+Control!$B$34*Control!$B$35+IF(AND(Control!$B$6="Y",E$4>=Control!$B$39),Control!$B$37*Control!$B$38,0)))/(Control!$B$20*(Control!$B$30*Control!$B$31+Control!$B$34*Control!$B$35+IF(AND(Control!$B$5>0,Control!$B$6="Y",1>=Control!$B$39),Control!$B$37*Control!$B$38,0))))*POWER(1+Control!$B$17,E$4-1),0) | F14: =IF(Control!$B$5>0,Control!$B$46*((Control!$B$20*(Control!$B$30*Control!$B$31+Control!$B$34*Control!$B$35+IF(AND(Control!$B$6="Y",F$4>=Control!$B$39),Control!$B$37*Control!$B$38,0)))/(Control!$B$20*(Control!$B$30*Control!$B$31+Control!$B$34*Control!$B$35+IF(AND(Control!$B$5>0,Control!$B$6="Y",1>=Control!$B$39),Control!$B$37*Control!$B$38,0))))*POWER(1+Control!$B$17,F$4-1),0) | G14: =IF(Control!$B$5>0,Control!$B$46*((Control!$B$20*(Control!$B$30*Control!$B$31+Control!$B$34*Control!$B$35+IF(AND(Control!$B$6="Y",G$4>=Control!$B$39),Control!$B$37*Control!$B$38,0)))/(Control!$B$20*(Control!$B$30*Control!$B$31+Control!$B$34*Control!$B$35+IF(AND(Control!$B$5>0,Control!$B$6="Y",1>=Control!$B$39),Control!$B$37*Control!$B$38,0))))*POWER(1+Control!$B$17,G$4-1),0) | H14: =IF(Control!$B$5>0,Control!$B$46*((Control!$B$20*(Control!$B$30*Control!$B$31+Control!$B$34*Control!$B$35+IF(AND(Control!$B$6="Y",H$4>=Control!$B$39),Control!$B$37*Control!$B$38,0)))/(Control!$B$20*(Control!$B$30*Control!$B$31+Control!$B$34*Control!$B$35+IF(AND(Control!$B$5>0,Control!$B$6="Y",1>=Control!$B$39),Control!$B$37*Control!$B$38,0))))*POWER(1+Control!$B$17,H$4-1),0) | I14: =IF(Control!$B$5>0,Control!$B$46*((Control!$B$20*(Control!$B$30*Control!$B$31+Control!$B$34*Control!$B$35+IF(AND(Control!$B$6="Y",I$4>=Control!$B$39),Control!$B$37*Control!$B$38,0)))/(Control!$B$20*(Control!$B$30*Control!$B$31+Control!$B$34*Control!$B$35+IF(AND(Control!$B$5>0,Control!$B$6="Y",1>=Control!$B$39),Control!$B$37*Control!$B$38,0))))*POWER(1+Control!$B$17,I$4-1),0) | J14: =IF(Control!$B$5>0,Control!$B$46*((Control!$B$20*(Control!$B$30*Control!$B$31+Control!$B$34*Control!$B$35+IF(AND(Control!$B$6="Y",J$4>=Control!$B$39),Control!$B$37*Control!$B$38,0)))/(Control!$B$20*(Control!$B$30*Control!$B$31+Control!$B$34*Control!$B$35+IF(AND(Control!$B$5>0,Control!$B$6="Y",1>=Control!$B$39),Control!$B$37*Control!$B$38,0))))*POWER(1+Control!$B$17,J$4-1),0) | ... V14: =IF(Control!$B$5>0,Control!$B$46*((Control!$B$20*(Control!$B$30*Control!$B$31+Control!$B$34*Control!$B$35+IF(AND(Control!$B$6="Y",V$4>=Control!$B$39),Control!$B$37*Control!$B$38,0)))/(Control!$B$20*(Control!$B$30*Control!$B$31+Control!$B$34*Control!$B$35+IF(AND(Control!$B$5>0,Control!$B$6="Y",1>=Control!$B$39),Control!$B$37*Control!$B$38,0))))*POWER(1+Control!$B$17,V$4-1),0)
A15: GROSS REVENUE | C15: =C10+C13+C14 | D15: =D10+D13+D14 | E15: =E10+E13+E14 | F15: =F10+F13+F14 | G15: =G10+G13+G14 | H15: =H10+H13+H14 | I15: =I10+I13+I14 | J15: =J10+J13+J14 | ... V15: =V10+V13+V14
A16: OPERATING EXPENSES
A17: Channel commission | C17: =C10*Control!$B$52 | D17: =D10*Control!$B$52 | E17: =E10*Control!$B$52 | F17: =F10*Control!$B$52 | G17: =G10*Control!$B$52 | H17: =H10*Control!$B$52 | I17: =I10*Control!$B$52 | J17: =J10*Control!$B$52 | ... V17: =V10*Control!$B$52
A18: Meals & provisions cost | C18: =IF(Control!$B$5>0,C12*(Control!$B$43+Control!$B$45)*POWER(1+Control!$B$18,C$4-1),0) | D18: =IF(Control!$B$5>0,D12*(Control!$B$43+Control!$B$45)*POWER(1+Control!$B$18,D$4-1),0) | E18: =IF(Control!$B$5>0,E12*(Control!$B$43+Control!$B$45)*POWER(1+Control!$B$18,E$4-1),0) | F18: =IF(Control!$B$5>0,F12*(Control!$B$43+Control!$B$45)*POWER(1+Control!$B$18,F$4-1),0) | G18: =IF(Control!$B$5>0,G12*(Control!$B$43+Control!$B$45)*POWER(1+Control!$B$18,G$4-1),0) | H18: =IF(Control!$B$5>0,H12*(Control!$B$43+Control!$B$45)*POWER(1+Control!$B$18,H$4-1),0) | I18: =IF(Control!$B$5>0,I12*(Control!$B$43+Control!$B$45)*POWER(1+Control!$B$18,I$4-1),0) | J18: =IF(Control!$B$5>0,J12*(Control!$B$43+Control!$B$45)*POWER(1+Control!$B$18,J$4-1),0) | ... V18: =IF(Control!$B$5>0,V12*(Control!$B$43+Control!$B$45)*POWER(1+Control!$B$18,V$4-1),0)
A19: Tours & activities cost | C19: =IF(Control!$B$5>0,Control!$B$47*((Control!$B$20*(Control!$B$30*Control!$B$31+Control!$B$34*Control!$B$35+IF(AND(Control!$B$6="Y",C$4>=Control!$B$39),Control!$B$37*Control!$B$38,0)))/(Control!$B$20*(Control!$B$30*Control!$B$31+Control!$B$34*Control!$B$35+IF(AND(Control!$B$5>0,Control!$B$6="Y",1>=Control!$B$39),Control!$B$37*Control!$B$38,0))))*POWER(1+Control!$B$18,C$4-1),0) | D19: =IF(Control!$B$5>0,Control!$B$47*((Control!$B$20*(Control!$B$30*Control!$B$31+Control!$B$34*Control!$B$35+IF(AND(Control!$B$6="Y",D$4>=Control!$B$39),Control!$B$37*Control!$B$38,0)))/(Control!$B$20*(Control!$B$30*Control!$B$31+Control!$B$34*Control!$B$35+IF(AND(Control!$B$5>0,Control!$B$6="Y",1>=Control!$B$39),Control!$B$37*Control!$B$38,0))))*POWER(1+Control!$B$18,D$4-1),0) | E19: =IF(Control!$B$5>0,Control!$B$47*((Control!$B$20*(Control!$B$30*Control!$B$31+Control!$B$34*Control!$B$35+IF(AND(Control!$B$6="Y",E$4>=Control!$B$39),Control!$B$37*Control!$B$38,0)))/(Control!$B$20*(Control!$B$30*Control!$B$31+Control!$B$34*Control!$B$35+IF(AND(Control!$B$5>0,Control!$B$6="Y",1>=Control!$B$39),Control!$B$37*Control!$B$38,0))))*POWER(1+Control!$B$18,E$4-1),0) | F19: =IF(Control!$B$5>0,Control!$B$47*((Control!$B$20*(Control!$B$30*Control!$B$31+Control!$B$34*Control!$B$35+IF(AND(Control!$B$6="Y",F$4>=Control!$B$39),Control!$B$37*Control!$B$38,0)))/(Control!$B$20*(Control!$B$30*Control!$B$31+Control!$B$34*Control!$B$35+IF(AND(Control!$B$5>0,Control!$B$6="Y",1>=Control!$B$39),Control!$B$37*Control!$B$38,0))))*POWER(1+Control!$B$18,F$4-1),0) | G19: =IF(Control!$B$5>0,Control!$B$47*((Control!$B$20*(Control!$B$30*Control!$B$31+Control!$B$34*Control!$B$35+IF(AND(Control!$B$6="Y",G$4>=Control!$B$39),Control!$B$37*Control!$B$38,0)))/(Control!$B$20*(Control!$B$30*Control!$B$31+Control!$B$34*Control!$B$35+IF(AND(Control!$B$5>0,Control!$B$6="Y",1>=Control!$B$39),Control!$B$37*Control!$B$38,0))))*POWER(1+Control!$B$18,G$4-1),0) | H19: =IF(Control!$B$5>0,Control!$B$47*((Control!$B$20*(Control!$B$30*Control!$B$31+Control!$B$34*Control!$B$35+IF(AND(Control!$B$6="Y",H$4>=Control!$B$39),Control!$B$37*Control!$B$38,0)))/(Control!$B$20*(Control!$B$30*Control!$B$31+Control!$B$34*Control!$B$35+IF(AND(Control!$B$5>0,Control!$B$6="Y",1>=Control!$B$39),Control!$B$37*Control!$B$38,0))))*POWER(1+Control!$B$18,H$4-1),0) | I19: =IF(Control!$B$5>0,Control!$B$47*((Control!$B$20*(Control!$B$30*Control!$B$31+Control!$B$34*Control!$B$35+IF(AND(Control!$B$6="Y",I$4>=Control!$B$39),Control!$B$37*Control!$B$38,0)))/(Control!$B$20*(Control!$B$30*Control!$B$31+Control!$B$34*Control!$B$35+IF(AND(Control!$B$5>0,Control!$B$6="Y",1>=Control!$B$39),Control!$B$37*Control!$B$38,0))))*POWER(1+Control!$B$18,I$4-1),0) | J19: =IF(Control!$B$5>0,Control!$B$47*((Control!$B$20*(Control!$B$30*Control!$B$31+Control!$B$34*Control!$B$35+IF(AND(Control!$B$6="Y",J$4>=Control!$B$39),Control!$B$37*Control!$B$38,0)))/(Control!$B$20*(Control!$B$30*Control!$B$31+Control!$B$34*Control!$B$35+IF(AND(Control!$B$5>0,Control!$B$6="Y",1>=Control!$B$39),Control!$B$37*Control!$B$38,0))))*POWER(1+Control!$B$18,J$4-1),0) | ... V19: =IF(Control!$B$5>0,Control!$B$47*((Control!$B$20*(Control!$B$30*Control!$B$31+Control!$B$34*Control!$B$35+IF(AND(Control!$B$6="Y",V$4>=Control!$B$39),Control!$B$37*Control!$B$38,0)))/(Control!$B$20*(Control!$B$30*Control!$B$31+Control!$B$34*Control!$B$35+IF(AND(Control!$B$5>0,Control!$B$6="Y",1>=Control!$B$39),Control!$B$37*Control!$B$38,0))))*POWER(1+Control!$B$18,V$4-1),0)
A20: Salaries & wages | C20: =IF(Control!$B$5>0,Control!$B$48*12*POWER(1+Control!$B$18,C$4-1),0) | D20: =IF(Control!$B$5>0,Control!$B$48*12*POWER(1+Control!$B$18,D$4-1),0) | E20: =IF(Control!$B$5>0,Control!$B$48*12*POWER(1+Control!$B$18,E$4-1),0) | F20: =IF(Control!$B$5>0,Control!$B$48*12*POWER(1+Control!$B$18,F$4-1),0) | G20: =IF(Control!$B$5>0,Control!$B$48*12*POWER(1+Control!$B$18,G$4-1),0) | H20: =IF(Control!$B$5>0,Control!$B$48*12*POWER(1+Control!$B$18,H$4-1),0) | I20: =IF(Control!$B$5>0,Control!$B$48*12*POWER(1+Control!$B$18,I$4-1),0) | J20: =IF(Control!$B$5>0,Control!$B$48*12*POWER(1+Control!$B$18,J$4-1),0) | ... V20: =IF(Control!$B$5>0,Control!$B$48*12*POWER(1+Control!$B$18,V$4-1),0)
A21: Utilities & municipal | C21: =IF(Control!$B$5>0,Control!$B$49*12*POWER(1+Control!$B$18,C$4-1),0) | D21: =IF(Control!$B$5>0,Control!$B$49*12*POWER(1+Control!$B$18,D$4-1),0) | E21: =IF(Control!$B$5>0,Control!$B$49*12*POWER(1+Control!$B$18,E$4-1),0) | F21: =IF(Control!$B$5>0,Control!$B$49*12*POWER(1+Control!$B$18,F$4-1),0) | G21: =IF(Control!$B$5>0,Control!$B$49*12*POWER(1+Control!$B$18,G$4-1),0) | H21: =IF(Control!$B$5>0,Control!$B$49*12*POWER(1+Control!$B$18,H$4-1),0) | I21: =IF(Control!$B$5>0,Control!$B$49*12*POWER(1+Control!$B$18,I$4-1),0) | J21: =IF(Control!$B$5>0,Control!$B$49*12*POWER(1+Control!$B$18,J$4-1),0) | ... V21: =IF(Control!$B$5>0,Control!$B$49*12*POWER(1+Control!$B$18,V$4-1),0)
A22: Repairs & maintenance | C22: =IF(Control!$B$5>0,Control!$B$50*12*POWER(1+Control!$B$18,C$4-1),0) | D22: =IF(Control!$B$5>0,Control!$B$50*12*POWER(1+Control!$B$18,D$4-1),0) | E22: =IF(Control!$B$5>0,Control!$B$50*12*POWER(1+Control!$B$18,E$4-1),0) | F22: =IF(Control!$B$5>0,Control!$B$50*12*POWER(1+Control!$B$18,F$4-1),0) | G22: =IF(Control!$B$5>0,Control!$B$50*12*POWER(1+Control!$B$18,G$4-1),0) | H22: =IF(Control!$B$5>0,Control!$B$50*12*POWER(1+Control!$B$18,H$4-1),0) | I22: =IF(Control!$B$5>0,Control!$B$50*12*POWER(1+Control!$B$18,I$4-1),0) | J22: =IF(Control!$B$5>0,Control!$B$50*12*POWER(1+Control!$B$18,J$4-1),0) | ... V22: =IF(Control!$B$5>0,Control!$B$50*12*POWER(1+Control!$B$18,V$4-1),0)
A23: Other operating | C23: =IF(Control!$B$5>0,Control!$B$51*12*POWER(1+Control!$B$18,C$4-1),0) | D23: =IF(Control!$B$5>0,Control!$B$51*12*POWER(1+Control!$B$18,D$4-1),0) | E23: =IF(Control!$B$5>0,Control!$B$51*12*POWER(1+Control!$B$18,E$4-1),0) | F23: =IF(Control!$B$5>0,Control!$B$51*12*POWER(1+Control!$B$18,F$4-1),0) | G23: =IF(Control!$B$5>0,Control!$B$51*12*POWER(1+Control!$B$18,G$4-1),0) | H23: =IF(Control!$B$5>0,Control!$B$51*12*POWER(1+Control!$B$18,H$4-1),0) | I23: =IF(Control!$B$5>0,Control!$B$51*12*POWER(1+Control!$B$18,I$4-1),0) | J23: =IF(Control!$B$5>0,Control!$B$51*12*POWER(1+Control!$B$18,J$4-1),0) | ... V23: =IF(Control!$B$5>0,Control!$B$51*12*POWER(1+Control!$B$18,V$4-1),0)
A24: FF&E / capex reserve | C24: =C10*Control!$B$26 | D24: =D10*Control!$B$26 | E24: =E10*Control!$B$26 | F24: =F10*Control!$B$26 | G24: =G10*Control!$B$26 | H24: =H10*Control!$B$26 | I24: =I10*Control!$B$26 | J24: =J10*Control!$B$26 | ... V24: =V10*Control!$B$26
A25: TOTAL EXPENSES | C25: =SUM(C17:C24) | D25: =SUM(D17:D24) | E25: =SUM(E17:E24) | F25: =SUM(F17:F24) | G25: =SUM(G17:G24) | H25: =SUM(H17:H24) | I25: =SUM(I17:I24) | J25: =SUM(J17:J24) | ... V25: =SUM(V17:V24)
A26: NET OPERATING INCOME (NOI, pre-tax) | C26: =C15-C25 | D26: =D15-D25 | E26: =E15-E25 | F26: =F15-F25 | G26: =G15-G25 | H26: =H15-H25 | I26: =I15-I25 | J26: =J15-J25 | ... V26: =V15-V25
A27: Income tax | C27: =-C26*Control!$B$23 | D27: =-D26*Control!$B$23 | E27: =-E26*Control!$B$23 | F27: =-F26*Control!$B$23 | G27: =-G26*Control!$B$23 | H27: =-H26*Control!$B$23 | I27: =-I26*Control!$B$23 | J27: =-J26*Control!$B$23 | ... V27: =-V26*Control!$B$23
A28: NET PROFIT AFTER TAX | C28: =C26+C27 | D28: =D26+D27 | E28: =E26+E27 | F28: =F26+F27 | G28: =G26+G27 | H28: =H26+H27 | I28: =I26+I27 | J28: =J26+J27 | ... V28: =V26+V27

Sheet Beachside P&L
A1: BEACHSIDE ESCAPE — P&L (annual, 20-year)
A2: Big Bay. 10 months long-term + Dec/Jan peak nightly (90% occupancy). After reserve, after tax.
A4: Year | C4: 1 | D4: 2 | E4: 3 | F4: 4 | G4: 5 | H4: 6 | I4: 7 | J4: 8 | K4: 9 | L4: 10 | M4: 11 | N4: 12 | O4: 13 | P4: 14 | Q4: 15 | R4: 16 | S4: 17 | T4: 18 | U4: 19 | V4: 20
A6: Long-term rental income | C6: =IF(Control!$B$7>0,Control!$B$54*Control!$B$55*POWER(1+Control!$B$17,C$4-1),0) | D6: =IF(Control!$B$7>0,Control!$B$54*Control!$B$55*POWER(1+Control!$B$17,D$4-1),0) | E6: =IF(Control!$B$7>0,Control!$B$54*Control!$B$55*POWER(1+Control!$B$17,E$4-1),0) | F6: =IF(Control!$B$7>0,Control!$B$54*Control!$B$55*POWER(1+Control!$B$17,F$4-1),0) | G6: =IF(Control!$B$7>0,Control!$B$54*Control!$B$55*POWER(1+Control!$B$17,G$4-1),0) | H6: =IF(Control!$B$7>0,Control!$B$54*Control!$B$55*POWER(1+Control!$B$17,H$4-1),0) | I6: =IF(Control!$B$7>0,Control!$B$54*Control!$B$55*POWER(1+Control!$B$17,I$4-1),0) | J6: =IF(Control!$B$7>0,Control!$B$54*Control!$B$55*POWER(1+Control!$B$17,J$4-1),0) | ... V6: =IF(Control!$B$7>0,Control!$B$54*Control!$B$55*POWER(1+Control!$B$17,V$4-1),0)
A7: Peak nightly income (Dec+Jan) | C7: =IF(Control!$B$7>0,Control!$B$56*Control!$B$57*Control!$B$58*Control!$B$59*POWER(1+Control!$B$17,C$4-1),0) | D7: =IF(Control!$B$7>0,Control!$B$56*Control!$B$57*Control!$B$58*Control!$B$59*POWER(1+Control!$B$17,D$4-1),0) | E7: =IF(Control!$B$7>0,Control!$B$56*Control!$B$57*Control!$B$58*Control!$B$59*POWER(1+Control!$B$17,E$4-1),0) | F7: =IF(Control!$B$7>0,Control!$B$56*Control!$B$57*Control!$B$58*Control!$B$59*POWER(1+Control!$B$17,F$4-1),0) | G7: =IF(Control!$B$7>0,Control!$B$56*Control!$B$57*Control!$B$58*Control!$B$59*POWER(1+Control!$B$17,G$4-1),0) | H7: =IF(Control!$B$7>0,Control!$B$56*Control!$B$57*Control!$B$58*Control!$B$59*POWER(1+Control!$B$17,H$4-1),0) | I7: =IF(Control!$B$7>0,Control!$B$56*Control!$B$57*Control!$B$58*Control!$B$59*POWER(1+Control!$B$17,I$4-1),0) | J7: =IF(Control!$B$7>0,Control!$B$56*Control!$B$57*Control!$B$58*Control!$B$59*POWER(1+Control!$B$17,J$4-1),0) | ... V7: =IF(Control!$B$7>0,Control!$B$56*Control!$B$57*Control!$B$58*Control!$B$59*POWER(1+Control!$B$17,V$4-1),0)
A8: GROSS REVENUE | C8: =SUM(C6:C7) | D8: =SUM(D6:D7) | E8: =SUM(E6:E7) | F8: =SUM(F6:F7) | G8: =SUM(G6:G7) | H8: =SUM(H6:H7) | I8: =SUM(I6:I7) | J8: =SUM(J6:J7) | ... V8: =SUM(V6:V7)
A9: OPERATING EXPENSES
A10: Channel commission (nightly only) | C10: =C7*Control!$B$60 | D10: =D7*Control!$B$60 | E10: =E7*Control!$B$60 | F10: =F7*Control!$B$60 | G10: =G7*Control!$B$60 | H10: =H7*Control!$B$60 | I10: =I7*Control!$B$60 | J10: =J7*Control!$B$60 | ... V10: =V7*Control!$B$60
A11: Utilities & municipal | C11: =IF(Control!$B$7>0,Control!$B$61*12*POWER(1+Control!$B$18,C$4-1),0) | D11: =IF(Control!$B$7>0,Control!$B$61*12*POWER(1+Control!$B$18,D$4-1),0) | E11: =IF(Control!$B$7>0,Control!$B$61*12*POWER(1+Control!$B$18,E$4-1),0) | F11: =IF(Control!$B$7>0,Control!$B$61*12*POWER(1+Control!$B$18,F$4-1),0) | G11: =IF(Control!$B$7>0,Control!$B$61*12*POWER(1+Control!$B$18,G$4-1),0) | H11: =IF(Control!$B$7>0,Control!$B$61*12*POWER(1+Control!$B$18,H$4-1),0) | I11: =IF(Control!$B$7>0,Control!$B$61*12*POWER(1+Control!$B$18,I$4-1),0) | J11: =IF(Control!$B$7>0,Control!$B$61*12*POWER(1+Control!$B$18,J$4-1),0) | ... V11: =IF(Control!$B$7>0,Control!$B$61*12*POWER(1+Control!$B$18,V$4-1),0)
A12: Repairs & maintenance | C12: =IF(Control!$B$7>0,Control!$B$62*12*POWER(1+Control!$B$18,C$4-1),0) | D12: =IF(Control!$B$7>0,Control!$B$62*12*POWER(1+Control!$B$18,D$4-1),0) | E12: =IF(Control!$B$7>0,Control!$B$62*12*POWER(1+Control!$B$18,E$4-1),0) | F12: =IF(Control!$B$7>0,Control!$B$62*12*POWER(1+Control!$B$18,F$4-1),0) | G12: =IF(Control!$B$7>0,Control!$B$62*12*POWER(1+Control!$B$18,G$4-1),0) | H12: =IF(Control!$B$7>0,Control!$B$62*12*POWER(1+Control!$B$18,H$4-1),0) | I12: =IF(Control!$B$7>0,Control!$B$62*12*POWER(1+Control!$B$18,I$4-1),0) | J12: =IF(Control!$B$7>0,Control!$B$62*12*POWER(1+Control!$B$18,J$4-1),0) | ... V12: =IF(Control!$B$7>0,Control!$B$62*12*POWER(1+Control!$B$18,V$4-1),0)
A13: Levies | C13: =IF(Control!$B$7>0,Control!$B$63*12*POWER(1+Control!$B$18,C$4-1),0) | D13: =IF(Control!$B$7>0,Control!$B$63*12*POWER(1+Control!$B$18,D$4-1),0) | E13: =IF(Control!$B$7>0,Control!$B$63*12*POWER(1+Control!$B$18,E$4-1),0) | F13: =IF(Control!$B$7>0,Control!$B$63*12*POWER(1+Control!$B$18,F$4-1),0) | G13: =IF(Control!$B$7>0,Control!$B$63*12*POWER(1+Control!$B$18,G$4-1),0) | H13: =IF(Control!$B$7>0,Control!$B$63*12*POWER(1+Control!$B$18,H$4-1),0) | I13: =IF(Control!$B$7>0,Control!$B$63*12*POWER(1+Control!$B$18,I$4-1),0) | J13: =IF(Control!$B$7>0,Control!$B$63*12*POWER(1+Control!$B$18,J$4-1),0) | ... V13: =IF(Control!$B$7>0,Control!$B$63*12*POWER(1+Control!$B$18,V$4-1),0)
A14: FF&E / capex reserve | C14: =C8*Control!$B$26 | D14: =D8*Control!$B$26 | E14: =E8*Control!$B$26 | F14: =F8*Control!$B$26 | G14: =G8*Control!$B$26 | H14: =H8*Control!$B$26 | I14: =I8*Control!$B$26 | J14: =J8*Control!$B$26 | ... V14: =V8*Control!$B$26
A15: TOTAL EXPENSES | C15: =SUM(C10:C14) | D15: =SUM(D10:D14) | E15: =SUM(E10:E14) | F15: =SUM(F10:F14) | G15: =SUM(G10:G14) | H15: =SUM(H10:H14) | I15: =SUM(I10:I14) | J15: =SUM(J10:J14) | ... V15: =SUM(V10:V14)
A16: NET OPERATING INCOME (NOI, pre-tax) | C16: =C8-C15 | D16: =D8-D15 | E16: =E8-E15 | F16: =F8-F15 | G16: =G8-G15 | H16: =H8-H15 | I16: =I8-I15 | J16: =J8-J15 | ... V16: =V8-V15
A17: Income tax | C17: =-C16*Control!$B$23 | D17: =-D16*Control!$B$23 | E17: =-E16*Control!$B$23 | F17: =-F16*Control!$B$23 | G17: =-G16*Control!$B$23 | H17: =-H16*Control!$B$23 | I17: =-I16*Control!$B$23 | J17: =-J16*Control!$B$23 | ... V17: =-V16*Control!$B$23
A18: NET PROFIT AFTER TAX | C18: =C16+C17 | D18: =D16+D17 | E18: =E16+E17 | F18: =F16+F17 | G18: =G16+G17 | H18: =H16+H17 | I18: =I16+I17 | J18: =J16+J17 | ... V18: =V16+V17

Sheet Menlyn P&L
A1: MENLYN MAIN — P&L (annual, 20-year)
A2: Long-term residential rental only. After reserve, after tax.
A4: Year | C4: 1 | D4: 2 | E4: 3 | F4: 4 | G4: 5 | H4: 6 | I4: 7 | J4: 8 | K4: 9 | L4: 10 | M4: 11 | N4: 12 | O4: 13 | P4: 14 | Q4: 15 | R4: 16 | S4: 17 | T4: 18 | U4: 19 | V4: 20
A6: GROSS REVENUE (rental) | C6: =IF(Control!$B$8>0,Control!$B$65*12*POWER(1+Control!$B$17,C$4-1),0) | D6: =IF(Control!$B$8>0,Control!$B$65*12*POWER(1+Control!$B$17,D$4-1),0) | E6: =IF(Control!$B$8>0,Control!$B$65*12*POWER(1+Control!$B$17,E$4-1),0) | F6: =IF(Control!$B$8>0,Control!$B$65*12*POWER(1+Control!$B$17,F$4-1),0) | G6: =IF(Control!$B$8>0,Control!$B$65*12*POWER(1+Control!$B$17,G$4-1),0) | H6: =IF(Control!$B$8>0,Control!$B$65*12*POWER(1+Control!$B$17,H$4-1),0) | I6: =IF(Control!$B$8>0,Control!$B$65*12*POWER(1+Control!$B$17,I$4-1),0) | J6: =IF(Control!$B$8>0,Control!$B$65*12*POWER(1+Control!$B$17,J$4-1),0) | ... V6: =IF(Control!$B$8>0,Control!$B$65*12*POWER(1+Control!$B$17,V$4-1),0)
A7: OPERATING EXPENSES
A8: Utilities & municipal | C8: =IF(Control!$B$8>0,Control!$B$66*12*POWER(1+Control!$B$18,C$4-1),0) | D8: =IF(Control!$B$8>0,Control!$B$66*12*POWER(1+Control!$B$18,D$4-1),0) | E8: =IF(Control!$B$8>0,Control!$B$66*12*POWER(1+Control!$B$18,E$4-1),0) | F8: =IF(Control!$B$8>0,Control!$B$66*12*POWER(1+Control!$B$18,F$4-1),0) | G8: =IF(Control!$B$8>0,Control!$B$66*12*POWER(1+Control!$B$18,G$4-1),0) | H8: =IF(Control!$B$8>0,Control!$B$66*12*POWER(1+Control!$B$18,H$4-1),0) | I8: =IF(Control!$B$8>0,Control!$B$66*12*POWER(1+Control!$B$18,I$4-1),0) | J8: =IF(Control!$B$8>0,Control!$B$66*12*POWER(1+Control!$B$18,J$4-1),0) | ... V8: =IF(Control!$B$8>0,Control!$B$66*12*POWER(1+Control!$B$18,V$4-1),0)
A9: Repairs & maintenance | C9: =IF(Control!$B$8>0,Control!$B$67*12*POWER(1+Control!$B$18,C$4-1),0) | D9: =IF(Control!$B$8>0,Control!$B$67*12*POWER(1+Control!$B$18,D$4-1),0) | E9: =IF(Control!$B$8>0,Control!$B$67*12*POWER(1+Control!$B$18,E$4-1),0) | F9: =IF(Control!$B$8>0,Control!$B$67*12*POWER(1+Control!$B$18,F$4-1),0) | G9: =IF(Control!$B$8>0,Control!$B$67*12*POWER(1+Control!$B$18,G$4-1),0) | H9: =IF(Control!$B$8>0,Control!$B$67*12*POWER(1+Control!$B$18,H$4-1),0) | I9: =IF(Control!$B$8>0,Control!$B$67*12*POWER(1+Control!$B$18,I$4-1),0) | J9: =IF(Control!$B$8>0,Control!$B$67*12*POWER(1+Control!$B$18,J$4-1),0) | ... V9: =IF(Control!$B$8>0,Control!$B$67*12*POWER(1+Control!$B$18,V$4-1),0)
A10: Levies / rates | C10: =IF(Control!$B$8>0,Control!$B$68*12*POWER(1+Control!$B$18,C$4-1),0) | D10: =IF(Control!$B$8>0,Control!$B$68*12*POWER(1+Control!$B$18,D$4-1),0) | E10: =IF(Control!$B$8>0,Control!$B$68*12*POWER(1+Control!$B$18,E$4-1),0) | F10: =IF(Control!$B$8>0,Control!$B$68*12*POWER(1+Control!$B$18,F$4-1),0) | G10: =IF(Control!$B$8>0,Control!$B$68*12*POWER(1+Control!$B$18,G$4-1),0) | H10: =IF(Control!$B$8>0,Control!$B$68*12*POWER(1+Control!$B$18,H$4-1),0) | I10: =IF(Control!$B$8>0,Control!$B$68*12*POWER(1+Control!$B$18,I$4-1),0) | J10: =IF(Control!$B$8>0,Control!$B$68*12*POWER(1+Control!$B$18,J$4-1),0) | ... V10: =IF(Control!$B$8>0,Control!$B$68*12*POWER(1+Control!$B$18,V$4-1),0)
A11: FF&E / capex reserve | C11: =C6*Control!$B$26 | D11: =D6*Control!$B$26 | E11: =E6*Control!$B$26 | F11: =F6*Control!$B$26 | G11: =G6*Control!$B$26 | H11: =H6*Control!$B$26 | I11: =I6*Control!$B$26 | J11: =J6*Control!$B$26 | ... V11: =V6*Control!$B$26
A12: TOTAL EXPENSES | C12: =SUM(C8:C11) | D12: =SUM(D8:D11) | E12: =SUM(E8:E11) | F12: =SUM(F8:F11) | G12: =SUM(G8:G11) | H12: =SUM(H8:H11) | I12: =SUM(I8:I11) | J12: =SUM(J8:J11) | ... V12: =SUM(V8:V11)
A13: NET OPERATING INCOME (NOI, pre-tax) | C13: =C6-C12 | D13: =D6-D12 | E13: =E6-E12 | F13: =F6-F12 | G13: =G6-G12 | H13: =H6-H12 | I13: =I6-I12 | J13: =J6-J12 | ... V13: =V6-V12
A14: Income tax | C14: =-C13*Control!$B$23 | D14: =-D13*Control!$B$23 | E14: =-E13*Control!$B$23 | F14: =-F13*Control!$B$23 | G14: =-G13*Control!$B$23 | H14: =-H13*Control!$B$23 | I14: =-I13*Control!$B$23 | J14: =-J13*Control!$B$23 | ... V14: =-V13*Control!$B$23
A15: NET PROFIT AFTER TAX | C15: =C13+C14 | D15: =D13+D14 | E15: =E13+E14 | F15: =F13+F14 | G15: =G13+G14 | H15: =H13+H14 | I15: =I13+I14 | J15: =J13+J14 | ... V15: =V13+V14

Sheet Portfolio NewCo
A1: PORTFOLIO — NewCo consolidated (20-year)
A2: NewCo owns 100% of the three properties. Partner owns 50% of NewCo. Distributions = 50% of after-tax profit, less any capex funded from NewCo cash.
A4: Year | B4: 1 | C4: 2 | D4: 3 | E4: 4 | F4: 5 | G4: 6 | H4: 7 | I4: 8 | J4: 9 | K4: 10 | L4: 11 | M4: 12 | N4: 13 | O4: 14 | P4: 15 | Q4: 16 | R4: 17 | S4: 18 | T4: 19 | U4: 20
A6: African Sky NOI | B6: ='African Sky P&L'!C26 | C6: ='African Sky P&L'!D26 | D6: ='African Sky P&L'!E26 | E6: ='African Sky P&L'!F26 | F6: ='African Sky P&L'!G26 | G6: ='African Sky P&L'!H26 | H6: ='African Sky P&L'!I26 | I6: ='African Sky P&L'!J26 | ... U6: ='African Sky P&L'!V26
A7: Beachside NOI | B7: ='Beachside P&L'!C16 | C7: ='Beachside P&L'!D16 | D7: ='Beachside P&L'!E16 | E7: ='Beachside P&L'!F16 | F7: ='Beachside P&L'!G16 | G7: ='Beachside P&L'!H16 | H7: ='Beachside P&L'!I16 | I7: ='Beachside P&L'!J16 | ... U7: ='Beachside P&L'!V16
A8: Menlyn NOI | B8: ='Menlyn P&L'!C13 | C8: ='Menlyn P&L'!D13 | D8: ='Menlyn P&L'!E13 | E8: ='Menlyn P&L'!F13 | F8: ='Menlyn P&L'!G13 | G8: ='Menlyn P&L'!H13 | H8: ='Menlyn P&L'!I13 | I8: ='Menlyn P&L'!J13 | ... U8: ='Menlyn P&L'!V13
A9: PORTFOLIO NOI | B9: =SUM(B6:B8) | C9: =SUM(C6:C8) | D9: =SUM(D6:D8) | E9: =SUM(E6:E8) | F9: =SUM(F6:F8) | G9: =SUM(G6:G8) | H9: =SUM(H6:H8) | I9: =SUM(I6:I8) | ... U9: =SUM(U6:U8)
A10: African Sky NPAT | B10: ='African Sky P&L'!C28 | C10: ='African Sky P&L'!D28 | D10: ='African Sky P&L'!E28 | E10: ='African Sky P&L'!F28 | F10: ='African Sky P&L'!G28 | G10: ='African Sky P&L'!H28 | H10: ='African Sky P&L'!I28 | I10: ='African Sky P&L'!J28 | ... U10: ='African Sky P&L'!V28
A11: Beachside NPAT | B11: ='Beachside P&L'!C18 | C11: ='Beachside P&L'!D18 | D11: ='Beachside P&L'!E18 | E11: ='Beachside P&L'!F18 | F11: ='Beachside P&L'!G18 | G11: ='Beachside P&L'!H18 | H11: ='Beachside P&L'!I18 | I11: ='Beachside P&L'!J18 | ... U11: ='Beachside P&L'!V18
A12: Menlyn NPAT | B12: ='Menlyn P&L'!C15 | C12: ='Menlyn P&L'!D15 | D12: ='Menlyn P&L'!E15 | E12: ='Menlyn P&L'!F15 | F12: ='Menlyn P&L'!G15 | G12: ='Menlyn P&L'!H15 | H12: ='Menlyn P&L'!I15 | I12: ='Menlyn P&L'!J15 | ... U12: ='Menlyn P&L'!V15
A13: PORTFOLIO NPAT | B13: =SUM(B10:B12) | C13: =SUM(C10:C12) | D13: =SUM(D10:D12) | E13: =SUM(E10:E12) | F13: =SUM(F10:F12) | G13: =SUM(G10:G12) | H13: =SUM(H10:H12) | I13: =SUM(I10:I12) | ... U13: =SUM(U10:U12)
A14: Less: Winchester construction capex | B14: =-IF(AND(Control!$B$5>0,Control!$B$6="Y",B$4=Control!$B$39-1),Control!$B$40,0) | C14: =-IF(AND(Control!$B$5>0,Control!$B$6="Y",C$4=Control!$B$39-1),Control!$B$40,0) | D14: =-IF(AND(Control!$B$5>0,Control!$B$6="Y",D$4=Control!$B$39-1),Control!$B$40,0) | E14: =-IF(AND(Control!$B$5>0,Control!$B$6="Y",E$4=Control!$B$39-1),Control!$B$40,0) | F14: =-IF(AND(Control!$B$5>0,Control!$B$6="Y",F$4=Control!$B$39-1),Control!$B$40,0) | G14: =-IF(AND(Control!$B$5>0,Control!$B$6="Y",G$4=Control!$B$39-1),Control!$B$40,0) | H14: =-IF(AND(Control!$B$5>0,Control!$B$6="Y",H$4=Control!$B$39-1),Control!$B$40,0) | I14: =-IF(AND(Control!$B$5>0,Control!$B$6="Y",I$4=Control!$B$39-1),Control!$B$40,0) | ... U14: =-IF(AND(Control!$B$5>0,Control!$B$6="Y",U$4=Control!$B$39-1),Control!$B$40,0)
A15: Distributable profit | B15: =B13+B14 | C15: =C13+C14 | D15: =D13+D14 | E15: =E13+E14 | F15: =F13+F14 | G15: =G13+G14 | H15: =H13+H14 | I15: =I13+I14 | ... U15: =U13+U14
A16: Partner distribution (property-specific %) | B16: =SUM(B22:B24) | C16: =SUM(C22:C24) | D16: =SUM(D22:D24) | E16: =SUM(E22:E24) | F16: =SUM(F22:F24) | G16: =SUM(G22:G24) | H16: =SUM(H22:H24) | I16: =SUM(I22:I24) | ... U16: =SUM(U22:U24)
A17: Cumulative partner distribution | B17: =B16 | C17: =B17+C16 | D17: =C17+D16 | E17: =D17+E16 | F17: =E17+F16 | G17: =F17+G16 | H17: =G17+H16 | I17: =H17+I16 | J17: =I17+J16 | ... U17: =T17+U16
A18: DISTRIBUTION ALLOCATION HELPER — driven by Control column C
A19: African Sky distributable cash | B19: =B10+B14 | C19: =C10+C14 | D19: =D10+D14 | E19: =E10+E14 | F19: =F10+F14 | G19: =G10+G14 | H19: =H10+H14 | I19: =I10+I14 | ... U19: =U10+U14
A20: Beachside distributable cash | B20: =B11 | C20: =C11 | D20: =D11 | E20: =E11 | F20: =F11 | G20: =G11 | H20: =H11 | I20: =I11 | ... U20: =U11
A21: Menlyn distributable cash | B21: =B12 | C21: =C12 | D21: =D12 | E21: =E12 | F21: =F12 | G21: =G12 | H21: =H12 | I21: =I12 | ... U21: =U12
A22: African Sky partner distribution | B22: =B19*Control!$C$5 | C22: =C19*Control!$C$5 | D22: =D19*Control!$C$5 | E22: =E19*Control!$C$5 | F22: =F19*Control!$C$5 | G22: =G19*Control!$C$5 | H22: =H19*Control!$C$5 | I22: =I19*Control!$C$5 | ... U22: =U19*Control!$C$5
A23: Beachside partner distribution | B23: =B20*Control!$C$7 | C23: =C20*Control!$C$7 | D23: =D20*Control!$C$7 | E23: =E20*Control!$C$7 | F23: =F20*Control!$C$7 | G23: =G20*Control!$C$7 | H23: =H20*Control!$C$7 | I23: =I20*Control!$C$7 | ... U23: =U20*Control!$C$7
A24: Menlyn partner distribution | B24: =B21*Control!$C$8 | C24: =C21*Control!$C$8 | D24: =D21*Control!$C$8 | E24: =E21*Control!$C$8 | F24: =F21*Control!$C$8 | G24: =G21*Control!$C$8 | H24: =H21*Control!$C$8 | I24: =I21*Control!$C$8 | ... U24: =U21*Control!$C$8
A25: African Sky cumulative distribution | B25: =B22 | C25: =B25+C22 | D25: =C25+D22 | E25: =D25+E22 | F25: =E25+F22 | G25: =F25+G22 | H25: =G25+H22 | I25: =H25+I22 | J25: =I25+J22 | ... U25: =T25+U22
A26: Beachside cumulative distribution | B26: =B23 | C26: =B26+C23 | D26: =C26+D23 | E26: =D26+E23 | F26: =E26+F23 | G26: =F26+G23 | H26: =G26+H23 | I26: =H26+I23 | J26: =I26+J23 | ... U26: =T26+U23
A27: Menlyn cumulative distribution | B27: =B24 | C27: =B27+C24 | D27: =C27+D24 | E27: =D27+E24 | F27: =E27+F24 | G27: =F27+G24 | H27: =G27+H24 | I27: =H27+I24 | J27: =I27+J24 | ... U27: =T27+U24

Sheet INV - 3-Statement Model
A1: 3-STATEMENT MODEL — NewCo consolidated + investor tracking
A2: Integrated model linked to Control, property P&Ls, Portfolio NewCo, Valuation, and Investor KPIs. Formation column shows today; Year 1–20 columns are live-linked forecast periods.
A3: Currency: ZAR. Base case: no external debt; distributable post-tax profit is paid out after Winchester construction capex is funded from NewCo cash.
A5: Year | B5: Formation / Today | C5: 1 | D5: 2 | E5: 3 | F5: 4 | G5: 5 | H5: 6 | I5: 7 | J5: 8 | K5: 9 | L5: 10 | M5: 11 | N5: 12 | O5: 13 | P5: 14 | Q5: 15 | R5: 16 | S5: 17 | T5: 18 | U5: 19 | V5: 20
A7: CONSOLIDATED INCOME STATEMENT
A8: Gross revenue | B8: =0 | C8: =SUM('African Sky P&L'!C15,'Beachside P&L'!C8,'Menlyn P&L'!C6) | D8: =SUM('African Sky P&L'!D15,'Beachside P&L'!D8,'Menlyn P&L'!D6) | E8: =SUM('African Sky P&L'!E15,'Beachside P&L'!E8,'Menlyn P&L'!E6) | F8: =SUM('African Sky P&L'!F15,'Beachside P&L'!F8,'Menlyn P&L'!F6) | G8: =SUM('African Sky P&L'!G15,'Beachside P&L'!G8,'Menlyn P&L'!G6) | H8: =SUM('African Sky P&L'!H15,'Beachside P&L'!H8,'Menlyn P&L'!H6) | I8: =SUM('African Sky P&L'!I15,'Beachside P&L'!I8,'Menlyn P&L'!I6) | J8: =SUM('African Sky P&L'!J15,'Beachside P&L'!J8,'Menlyn P&L'!J6) | ... V8: =SUM('African Sky P&L'!V15,'Beachside P&L'!V8,'Menlyn P&L'!V6)
A9: Operating expenses | B9: =0 | C9: =C8-C10 | D9: =D8-D10 | E9: =E8-E10 | F9: =F8-F10 | G9: =G8-G10 | H9: =H8-H10 | I9: =I8-I10 | J9: =J8-J10 | ... V9: =V8-V10
A10: NET OPERATING INCOME (NOI) | B10: =0 | C10: ='Portfolio NewCo'!B9 | D10: ='Portfolio NewCo'!C9 | E10: ='Portfolio NewCo'!D9 | F10: ='Portfolio NewCo'!E9 | G10: ='Portfolio NewCo'!F9 | H10: ='Portfolio NewCo'!G9 | I10: ='Portfolio NewCo'!H9 | J10: ='Portfolio NewCo'!I9 | ... V10: ='Portfolio NewCo'!U9
A11: Income tax | B11: =0 | C11: =C12-C10 | D11: =D12-D10 | E11: =E12-E10 | F11: =F12-F10 | G11: =G12-G10 | H11: =H12-H10 | I11: =I12-I10 | J11: =J12-J10 | ... V11: =V12-V10
A12: NET PROFIT AFTER TAX (NPAT) | B12: =0 | C12: ='Portfolio NewCo'!B13 | D12: ='Portfolio NewCo'!C13 | E12: ='Portfolio NewCo'!D13 | F12: ='Portfolio NewCo'!E13 | G12: ='Portfolio NewCo'!F13 | H12: ='Portfolio NewCo'!G13 | I12: ='Portfolio NewCo'!H13 | J12: ='Portfolio NewCo'!I13 | ... V12: ='Portfolio NewCo'!U13
A13: NPAT margin | B13: ="" | C13: =IFERROR(C12/C8,0) | D13: =IFERROR(D12/D8,0) | E13: =IFERROR(E12/E8,0) | F13: =IFERROR(F12/F8,0) | G13: =IFERROR(G12/G8,0) | H13: =IFERROR(H12/H8,0) | I13: =IFERROR(I12/I8,0) | J13: =IFERROR(J12/J8,0) | ... V13: =IFERROR(V12/V8,0)
A15: INVESTOR — INCOME STATEMENT VIEW
A16: Blended partner ownership % | B16: =IFERROR(Valuation!$F$10/Valuation!$F$9,0) | C16: =IFERROR(Valuation!$F$10/Valuation!$F$9,0) | D16: =IFERROR(Valuation!$F$10/Valuation!$F$9,0) | E16: =IFERROR(Valuation!$F$10/Valuation!$F$9,0) | F16: =IFERROR(Valuation!$F$10/Valuation!$F$9,0) | G16: =IFERROR(Valuation!$F$10/Valuation!$F$9,0) | H16: =IFERROR(Valuation!$F$10/Valuation!$F$9,0) | I16: =IFERROR(Valuation!$F$10/Valuation!$F$9,0) | ... V16: =IFERROR(Valuation!$F$10/Valuation!$F$9,0)
A17: Investor share of NOI | B17: =0 | C17: =C10*C16 | D17: =D10*D16 | E17: =E10*E16 | F17: =F10*F16 | G17: =G10*G16 | H17: =H10*H16 | I17: =I10*I16 | J17: =J10*J16 | ... V17: =V10*V16
A18: Investor share of NPAT | B18: =0 | C18: =C12*C16 | D18: =D12*D16 | E18: =E12*E16 | F18: =F12*F16 | G18: =G12*G16 | H18: =H12*H16 | I18: =I12*I16 | J18: =J12*J16 | ... V18: =V12*V16
A19: Cash-on-cash yield | B19: ="" | C19: ='INV - Investor KPIs'!C9 | D19: ='INV - Investor KPIs'!D9 | E19: ='INV - Investor KPIs'!E9 | F19: ='INV - Investor KPIs'!F9 | G19: ='INV - Investor KPIs'!G9 | H19: ='INV - Investor KPIs'!H9 | I19: ='INV - Investor KPIs'!I9 | J19: ='INV - Investor KPIs'!J9 | ... V19: ='INV - Investor KPIs'!V9
A21: CONSOLIDATED BALANCE SHEET
A22: Cash | B22: =0 | C22: =C46 | D22: =D46 | E22: =E46 | F22: =F46 | G22: =G46 | H22: =H46 | I22: =I46 | J22: =J46 | ... V22: =V46
A23: Property assets / portfolio fair value | B23: =Valuation!$F$9 | C23: =Valuation!$F$9*POWER(1+Control!$B$74,C$5) | D23: =Valuation!$F$9*POWER(1+Control!$B$74,D$5) | E23: =Valuation!$F$9*POWER(1+Control!$B$74,E$5) | F23: =Valuation!$F$9*POWER(1+Control!$B$74,F$5) | G23: =Valuation!$F$9*POWER(1+Control!$B$74,G$5) | H23: =Valuation!$F$9*POWER(1+Control!$B$74,H$5) | I23: =Valuation!$F$9*POWER(1+Control!$B$74,I$5) | J23: =Valuation!$F$9*POWER(1+Control!$B$74,J$5) | ... V23: =Valuation!$F$9*POWER(1+Control!$B$74,V$5)
A24: TOTAL ASSETS | B24: =SUM(B22:B23) | C24: =SUM(C22:C23) | D24: =SUM(D22:D23) | E24: =SUM(E22:E23) | F24: =SUM(F22:F23) | G24: =SUM(G22:G23) | H24: =SUM(H22:H23) | I24: =SUM(I22:I23) | ... V24: =SUM(V22:V23)
A25: Debt | B25: =0 | C25: =0 | D25: =0 | E25: =0 | F25: =0 | G25: =0 | H25: =0 | I25: =0 | ... V25: =0
A26: TOTAL LIABILITIES | B26: =B25 | C26: =C25 | D26: =D25 | E26: =E25 | F26: =F25 | G26: =G25 | H26: =H25 | I26: =I25 | ... V26: =V25
A27: Opening contributed property equity | B27: =Valuation!$F$9 | C27: =Valuation!$F$9 | D27: =Valuation!$F$9 | E27: =Valuation!$F$9 | F27: =Valuation!$F$9 | G27: =Valuation!$F$9 | H27: =Valuation!$F$9 | I27: =Valuation!$F$9 | ... V27: =Valuation!$F$9
A28: Cumulative retained earnings | B28: =0 | C28: =B28+C42+C44 | D28: =C28+D42+D44 | E28: =D28+E42+E44 | F28: =E28+F42+F44 | G28: =F28+G42+G44 | H28: =G28+H42+H44 | I28: =H28+I42+I44 | J28: =I28+J42+J44 | ... V28: =U28+V42+V44
A29: Fair value / revaluation reserve | B29: =B30-B27-B28 | C29: =C30-C27-C28 | D29: =D30-D27-D28 | E29: =E30-E27-E28 | F29: =F30-F27-F28 | G29: =G30-G27-G28 | H29: =H30-H27-H28 | I29: =I30-I27-I28 | ... V29: =V30-V27-V28
A30: TOTAL EQUITY | B30: =B24-B26 | C30: =C24-C26 | D30: =D24-D26 | E30: =E24-E26 | F30: =F24-F26 | G30: =G24-G26 | H30: =H24-H26 | I30: =I24-I26 | ... V30: =V24-V26
A31: TOTAL LIABILITIES + EQUITY | B31: =B26+B30 | C31: =C26+C30 | D31: =D26+D30 | E31: =E26+E30 | F31: =F26+F30 | G31: =G26+G30 | H31: =H26+H30 | I31: =I26+I30 | ... V31: =V26+V30
A32: Balance sheet check | B32: =B24-B31 | C32: =C24-C31 | D32: =D24-D31 | E32: =E24-E31 | F32: =F24-F31 | G32: =G24-G31 | H32: =H24-H31 | I32: =I24-I31 | ... V32: =V24-V31
A34: INVESTOR — BALANCE SHEET VIEW
A35: Partner NAV if exit this year | B35: =Valuation!$F$10 | C35: ='INV - Investor KPIs'!C11 | D35: ='INV - Investor KPIs'!D11 | E35: ='INV - Investor KPIs'!E11 | F35: ='INV - Investor KPIs'!F11 | G35: ='INV - Investor KPIs'!G11 | H35: ='INV - Investor KPIs'!H11 | I35: ='INV - Investor KPIs'!I11 | J35: ='INV - Investor KPIs'!J11 | ... V35: ='INV - Investor KPIs'!V11
A36: Unrecovered capital | B36: =Control!$B$15 | C36: ='INV - Investor KPIs'!C8 | D36: ='INV - Investor KPIs'!D8 | E36: ='INV - Investor KPIs'!E8 | F36: ='INV - Investor KPIs'!F8 | G36: ='INV - Investor KPIs'!G8 | H36: ='INV - Investor KPIs'!H8 | I36: ='INV - Investor KPIs'!I8 | J36: ='INV - Investor KPIs'!J8 | ... V36: ='INV - Investor KPIs'!V8
A37: Total value if exit this year | B37: =B35 | C37: ='INV - Investor KPIs'!C12 | D37: ='INV - Investor KPIs'!D12 | E37: ='INV - Investor KPIs'!E12 | F37: ='INV - Investor KPIs'!F12 | G37: ='INV - Investor KPIs'!G12 | H37: ='INV - Investor KPIs'!H12 | I37: ='INV - Investor KPIs'!I12 | J37: ='INV - Investor KPIs'!J12 | ... V37: ='INV - Investor KPIs'!V12
A38: Total MOIC if exit | B38: =B37/Control!$B$15 | C38: ='INV - Investor KPIs'!C13 | D38: ='INV - Investor KPIs'!D13 | E38: ='INV - Investor KPIs'!E13 | F38: ='INV - Investor KPIs'!F13 | G38: ='INV - Investor KPIs'!G13 | H38: ='INV - Investor KPIs'!H13 | I38: ='INV - Investor KPIs'!I13 | J38: ='INV - Investor KPIs'!J13 | ... V38: ='INV - Investor KPIs'!V13
A40: CONSOLIDATED CASH FLOW STATEMENT
A41: Beginning cash | B41: =0 | C41: =B46 | D41: =C46 | E41: =D46 | F41: =E46 | G41: =F46 | H41: =G46 | I41: =H46 | J41: =I46 | ... V41: =U46
A42: NPAT | B42: =0 | C42: =C12 | D42: =D12 | E42: =E12 | F42: =F12 | G42: =G12 | H42: =H12 | I42: =I12 | J42: =J12 | ... V42: =V12
A43: Winchester construction capex | B43: =0 | C43: ='Portfolio NewCo'!B14 | D43: ='Portfolio NewCo'!C14 | E43: ='Portfolio NewCo'!D14 | F43: ='Portfolio NewCo'!E14 | G43: ='Portfolio NewCo'!F14 | H43: ='Portfolio NewCo'!G14 | I43: ='Portfolio NewCo'!H14 | J43: ='Portfolio NewCo'!I14 | ... V43: ='Portfolio NewCo'!U14
A44: Shareholder distributions | B44: =0 | C44: =-'Portfolio NewCo'!B15 | D44: =-'Portfolio NewCo'!C15 | E44: =-'Portfolio NewCo'!D15 | F44: =-'Portfolio NewCo'!E15 | G44: =-'Portfolio NewCo'!F15 | H44: =-'Portfolio NewCo'!G15 | I44: =-'Portfolio NewCo'!H15 | J44: =-'Portfolio NewCo'!I15 | ... V44: =-'Portfolio NewCo'!U15
A45: Net change in cash | B45: =SUM(B42:B44) | C45: =SUM(C42:C44) | D45: =SUM(D42:D44) | E45: =SUM(E42:E44) | F45: =SUM(F42:F44) | G45: =SUM(G42:G44) | H45: =SUM(H42:H44) | I45: =SUM(I42:I44) | ... V45: =SUM(V42:V44)
A46: ENDING CASH | B46: =B41+B45 | C46: =C41+C45 | D46: =D41+D45 | E46: =E41+E45 | F46: =F41+F45 | G46: =G41+G45 | H46: =H41+H45 | I46: =I41+I45 | ... V46: =V41+V45
A47: Cash tie-out check | B47: =B46-B22 | C47: =C46-C22 | D47: =D46-D22 | E47: =E46-E22 | F47: =F46-F22 | G47: =G46-G22 | H47: =H46-H22 | I47: =I46-I22 | ... V47: =V46-V22
A49: INVESTOR — CASH FLOW VIEW
A50: Partner initial investment | B50: =-Control!$B$15 | C50: =0 | D50: =0 | E50: =0 | F50: =0 | G50: =0 | H50: =0 | I50: =0 | J50: =0 | ... V50: =0
A51: Partner cash distribution | B51: =0 | C51: ='INV - Investor KPIs'!C6 | D51: ='INV - Investor KPIs'!D6 | E51: ='INV - Investor KPIs'!E6 | F51: ='INV - Investor KPIs'!F6 | G51: ='INV - Investor KPIs'!G6 | H51: ='INV - Investor KPIs'!H6 | I51: ='INV - Investor KPIs'!I6 | J51: ='INV - Investor KPIs'!J6 | ... V51: ='INV - Investor KPIs'!V6
A52: Cumulative partner distributions | B52: =0 | C52: ='INV - Investor KPIs'!C7 | D52: ='INV - Investor KPIs'!D7 | E52: ='INV - Investor KPIs'!E7 | F52: ='INV - Investor KPIs'!F7 | G52: ='INV - Investor KPIs'!G7 | H52: ='INV - Investor KPIs'!H7 | I52: ='INV - Investor KPIs'!I7 | J52: ='INV - Investor KPIs'!J7 | ... V52: ='INV - Investor KPIs'!V7
A53: Cash MOIC | B53: =0 | C53: ='INV - Investor KPIs'!C10 | D53: ='INV - Investor KPIs'!D10 | E53: ='INV - Investor KPIs'!E10 | F53: ='INV - Investor KPIs'!F10 | G53: ='INV - Investor KPIs'!G10 | H53: ='INV - Investor KPIs'!H10 | I53: ='INV - Investor KPIs'!I10 | J53: ='INV - Investor KPIs'!J10 | ... V53: ='INV - Investor KPIs'!V10
A54: Cash payback achieved? | B54: ="No" | C54: =IF(C52>=Control!$B$15,"Yes","No") | D54: =IF(D52>=Control!$B$15,"Yes","No") | E54: =IF(E52>=Control!$B$15,"Yes","No") | F54: =IF(F52>=Control!$B$15,"Yes","No") | G54: =IF(G52>=Control!$B$15,"Yes","No") | H54: =IF(H52>=Control!$B$15,"Yes","No") | I54: =IF(I52>=Control!$B$15,"Yes","No") | J54: =IF(J52>=Control!$B$15,"Yes","No") | ... V54: =IF(V52>=Control!$B$15,"Yes","No")
A56: MODEL CHECKS
A57: BS balances? | B57: =IF(ABS(B32)<1,"OK","ERROR") | C57: =IF(ABS(C32)<1,"OK","ERROR") | D57: =IF(ABS(D32)<1,"OK","ERROR") | E57: =IF(ABS(E32)<1,"OK","ERROR") | F57: =IF(ABS(F32)<1,"OK","ERROR") | G57: =IF(ABS(G32)<1,"OK","ERROR") | H57: =IF(ABS(H32)<1,"OK","ERROR") | I57: =IF(ABS(I32)<1,"OK","ERROR") | ... V57: =IF(ABS(V32)<1,"OK","ERROR")
A58: Ending cash ties to BS cash? | B58: =IF(ABS(B47)<1,"OK","ERROR") | C58: =IF(ABS(C47)<1,"OK","ERROR") | D58: =IF(ABS(D47)<1,"OK","ERROR") | E58: =IF(ABS(E47)<1,"OK","ERROR") | F58: =IF(ABS(F47)<1,"OK","ERROR") | G58: =IF(ABS(G47)<1,"OK","ERROR") | H58: =IF(ABS(H47)<1,"OK","ERROR") | I58: =IF(ABS(I47)<1,"OK","ERROR") | ... V58: =IF(ABS(V47)<1,"OK","ERROR")
A59: NPAT links to cash flow? | B59: =IF(ABS(B12-B42)<1,"OK","ERROR") | C59: =IF(ABS(C12-C42)<1,"OK","ERROR") | D59: =IF(ABS(D12-D42)<1,"OK","ERROR") | E59: =IF(ABS(E12-E42)<1,"OK","ERROR") | F59: =IF(ABS(F12-F42)<1,"OK","ERROR") | G59: =IF(ABS(G12-G42)<1,"OK","ERROR") | H59: =IF(ABS(H12-H42)<1,"OK","ERROR") | I59: =IF(ABS(I12-I42)<1,"OK","ERROR") | ... V59: =IF(ABS(V12-V42)<1,"OK","ERROR")
A60: Master check | B60: =IF(COUNTIF(B57:V59,"ERROR")=0,"✓ ALL CHECKS PASS","✗ REVIEW CHECKS")

Sheet INV - Property KPIs
A1: PROPERTY RETURNS & KPIs — per asset (property-specific partner %)
A2: Each property uses its own partner ownership %. Distributions, NAV, buy-in, IRR and MOIC are calculated from the property-specific partner %.
A4: Metric | B4: African Sky | C4: Beachside | D4: Menlyn | F4: Portfolio Total
A5: Partner buy-in component | B5: =IF(Control!$B$5>0,Control!$B$12/Control!$B$11*Control!$B$5,0) | C5: =IF(Control!$B$7>0,Control!$B$13/Control!$B$11*Control!$B$7,0) | D5: =IF(Control!$B$8>0,Control!$B$14/Control!$B$11*Control!$B$8,0) | F5: =Control!$B$15
A6: Adopted property value (100%) | B6: =Valuation!C9 | C6: =Valuation!D9 | D6: =Valuation!E9 | F6: =Valuation!$F$9
A7: Partner NAV @ property-specific % | B7: =Valuation!C10 | C7: =Valuation!D10 | D7: =Valuation!E10 | F7: =Valuation!$F$10
A8: Average annual NOI (Yr 1-3) | B8: =AVERAGE('African Sky P&L'!C26:E26) | C8: =AVERAGE('Beachside P&L'!C16:E16) | D8: =AVERAGE('Menlyn P&L'!C13:E13) | F8: =AVERAGE('Portfolio NewCo'!B9:D9)
A9: NOI yield on adopted value | B9: =IFERROR(B8/B6,"") | C9: =IFERROR(C8/C6,"") | D9: =IFERROR(D8/D6,"") | F9: =IFERROR(F8/F6,"")
A10: Implied earnings multiple (value ÷ NOI) | B10: =IFERROR(B6/B8,"") | C10: =IFERROR(C6/C8,"") | D10: =IFERROR(D6/D8,"") | F10: =IFERROR(F6/F8,"")
A11: 5-year Cash MOIC | B11: =IF(B5=0,"",INDEX($B$28:$U$28,1,5)/B5) | C11: =IF(C5=0,"",INDEX($B$29:$U$29,1,5)/C5) | D11: =IF(D5=0,"",INDEX($B$30:$U$30,1,5)/D5) | F11: =IFERROR(INDEX('INV - Investor KPIs'!$C$10:$V$10,1,5),"")
A12: 5-year Total MOIC | B12: =IF(B5=0,"",(INDEX($B$28:$U$28,1,5)+B7*POWER(1+Control!$B$74,5)*(1-Control!$B$75))/B5) | C12: =IF(C5=0,"",(INDEX($B$29:$U$29,1,5)+C7*POWER(1+Control!$B$74,5)*(1-Control!$B$75))/C5) | D12: =IF(D5=0,"",(INDEX($B$30:$U$30,1,5)+D7*POWER(1+Control!$B$74,5)*(1-Control!$B$75))/D5) | F12: =IFERROR(INDEX('INV - Investor KPIs'!$C$13:$V$13,1,5),"")
A13: 5-year Total IRR | B13: =IF(B5=0,"",IFERROR(IRR(B32:G32),"")) | C13: =IF(C5=0,"",IFERROR(IRR(B33:G33),"")) | D13: =IF(D5=0,"",IFERROR(IRR(B34:G34),"")) | F13: ='INV - Investor KPIs'!C18
A14: 10-year Cash MOIC | B14: =IF(B5=0,"",INDEX($B$28:$U$28,1,10)/B5) | C14: =IF(C5=0,"",INDEX($B$29:$U$29,1,10)/C5) | D14: =IF(D5=0,"",INDEX($B$30:$U$30,1,10)/D5) | F14: =IFERROR(INDEX('INV - Investor KPIs'!$C$10:$V$10,1,10),"")
A15: 10-year Total MOIC | B15: =IF(B5=0,"",(INDEX($B$28:$U$28,1,10)+B7*POWER(1+Control!$B$74,10)*(1-Control!$B$75))/B5) | C15: =IF(C5=0,"",(INDEX($B$29:$U$29,1,10)+C7*POWER(1+Control!$B$74,10)*(1-Control!$B$75))/C5) | D15: =IF(D5=0,"",(INDEX($B$30:$U$30,1,10)+D7*POWER(1+Control!$B$74,10)*(1-Control!$B$75))/D5) | F15: =IFERROR(INDEX('INV - Investor KPIs'!$C$13:$V$13,1,10),"")
A16: 10-year Total IRR | B16: =IF(B5=0,"",IFERROR(IRR(B35:L35),"")) | C16: =IF(C5=0,"",IFERROR(IRR(B36:L36),"")) | D16: =IF(D5=0,"",IFERROR(IRR(B37:L37),"")) | F16: ='INV - Investor KPIs'!D18
A17: 15-year Cash MOIC | B17: =IF(B5=0,"",INDEX($B$28:$U$28,1,15)/B5) | C17: =IF(C5=0,"",INDEX($B$29:$U$29,1,15)/C5) | D17: =IF(D5=0,"",INDEX($B$30:$U$30,1,15)/D5) | F17: =IFERROR(INDEX('INV - Investor KPIs'!$C$10:$V$10,1,15),"")
A18: 15-year Total MOIC | B18: =IF(B5=0,"",(INDEX($B$28:$U$28,1,15)+B7*POWER(1+Control!$B$74,15)*(1-Control!$B$75))/B5) | C18: =IF(C5=0,"",(INDEX($B$29:$U$29,1,15)+C7*POWER(1+Control!$B$74,15)*(1-Control!$B$75))/C5) | D18: =IF(D5=0,"",(INDEX($B$30:$U$30,1,15)+D7*POWER(1+Control!$B$74,15)*(1-Control!$B$75))/D5) | F18: =IFERROR(INDEX('INV - Investor KPIs'!$C$13:$V$13,1,15),"")
A19: 15-year Total IRR | B19: =IF(B5=0,"",IFERROR(IRR(B38:Q38),"")) | C19: =IF(C5=0,"",IFERROR(IRR(B39:Q39),"")) | D19: =IF(D5=0,"",IFERROR(IRR(B40:Q40),"")) | F19: ='INV - Investor KPIs'!E18
A20: 20-year Cash MOIC | B20: =IF(B5=0,"",INDEX($B$28:$U$28,1,20)/B5) | C20: =IF(C5=0,"",INDEX($B$29:$U$29,1,20)/C5) | D20: =IF(D5=0,"",INDEX($B$30:$U$30,1,20)/D5) | F20: =IFERROR(INDEX('INV - Investor KPIs'!$C$10:$V$10,1,20),"")
A21: 20-year Total MOIC | B21: =IF(B5=0,"",(INDEX($B$28:$U$28,1,20)+B7*POWER(1+Control!$B$74,20)*(1-Control!$B$75))/B5) | C21: =IF(C5=0,"",(INDEX($B$29:$U$29,1,20)+C7*POWER(1+Control!$B$74,20)*(1-Control!$B$75))/C5) | D21: =IF(D5=0,"",(INDEX($B$30:$U$30,1,20)+D7*POWER(1+Control!$B$74,20)*(1-Control!$B$75))/D5) | F21: =IFERROR(INDEX('INV - Investor KPIs'!$C$13:$V$13,1,20),"")
A22: 20-year Total IRR | B22: =IF(B5=0,"",IFERROR(IRR(B41:V41),"")) | C22: =IF(C5=0,"",IFERROR(IRR(B42:V42),"")) | D22: =IF(D5=0,"",IFERROR(IRR(B43:V43),"")) | F22: ='INV - Investor KPIs'!F18
A24: 50% PARTNER DISTRIBUTION HELPERS — by property
A25: AS partner dist | B25: ='Portfolio NewCo'!B22 | C25: ='Portfolio NewCo'!C22 | D25: ='Portfolio NewCo'!D22 | E25: ='Portfolio NewCo'!E22 | F25: ='Portfolio NewCo'!F22 | G25: ='Portfolio NewCo'!G22 | H25: ='Portfolio NewCo'!H22 | I25: ='Portfolio NewCo'!I22 | ... U25: ='Portfolio NewCo'!U22
A26: BS partner dist | B26: ='Portfolio NewCo'!B23 | C26: ='Portfolio NewCo'!C23 | D26: ='Portfolio NewCo'!D23 | E26: ='Portfolio NewCo'!E23 | F26: ='Portfolio NewCo'!F23 | G26: ='Portfolio NewCo'!G23 | H26: ='Portfolio NewCo'!H23 | I26: ='Portfolio NewCo'!I23 | ... U26: ='Portfolio NewCo'!U23
A27: MN partner dist | B27: ='Portfolio NewCo'!B24 | C27: ='Portfolio NewCo'!C24 | D27: ='Portfolio NewCo'!D24 | E27: ='Portfolio NewCo'!E24 | F27: ='Portfolio NewCo'!F24 | G27: ='Portfolio NewCo'!G24 | H27: ='Portfolio NewCo'!H24 | I27: ='Portfolio NewCo'!I24 | ... U27: ='Portfolio NewCo'!U24
A28: AS cumulative | B28: ='Portfolio NewCo'!B25 | C28: ='Portfolio NewCo'!C25 | D28: ='Portfolio NewCo'!D25 | E28: ='Portfolio NewCo'!E25 | F28: ='Portfolio NewCo'!F25 | G28: ='Portfolio NewCo'!G25 | H28: ='Portfolio NewCo'!H25 | I28: ='Portfolio NewCo'!I25 | ... U28: ='Portfolio NewCo'!U25
A29: BS cumulative | B29: ='Portfolio NewCo'!B26 | C29: ='Portfolio NewCo'!C26 | D29: ='Portfolio NewCo'!D26 | E29: ='Portfolio NewCo'!E26 | F29: ='Portfolio NewCo'!F26 | G29: ='Portfolio NewCo'!G26 | H29: ='Portfolio NewCo'!H26 | I29: ='Portfolio NewCo'!I26 | ... U29: ='Portfolio NewCo'!U26
A30: MN cumulative | B30: ='Portfolio NewCo'!B27 | C30: ='Portfolio NewCo'!C27 | D30: ='Portfolio NewCo'!D27 | E30: ='Portfolio NewCo'!E27 | F30: ='Portfolio NewCo'!F27 | G30: ='Portfolio NewCo'!G27 | H30: ='Portfolio NewCo'!H27 | I30: ='Portfolio NewCo'!I27 | ... U30: ='Portfolio NewCo'!U27
A32: AS total-exit 5y | B32: =-B5 | C32: =INDEX($B$25:$U$25,1,1) | D32: =INDEX($B$25:$U$25,1,2) | E32: =INDEX($B$25:$U$25,1,3) | F32: =INDEX($B$25:$U$25,1,4) | G32: =INDEX($B$25:$U$25,1,5)+B7*POWER(1+Control!$B$74,5)*(1-Control!$B$75)
A33: BS total-exit 5y | B33: =-C5 | C33: =INDEX($B$26:$U$26,1,1) | D33: =INDEX($B$26:$U$26,1,2) | E33: =INDEX($B$26:$U$26,1,3) | F33: =INDEX($B$26:$U$26,1,4) | G33: =INDEX($B$26:$U$26,1,5)+C7*POWER(1+Control!$B$74,5)*(1-Control!$B$75)
A34: MN total-exit 5y | B34: =-D5 | C34: =INDEX($B$27:$U$27,1,1) | D34: =INDEX($B$27:$U$27,1,2) | E34: =INDEX($B$27:$U$27,1,3) | F34: =INDEX($B$27:$U$27,1,4) | G34: =INDEX($B$27:$U$27,1,5)+D7*POWER(1+Control!$B$74,5)*(1-Control!$B$75)
A35: AS total-exit 10y | B35: =-B5 | C35: =INDEX($B$25:$U$25,1,1) | D35: =INDEX($B$25:$U$25,1,2) | E35: =INDEX($B$25:$U$25,1,3) | F35: =INDEX($B$25:$U$25,1,4) | G35: =INDEX($B$25:$U$25,1,5) | H35: =INDEX($B$25:$U$25,1,6) | I35: =INDEX($B$25:$U$25,1,7) | J35: =INDEX($B$25:$U$25,1,8) | K35: =INDEX($B$25:$U$25,1,9) | L35: =INDEX($B$25:$U$25,1,10)+B7*POWER(1+Control!$B$74,10)*(1-Control!$B$75)
A36: BS total-exit 10y | B36: =-C5 | C36: =INDEX($B$26:$U$26,1,1) | D36: =INDEX($B$26:$U$26,1,2) | E36: =INDEX($B$26:$U$26,1,3) | F36: =INDEX($B$26:$U$26,1,4) | G36: =INDEX($B$26:$U$26,1,5) | H36: =INDEX($B$26:$U$26,1,6) | I36: =INDEX($B$26:$U$26,1,7) | J36: =INDEX($B$26:$U$26,1,8) | K36: =INDEX($B$26:$U$26,1,9) | L36: =INDEX($B$26:$U$26,1,10)+C7*POWER(1+Control!$B$74,10)*(1-Control!$B$75)
A37: MN total-exit 10y | B37: =-D5 | C37: =INDEX($B$27:$U$27,1,1) | D37: =INDEX($B$27:$U$27,1,2) | E37: =INDEX($B$27:$U$27,1,3) | F37: =INDEX($B$27:$U$27,1,4) | G37: =INDEX($B$27:$U$27,1,5) | H37: =INDEX($B$27:$U$27,1,6) | I37: =INDEX($B$27:$U$27,1,7) | J37: =INDEX($B$27:$U$27,1,8) | K37: =INDEX($B$27:$U$27,1,9) | L37: =INDEX($B$27:$U$27,1,10)+D7*POWER(1+Control!$B$74,10)*(1-Control!$B$75)
A38: AS total-exit 15y | B38: =-B5 | C38: =INDEX($B$25:$U$25,1,1) | D38: =INDEX($B$25:$U$25,1,2) | E38: =INDEX($B$25:$U$25,1,3) | F38: =INDEX($B$25:$U$25,1,4) | G38: =INDEX($B$25:$U$25,1,5) | H38: =INDEX($B$25:$U$25,1,6) | I38: =INDEX($B$25:$U$25,1,7) | J38: =INDEX($B$25:$U$25,1,8) | K38: =INDEX($B$25:$U$25,1,9) | L38: =INDEX($B$25:$U$25,1,10) | M38: =INDEX($B$25:$U$25,1,11) | N38: =INDEX($B$25:$U$25,1,12) | O38: =INDEX($B$25:$U$25,1,13) | P38: =INDEX($B$25:$U$25,1,14) | Q38: =INDEX($B$25:$U$25,1,15)+B7*POWER(1+Control!$B$74,15)*(1-Control!$B$75)
A39: BS total-exit 15y | B39: =-C5 | C39: =INDEX($B$26:$U$26,1,1) | D39: =INDEX($B$26:$U$26,1,2) | E39: =INDEX($B$26:$U$26,1,3) | F39: =INDEX($B$26:$U$26,1,4) | G39: =INDEX($B$26:$U$26,1,5) | H39: =INDEX($B$26:$U$26,1,6) | I39: =INDEX($B$26:$U$26,1,7) | J39: =INDEX($B$26:$U$26,1,8) | K39: =INDEX($B$26:$U$26,1,9) | L39: =INDEX($B$26:$U$26,1,10) | M39: =INDEX($B$26:$U$26,1,11) | N39: =INDEX($B$26:$U$26,1,12) | O39: =INDEX($B$26:$U$26,1,13) | P39: =INDEX($B$26:$U$26,1,14) | Q39: =INDEX($B$26:$U$26,1,15)+C7*POWER(1+Control!$B$74,15)*(1-Control!$B$75)
A40: MN total-exit 15y | B40: =-D5 | C40: =INDEX($B$27:$U$27,1,1) | D40: =INDEX($B$27:$U$27,1,2) | E40: =INDEX($B$27:$U$27,1,3) | F40: =INDEX($B$27:$U$27,1,4) | G40: =INDEX($B$27:$U$27,1,5) | H40: =INDEX($B$27:$U$27,1,6) | I40: =INDEX($B$27:$U$27,1,7) | J40: =INDEX($B$27:$U$27,1,8) | K40: =INDEX($B$27:$U$27,1,9) | L40: =INDEX($B$27:$U$27,1,10) | M40: =INDEX($B$27:$U$27,1,11) | N40: =INDEX($B$27:$U$27,1,12) | O40: =INDEX($B$27:$U$27,1,13) | P40: =INDEX($B$27:$U$27,1,14) | Q40: =INDEX($B$27:$U$27,1,15)+D7*POWER(1+Control!$B$74,15)*(1-Control!$B$75)
A41: AS total-exit 20y | B41: =-B5 | C41: =INDEX($B$25:$U$25,1,1) | D41: =INDEX($B$25:$U$25,1,2) | E41: =INDEX($B$25:$U$25,1,3) | F41: =INDEX($B$25:$U$25,1,4) | G41: =INDEX($B$25:$U$25,1,5) | H41: =INDEX($B$25:$U$25,1,6) | I41: =INDEX($B$25:$U$25,1,7) | J41: =INDEX($B$25:$U$25,1,8) | K41: =INDEX($B$25:$U$25,1,9) | L41: =INDEX($B$25:$U$25,1,10) | M41: =INDEX($B$25:$U$25,1,11) | N41: =INDEX($B$25:$U$25,1,12) | O41: =INDEX($B$25:$U$25,1,13) | P41: =INDEX($B$25:$U$25,1,14) | Q41: =INDEX($B$25:$U$25,1,15) | R41: =INDEX($B$25:$U$25,1,16) | S41: =INDEX($B$25:$U$25,1,17) | T41: =INDEX($B$25:$U$25,1,18) | U41: =INDEX($B$25:$U$25,1,19) | V41: =INDEX($B$25:$U$25,1,20)+B7*POWER(1+Control!$B$74,20)*(1-Control!$B$75)
A42: BS total-exit 20y | B42: =-C5 | C42: =INDEX($B$26:$U$26,1,1) | D42: =INDEX($B$26:$U$26,1,2) | E42: =INDEX($B$26:$U$26,1,3) | F42: =INDEX($B$26:$U$26,1,4) | G42: =INDEX($B$26:$U$26,1,5) | H42: =INDEX($B$26:$U$26,1,6) | I42: =INDEX($B$26:$U$26,1,7) | J42: =INDEX($B$26:$U$26,1,8) | K42: =INDEX($B$26:$U$26,1,9) | L42: =INDEX($B$26:$U$26,1,10) | M42: =INDEX($B$26:$U$26,1,11) | N42: =INDEX($B$26:$U$26,1,12) | O42: =INDEX($B$26:$U$26,1,13) | P42: =INDEX($B$26:$U$26,1,14) | Q42: =INDEX($B$26:$U$26,1,15) | R42: =INDEX($B$26:$U$26,1,16) | S42: =INDEX($B$26:$U$26,1,17) | T42: =INDEX($B$26:$U$26,1,18) | U42: =INDEX($B$26:$U$26,1,19) | V42: =INDEX($B$26:$U$26,1,20)+C7*POWER(1+Control!$B$74,20)*(1-Control!$B$75)
A43: MN total-exit 20y | B43: =-D5 | C43: =INDEX($B$27:$U$27,1,1) | D43: =INDEX($B$27:$U$27,1,2) | E43: =INDEX($B$27:$U$27,1,3) | F43: =INDEX($B$27:$U$27,1,4) | G43: =INDEX($B$27:$U$27,1,5) | H43: =INDEX($B$27:$U$27,1,6) | I43: =INDEX($B$27:$U$27,1,7) | J43: =INDEX($B$27:$U$27,1,8) | K43: =INDEX($B$27:$U$27,1,9) | L43: =INDEX($B$27:$U$27,1,10) | M43: =INDEX($B$27:$U$27,1,11) | N43: =INDEX($B$27:$U$27,1,12) | O43: =INDEX($B$27:$U$27,1,13) | P43: =INDEX($B$27:$U$27,1,14) | Q43: =INDEX($B$27:$U$27,1,15) | R43: =INDEX($B$27:$U$27,1,16) | S43: =INDEX($B$27:$U$27,1,17) | T43: =INDEX($B$27:$U$27,1,18) | U43: =INDEX($B$27:$U$27,1,19) | V43: =INDEX($B$27:$U$27,1,20)+D7*POWER(1+Control!$B$74,20)*(1-Control!$B$75)

Sheet INV - Investor KPIs
A1: INVESTOR RETURNS & KPIs — property-specific partner %
A2: Cash = property-specific partner distributions. Total = distributions + property-specific partner share of property value at exit.
A4: Year | C4: 1 | D4: 2 | E4: 3 | F4: 4 | G4: 5 | H4: 6 | I4: 7 | J4: 8 | K4: 9 | L4: 10 | M4: 11 | N4: 12 | O4: 13 | P4: 14 | Q4: 15 | R4: 16 | S4: 17 | T4: 18 | U4: 19 | V4: 20
A6: Partner distribution | C6: ='Portfolio NewCo'!B16 | D6: ='Portfolio NewCo'!C16 | E6: ='Portfolio NewCo'!D16 | F6: ='Portfolio NewCo'!E16 | G6: ='Portfolio NewCo'!F16 | H6: ='Portfolio NewCo'!G16 | I6: ='Portfolio NewCo'!H16 | J6: ='Portfolio NewCo'!I16 | ... V6: ='Portfolio NewCo'!U16
A7: Cumulative distribution | C7: ='Portfolio NewCo'!B17 | D7: ='Portfolio NewCo'!C17 | E7: ='Portfolio NewCo'!D17 | F7: ='Portfolio NewCo'!E17 | G7: ='Portfolio NewCo'!F17 | H7: ='Portfolio NewCo'!G17 | I7: ='Portfolio NewCo'!H17 | J7: ='Portfolio NewCo'!I17 | ... V7: ='Portfolio NewCo'!U17
A8: Unrecovered capital | C8: =MAX(0,Control!$B$15-C7) | D8: =MAX(0,Control!$B$15-D7) | E8: =MAX(0,Control!$B$15-E7) | F8: =MAX(0,Control!$B$15-F7) | G8: =MAX(0,Control!$B$15-G7) | H8: =MAX(0,Control!$B$15-H7) | I8: =MAX(0,Control!$B$15-I7) | J8: =MAX(0,Control!$B$15-J7) | ... V8: =MAX(0,Control!$B$15-V7)
A9: Cash-on-cash yield | C9: =IF(Control!$B$15=0,"",C6/Control!$B$15) | D9: =IF(Control!$B$15=0,"",D6/Control!$B$15) | E9: =IF(Control!$B$15=0,"",E6/Control!$B$15) | F9: =IF(Control!$B$15=0,"",F6/Control!$B$15) | G9: =IF(Control!$B$15=0,"",G6/Control!$B$15) | H9: =IF(Control!$B$15=0,"",H6/Control!$B$15) | I9: =IF(Control!$B$15=0,"",I6/Control!$B$15) | J9: =IF(Control!$B$15=0,"",J6/Control!$B$15) | ... V9: =IF(Control!$B$15=0,"",V6/Control!$B$15)
A10: Cash MOIC | C10: =IF(Control!$B$15=0,"",C7/Control!$B$15) | D10: =IF(Control!$B$15=0,"",D7/Control!$B$15) | E10: =IF(Control!$B$15=0,"",E7/Control!$B$15) | F10: =IF(Control!$B$15=0,"",F7/Control!$B$15) | G10: =IF(Control!$B$15=0,"",G7/Control!$B$15) | H10: =IF(Control!$B$15=0,"",H7/Control!$B$15) | I10: =IF(Control!$B$15=0,"",I7/Control!$B$15) | J10: =IF(Control!$B$15=0,"",J7/Control!$B$15) | ... V10: =IF(Control!$B$15=0,"",V7/Control!$B$15)
A11: Partner NAV if exit this year | C11: =Valuation!$F$10*POWER(1+Control!$B$74,C$4)*(1-Control!$B$75) | D11: =Valuation!$F$10*POWER(1+Control!$B$74,D$4)*(1-Control!$B$75) | E11: =Valuation!$F$10*POWER(1+Control!$B$74,E$4)*(1-Control!$B$75) | F11: =Valuation!$F$10*POWER(1+Control!$B$74,F$4)*(1-Control!$B$75) | G11: =Valuation!$F$10*POWER(1+Control!$B$74,G$4)*(1-Control!$B$75) | H11: =Valuation!$F$10*POWER(1+Control!$B$74,H$4)*(1-Control!$B$75) | I11: =Valuation!$F$10*POWER(1+Control!$B$74,I$4)*(1-Control!$B$75) | J11: =Valuation!$F$10*POWER(1+Control!$B$74,J$4)*(1-Control!$B$75) | ... V11: =Valuation!$F$10*POWER(1+Control!$B$74,V$4)*(1-Control!$B$75)
A12: Total value if exit (cash + NAV) | C12: =C7+C11 | D12: =D7+D11 | E12: =E7+E11 | F12: =F7+F11 | G12: =G7+G11 | H12: =H7+H11 | I12: =I7+I11 | J12: =J7+J11 | ... V12: =V7+V11
A13: Total MOIC (incl. property value) | C13: =IF(Control!$B$15=0,"",C12/Control!$B$15) | D13: =IF(Control!$B$15=0,"",D12/Control!$B$15) | E13: =IF(Control!$B$15=0,"",E12/Control!$B$15) | F13: =IF(Control!$B$15=0,"",F12/Control!$B$15) | G13: =IF(Control!$B$15=0,"",G12/Control!$B$15) | H13: =IF(Control!$B$15=0,"",H12/Control!$B$15) | I13: =IF(Control!$B$15=0,"",I12/Control!$B$15) | J13: =IF(Control!$B$15=0,"",J12/Control!$B$15) | ... V13: =IF(Control!$B$15=0,"",V12/Control!$B$15)
A15: HOLD-PERIOD KPIs
A16: Hold period | B16: 3-year | C16: 5-year | D16: 10-year | E16: 15-year | F16: 20-year
A17: Cash IRR | B17: =IF(Control!$B$15=0,"",IFERROR(IRR(C30:F30),"")) | C17: =IF(Control!$B$15=0,"",IFERROR(IRR(C31:H31),"")) | D17: =IF(Control!$B$15=0,"",IFERROR(IRR(C32:M32),"")) | E17: =IF(Control!$B$15=0,"",IFERROR(IRR(C33:R33),"")) | F17: =IF(Control!$B$15=0,"",IFERROR(IRR(C34:W34),""))
A18: Total IRR (incl. property value) | B18: =IF(Control!$B$15=0,"",IFERROR(IRR(C35:F35),"")) | C18: =IF(Control!$B$15=0,"",IFERROR(IRR(C36:H36),"")) | D18: =IF(Control!$B$15=0,"",IFERROR(IRR(C37:M37),"")) | E18: =IF(Control!$B$15=0,"",IFERROR(IRR(C38:R38),"")) | F18: =IF(Control!$B$15=0,"",IFERROR(IRR(C39:W39),""))
A19: Cash MOIC | B19: =IF(Control!$B$15=0,"",INDEX($C$10:$V$10,1,3)) | C19: =IF(Control!$B$15=0,"",INDEX($C$10:$V$10,1,5)) | D19: =IF(Control!$B$15=0,"",INDEX($C$10:$V$10,1,10)) | E19: =IF(Control!$B$15=0,"",INDEX($C$10:$V$10,1,15)) | F19: =IF(Control!$B$15=0,"",INDEX($C$10:$V$10,1,20))
A20: Total MOIC | B20: =IF(Control!$B$15=0,"",INDEX($C$13:$V$13,1,3)) | C20: =IF(Control!$B$15=0,"",INDEX($C$13:$V$13,1,5)) | D20: =IF(Control!$B$15=0,"",INDEX($C$13:$V$13,1,10)) | E20: =IF(Control!$B$15=0,"",INDEX($C$13:$V$13,1,15)) | F20: =IF(Control!$B$15=0,"",INDEX($C$13:$V$13,1,20))
A22: 50% PARTNER VIEW — key investor context
A23: Buy-in paid by 50% partner | B23: =Control!$B$15
A24: Partner NAV today @ 50% | B24: =Valuation!$F$10
A25: Cash payback year | B25: =IF(Control!$B$15=0,"No active properties",COUNTIF('Portfolio NewCo'!B17:U17,"<"&Control!$B$15)+1)
A29: — exit cashflow helpers (t0 col C … t20 col W) —
A30: cash 3y | C30: =-Control!$B$15 | D30: =INDEX($C$6:$V$6,1,1) | E30: =INDEX($C$6:$V$6,1,2) | F30: =INDEX($C$6:$V$6,1,3)
A31: cash 5y | C31: =-Control!$B$15 | D31: =INDEX($C$6:$V$6,1,1) | E31: =INDEX($C$6:$V$6,1,2) | F31: =INDEX($C$6:$V$6,1,3) | G31: =INDEX($C$6:$V$6,1,4) | H31: =INDEX($C$6:$V$6,1,5)
A32: cash 10y | C32: =-Control!$B$15 | D32: =INDEX($C$6:$V$6,1,1) | E32: =INDEX($C$6:$V$6,1,2) | F32: =INDEX($C$6:$V$6,1,3) | G32: =INDEX($C$6:$V$6,1,4) | H32: =INDEX($C$6:$V$6,1,5) | I32: =INDEX($C$6:$V$6,1,6) | J32: =INDEX($C$6:$V$6,1,7) | K32: =INDEX($C$6:$V$6,1,8) | L32: =INDEX($C$6:$V$6,1,9) | M32: =INDEX($C$6:$V$6,1,10)
A33: cash 15y | C33: =-Control!$B$15 | D33: =INDEX($C$6:$V$6,1,1) | E33: =INDEX($C$6:$V$6,1,2) | F33: =INDEX($C$6:$V$6,1,3) | G33: =INDEX($C$6:$V$6,1,4) | H33: =INDEX($C$6:$V$6,1,5) | I33: =INDEX($C$6:$V$6,1,6) | J33: =INDEX($C$6:$V$6,1,7) | K33: =INDEX($C$6:$V$6,1,8) | L33: =INDEX($C$6:$V$6,1,9) | M33: =INDEX($C$6:$V$6,1,10) | N33: =INDEX($C$6:$V$6,1,11) | O33: =INDEX($C$6:$V$6,1,12) | P33: =INDEX($C$6:$V$6,1,13) | Q33: =INDEX($C$6:$V$6,1,14) | R33: =INDEX($C$6:$V$6,1,15)
A34: cash 20y | C34: =-Control!$B$15 | D34: =INDEX($C$6:$V$6,1,1) | E34: =INDEX($C$6:$V$6,1,2) | F34: =INDEX($C$6:$V$6,1,3) | G34: =INDEX($C$6:$V$6,1,4) | H34: =INDEX($C$6:$V$6,1,5) | I34: =INDEX($C$6:$V$6,1,6) | J34: =INDEX($C$6:$V$6,1,7) | K34: =INDEX($C$6:$V$6,1,8) | L34: =INDEX($C$6:$V$6,1,9) | M34: =INDEX($C$6:$V$6,1,10) | N34: =INDEX($C$6:$V$6,1,11) | O34: =INDEX($C$6:$V$6,1,12) | P34: =INDEX($C$6:$V$6,1,13) | Q34: =INDEX($C$6:$V$6,1,14) | R34: =INDEX($C$6:$V$6,1,15) | S34: =INDEX($C$6:$V$6,1,16) | T34: =INDEX($C$6:$V$6,1,17) | U34: =INDEX($C$6:$V$6,1,18) | V34: =INDEX($C$6:$V$6,1,19) | W34: =INDEX($C$6:$V$6,1,20)
A35: total 3y | C35: =-Control!$B$15 | D35: =INDEX($C$6:$V$6,1,1) | E35: =INDEX($C$6:$V$6,1,2) | F35: =INDEX($C$6:$V$6,1,3)+Valuation!$F$10*POWER(1+Control!$B$74,3)*(1-Control!$B$75)
A36: total 5y | C36: =-Control!$B$15 | D36: =INDEX($C$6:$V$6,1,1) | E36: =INDEX($C$6:$V$6,1,2) | F36: =INDEX($C$6:$V$6,1,3) | G36: =INDEX($C$6:$V$6,1,4) | H36: =INDEX($C$6:$V$6,1,5)+Valuation!$F$10*POWER(1+Control!$B$74,5)*(1-Control!$B$75)
A37: total 10y | C37: =-Control!$B$15 | D37: =INDEX($C$6:$V$6,1,1) | E37: =INDEX($C$6:$V$6,1,2) | F37: =INDEX($C$6:$V$6,1,3) | G37: =INDEX($C$6:$V$6,1,4) | H37: =INDEX($C$6:$V$6,1,5) | I37: =INDEX($C$6:$V$6,1,6) | J37: =INDEX($C$6:$V$6,1,7) | K37: =INDEX($C$6:$V$6,1,8) | L37: =INDEX($C$6:$V$6,1,9) | M37: =INDEX($C$6:$V$6,1,10)+Valuation!$F$10*POWER(1+Control!$B$74,10)*(1-Control!$B$75)
A38: total 15y | C38: =-Control!$B$15 | D38: =INDEX($C$6:$V$6,1,1) | E38: =INDEX($C$6:$V$6,1,2) | F38: =INDEX($C$6:$V$6,1,3) | G38: =INDEX($C$6:$V$6,1,4) | H38: =INDEX($C$6:$V$6,1,5) | I38: =INDEX($C$6:$V$6,1,6) | J38: =INDEX($C$6:$V$6,1,7) | K38: =INDEX($C$6:$V$6,1,8) | L38: =INDEX($C$6:$V$6,1,9) | M38: =INDEX($C$6:$V$6,1,10) | N38: =INDEX($C$6:$V$6,1,11) | O38: =INDEX($C$6:$V$6,1,12) | P38: =INDEX($C$6:$V$6,1,13) | Q38: =INDEX($C$6:$V$6,1,14) | R38: =INDEX($C$6:$V$6,1,15)+Valuation!$F$10*POWER(1+Control!$B$74,15)*(1-Control!$B$75)
A39: total 20y | C39: =-Control!$B$15 | D39: =INDEX($C$6:$V$6,1,1) | E39: =INDEX($C$6:$V$6,1,2) | F39: =INDEX($C$6:$V$6,1,3) | G39: =INDEX($C$6:$V$6,1,4) | H39: =INDEX($C$6:$V$6,1,5) | I39: =INDEX($C$6:$V$6,1,6) | J39: =INDEX($C$6:$V$6,1,7) | K39: =INDEX($C$6:$V$6,1,8) | L39: =INDEX($C$6:$V$6,1,9) | M39: =INDEX($C$6:$V$6,1,10) | N39: =INDEX($C$6:$V$6,1,11) | O39: =INDEX($C$6:$V$6,1,12) | P39: =INDEX($C$6:$V$6,1,13) | Q39: =INDEX($C$6:$V$6,1,14) | R39: =INDEX($C$6:$V$6,1,15) | S39: =INDEX($C$6:$V$6,1,16) | T39: =INDEX($C$6:$V$6,1,17) | U39: =INDEX($C$6:$V$6,1,18) | V39: =INDEX($C$6:$V$6,1,19) | W39: =INDEX($C$6:$V$6,1,20)+Valuation!$F$10*POWER(1+Control!$B$74,20)*(1-Control!$B$75)

Sheet INV - Sensitivity Risks
A1: SENSITIVITY & RISKS — live one-way IRR data-tables
A2: Each row recomputes the FULL 20-year partner return with one input changed (all other Control inputs held live). Base row is highlighted and equals the main model. Scenario input cells are yellow — edit them freely.
A4: Note: scenarios recompute the full 20-year return. 5-, 10-, and 15-year base-case partner KPIs are now shown on Investor KPIs and Investor Close Summary to avoid mixing base hold periods with scenario sensitivities.
A6: Occupancy | B6: 20-yr Total IRR | C6: 20-yr Total MOIC | D6: Payback (yr)
A7: 0.65 | B7: =IRR(C51:W51) | C7: =SUM(D51:W51)/Control!$B$15 | D7: =COUNTIF(D52:V52,"<"&Control!$B$15)+1
A8: 0.7 | B8: =IRR(C53:W53) | C8: =SUM(D53:W53)/Control!$B$15 | D8: =COUNTIF(D54:V54,"<"&Control!$B$15)+1
A9: 0.75 | B9: =IRR(C55:W55) | C9: =SUM(D55:W55)/Control!$B$15 | D9: =COUNTIF(D56:V56,"<"&Control!$B$15)+1
A10: 0.8 | B10: =IRR(C57:W57) | C10: =SUM(D57:W57)/Control!$B$15 | D10: =COUNTIF(D58:V58,"<"&Control!$B$15)+1
A11: 0.85 | B11: =IRR(C59:W59) | C11: =SUM(D59:W59)/Control!$B$15 | D11: =COUNTIF(D60:V60,"<"&Control!$B$15)+1
A13: ADR / RATE ESCALATION p.a. (Control!B11)
A14: ADR escalation | B14: 20-yr Total IRR | C14: 20-yr Total MOIC | D14: Payback (yr)
A15: 0.03 | B15: =IRR(C63:W63) | C15: =SUM(D63:W63)/Control!$B$15 | D15: =COUNTIF(D64:V64,"<"&Control!$B$15)+1
A16: 0.04 | B16: =IRR(C65:W65) | C16: =SUM(D65:W65)/Control!$B$15 | D16: =COUNTIF(D66:V66,"<"&Control!$B$15)+1
A17: 0.05 | B17: =IRR(C67:W67) | C17: =SUM(D67:W67)/Control!$B$15 | D17: =COUNTIF(D68:V68,"<"&Control!$B$15)+1
A18: 0.06 | B18: =IRR(C69:W69) | C18: =SUM(D69:W69)/Control!$B$15 | D18: =COUNTIF(D70:V70,"<"&Control!$B$15)+1
A19: 0.07 | B19: =IRR(C71:W71) | C19: =SUM(D71:W71)/Control!$B$15 | D19: =COUNTIF(D72:V72,"<"&Control!$B$15)+1
A21: TOUR GROSS PROFIT (× base, via ASKY Tours Calcs)
A22: Tour GP (× base) | B22: 20-yr Total IRR | C22: 20-yr Total MOIC | D22: Payback (yr)
A23: 0.6 | B23: =IRR(C75:W75) | C23: =SUM(D75:W75)/Control!$B$15 | D23: =COUNTIF(D76:V76,"<"&Control!$B$15)+1
A24: 0.8 | B24: =IRR(C77:W77) | C24: =SUM(D77:W77)/Control!$B$15 | D24: =COUNTIF(D78:V78,"<"&Control!$B$15)+1
A25: 1 | B25: =IRR(C79:W79) | C25: =SUM(D79:W79)/Control!$B$15 | D25: =COUNTIF(D80:V80,"<"&Control!$B$15)+1
A26: 1.2 | B26: =IRR(C81:W81) | C26: =SUM(D81:W81)/Control!$B$15 | D26: =COUNTIF(D82:V82,"<"&Control!$B$15)+1
A27: 1.4 | B27: =IRR(C83:W83) | C27: =SUM(D83:W83)/Control!$B$15 | D27: =COUNTIF(D84:V84,"<"&Control!$B$15)+1
A29: EXIT PROPERTY GROWTH p.a. (Control!B70)
A30: Exit growth | B30: 20-yr Total IRR | C30: 20-yr Total MOIC | D30: Payback (yr)
A31: 0 | B31: =IRR(C87:W87) | C31: =SUM(D87:W87)/Control!$B$15 | D31: =COUNTIF(D88:V88,"<"&Control!$B$15)+1
A32: 0.03 | B32: =IRR(C89:W89) | C32: =SUM(D89:W89)/Control!$B$15 | D32: =COUNTIF(D90:V90,"<"&Control!$B$15)+1
A33: 0.05 | B33: =IRR(C91:W91) | C33: =SUM(D91:W91)/Control!$B$15 | D33: =COUNTIF(D92:V92,"<"&Control!$B$15)+1
A34: 0.07 | B34: =IRR(C93:W93) | C34: =SUM(D93:W93)/Control!$B$15 | D34: =COUNTIF(D94:V94,"<"&Control!$B$15)+1
A35: 0.09 | B35: =IRR(C95:W95) | C35: =SUM(D95:W95)/Control!$B$15 | D35: =COUNTIF(D96:V96,"<"&Control!$B$15)+1
A38: RISK REGISTER & MITIGANTS
A39: Risk | B39: Why it matters | E39: Mitigant / response
A40: VAT / tax treatment | B40: Can affect net cashflows and transaction structure; turnover (incl. tours) is well over the R1m threshold. | E40: Keep flagged; obtain accountant sign-off before closing.
A41: Property transfer / legal structuring | B41: Transfer duty, VAT, CGT, s42 roll-over and shareholder docs affect execution. | E41: Attorney review and final deal structure before signature.
A42: African Sky operating income vs property value | B42: Operating NOI implies a high value if capitalised directly. | E42: Model adopts a conservative property value; operating upside shown separately.
A43: Tour take-up / supplier cost | B43: Tours materially contribute gross profit (see Tour GP table above). | E43: ASKY Tours Calcs is the source; update supplier costs/take-up as quotes firm up.
A44: Occupancy vs realised history | B44: Model runs 75%; realised bookings imply ~67-71% (see ASKY Stay Calc). | E44: Occupancy table above shows the return at 65-85%.
A45: Winchester expansion optional | B45: Timing/cost risk affects Year 1/2 cashflow only when Winchester expansion is set to Y on Control. | E45: Construction capex and revenue are gated by Control!B7; if N, sensitivity engine excludes Winchester.
A46: Exit growth assumption | B46: Exit NAV grows at the property value growth p.a. assumption (Control!B70); a large part of total return. | E46: Exit-growth table above shows the return at 0-9%.
A49: — live calculation engine below (safe to ignore / can be hidden) —
A51: [calc] Occupancy 0.65 dist | C51: =-Control!$B$15 | D51: =Control!$B$11*(((((((Control!$B$20*$A$7)*((Control!$B$28+Control!$B$29*(Control!$B$38-2))+(Control!$B$32+Control!$B$33*(Control!$B$38-2))+IF(AND(Control!$B$5>0,Control!$B$6="Y",1>=Control!$B$39),Control!$B$36,0))*POWER(1+Control!$B$17,0))+((((Control!$B$20*$A$7)*Control!$B$38*2+IF(AND(Control!$B$5>0,Control!$B$6="Y",1>=Control!$B$39),(Control!$B$20*$A$7)*2,0))*Control!$B$41)*(Control!$B$42+Control!$B$44)*POWER(1+Control!$B$17,0))+(Control!$B$46*POWER(1+Control!$B$17,0)))-(((Control!$B$20*$A$7)*((Control!$B$28+Control!$B$29*(Control!$B$38-2))+(Control!$B$32+Control!$B$33*(Control!$B$38-2))+IF(AND(Control!$B$5>0,Control!$B$6="Y",1>=Control!$B$39),Control!$B$36,0))*POWER(1+Control!$B$17,0))*Control!$B$52+(((Control!$B$20*$A$7)*Control!$B$38*2+IF(AND(Control!$B$5>0,Control!$B$6="Y",1>=Control!$B$39),(Control!$B$20*$A$7)*2,0))*Control!$B$41)*(Control!$B$43+Control!$B$45)*POWER(1+Control!$B$18,0)+Control!$B$47*POWER(1+Control!$B$18,0)+(Control!$B$48+Control!$B$49+Control!$B$50+Control!$B$51)*12*POWER(1+Control!$B$18,0)+((Control!$B$20*$A$7)*((Control!$B$28+Control!$B$29*(Control!$B$38-2))+(Control!$B$32+Control!$B$33*(Control!$B$38-2))+IF(AND(Control!$B$5>0,Control!$B$6="Y",1>=Control!$B$39),Control!$B$36,0))*POWER(1+Control!$B$17,0))*Control!$B$26))+(((Control!$B$54*Control!$B$55+Control!$B$56*Control!$B$57*Control!$B$58*Control!$B$59)*POWER(1+Control!$B$17,0))-((Control!$B$56*Control!$B$57*Control!$B$58*Control!$B$59*POWER(1+Control!$B$17,0))*Control!$B$60+(Control!$B$61+Control!$B$62+Control!$B$63)*12*POWER(1+Control!$B$18,0)+((Control!$B$54*Control!$B$55+Control!$B$56*Control!$B$57*Control!$B$58*Control!$B$59)*POWER(1+Control!$B$17,0))*Control!$B$26))+((Control!$B$65*12*POWER(1+Control!$B$17,0))-((Control!$B$66+Control!$B$67+Control!$B$68)*12*POWER(1+Control!$B$18,0)+(Control!$B$65*12*POWER(1+Control!$B$17,0))*Control!$B$26)))*(1-Control!$B$23))-IF(AND(Control!$B$5>0,Control!$B$6="Y",1=Control!$B$39-1),Control!$B$40,0)) | E51: =Control!$B$11*(((((((Control!$B$20*$A$7)*((Control!$B$28+Control!$B$29*(Control!$B$38-2))+(Control!$B$32+Control!$B$33*(Control!$B$38-2))+IF(AND(Control!$B$5>0,Control!$B$6="Y",2>=Control!$B$39),Control!$B$36,0))*POWER(1+Control!$B$17,1))+((((Control!$B$20*$A$7)*Control!$B$38*2+IF(AND(Control!$B$5>0,Control!$B$6="Y",2>=Control!$B$39),(Control!$B$20*$A$7)*2,0))*Control!$B$41)*(Control!$B$42+Control!$B$44)*POWER(1+Control!$B$17,1))+(Control!$B$46*POWER(1+Control!$B$17,1)))-(((Control!$B$20*$A$7)*((Control!$B$28+Control!$B$29*(Control!$B$38-2))+(Control!$B$32+Control!$B$33*(Control!$B$38-2))+IF(AND(Control!$B$5>0,Control!$B$6="Y",2>=Control!$B$39),Control!$B$36,0))*POWER(1+Control!$B$17,1))*Control!$B$52+(((Control!$B$20*$A$7)*Control!$B$38*2+IF(AND(Control!$B$5>0,Control!$B$6="Y",2>=Control!$B$39),(Control!$B$20*$A$7)*2,0))*Control!$B$41)*(Control!$B$43+Control!$B$45)*POWER(1+Control!$B$18,1)+Control!$B$47*POWER(1+Control!$B$18,1)+(Control!$B$48+Control!$B$49+Control!$B$50+Control!$B$51)*12*POWER(1+Control!$B$18,1)+((Control!$B$20*$A$7)*((Control!$B$28+Control!$B$29*(Control!$B$38-2))+(Control!$B$32+Control!$B$33*(Control!$B$38-2))+IF(AND(Control!$B$5>0,Control!$B$6="Y",2>=Control!$B$39),Control!$B$36,0))*POWER(1+Control!$B$17,1))*Control!$B$26))+(((Control!$B$54*Control!$B$55+Control!$B$56*Control!$B$57*Control!$B$58*Control!$B$59)*POWER(1+Control!$B$17,1))-((Control!$B$56*Control!$B$57*Control!$B$58*Control!$B$59*POWER(1+Control!$B$17,1))*Control!$B$60+(Control!$B$61+Control!$B$62+Control!$B$63)*12*POWER(1+Control!$B$18,1)+((Control!$B$54*Control!$B$55+Control!$B$56*Control!$B$57*Control!$B$58*Control!$B$59)*POWER(1+Control!$B$17,1))*Control!$B$26))+((Control!$B$65*12*POWER(1+Control!$B$17,1))-((Control!$B$66+Control!$B$67+Control!$B$68)*12*POWER(1+Control!$B$18,1)+(Control!$B$65*12*POWER(1+Control!$B$17,1))*Control!$B$26)))*(1-Control!$B$23))-IF(AND(Control!$B$5>0,Control!$B$6="Y",2=Control!$B$39-1),Control!$B$40,0)) | F51: =Control!$B$11*(((((((Control!$B$20*$A$7)*((Control!$B$28+Control!$B$29*(Control!$B$38-2))+(Control!$B$32+Control!$B$33*(Control!$B$38-2))+IF(AND(Control!$B$5>0,Control!$B$6="Y",3>=Control!$B$39),Control!$B$36,0))*POWER(1+Control!$B$17,2))+((((Control!$B$20*$A$7)*Control!$B$38*2+IF(AND(Control!$B$5>0,Control!$B$6="Y",3>=Control!$B$39),(Control!$B$20*$A$7)*2,0))*Control!$B$41)*(Control!$B$42+Control!$B$44)*POWER(1+Control!$B$17,2))+(Control!$B$46*POWER(1+Control!$B$17,2)))-(((Control!$B$20*$A$7)*((Control!$B$28+Control!$B$29*(Control!$B$38-2))+(Control!$B$32+Control!$B$33*(Control!$B$38-2))+IF(AND(Control!$B$5>0,Control!$B$6="Y",3>=Control!$B$39),Control!$B$36,0))*POWER(1+Control!$B$17,2))*Control!$B$52+(((Control!$B$20*$A$7)*Control!$B$38*2+IF(AND(Control!$B$5>0,Control!$B$6="Y",3>=Control!$B$39),(Control!$B$20*$A$7)*2,0))*Control!$B$41)*(Control!$B$43+Control!$B$45)*POWER(1+Control!$B$18,2)+Control!$B$47*POWER(1+Control!$B$18,2)+(Control!$B$48+Control!$B$49+Control!$B$50+Control!$B$51)*12*POWER(1+Control!$B$18,2)+((Control!$B$20*$A$7)*((Control!$B$28+Control!$B$29*(Control!$B$38-2))+(Control!$B$32+Control!$B$33*(Control!$B$38-2))+IF(AND(Control!$B$5>0,Control!$B$6="Y",3>=Control!$B$39),Control!$B$36,0))*POWER(1+Control!$B$17,2))*Control!$B$26))+(((Control!$B$54*Control!$B$55+Control!$B$56*Control!$B$57*Control!$B$58*Control!$B$59)*POWER(1+Control!$B$17,2))-((Control!$B$56*Control!$B$57*Control!$B$58*Control!$B$59*POWER(1+Control!$B$17,2))*Control!$B$60+(Control!$B$61+Control!$B$62+Control!$B$63)*12*POWER(1+Control!$B$18,2)+((Control!$B$54*Control!$B$55+Control!$B$56*Control!$B$57*Control!$B$58*Control!$B$59)*POWER(1+Control!$B$17,2))*Control!$B$26))+((Control!$B$65*12*POWER(1+Control!$B$17,2))-((Control!$B$66+Control!$B$67+Control!$B$68)*12*POWER(1+Control!$B$18,2)+(Control!$B$65*12*POWER(1+Control!$B$17,2))*Control!$B$26)))*(1-Control!$B$23))-IF(AND(Control!$B$5>0,Control!$B$6="Y",3=Control!$B$39-1),Control!$B$40,0)) | G51: =Control!$B$11*(((((((Control!$B$20*$A$7)*((Control!$B$28+Control!$B$29*(Control!$B$38-2))+(Control!$B$32+Control!$B$33*(Control!$B$38-2))+IF(AND(Control!$B$5>0,Control!$B$6="Y",4>=Control!$B$39),Control!$B$36,0))*POWER(1+Control!$B$17,3))+((((Control!$B$20*$A$7)*Control!$B$38*2+IF(AND(Control!$B$5>0,Control!$B$6="Y",4>=Control!$B$39),(Control!$B$20*$A$7)*2,0))*Control!$B$41)*(Control!$B$42+Control!$B$44)*POWER(1+Control!$B$17,3))+(Control!$B$46*POWER(1+Control!$B$17,3)))-(((Control!$B$20*$A$7)*((Control!$B$28+Control!$B$29*(Control!$B$38-2))+(Control!$B$32+Control!$B$33*(Control!$B$38-2))+IF(AND(Control!$B$5>0,Control!$B$6="Y",4>=Control!$B$39),Control!$B$36,0))*POWER(1+Control!$B$17,3))*Control!$B$52+(((Control!$B$20*$A$7)*Control!$B$38*2+IF(AND(Control!$B$5>0,Control!$B$6="Y",4>=Control!$B$39),(Control!$B$20*$A$7)*2,0))*Control!$B$41)*(Control!$B$43+Control!$B$45)*POWER(1+Control!$B$18,3)+Control!$B$47*POWER(1+Control!$B$18,3)+(Control!$B$48+Control!$B$49+Control!$B$50+Control!$B$51)*12*POWER(1+Control!$B$18,3)+((Control!$B$20*$A$7)*((Control!$B$28+Control!$B$29*(Control!$B$38-2))+(Control!$B$32+Control!$B$33*(Control!$B$38-2))+IF(AND(Control!$B$5>0,Control!$B$6="Y",4>=Control!$B$39),Control!$B$36,0))*POWER(1+Control!$B$17,3))*Control!$B$26))+(((Control!$B$54*Control!$B$55+Control!$B$56*Control!$B$57*Control!$B$58*Control!$B$59)*POWER(1+Control!$B$17,3))-((Control!$B$56*Control!$B$57*Control!$B$58*Control!$B$59*POWER(1+Control!$B$17,3))*Control!$B$60+(Control!$B$61+Control!$B$62+Control!$B$63)*12*POWER(1+Control!$B$18,3)+((Control!$B$54*Control!$B$55+Control!$B$56*Control!$B$57*Control!$B$58*Control!$B$59)*POWER(1+Control!$B$17,3))*Control!$B$26))+((Control!$B$65*12*POWER(1+Control!$B$17,3))-((Control!$B$66+Control!$B$67+Control!$B$68)*12*POWER(1+Control!$B$18,3)+(Control!$B$65*12*POWER(1+Control!$B$17,3))*Control!$B$26)))*(1-Control!$B$23))-IF(AND(Control!$B$5>0,Control!$B$6="Y",4=Control!$B$39-1),Control!$B$40,0)) | H51: =Control!$B$11*(((((((Control!$B$20*$A$7)*((Control!$B$28+Control!$B$29*(Control!$B$38-2))+(Control!$B$32+Control!$B$33*(Control!$B$38-2))+IF(AND(Control!$B$5>0,Control!$B$6="Y",5>=Control!$B$39),Control!$B$36,0))*POWER(1+Control!$B$17,4))+((((Control!$B$20*$A$7)*Control!$B$38*2+IF(AND(Control!$B$5>0,Control!$B$6="Y",5>=Control!$B$39),(Control!$B$20*$A$7)*2,0))*Control!$B$41)*(Control!$B$42+Control!$B$44)*POWER(1+Control!$B$17,4))+(Control!$B$46*POWER(1+Control!$B$17,4)))-(((Control!$B$20*$A$7)*((Control!$B$28+Control!$B$29*(Control!$B$38-2))+(Control!$B$32+Control!$B$33*(Control!$B$38-2))+IF(AND(Control!$B$5>0,Control!$B$6="Y",5>=Control!$B$39),Control!$B$36,0))*POWER(1+Control!$B$17,4))*Control!$B$52+(((Control!$B$20*$A$7)*Control!$B$38*2+IF(AND(Control!$B$5>0,Control!$B$6="Y",5>=Control!$B$39),(Control!$B$20*$A$7)*2,0))*Control!$B$41)*(Control!$B$43+Control!$B$45)*POWER(1+Control!$B$18,4)+Control!$B$47*POWER(1+Control!$B$18,4)+(Control!$B$48+Control!$B$49+Control!$B$50+Control!$B$51)*12*POWER(1+Control!$B$18,4)+((Control!$B$20*$A$7)*((Control!$B$28+Control!$B$29*(Control!$B$38-2))+(Control!$B$32+Control!$B$33*(Control!$B$38-2))+IF(AND(Control!$B$5>0,Control!$B$6="Y",5>=Control!$B$39),Control!$B$36,0))*POWER(1+Control!$B$17,4))*Control!$B$26))+(((Control!$B$54*Control!$B$55+Control!$B$56*Control!$B$57*Control!$B$58*Control!$B$59)*POWER(1+Control!$B$17,4))-((Control!$B$56*Control!$B$57*Control!$B$58*Control!$B$59*POWER(1+Control!$B$17,4))*Control!$B$60+(Control!$B$61+Control!$B$62+Control!$B$63)*12*POWER(1+Control!$B$18,4)+((Control!$B$54*Control!$B$55+Control!$B$56*Control!$B$57*Control!$B$58*Control!$B$59)*POWER(1+Control!$B$17,4))*Control!$B$26))+((Control!$B$65*12*POWER(1+Control!$B$17,4))-((Control!$B$66+Control!$B$67+Control!$B$68)*12*POWER(1+Control!$B$18,4)+(Control!$B$65*12*POWER(1+Control!$B$17,4))*Control!$B$26)))*(1-Control!$B$23))-IF(AND(Control!$B$5>0,Control!$B$6="Y",5=Control!$B$39-1),Control!$B$40,0)) | I51: =Control!$B$11*(((((((Control!$B$20*$A$7)*((Control!$B$28+Control!$B$29*(Control!$B$38-2))+(Control!$B$32+Control!$B$33*(Control!$B$38-2))+IF(AND(Control!$B$5>0,Control!$B$6="Y",6>=Control!$B$39),Control!$B$36,0))*POWER(1+Control!$B$17,5))+((((Control!$B$20*$A$7)*Control!$B$38*2+IF(AND(Control!$B$5>0,Control!$B$6="Y",6>=Control!$B$39),(Control!$B$20*$A$7)*2,0))*Control!$B$41)*(Control!$B$42+Control!$B$44)*POWER(1+Control!$B$17,5))+(Control!$B$46*POWER(1+Control!$B$17,5)))-(((Control!$B$20*$A$7)*((Control!$B$28+Control!$B$29*(Control!$B$38-2))+(Control!$B$32+Control!$B$33*(Control!$B$38-2))+IF(AND(Control!$B$5>0,Control!$B$6="Y",6>=Control!$B$39),Control!$B$36,0))*POWER(1+Control!$B$17,5))*Control!$B$52+(((Control!$B$20*$A$7)*Control!$B$38*2+IF(AND(Control!$B$5>0,Control!$B$6="Y",6>=Control!$B$39),(Control!$B$20*$A$7)*2,0))*Control!$B$41)*(Control!$B$43+Control!$B$45)*POWER(1+Control!$B$18,5)+Control!$B$47*POWER(1+Control!$B$18,5)+(Control!$B$48+Control!$B$49+Control!$B$50+Control!$B$51)*12*POWER(1+Control!$B$18,5)+((Control!$B$20*$A$7)*((Control!$B$28+Control!$B$29*(Control!$B$38-2))+(Control!$B$32+Control!$B$33*(Control!$B$38-2))+IF(AND(Control!$B$5>0,Control!$B$6="Y",6>=Control!$B$39),Control!$B$36,0))*POWER(1+Control!$B$17,5))*Control!$B$26))+(((Control!$B$54*Control!$B$55+Control!$B$56*Control!$B$57*Control!$B$58*Control!$B$59)*POWER(1+Control!$B$17,5))-((Control!$B$56*Control!$B$57*Control!$B$58*Control!$B$59*POWER(1+Control!$B$17,5))*Control!$B$60+(Control!$B$61+Control!$B$62+Control!$B$63)*12*POWER(1+Control!$B$18,5)+((Control!$B$54*Control!$B$55+Control!$B$56*Control!$B$57*Control!$B$58*Control!$B$59)*POWER(1+Control!$B$17,5))*Control!$B$26))+((Control!$B$65*12*POWER(1+Control!$B$17,5))-((Control!$B$66+Control!$B$67+Control!$B$68)*12*POWER(1+Control!$B$18,5)+(Control!$B$65*12*POWER(1+Control!$B$17,5))*Control!$B$26)))*(1-Control!$B$23))-IF(AND(Control!$B$5>0,Control!$B$6="Y",6=Control!$B$39-1),Control!$B$40,0)) | J51: =Control!$B$11*(((((((Control!$B$20*$A$7)*((Control!$B$28+Control!$B$29*(Control!$B$38-2))+(Control!$B$32+Control!$B$33*(Control!$B$38-2))+IF(AND(Control!$B$5>0,Control!$B$6="Y",7>=Control!$B$39),Control!$B$36,0))*POWER(1+Control!$B$17,6))+((((Control!$B$20*$A$7)*Control!$B$38*2+IF(AND(Control!$B$5>0,Control!$B$6="Y",7>=Control!$B$39),(Control!$B$20*$A$7)*2,0))*Control!$B$41)*(Control!$B$42+Control!$B$44)*POWER(1+Control!$B$17,6))+(Control!$B$46*POWER(1+Control!$B$17,6)))-(((Control!$B$20*$A$7)*((Control!$B$28+Control!$B$29*(Control!$B$38-2))+(Control!$B$32+Control!$B$33*(Control!$B$38-2))+IF(AND(Control!$B$5>0,Control!$B$6="Y",7>=Control!$B$39),Control!$B$36,0))*POWER(1+Control!$B$17,6))*Control!$B$52+(((Control!$B$20*$A$7)*Control!$B$38*2+IF(AND(Control!$B$5>0,Control!$B$6="Y",7>=Control!$B$39),(Control!$B$20*$A$7)*2,0))*Control!$B$41)*(Control!$B$43+Control!$B$45)*POWER(1+Control!$B$18,6)+Control!$B$47*POWER(1+Control!$B$18,6)+(Control!$B$48+Control!$B$49+Control!$B$50+Control!$B$51)*12*POWER(1+Control!$B$18,6)+((Control!$B$20*$A$7)*((Control!$B$28+Control!$B$29*(Control!$B$38-2))+(Control!$B$32+Control!$B$33*(Control!$B$38-2))+IF(AND(Control!$B$5>0,Control!$B$6="Y",7>=Control!$B$39),Control!$B$36,0))*POWER(1+Control!$B$17,6))*Control!$B$26))+(((Control!$B$54*Control!$B$55+Control!$B$56*Control!$B$57*Control!$B$58*Control!$B$59)*POWER(1+Control!$B$17,6))-((Control!$B$56*Control!$B$57*Control!$B$58*Control!$B$59*POWER(1+Control!$B$17,6))*Control!$B$60+(Control!$B$61+Control!$B$62+Control!$B$63)*12*POWER(1+Control!$B$18,6)+((Control!$B$54*Control!$B$55+Control!$B$56*Control!$B$57*Control!$B$58*Control!$B$59)*POWER(1+Control!$B$17,6))*Control!$B$26))+((Control!$B$65*12*POWER(1+Control!$B$17,6))-((Control!$B$66+Control!$B$67+Control!$B$68)*12*POWER(1+Control!$B$18,6)+(Control!$B$65*12*POWER(1+Control!$B$17,6))*Control!$B$26)))*(1-Control!$B$23))-IF(AND(Control!$B$5>0,Control!$B$6="Y",7=Control!$B$39-1),Control!$B$40,0)) | K51: =Control!$B$11*(((((((Control!$B$20*$A$7)*((Control!$B$28+Control!$B$29*(Control!$B$38-2))+(Control!$B$32+Control!$B$33*(Control!$B$38-2))+IF(AND(Control!$B$5>0,Control!$B$6="Y",8>=Control!$B$39),Control!$B$36,0))*POWER(1+Control!$B$17,7))+((((Control!$B$20*$A$7)*Control!$B$38*2+IF(AND(Control!$B$5>0,Control!$B$6="Y",8>=Control!$B$39),(Control!$B$20*$A$7)*2,0))*Control!$B$41)*(Control!$B$42+Control!$B$44)*POWER(1+Control!$B$17,7))+(Control!$B$46*POWER(1+Control!$B$17,7)))-(((Control!$B$20*$A$7)*((Control!$B$28+Control!$B$29*(Control!$B$38-2))+(Control!$B$32+Control!$B$33*(Control!$B$38-2))+IF(AND(Control!$B$5>0,Control!$B$6="Y",8>=Control!$B$39),Control!$B$36,0))*POWER(1+Control!$B$17,7))*Control!$B$52+(((Control!$B$20*$A$7)*Control!$B$38*2+IF(AND(Control!$B$5>0,Control!$B$6="Y",8>=Control!$B$39),(Control!$B$20*$A$7)*2,0))*Control!$B$41)*(Control!$B$43+Control!$B$45)*POWER(1+Control!$B$18,7)+Control!$B$47*POWER(1+Control!$B$18,7)+(Control!$B$48+Control!$B$49+Control!$B$50+Control!$B$51)*12*POWER(1+Control!$B$18,7)+((Control!$B$20*$A$7)*((Control!$B$28+Control!$B$29*(Control!$B$38-2))+(Control!$B$32+Control!$B$33*(Control!$B$38-2))+IF(AND(Control!$B$5>0,Control!$B$6="Y",8>=Control!$B$39),Control!$B$36,0))*POWER(1+Control!$B$17,7))*Control!$B$26))+(((Control!$B$54*Control!$B$55+Control!$B$56*Control!$B$57*Control!$B$58*Control!$B$59)*POWER(1+Control!$B$17,7))-((Control!$B$56*Control!$B$57*Control!$B$58*Control!$B$59*POWER(1+Control!$B$17,7))*Control!$B$60+(Control!$B$61+Control!$B$62+Control!$B$63)*12*POWER(1+Control!$B$18,7)+((Control!$B$54*Control!$B$55+Control!$B$56*Control!$B$57*Control!$B$58*Control!$B$59)*POWER(1+Control!$B$17,7))*Control!$B$26))+((Control!$B$65*12*POWER(1+Control!$B$17,7))-((Control!$B$66+Control!$B$67+Control!$B$68)*12*POWER(1+Control!$B$18,7)+(Control!$B$65*12*POWER(1+Control!$B$17,7))*Control!$B$26)))*(1-Control!$B$23))-IF(AND(Control!$B$5>0,Control!$B$6="Y",8=Control!$B$39-1),Control!$B$40,0)) | L51: =Control!$B$11*(((((((Control!$B$20*$A$7)*((Control!$B$28+Control!$B$29*(Control!$B$38-2))+(Control!$B$32+Control!$B$33*(Control!$B$38-2))+IF(AND(Control!$B$5>0,Control!$B$6="Y",9>=Control!$B$39),Control!$B$36,0))*POWER(1+Control!$B$17,8))+((((Control!$B$20*$A$7)*Control!$B$38*2+IF(AND(Control!$B$5>0,Control!$B$6="Y",9>=Control!$B$39),(Control!$B$20*$A$7)*2,0))*Control!$B$41)*(Control!$B$42+Control!$B$44)*POWER(1+Control!$B$17,8))+(Control!$B$46*POWER(1+Control!$B$17,8)))-(((Control!$B$20*$A$7)*((Control!$B$28+Control!$B$29*(Control!$B$38-2))+(Control!$B$32+Control!$B$33*(Control!$B$38-2))+IF(AND(Control!$B$5>0,Control!$B$6="Y",9>=Control!$B$39),Control!$B$36,0))*POWER(1+Control!$B$17,8))*Control!$B$52+(((Control!$B$20*$A$7)*Control!$B$38*2+IF(AND(Control!$B$5>0,Control!$B$6="Y",9>=Control!$B$39),(Control!$B$20*$A$7)*2,0))*Control!$B$41)*(Control!$B$43+Control!$B$45)*POWER(1+Control!$B$18,8)+Control!$B$47*POWER(1+Control!$B$18,8)+(Control!$B$48+Control!$B$49+Control!$B$50+Control!$B$51)*12*POWER(1+Control!$B$18,8)+((Control!$B$20*$A$7)*((Control!$B$28+Control!$B$29*(Control!$B$38-2))+(Control!$B$32+Control!$B$33*(Control!$B$38-2))+IF(AND(Control!$B$5>0,Control!$B$6="Y",9>=Control!$B$39),Control!$B$36,0))*POWER(1+Control!$B$17,8))*Control!$B$26))+(((Control!$B$54*Control!$B$55+Control!$B$56*Control!$B$57*Control!$B$58*Control!$B$59)*POWER(1+Control!$B$17,8))-((Control!$B$56*Control!$B$57*Control!$B$58*Control!$B$59*POWER(1+Control!$B$17,8))*Control!$B$60+(Control!$B$61+Control!$B$62+Control!$B$63)*12*POWER(1+Control!$B$18,8)+((Control!$B$54*Control!$B$55+Control!$B$56*Control!$B$57*Control!$B$58*Control!$B$59)*POWER(1+Control!$B$17,8))*Control!$B$26))+((Control!$B$65*12*POWER(1+Control!$B$17,8))-((Control!$B$66+Control!$B$67+Control!$B$68)*12*POWER(1+Control!$B$18,8)+(Control!$B$65*12*POWER(1+Control!$B$17,8))*Control!$B$26)))*(1-Control!$B$23))-IF(AND(Control!$B$5>0,Control!$B$6="Y",9=Control!$B$39-1),Control!$B$40,0)) | M51: =Control!$B$11*(((((((Control!$B$20*$A$7)*((Control!$B$28+Control!$B$29*(Control!$B$38-2))+(Control!$B$32+Control!$B$33*(Control!$B$38-2))+IF(AND(Control!$B$5>0,Control!$B$6="Y",10>=Control!$B$39),Control!$B$36,0))*POWER(1+Control!$B$17,9))+((((Control!$B$20*$A$7)*Control!$B$38*2+IF(AND(Control!$B$5>0,Control!$B$6="Y",10>=Control!$B$39),(Control!$B$20*$A$7)*2,0))*Control!$B$41)*(Control!$B$42+Control!$B$44)*POWER(1+Control!$B$17,9))+(Control!$B$46*POWER(1+Control!$B$17,9)))-(((Control!$B$20*$A$7)*((Control!$B$28+Control!$B$29*(Control!$B$38-2))+(Control!$B$32+Control!$B$33*(Control!$B$38-2))+IF(AND(Control!$B$5>0,Control!$B$6="Y",10>=Control!$B$39),Control!$B$36,0))*POWER(1+Control!$B$17,9))*Control!$B$52+(((Control!$B$20*$A$7)*Control!$B$38*2+IF(AND(Control!$B$5>0,Control!$B$6="Y",10>=Control!$B$39),(Control!$B$20*$A$7)*2,0))*Control!$B$41)*(Control!$B$43+Control!$B$45)*POWER(1+Control!$B$18,9)+Control!$B$47*POWER(1+Control!$B$18,9)+(Control!$B$48+Control!$B$49+Control!$B$50+Control!$B$51)*12*POWER(1+Control!$B$18,9)+((Control!$B$20*$A$7)*((Control!$B$28+Control!$B$29*(Control!$B$38-2))+(Control!$B$32+Control!$B$33*(Control!$B$38-2))+IF(AND(Control!$B$5>0,Control!$B$6="Y",10>=Control!$B$39),Control!$B$36,0))*POWER(1+Control!$B$17,9))*Control!$B$26))+(((Control!$B$54*Control!$B$55+Control!$B$56*Control!$B$57*Control!$B$58*Control!$B$59)*POWER(1+Control!$B$17,9))-((Control!$B$56*Control!$B$57*Control!$B$58*Control!$B$59*POWER(1+Control!$B$17,9))*Control!$B$60+(Control!$B$61+Control!$B$62+Control!$B$63)*12*POWER(1+Control!$B$18,9)+((Control!$B$54*Control!$B$55+Control!$B$56*Control!$B$57*Control!$B$58*Control!$B$59)*POWER(1+Control!$B$17,9))*Control!$B$26))+((Control!$B$65*12*POWER(1+Control!$B$17,9))-((Control!$B$66+Control!$B$67+Control!$B$68)*12*POWER(1+Control!$B$18,9)+(Control!$B$65*12*POWER(1+Control!$B$17,9))*Control!$B$26)))*(1-Control!$B$23))-IF(AND(Control!$B$5>0,Control!$B$6="Y",10=Control!$B$39-1),Control!$B$40,0)) | N51: =Control!$B$11*(((((((Control!$B$20*$A$7)*((Control!$B$28+Control!$B$29*(Control!$B$38-2))+(Control!$B$32+Control!$B$33*(Control!$B$38-2))+IF(AND(Control!$B$5>0,Control!$B$6="Y",11>=Control!$B$39),Control!$B$36,0))*POWER(1+Control!$B$17,10))+((((Control!$B$20*$A$7)*Control!$B$38*2+IF(AND(Control!$B$5>0,Control!$B$6="Y",11>=Control!$B$39),(Control!$B$20*$A$7)*2,0))*Control!$B$41)*(Control!$B$42+Control!$B$44)*POWER(1+Control!$B$17,10))+(Control!$B$46*POWER(1+Control!$B$17,10)))-(((Control!$B$20*$A$7)*((Control!$B$28+Control!$B$29*(Control!$B$38-2))+(Control!$B$32+Control!$B$33*(Control!$B$38-2))+IF(AND(Control!$B$5>0,Control!$B$6="Y",11>=Control!$B$39),Control!$B$36,0))*POWER(1+Control!$B$17,10))*Control!$B$52+(((Control!$B$20*$A$7)*Control!$B$38*2+IF(AND(Control!$B$5>0,Control!$B$6="Y",11>=Control!$B$39),(Control!$B$20*$A$7)*2,0))*Control!$B$41)*(Control!$B$43+Control!$B$45)*POWER(1+Control!$B$18,10)+Control!$B$47*POWER(1+Control!$B$18,10)+(Control!$B$48+Control!$B$49+Control!$B$50+Control!$B$51)*12*POWER(1+Control!$B$18,10)+((Control!$B$20*$A$7)*((Control!$B$28+Control!$B$29*(Control!$B$38-2))+(Control!$B$32+Control!$B$33*(Control!$B$38-2))+IF(AND(Control!$B$5>0,Control!$B$6="Y",11>=Control!$B$39),Control!$B$36,0))*POWER(1+Control!$B$17,10))*Control!$B$26))+(((Control!$B$54*Control!$B$55+Control!$B$56*Control!$B$57*Control!$B$58*Control!$B$59)*POWER(1+Control!$B$17,10))-((Control!$B$56*Control!$B$57*Control!$B$58*Control!$B$59*POWER(1+Control!$B$17,10))*Control!$B$60+(Control!$B$61+Control!$B$62+Control!$B$63)*12*POWER(1+Control!$B$18,10)+((Control!$B$54*Control!$B$55+Control!$B$56*Control!$B$57*Control!$B$58*Control!$B$59)*POWER(1+Control!$B$17,10))*Control!$B$26))+((Control!$B$65*12*POWER(1+Control!$B$17,10))-((Control!$B$66+Control!$B$67+Control!$B$68)*12*POWER(1+Control!$B$18,10)+(Control!$B$65*12*POWER(1+Control!$B$17,10))*Control!$B$26)))*(1-Control!$B$23))-IF(AND(Control!$B$5>0,Control!$B$6="Y",11=Control!$B$39-1),Control!$B$40,0)) | O51: =Control!$B$11*(((((((Control!$B$20*$A$7)*((Control!$B$28+Control!$B$29*(Control!$B$38-2))+(Control!$B$32+Control!$B$33*(Control!$B$38-2))+IF(AND(Control!$B$5>0,Control!$B$6="Y",12>=Control!$B$39),Control!$B$36,0))*POWER(1+Control!$B$17,11))+((((Control!$B$20*$A$7)*Control!$B$38*2+IF(AND(Control!$B$5>0,Control!$B$6="Y",12>=Control!$B$39),(Control!$B$20*$A$7)*2,0))*Control!$B$41)*(Control!$B$42+Control!$B$44)*POWER(1+Control!$B$17,11))+(Control!$B$46*POWER(1+Control!$B$17,11)))-(((Control!$B$20*$A$7)*((Control!$B$28+Control!$B$29*(Control!$B$38-2))+(Control!$B$32+Control!$B$33*(Control!$B$38-2))+IF(AND(Control!$B$5>0,Control!$B$6="Y",12>=Control!$B$39),Control!$B$36,0))*POWER(1+Control!$B$17,11))*Control!$B$52+(((Control!$B$20*$A$7)*Control!$B$38*2+IF(AND(Control!$B$5>0,Control!$B$6="Y",12>=Control!$B$39),(Control!$B$20*$A$7)*2,0))*Control!$B$41)*(Control!$B$43+Control!$B$45)*POWER(1+Control!$B$18,11)+Control!$B$47*POWER(1+Control!$B$18,11)+(Control!$B$48+Control!$B$49+Control!$B$50+Control!$B$51)*12*POWER(1+Control!$B$18,11)+((Control!$B$20*$A$7)*((Control!$B$28+Control!$B$29*(Control!$B$38-2))+(Control!$B$32+Control!$B$33*(Control!$B$38-2))+IF(AND(Control!$B$5>0,Control!$B$6="Y",12>=Control!$B$39),Control!$B$36,0))*POWER(1+Control!$B$17,11))*Control!$B$26))+(((Control!$B$54*Control!$B$55+Control!$B$56*Control!$B$57*Control!$B$58*Control!$B$59)*POWER(1+Control!$B$17,11))-((Control!$B$56*Control!$B$57*Control!$B$58*Control!$B$59*POWER(1+Control!$B$17,11))*Control!$B$60+(Control!$B$61+Control!$B$62+Control!$B$63)*12*POWER(1+Control!$B$18,11)+((Control!$B$54*Control!$B$55+Control!$B$56*Control!$B$57*Control!$B$58*Control!$B$59)*POWER(1+Control!$B$17,11))*Control!$B$26))+((Control!$B$65*12*POWER(1+Control!$B$17,11))-((Control!$B$66+Control!$B$67+Control!$B$68)*12*POWER(1+Control!$B$18,11)+(Control!$B$65*12*POWER(1+Control!$B$17,11))*Control!$B$26)))*(1-Control!$B$23))-IF(AND(Control!$B$5>0,Control!$B$6="Y",12=Control!$B$39-1),Control!$B$40,0)) | P51: =Control!$B$11*(((((((Control!$B$20*$A$7)*((Control!$B$28+Control!$B$29*(Control!$B$38-2))+(Control!$B$32+Control!$B$33*(Control!$B$38-2))+IF(AND(Control!$B$5>0,Control!$B$6="Y",13>=Control!$B$39),Control!$B$36,0))*POWER(1+Control!$B$17,12))+((((Control!$B$20*$A$7)*Control!$B$38*2+IF(AND(Control!$B$5>0,Control!$B$6="Y",13>=Control!$B$39),(Control!$B$20*$A$7)*2,0))*Control!$B$41)*(Control!$B$42+Control!$B$44)*POWER(1+Control!$B$17,12))+(Control!$B$46*POWER(1+Control!$B$17,12)))-(((Control!$B$20*$A$7)*((Control!$B$28+Control!$B$29*(Control!$B$38-2))+(Control!$B$32+Control!$B$33*(Control!$B$38-2))+IF(AND(Control!$B$5>0,Control!$B$6="Y",13>=Control!$B$39),Control!$B$36,0))*POWER(1+Control!$B$17,12))*Control!$B$52+(((Control!$B$20*$A$7)*Control!$B$38*2+IF(AND(Control!$B$5>0,Control!$B$6="Y",13>=Control!$B$39),(Control!$B$20*$A$7)*2,0))*Control!$B$41)*(Control!$B$43+Control!$B$45)*POWER(1+Control!$B$18,12)+Control!$B$47*POWER(1+Control!$B$18,12)+(Control!$B$48+Control!$B$49+Control!$B$50+Control!$B$51)*12*POWER(1+Control!$B$18,12)+((Control!$B$20*$A$7)*((Control!$B$28+Control!$B$29*(Control!$B$38-2))+(Control!$B$32+Control!$B$33*(Control!$B$38-2))+IF(AND(Control!$B$5>0,Control!$B$6="Y",13>=Control!$B$39),Control!$B$36,0))*POWER(1+Control!$B$17,12))*Control!$B$26))+(((Control!$B$54*Control!$B$55+Control!$B$56*Control!$B$57*Control!$B$58*Control!$B$59)*POWER(1+Control!$B$17,12))-((Control!$B$56*Control!$B$57*Control!$B$58*Control!$B$59*POWER(1+Control!$B$17,12))*Control!$B$60+(Control!$B$61+Control!$B$62+Control!$B$63)*12*POWER(1+Control!$B$18,12)+((Control!$B$54*Control!$B$55+Control!$B$56*Control!$B$57*Control!$B$58*Control!$B$59)*POWER(1+Control!$B$17,12))*Control!$B$26))+((Control!$B$65*12*POWER(1+Control!$B$17,12))-((Control!$B$66+Control!$B$67+Control!$B$68)*12*POWER(1+Control!$B$18,12)+(Control!$B$65*12*POWER(1+Control!$B$17,12))*Control!$B$26)))*(1-Control!$B$23))-IF(AND(Control!$B$5>0,Control!$B$6="Y",13=Control!$B$39-1),Control!$B$40,0)) | Q51: =Control!$B$11*(((((((Control!$B$20*$A$7)*((Control!$B$28+Control!$B$29*(Control!$B$38-2))+(Control!$B$32+Control!$B$33*(Control!$B$38-2))+IF(AND(Control!$B$5>0,Control!$B$6="Y",14>=Control!$B$39),Control!$B$36,0))*POWER(1+Control!$B$17,13))+((((Control!$B$20*$A$7)*Control!$B$38*2+IF(AND(Control!$B$5>0,Control!$B$6="Y",14>=Control!$B$39),(Control!$B$20*$A$7)*2,0))*Control!$B$41)*(Control!$B$42+Control!$B$44)*POWER(1+Control!$B$17,13))+(Control!$B$46*POWER(1+Control!$B$17,13)))-(((Control!$B$20*$A$7)*((Control!$B$28+Control!$B$29*(Control!$B$38-2))+(Control!$B$32+Control!$B$33*(Control!$B$38-2))+IF(AND(Control!$B$5>0,Control!$B$6="Y",14>=Control!$B$39),Control!$B$36,0))*POWER(1+Control!$B$17,13))*Control!$B$52+(((Control!$B$20*$A$7)*Control!$B$38*2+IF(AND(Control!$B$5>0,Control!$B$6="Y",14>=Control!$B$39),(Control!$B$20*$A$7)*2,0))*Control!$B$41)*(Control!$B$43+Control!$B$45)*POWER(1+Control!$B$18,13)+Control!$B$47*POWER(1+Control!$B$18,13)+(Control!$B$48+Control!$B$49+Control!$B$50+Control!$B$51)*12*POWER(1+Control!$B$18,13)+((Control!$B$20*$A$7)*((Control!$B$28+Control!$B$29*(Control!$B$38-2))+(Control!$B$32+Control!$B$33*(Control!$B$38-2))+IF(AND(Control!$B$5>0,Control!$B$6="Y",14>=Control!$B$39),Control!$B$36,0))*POWER(1+Control!$B$17,13))*Control!$B$26))+(((Control!$B$54*Control!$B$55+Control!$B$56*Control!$B$57*Control!$B$58*Control!$B$59)*POWER(1+Control!$B$17,13))-((Control!$B$56*Control!$B$57*Control!$B$58*Control!$B$59*POWER(1+Control!$B$17,13))*Control!$B$60+(Control!$B$61+Control!$B$62+Control!$B$63)*12*POWER(1+Control!$B$18,13)+((Control!$B$54*Control!$B$55+Control!$B$56*Control!$B$57*Control!$B$58*Control!$B$59)*POWER(1+Control!$B$17,13))*Control!$B$26))+((Control!$B$65*12*POWER(1+Control!$B$17,13))-((Control!$B$66+Control!$B$67+Control!$B$68)*12*POWER(1+Control!$B$18,13)+(Control!$B$65*12*POWER(1+Control!$B$17,13))*Control!$B$26)))*(1-Control!$B$23))-IF(AND(Control!$B$5>0,Control!$B$6="Y",14=Control!$B$39-1),Control!$B$40,0)) | R51: =Control!$B$11*(((((((Control!$B$20*$A$7)*((Control!$B$28+Control!$B$29*(Control!$B$38-2))+(Control!$B$32+Control!$B$33*(Control!$B$38-2))+IF(AND(Control!$B$5>0,Control!$B$6="Y",15>=Control!$B$39),Control!$B$36,0))*POWER(1+Control!$B$17,14))+((((Control!$B$20*$A$7)*Control!$B$38*2+IF(AND(Control!$B$5>0,Control!$B$6="Y",15>=Control!$B$39),(Control!$B$20*$A$7)*2,0))*Control!$B$41)*(Control!$B$42+Control!$B$44)*POWER(1+Control!$B$17,14))+(Control!$B$46*POWER(1+Control!$B$17,14)))-(((Control!$B$20*$A$7)*((Control!$B$28+Control!$B$29*(Control!$B$38-2))+(Control!$B$32+Control!$B$33*(Control!$B$38-2))+IF(AND(Control!$B$5>0,Control!$B$6="Y",15>=Control!$B$39),Control!$B$36,0))*POWER(1+Control!$B$17,14))*Control!$B$52+(((Control!$B$20*$A$7)*Control!$B$38*2+IF(AND(Control!$B$5>0,Control!$B$6="Y",15>=Control!$B$39),(Control!$B$20*$A$7)*2,0))*Control!$B$41)*(Control!$B$43+Control!$B$45)*POWER(1+Control!$B$18,14)+Control!$B$47*POWER(1+Control!$B$18,14)+(Control!$B$48+Control!$B$49+Control!$B$50+Control!$B$51)*12*POWER(1+Control!$B$18,14)+((Control!$B$20*$A$7)*((Control!$B$28+Control!$B$29*(Control!$B$38-2))+(Control!$B$32+Control!$B$33*(Control!$B$38-2))+IF(AND(Control!$B$5>0,Control!$B$6="Y",15>=Control!$B$39),Control!$B$36,0))*POWER(1+Control!$B$17,14))*Control!$B$26))+(((Control!$B$54*Control!$B$55+Control!$B$56*Control!$B$57*Control!$B$58*Control!$B$59)*POWER(1+Control!$B$17,14))-((Control!$B$56*Control!$B$57*Control!$B$58*Control!$B$59*POWER(1+Control!$B$17,14))*Control!$B$60+(Control!$B$61+Control!$B$62+Control!$B$63)*12*POWER(1+Control!$B$18,14)+((Control!$B$54*Control!$B$55+Control!$B$56*Control!$B$57*Control!$B$58*Control!$B$59)*POWER(1+Control!$B$17,14))*Control!$B$26))+((Control!$B$65*12*POWER(1+Control!$B$17,14))-((Control!$B$66+Control!$B$67+Control!$B$68)*12*POWER(1+Control!$B$18,14)+(Control!$B$65*12*POWER(1+Control!$B$17,14))*Control!$B$26)))*(1-Control!$B$23))-IF(AND(Control!$B$5>0,Control!$B$6="Y",15=Control!$B$39-1),Control!$B$40,0)) | S51: =Control!$B$11*(((((((Control!$B$20*$A$7)*((Control!$B$28+Control!$B$29*(Control!$B$38-2))+(Control!$B$32+Control!$B$33*(Control!$B$38-2))+IF(AND(Control!$B$5>0,Control!$B$6="Y",16>=Control!$B$39),Control!$B$36,0))*POWER(1+Control!$B$17,15))+((((Control!$B$20*$A$7)*Control!$B$38*2+IF(AND(Control!$B$5>0,Control!$B$6="Y",16>=Control!$B$39),(Control!$B$20*$A$7)*2,0))*Control!$B$41)*(Control!$B$42+Control!$B$44)*POWER(1+Control!$B$17,15))+(Control!$B$46*POWER(1+Control!$B$17,15)))-(((Control!$B$20*$A$7)*((Control!$B$28+Control!$B$29*(Control!$B$38-2))+(Control!$B$32+Control!$B$33*(Control!$B$38-2))+IF(AND(Control!$B$5>0,Control!$B$6="Y",16>=Control!$B$39),Control!$B$36,0))*POWER(1+Control!$B$17,15))*Control!$B$52+(((Control!$B$20*$A$7)*Control!$B$38*2+IF(AND(Control!$B$5>0,Control!$B$6="Y",16>=Control!$B$39),(Control!$B$20*$A$7)*2,0))*Control!$B$41)*(Control!$B$43+Control!$B$45)*POWER(1+Control!$B$18,15)+Control!$B$47*POWER(1+Control!$B$18,15)+(Control!$B$48+Control!$B$49+Control!$B$50+Control!$B$51)*12*POWER(1+Control!$B$18,15)+((Control!$B$20*$A$7)*((Control!$B$28+Control!$B$29*(Control!$B$38-2))+(Control!$B$32+Control!$B$33*(Control!$B$38-2))+IF(AND(Control!$B$5>0,Control!$B$6="Y",16>=Control!$B$39),Control!$B$36,0))*POWER(1+Control!$B$17,15))*Control!$B$26))+(((Control!$B$54*Control!$B$55+Control!$B$56*Control!$B$57*Control!$B$58*Control!$B$59)*POWER(1+Control!$B$17,15))-((Control!$B$56*Control!$B$57*Control!$B$58*Control!$B$59*POWER(1+Control!$B$17,15))*Control!$B$60+(Control!$B$61+Control!$B$62+Control!$B$63)*12*POWER(1+Control!$B$18,15)+((Control!$B$54*Control!$B$55+Control!$B$56*Control!$B$57*Control!$B$58*Control!$B$59)*POWER(1+Control!$B$17,15))*Control!$B$26))+((Control!$B$65*12*POWER(1+Control!$B$17,15))-((Control!$B$66+Control!$B$67+Control!$B$68)*12*POWER(1+Control!$B$18,15)+(Control!$B$65*12*POWER(1+Control!$B$17,15))*Control!$B$26)))*(1-Control!$B$23))-IF(AND(Control!$B$5>0,Control!$B$6="Y",16=Control!$B$39-1),Control!$B$40,0)) | T51: =Control!$B$11*(((((((Control!$B$20*$A$7)*((Control!$B$28+Control!$B$29*(Control!$B$38-2))+(Control!$B$32+Control!$B$33*(Control!$B$38-2))+IF(AND(Control!$B$5>0,Control!$B$6="Y",17>=Control!$B$39),Control!$B$36,0))*POWER(1+Control!$B$17,16))+((((Control!$B$20*$A$7)*Control!$B$38*2+IF(AND(Control!$B$5>0,Control!$B$6="Y",17>=Control!$B$39),(Control!$B$20*$A$7)*2,0))*Control!$B$41)*(Control!$B$42+Control!$B$44)*POWER(1+Control!$B$17,16))+(Control!$B$46*POWER(1+Control!$B$17,16)))-(((Control!$B$20*$A$7)*((Control!$B$28+Control!$B$29*(Control!$B$38-2))+(Control!$B$32+Control!$B$33*(Control!$B$38-2))+IF(AND(Control!$B$5>0,Control!$B$6="Y",17>=Control!$B$39),Control!$B$36,0))*POWER(1+Control!$B$17,16))*Control!$B$52+(((Control!$B$20*$A$7)*Control!$B$38*2+IF(AND(Control!$B$5>0,Control!$B$6="Y",17>=Control!$B$39),(Control!$B$20*$A$7)*2,0))*Control!$B$41)*(Control!$B$43+Control!$B$45)*POWER(1+Control!$B$18,16)+Control!$B$47*POWER(1+Control!$B$18,16)+(Control!$B$48+Control!$B$49+Control!$B$50+Control!$B$51)*12*POWER(1+Control!$B$18,16)+((Control!$B$20*$A$7)*((Control!$B$28+Control!$B$29*(Control!$B$38-2))+(Control!$B$32+Control!$B$33*(Control!$B$38-2))+IF(AND(Control!$B$5>0,Control!$B$6="Y",17>=Control!$B$39),Control!$B$36,0))*POWER(1+Control!$B$17,16))*Control!$B$26))+(((Control!$B$54*Control!$B$55+Control!$B$56*Control!$B$57*Control!$B$58*Control!$B$59)*POWER(1+Control!$B$17,16))-((Control!$B$56*Control!$B$57*Control!$B$58*Control!$B$59*POWER(1+Control!$B$17,16))*Control!$B$60+(Control!$B$61+Control!$B$62+Control!$B$63)*12*POWER(1+Control!$B$18,16)+((Control!$B$54*Control!$B$55+Control!$B$56*Control!$B$57*Control!$B$58*Control!$B$59)*POWER(1+Control!$B$17,16))*Control!$B$26))+((Control!$B$65*12*POWER(1+Control!$B$17,16))-((Control!$B$66+Control!$B$67+Control!$B$68)*12*POWER(1+Control!$B$18,16)+(Control!$B$65*12*POWER(1+Control!$B$17,16))*Control!$B$26)))*(1-Control!$B$23))-IF(AND(Control!$B$5>0,Control!$B$6="Y",17=Control!$B$39-1),Control!$B$40,0)) | U51: =Control!$B$11*(((((((Control!$B$20*$A$7)*((Control!$B$28+Control!$B$29*(Control!$B$38-2))+(Control!$B$32+Control!$B$33*(Control!$B$38-2))+IF(AND(Control!$B$5>0,Control!$B$6="Y",18>=Control!$B$39),Control!$B$36,0))*POWER(1+Control!$B$17,17))+((((Control!$B$20*$A$7)*Control!$B$38*2+IF(AND(Control!$B$5>0,Control!$B$6="Y",18>=Control!$B$39),(Control!$B$20*$A$7)*2,0))*Control!$B$41)*(Control!$B$42+Control!$B$44)*POWER(1+Control!$B$17,17))+(Control!$B$46*POWER(1+Control!$B$17,17)))-(((Control!$B$20*$A$7)*((Control!$B$28+Control!$B$29*(Control!$B$38-2))+(Control!$B$32+Control!$B$33*(Control!$B$38-2))+IF(AND(Control!$B$5>0,Control!$B$6="Y",18>=Control!$B$39),Control!$B$36,0))*POWER(1+Control!$B$17,17))*Control!$B$52+(((Control!$B$20*$A$7)*Control!$B$38*2+IF(AND(Control!$B$5>0,Control!$B$6="Y",18>=Control!$B$39),(Control!$B$20*$A$7)*2,0))*Control!$B$41)*(Control!$B$43+Control!$B$45)*POWER(1+Control!$B$18,17)+Control!$B$47*POWER(1+Control!$B$18,17)+(Control!$B$48+Control!$B$49+Control!$B$50+Control!$B$51)*12*POWER(1+Control!$B$18,17)+((Control!$B$20*$A$7)*((Control!$B$28+Control!$B$29*(Control!$B$38-2))+(Control!$B$32+Control!$B$33*(Control!$B$38-2))+IF(AND(Control!$B$5>0,Control!$B$6="Y",18>=Control!$B$39),Control!$B$36,0))*POWER(1+Control!$B$17,17))*Control!$B$26))+(((Control!$B$54*Control!$B$55+Control!$B$56*Control!$B$57*Control!$B$58*Control!$B$59)*POWER(1+Control!$B$17,17))-((Control!$B$56*Control!$B$57*Control!$B$58*Control!$B$59*POWER(1+Control!$B$17,17))*Control!$B$60+(Control!$B$61+Control!$B$62+Control!$B$63)*12*POWER(1+Control!$B$18,17)+((Control!$B$54*Control!$B$55+Control!$B$56*Control!$B$57*Control!$B$58*Control!$B$59)*POWER(1+Control!$B$17,17))*Control!$B$26))+((Control!$B$65*12*POWER(1+Control!$B$17,17))-((Control!$B$66+Control!$B$67+Control!$B$68)*12*POWER(1+Control!$B$18,17)+(Control!$B$65*12*POWER(1+Control!$B$17,17))*Control!$B$26)))*(1-Control!$B$23))-IF(AND(Control!$B$5>0,Control!$B$6="Y",18=Control!$B$39-1),Control!$B$40,0)) | V51: =Control!$B$11*(((((((Control!$B$20*$A$7)*((Control!$B$28+Control!$B$29*(Control!$B$38-2))+(Control!$B$32+Control!$B$33*(Control!$B$38-2))+IF(AND(Control!$B$5>0,Control!$B$6="Y",19>=Control!$B$39),Control!$B$36,0))*POWER(1+Control!$B$17,18))+((((Control!$B$20*$A$7)*Control!$B$38*2+IF(AND(Control!$B$5>0,Control!$B$6="Y",19>=Control!$B$39),(Control!$B$20*$A$7)*2,0))*Control!$B$41)*(Control!$B$42+Control!$B$44)*POWER(1+Control!$B$17,18))+(Control!$B$46*POWER(1+Control!$B$17,18)))-(((Control!$B$20*$A$7)*((Control!$B$28+Control!$B$29*(Control!$B$38-2))+(Control!$B$32+Control!$B$33*(Control!$B$38-2))+IF(AND(Control!$B$5>0,Control!$B$6="Y",19>=Control!$B$39),Control!$B$36,0))*POWER(1+Control!$B$17,18))*Control!$B$52+(((Control!$B$20*$A$7)*Control!$B$38*2+IF(AND(Control!$B$5>0,Control!$B$6="Y",19>=Control!$B$39),(Control!$B$20*$A$7)*2,0))*Control!$B$41)*(Control!$B$43+Control!$B$45)*POWER(1+Control!$B$18,18)+Control!$B$47*POWER(1+Control!$B$18,18)+(Control!$B$48+Control!$B$49+Control!$B$50+Control!$B$51)*12*POWER(1+Control!$B$18,18)+((Control!$B$20*$A$7)*((Control!$B$28+Control!$B$29*(Control!$B$38-2))+(Control!$B$32+Control!$B$33*(Control!$B$38-2))+IF(AND(Control!$B$5>0,Control!$B$6="Y",19>=Control!$B$39),Control!$B$36,0))*POWER(1+Control!$B$17,18))*Control!$B$26))+(((Control!$B$54*Control!$B$55+Control!$B$56*Control!$B$57*Control!$B$58*Control!$B$59)*POWER(1+Control!$B$17,18))-((Control!$B$56*Control!$B$57*Control!$B$58*Control!$B$59*POWER(1+Control!$B$17,18))*Control!$B$60+(Control!$B$61+Control!$B$62+Control!$B$63)*12*POWER(1+Control!$B$18,18)+((Control!$B$54*Control!$B$55+Control!$B$56*Control!$B$57*Control!$B$58*Control!$B$59)*POWER(1+Control!$B$17,18))*Control!$B$26))+((Control!$B$65*12*POWER(1+Control!$B$17,18))-((Control!$B$66+Control!$B$67+Control!$B$68)*12*POWER(1+Control!$B$18,18)+(Control!$B$65*12*POWER(1+Control!$B$17,18))*Control!$B$26)))*(1-Control!$B$23))-IF(AND(Control!$B$5>0,Control!$B$6="Y",19=Control!$B$39-1),Control!$B$40,0)) | W51: =Control!$B$11*(((((((Control!$B$20*$A$7)*((Control!$B$28+Control!$B$29*(Control!$B$38-2))+(Control!$B$32+Control!$B$33*(Control!$B$38-2))+IF(AND(Control!$B$5>0,Control!$B$6="Y",20>=Control!$B$39),Control!$B$36,0))*POWER(1+Control!$B$17,19))+((((Control!$B$20*$A$7)*Control!$B$38*2+IF(AND(Control!$B$5>0,Control!$B$6="Y",20>=Control!$B$39),(Control!$B$20*$A$7)*2,0))*Control!$B$41)*(Control!$B$42+Control!$B$44)*POWER(1+Control!$B$17,19))+(Control!$B$46*POWER(1+Control!$B$17,19)))-(((Control!$B$20*$A$7)*((Control!$B$28+Control!$B$29*(Control!$B$38-2))+(Control!$B$32+Control!$B$33*(Control!$B$38-2))+IF(AND(Control!$B$5>0,Control!$B$6="Y",20>=Control!$B$39),Control!$B$36,0))*POWER(1+Control!$B$17,19))*Control!$B$52+(((Control!$B$20*$A$7)*Control!$B$38*2+IF(AND(Control!$B$5>0,Control!$B$6="Y",20>=Control!$B$39),(Control!$B$20*$A$7)*2,0))*Control!$B$41)*(Control!$B$43+Control!$B$45)*POWER(1+Control!$B$18,19)+Control!$B$47*POWER(1+Control!$B$18,19)+(Control!$B$48+Control!$B$49+Control!$B$50+Control!$B$51)*12*POWER(1+Control!$B$18,19)+((Control!$B$20*$A$7)*((Control!$B$28+Control!$B$29*(Control!$B$38-2))+(Control!$B$32+Control!$B$33*(Control!$B$38-2))+IF(AND(Control!$B$5>0,Control!$B$6="Y",20>=Control!$B$39),Control!$B$36,0))*POWER(1+Control!$B$17,19))*Control!$B$26))+(((Control!$B$54*Control!$B$55+Control!$B$56*Control!$B$57*Control!$B$58*Control!$B$59)*POWER(1+Control!$B$17,19))-((Control!$B$56*Control!$B$57*Control!$B$58*Control!$B$59*POWER(1+Control!$B$17,19))*Control!$B$60+(Control!$B$61+Control!$B$62+Control!$B$63)*12*POWER(1+Control!$B$18,19)+((Control!$B$54*Control!$B$55+Control!$B$56*Control!$B$57*Control!$B$58*Control!$B$59)*POWER(1+Control!$B$17,19))*Control!$B$26))+((Control!$B$65*12*POWER(1+Control!$B$17,19))-((Control!$B$66+Control!$B$67+Control!$B$68)*12*POWER(1+Control!$B$18,19)+(Control!$B$65*12*POWER(1+Control!$B$17,19))*Control!$B$26)))*(1-Control!$B$23))-IF(AND(Control!$B$5>0,Control!$B$6="Y",20=Control!$B$39-1),Control!$B$40,0))+Valuation!$F$10*POWER(1+Control!$B$74,20)*(1-Control!$B$75)
A52: [calc] Occupancy 0.65 cum | D52: =D51 | E52: =D52+E51 | F52: =E52+F51 | G52: =F52+G51 | H52: =G52+H51 | I52: =H52+I51 | J52: =I52+J51 | K52: =J52+K51 | L52: =K52+L51 | ... V52: =U52+V51
A53: [calc] Occupancy 0.7 dist | C53: =-Control!$B$15 | D53: =Control!$B$11*(((((((Control!$B$20*$A$8)*((Control!$B$28+Control!$B$29*(Control!$B$38-2))+(Control!$B$32+Control!$B$33*(Control!$B$38-2))+IF(AND(Control!$B$5>0,Control!$B$6="Y",1>=Control!$B$39),Control!$B$36,0))*POWER(1+Control!$B$17,0))+((((Control!$B$20*$A$8)*Control!$B$38*2+IF(AND(Control!$B$5>0,Control!$B$6="Y",1>=Control!$B$39),(Control!$B$20*$A$8)*2,0))*Control!$B$41)*(Control!$B$42+Control!$B$44)*POWER(1+Control!$B$17,0))+(Control!$B$46*POWER(1+Control!$B$17,0)))-(((Control!$B$20*$A$8)*((Control!$B$28+Control!$B$29*(Control!$B$38-2))+(Control!$B$32+Control!$B$33*(Control!$B$38-2))+IF(AND(Control!$B$5>0,Control!$B$6="Y",1>=Control!$B$39),Control!$B$36,0))*POWER(1+Control!$B$17,0))*Control!$B$52+(((Control!$B$20*$A$8)*Control!$B$38*2+IF(AND(Control!$B$5>0,Control!$B$6="Y",1>=Control!$B$39),(Control!$B$20*$A$8)*2,0))*Control!$B$41)*(Control!$B$43+Control!$B$45)*POWER(1+Control!$B$18,0)+Control!$B$47*POWER(1+Control!$B$18,0)+(Control!$B$48+Control!$B$49+Control!$B$50+Control!$B$51)*12*POWER(1+Control!$B$18,0)+((Control!$B$20*$A$8)*((Control!$B$28+Control!$B$29*(Control!$B$38-2))+(Control!$B$32+Control!$B$33*(Control!$B$38-2))+IF(AND(Control!$B$5>0,Control!$B$6="Y",1>=Control!$B$39),Control!$B$36,0))*POWER(1+Control!$B$17,0))*Control!$B$26))+(((Control!$B$54*Control!$B$55+Control!$B$56*Control!$B$57*Control!$B$58*Control!$B$59)*POWER(1+Control!$B$17,0))-((Control!$B$56*Control!$B$57*Control!$B$58*Control!$B$59*POWER(1+Control!$B$17,0))*Control!$B$60+(Control!$B$61+Control!$B$62+Control!$B$63)*12*POWER(1+Control!$B$18,0)+((Control!$B$54*Control!$B$55+Control!$B$56*Control!$B$57*Control!$B$58*Control!$B$59)*POWER(1+Control!$B$17,0))*Control!$B$26))+((Control!$B$65*12*POWER(1+Control!$B$17,0))-((Control!$B$66+Control!$B$67+Control!$B$68)*12*POWER(1+Control!$B$18,0)+(Control!$B$65*12*POWER(1+Control!$B$17,0))*Control!$B$26)))*(1-Control!$B$23))-IF(AND(Control!$B$5>0,Control!$B$6="Y",1=Control!$B$39-1),Control!$B$40,0)) | E53: =Control!$B$11*(((((((Control!$B$20*$A$8)*((Control!$B$28+Control!$B$29*(Control!$B$38-2))+(Control!$B$32+Control!$B$33*(Control!$B$38-2))+IF(AND(Control!$B$5>0,Control!$B$6="Y",2>=Control!$B$39),Control!$B$36,0))*POWER(1+Control!$B$17,1))+((((Control!$B$20*$A$8)*Control!$B$38*2+IF(AND(Control!$B$5>0,Control!$B$6="Y",2>=Control!$B$39),(Control!$B$20*$A$8)*2,0))*Control!$B$41)*(Control!$B$42+Control!$B$44)*POWER(1+Control!$B$17,1))+(Control!$B$46*POWER(1+Control!$B$17,1)))-(((Control!$B$20*$A$8)*((Control!$B$28+Control!$B$29*(Control!$B$38-2))+(Control!$B$32+Control!$B$33*(Control!$B$38-2))+IF(AND(Control!$B$5>0,Control!$B$6="Y",2>=Control!$B$39),Control!$B$36,0))*POWER(1+Control!$B$17,1))*Control!$B$52+(((Control!$B$20*$A$8)*Control!$B$38*2+IF(AND(Control!$B$5>0,Control!$B$6="Y",2>=Control!$B$39),(Control!$B$20*$A$8)*2,0))*Control!$B$41)*(Control!$B$43+Control!$B$45)*POWER(1+Control!$B$18,1)+Control!$B$47*POWER(1+Control!$B$18,1)+(Control!$B$48+Control!$B$49+Control!$B$50+Control!$B$51)*12*POWER(1+Control!$B$18,1)+((Control!$B$20*$A$8)*((Control!$B$28+Control!$B$29*(Control!$B$38-2))+(Control!$B$32+Control!$B$33*(Control!$B$38-2))+IF(AND(Control!$B$5>0,Control!$B$6="Y",2>=Control!$B$39),Control!$B$36,0))*POWER(1+Control!$B$17,1))*Control!$B$26))+(((Control!$B$54*Control!$B$55+Control!$B$56*Control!$B$57*Control!$B$58*Control!$B$59)*POWER(1+Control!$B$17,1))-((Control!$B$56*Control!$B$57*Control!$B$58*Control!$B$59*POWER(1+Control!$B$17,1))*Control!$B$60+(Control!$B$61+Control!$B$62+Control!$B$63)*12*POWER(1+Control!$B$18,1)+((Control!$B$54*Control!$B$55+Control!$B$56*Control!$B$57*Control!$B$58*Control!$B$59)*POWER(1+Control!$B$17,1))*Control!$B$26))+((Control!$B$65*12*POWER(1+Control!$B$17,1))-((Control!$B$66+Control!$B$67+Control!$B$68)*12*POWER(1+Control!$B$18,1)+(Control!$B$65*12*POWER(1+Control!$B$17,1))*Control!$B$26)))*(1-Control!$B$23))-IF(AND(Control!$B$5>0,Control!$B$6="Y",2=Control!$B$39-1),Control!$B$40,0)) | F53: =Control!$B$11*(((((((Control!$B$20*$A$8)*((Control!$B$28+Control!$B$29*(Control!$B$38-2))+(Control!$B$32+Control!$B$33*(Control!$B$38-2))+IF(AND(Control!$B$5>0,Control!$B$6="Y",3>=Control!$B$39),Control!$B$36,0))*POWER(1+Control!$B$17,2))+((((Control!$B$20*$A$8)*Control!$B$38*2+IF(AND(Control!$B$5>0,Control!$B$6="Y",3>=Control!$B$39),(Control!$B$20*$A$8)*2,0))*Control!$B$41)*(Control!$B$42+Control!$B$44)*POWER(1+Control!$B$17,2))+(Control!$B$46*POWER(1+Control!$B$17,2)))-(((Control!$B$20*$A$8)*((Control!$B$28+Control!$B$29*(Control!$B$38-2))+(Control!$B$32+Control!$B$33*(Control!$B$38-2))+IF(AND(Control!$B$5>0,Control!$B$6="Y",3>=Control!$B$39),Control!$B$36,0))*POWER(1+Control!$B$17,2))*Control!$B$52+(((Control!$B$20*$A$8)*Control!$B$38*2+IF(AND(Control!$B$5>0,Control!$B$6="Y",3>=Control!$B$39),(Control!$B$20*$A$8)*2,0))*Control!$B$41)*(Control!$B$43+Control!$B$45)*POWER(1+Control!$B$18,2)+Control!$B$47*POWER(1+Control!$B$18,2)+(Control!$B$48+Control!$B$49+Control!$B$50+Control!$B$51)*12*POWER(1+Control!$B$18,2)+((Control!$B$20*$A$8)*((Control!$B$28+Control!$B$29*(Control!$B$38-2))+(Control!$B$32+Control!$B$33*(Control!$B$38-2))+IF(AND(Control!$B$5>0,Control!$B$6="Y",3>=Control!$B$39),Control!$B$36,0))*POWER(1+Control!$B$17,2))*Control!$B$26))+(((Control!$B$54*Control!$B$55+Control!$B$56*Control!$B$57*Control!$B$58*Control!$B$59)*POWER(1+Control!$B$17,2))-((Control!$B$56*Control!$B$57*Control!$B$58*Control!$B$59*POWER(1+Control!$B$17,2))*Control!$B$60+(Control!$B$61+Control!$B$62+Control!$B$63)*12*POWER(1+Control!$B$18,2)+((Control!$B$54*Control!$B$55+Control!$B$56*Control!$B$57*Control!$B$58*Control!$B$59)*POWER(1+Control!$B$17,2))*Control!$B$26))+((Control!$B$65*12*POWER(1+Control!$B$17,2))-((Control!$B$66+Control!$B$67+Control!$B$68)*12*POWER(1+Control!$B$18,2)+(Control!$B$65*12*POWER(1+Control!$B$17,2))*Control!$B$26)))*(1-Control!$B$23))-IF(AND(Control!$B$5>0,Control!$B$6="Y",3=Control!$B$39-1),Control!$B$40,0)) | G53: =Control!$B$11*(((((((Control!$B$20*$A$8)*((Control!$B$28+Control!$B$29*(Control!$B$38-2))+(Control!$B$32+Control!$B$33*(Control!$B$38-2))+IF(AND(Control!$B$5>0,Control!$B$6="Y",4>=Control!$B$39),Control!$B$36,0))*POWER(1+Control!$B$17,3))+((((Control!$B$20*$A$8)*Control!$B$38*2+IF(AND(Control!$B$5>0,Control!$B$6="Y",4>=Control!$B$39),(Control!$B$20*$A$8)*2,0))*Control!$B$41)*(Control!$B$42+Control!$B$44)*POWER(1+Control!$B$17,3))+(Control!$B$46*POWER(1+Control!$B$17,3)))-(((Control!$B$20*$A$8)*((Control!$B$28+Control!$B$29*(Control!$B$38-2))+(Control!$B$32+Control!$B$33*(Control!$B$38-2))+IF(AND(Control!$B$5>0,Control!$B$6="Y",4>=Control!$B$39),Control!$B$36,0))*POWER(1+Control!$B$17,3))*Control!$B$52+(((Control!$B$20*$A$8)*Control!$B$38*2+IF(AND(Control!$B$5>0,Control!$B$6="Y",4>=Control!$B$39),(Control!$B$20*$A$8)*2,0))*Control!$B$41)*(Control!$B$43+Control!$B$45)*POWER(1+Control!$B$18,3)+Control!$B$47*POWER(1+Control!$B$18,3)+(Control!$B$48+Control!$B$49+Control!$B$50+Control!$B$51)*12*POWER(1+Control!$B$18,3)+((Control!$B$20*$A$8)*((Control!$B$28+Control!$B$29*(Control!$B$38-2))+(Control!$B$32+Control!$B$33*(Control!$B$38-2))+IF(AND(Control!$B$5>0,Control!$B$6="Y",4>=Control!$B$39),Control!$B$36,0))*POWER(1+Control!$B$17,3))*Control!$B$26))+(((Control!$B$54*Control!$B$55+Control!$B$56*Control!$B$57*Control!$B$58*Control!$B$59)*POWER(1+Control!$B$17,3))-((Control!$B$56*Control!$B$57*Control!$B$58*Control!$B$59*POWER(1+Control!$B$17,3))*Control!$B$60+(Control!$B$61+Control!$B$62+Control!$B$63)*12*POWER(1+Control!$B$18,3)+((Control!$B$54*Control!$B$55+Control!$B$56*Control!$B$57*Control!$B$58*Control!$B$59)*POWER(1+Control!$B$17,3))*Control!$B$26))+((Control!$B$65*12*POWER(1+Control!$B$17,3))-((Control!$B$66+Control!$B$67+Control!$B$68)*12*POWER(1+Control!$B$18,3)+(Control!$B$65*12*POWER(1+Control!$B$17,3))*Control!$B$26)))*(1-Control!$B$23))-IF(AND(Control!$B$5>0,Control!$B$6="Y",4=Control!$B$39-1),Control!$B$40,0)) | H53: =Control!$B$11*(((((((Control!$B$20*$A$8)*((Control!$B$28+Control!$B$29*(Control!$B$38-2))+(Control!$B$32+Control!$B$33*(Control!$B$38-2))+IF(AND(Control!$B$5>0,Control!$B$6="Y",5>=Control!$B$39),Control!$B$36,0))*POWER(1+Control!$B$17,4))+((((Control!$B$20*$A$8)*Control!$B$38*2+IF(AND(Control!$B$5>0,Control!$B$6="Y",5>=Control!$B$39),(Control!$B$20*$A$8)*2,0))*Control!$B$41)*(Control!$B$42+Control!$B$44)*POWER(1+Control!$B$17,4))+(Control!$B$46*POWER(1+Control!$B$17,4)))-(((Control!$B$20*$A$8)*((Control!$B$28+Control!$B$29*(Control!$B$38-2))+(Control!$B$32+Control!$B$33*(Control!$B$38-2))+IF(AND(Control!$B$5>0,Control!$B$6="Y",5>=Control!$B$39),Control!$B$36,0))*POWER(1+Control!$B$17,4))*Control!$B$52+(((Control!$B$20*$A$8)*Control!$B$38*2+IF(AND(Control!$B$5>0,Control!$B$6="Y",5>=Control!$B$39),(Control!$B$20*$A$8)*2,0))*Control!$B$41)*(Control!$B$43+Control!$B$45)*POWER(1+Control!$B$18,4)+Control!$B$47*POWER(1+Control!$B$18,4)+(Control!$B$48+Control!$B$49+Control!$B$50+Control!$B$51)*12*POWER(1+Control!$B$18,4)+((Control!$B$20*$A$8)*((Control!$B$28+Control!$B$29*(Control!$B$38-2))+(Control!$B$32+Control!$B$33*(Control!$B$38-2))+IF(AND(Control!$B$5>0,Control!$B$6="Y",5>=Control!$B$39),Control!$B$36,0))*POWER(1+Control!$B$17,4))*Control!$B$26))+(((Control!$B$54*Control!$B$55+Control!$B$56*Control!$B$57*Control!$B$58*Control!$B$59)*POWER(1+Control!$B$17,4))-((Control!$B$56*Control!$B$57*Control!$B$58*Control!$B$59*POWER(1+Control!$B$17,4))*Control!$B$60+(Control!$B$61+Control!$B$62+Control!$B$63)*12*POWER(1+Control!$B$18,4)+((Control!$B$54*Control!$B$55+Control!$B$56*Control!$B$57*Control!$B$58*Control!$B$59)*POWER(1+Control!$B$17,4))*Control!$B$26))+((Control!$B$65*12*POWER(1+Control!$B$17,4))-((Control!$B$66+Control!$B$67+Control!$B$68)*12*POWER(1+Control!$B$18,4)+(Control!$B$65*12*POWER(1+Control!$B$17,4))*Control!$B$26)))*(1-Control!$B$23))-IF(AND(Control!$B$5>0,Control!$B$6="Y",5=Control!$B$39-1),Control!$B$40,0)) | I53: =Control!$B$11*(((((((Control!$B$20*$A$8)*((Control!$B$28+Control!$B$29*(Control!$B$38-2))+(Control!$B$32+Control!$B$33*(Control!$B$38-2))+IF(AND(Control!$B$5>0,Control!$B$6="Y",6>=Control!$B$39),Control!$B$36,0))*POWER(1+Control!$B$17,5))+((((Control!$B$20*$A$8)*Control!$B$38*2+IF(AND(Control!$B$5>0,Control!$B$6="Y",6>=Control!$B$39),(Control!$B$20*$A$8)*2,0))*Control!$B$41)*(Control!$B$42+Control!$B$44)*POWER(1+Control!$B$17,5))+(Control!$B$46*POWER(1+Control!$B$17,5)))-(((Control!$B$20*$A$8)*((Control!$B$28+Control!$B$29*(Control!$B$38-2))+(Control!$B$32+Control!$B$33*(Control!$B$38-2))+IF(AND(Control!$B$5>0,Control!$B$6="Y",6>=Control!$B$39),Control!$B$36,0))*POWER(1+Control!$B$17,5))*Control!$B$52+(((Control!$B$20*$A$8)*Control!$B$38*2+IF(AND(Control!$B$5>0,Control!$B$6="Y",6>=Control!$B$39),(Control!$B$20*$A$8)*2,0))*Control!$B$41)*(Control!$B$43+Control!$B$45)*POWER(1+Control!$B$18,5)+Control!$B$47*POWER(1+Control!$B$18,5)+(Control!$B$48+Control!$B$49+Control!$B$50+Control!$B$51)*12*POWER(1+Control!$B$18,5)+((Control!$B$20*$A$8)*((Control!$B$28+Control!$B$29*(Control!$B$38-2))+(Control!$B$32+Control!$B$33*(Control!$B$38-2))+IF(AND(Control!$B$5>0,Control!$B$6="Y",6>=Control!$B$39),Control!$B$36,0))*POWER(1+Control!$B$17,5))*Control!$B$26))+(((Control!$B$54*Control!$B$55+Control!$B$56*Control!$B$57*Control!$B$58*Control!$B$59)*POWER(1+Control!$B$17,5))-((Control!$B$56*Control!$B$57*Control!$B$58*Control!$B$59*POWER(1+Control!$B$17,5))*Control!$B$60+(Control!$B$61+Control!$B$62+Control!$B$63)*12*POWER(1+Control!$B$18,5)+((Control!$B$54*Control!$B$55+Control!$B$56*Control!$B$57*Control!$B$58*Control!$B$59)*POWER(1+Control!$B$17,5))*Control!$B$26))+((Control!$B$65*12*POWER(1+Control!$B$17,5))-((Control!$B$66+Control!$B$67+Control!$B$68)*12*POWER(1+Control!$B$18,5)+(Control!$B$65*12*POWER(1+Control!$B$17,5))*Control!$B$26)))*(1-Control!$B$23))-IF(AND(Control!$B$5>0,Control!$B$6="Y",6=Control!$B$39-1),Control!$B$40,0)) | J53: =Control!$B$11*(((((((Control!$B$20*$A$8)*((Control!$B$28+Control!$B$29*(Control!$B$38-2))+(Control!$B$32+Control!$B$33*(Control!$B$38-2))+IF(AND(Control!$B$5>0,Control!$B$6="Y",7>=Control!$B$39),Control!$B$36,0))*POWER(1+Control!$B$17,6))+((((Control!$B$20*$A$8)*Control!$B$38*2+IF(AND(Control!$B$5>0,Control!$B$6="Y",7>=Control!$B$39),(Control!$B$20*$A$8)*2,0))*Control!$B$41)*(Control!$B$42+Control!$B$44)*POWER(1+Control!$B$17,6))+(Control!$B$46*POWER(1+Control!$B$17,6)))-(((Control!$B$20*$A$8)*((Control!$B$28+Control!$B$29*(Control!$B$38-2))+(Control!$B$32+Control!$B$33*(Control!$B$38-2))+IF(AND(Control!$B$5>0,Control!$B$6="Y",7>=Control!$B$39),Control!$B$36,0))*POWER(1+Control!$B$17,6))*Control!$B$52+(((Control!$B$20*$A$8)*Control!$B$38*2+IF(AND(Control!$B$5>0,Control!$B$6="Y",7>=Control!$B$39),(Control!$B$20*$A$8)*2,0))*Control!$B$41)*(Control!$B$43+Control!$B$45)*POWER(1+Control!$B$18,6)+Control!$B$47*POWER(1+Control!$B$18,6)+(Control!$B$48+Control!$B$49+Control!$B$50+Control!$B$51)*12*POWER(1+Control!$B$18,6)+((Control!$B$20*$A$8)*((Control!$B$28+Control!$B$29*(Control!$B$38-2))+(Control!$B$32+Control!$B$33*(Control!$B$38-2))+IF(AND(Control!$B$5>0,Control!$B$6="Y",7>=Control!$B$39),Control!$B$36,0))*POWER(1+Control!$B$17,6))*Control!$B$26))+(((Control!$B$54*Control!$B$55+Control!$B$56*Control!$B$57*Control!$B$58*Control!$B$59)*POWER(1+Control!$B$17,6))-((Control!$B$56*Control!$B$57*Control!$B$58*Control!$B$59*POWER(1+Control!$B$17,6))*Control!$B$60+(Control!$B$61+Control!$B$62+Control!$B$63)*12*POWER(1+Control!$B$18,6)+((Control!$B$54*Control!$B$55+Control!$B$56*Control!$B$57*Control!$B$58*Control!$B$59)*POWER(1+Control!$B$17,6))*Control!$B$26))+((Control!$B$65*12*POWER(1+Control!$B$17,6))-((Control!$B$66+Control!$B$67+Control!$B$68)*12*POWER(1+Control!$B$18,6)+(Control!$B$65*12*POWER(1+Control!$B$17,6))*Control!$B$26)))*(1-Control!$B$23))-IF(AND(Control!$B$5>0,Control!$B$6="Y",7=Control!$B$39-1),Control!$B$40,0)) | K53: =Control!$B$11*(((((((Control!$B$20*$A$8)*((Control!$B$28+Control!$B$29*(Control!$B$38-2))+(Control!$B$32+Control!$B$33*(Control!$B$38-2))+IF(AND(Control!$B$5>0,Control!$B$6="Y",8>=Control!$B$39),Control!$B$36,0))*POWER(1+Control!$B$17,7))+((((Control!$B$20*$A$8)*Control!$B$38*2+IF(AND(Control!$B$5>0,Control!$B$6="Y",8>=Control!$B$39),(Control!$B$20*$A$8)*2,0))*Control!$B$41)*(Control!$B$42+Control!$B$44)*POWER(1+Control!$B$17,7))+(Control!$B$46*POWER(1+Control!$B$17,7)))-(((Control!$B$20*$A$8)*((Control!$B$28+Control!$B$29*(Control!$B$38-2))+(Control!$B$32+Control!$B$33*(Control!$B$38-2))+IF(AND(Control!$B$5>0,Control!$B$6="Y",8>=Control!$B$39),Control!$B$36,0))*POWER(1+Control!$B$17,7))*Control!$B$52+(((Control!$B$20*$A$8)*Control!$B$38*2+IF(AND(Control!$B$5>0,Control!$B$6="Y",8>=Control!$B$39),(Control!$B$20*$A$8)*2,0))*Control!$B$41)*(Control!$B$43+Control!$B$45)*POWER(1+Control!$B$18,7)+Control!$B$47*POWER(1+Control!$B$18,7)+(Control!$B$48+Control!$B$49+Control!$B$50+Control!$B$51)*12*POWER(1+Control!$B$18,7)+((Control!$B$20*$A$8)*((Control!$B$28+Control!$B$29*(Control!$B$38-2))+(Control!$B$32+Control!$B$33*(Control!$B$38-2))+IF(AND(Control!$B$5>0,Control!$B$6="Y",8>=Control!$B$39),Control!$B$36,0))*POWER(1+Control!$B$17,7))*Control!$B$26))+(((Control!$B$54*Control!$B$55+Control!$B$56*Control!$B$57*Control!$B$58*Control!$B$59)*POWER(1+Control!$B$17,7))-((Control!$B$56*Control!$B$57*Control!$B$58*Control!$B$59*POWER(1+Control!$B$17,7))*Control!$B$60+(Control!$B$61+Control!$B$62+Control!$B$63)*12*POWER(1+Control!$B$18,7)+((Control!$B$54*Control!$B$55+Control!$B$56*Control!$B$57*Control!$B$58*Control!$B$59)*POWER(1+Control!$B$17,7))*Control!$B$26))+((Control!$B$65*12*POWER(1+Control!$B$17,7))-((Control!$B$66+Control!$B$67+Control!$B$68)*12*POWER(1+Control!$B$18,7)+(Control!$B$65*12*POWER(1+Control!$B$17,7))*Control!$B$26)))*(1-Control!$B$23))-IF(AND(Control!$B$5>0,Control!$B$6="Y",8=Control!$B$39-1),Control!$B$40,0)) | L53: =Control!$B$11*(((((((Control!$B$20*$A$8)*((Control!$B$28+Control!$B$29*(Control!$B$38-2))+(Control!$B$32+Control!$B$33*(Control!$B$38-2))+IF(AND(Control!$B$5>0,Control!$B$6="Y",9>=Control!$B$39),Control!$B$36,0))*POWER(1+Control!$B$17,8))+((((Control!$B$20*$A$8)*Control!$B$38*2+IF(AND(Control!$B$5>0,Control!$B$6="Y",9>=Control!$B$39),(Control!$B$20*$A$8)*2,0))*Control!$B$41)*(Control!$B$42+Control!$B$44)*POWER(1+Control!$B$17,8))+(Control!$B$46*POWER(1+Control!$B$17,8)))-(((Control!$B$20*$A$8)*((Control!$B$28+Control!$B$29*(Control!$B$38-2))+(Control!$B$32+Control!$B$33*(Control!$B$38-2))+IF(AND(Control!$B$5>0,Control!$B$6="Y",9>=Control!$B$39),Control!$B$36,0))*POWER(1+Control!$B$17,8))*Control!$B$52+(((Control!$B$20*$A$8)*Control!$B$38*2+IF(AND(Control!$B$5>0,Control!$B$6="Y",9>=Control!$B$39),(Control!$B$20*$A$8)*2,0))*Control!$B$41)*(Control!$B$43+Control!$B$45)*POWER(1+Control!$B$18,8)+Control!$B$47*POWER(1+Control!$B$18,8)+(Control!$B$48+Control!$B$49+Control!$B$50+Control!$B$51)*12*POWER(1+Control!$B$18,8)+((Control!$B$20*$A$8)*((Control!$B$28+Control!$B$29*(Control!$B$38-2))+(Control!$B$32+Control!$B$33*(Control!$B$38-2))+IF(AND(Control!$B$5>0,Control!$B$6="Y",9>=Control!$B$39),Control!$B$36,0))*POWER(1+Control!$B$17,8))*Control!$B$26))+(((Control!$B$54*Control!$B$55+Control!$B$56*Control!$B$57*Control!$B$58*Control!$B$59)*POWER(1+Control!$B$17,8))-((Control!$B$56*Control!$B$57*Control!$B$58*Control!$B$59*POWER(1+Control!$B$17,8))*Control!$B$60+(Control!$B$61+Control!$B$62+Control!$B$63)*12*POWER(1+Control!$B$18,8)+((Control!$B$54*Control!$B$55+Control!$B$56*Control!$B$57*Control!$B$58*Control!$B$59)*POWER(1+Control!$B$17,8))*Control!$B$26))+((Control!$B$65*12*POWER(1+Control!$B$17,8))-((Control!$B$66+Control!$B$67+Control!$B$68)*12*POWER(1+Control!$B$18,8)+(Control!$B$65*12*POWER(1+Control!$B$17,8))*Control!$B$26)))*(1-Control!$B$23))-IF(AND(Control!$B$5>0,Control!$B$6="Y",9=Control!$B$39-1),Control!$B$40,0)) | M53: =Control!$B$11*(((((((Control!$B$20*$A$8)*((Control!$B$28+Control!$B$29*(Control!$B$38-2))+(Control!$B$32+Control!$B$33*(Control!$B$38-2))+IF(AND(Control!$B$5>0,Control!$B$6="Y",10>=Control!$B$39),Control!$B$36,0))*POWER(1+Control!$B$17,9))+((((Control!$B$20*$A$8)*Control!$B$38*2+IF(AND(Control!$B$5>0,Control!$B$6="Y",10>=Control!$B$39),(Control!$B$20*$A$8)*2,0))*Control!$B$41)*(Control!$B$42+Control!$B$44)*POWER(1+Control!$B$17,9))+(Control!$B$46*POWER(1+Control!$B$17,9)))-(((Control!$B$20*$A$8)*((Control!$B$28+Control!$B$29*(Control!$B$38-2))+(Control!$B$32+Control!$B$33*(Control!$B$38-2))+IF(AND(Control!$B$5>0,Control!$B$6="Y",10>=Control!$B$39),Control!$B$36,0))*POWER(1+Control!$B$17,9))*Control!$B$52+(((Control!$B$20*$A$8)*Control!$B$38*2+IF(AND(Control!$B$5>0,Control!$B$6="Y",10>=Control!$B$39),(Control!$B$20*$A$8)*2,0))*Control!$B$41)*(Control!$B$43+Control!$B$45)*POWER(1+Control!$B$18,9)+Control!$B$47*POWER(1+Control!$B$18,9)+(Control!$B$48+Control!$B$49+Control!$B$50+Control!$B$51)*12*POWER(1+Control!$B$18,9)+((Control!$B$20*$A$8)*((Control!$B$28+Control!$B$29*(Control!$B$38-2))+(Control!$B$32+Control!$B$33*(Control!$B$38-2))+IF(AND(Control!$B$5>0,Control!$B$6="Y",10>=Control!$B$39),Control!$B$36,0))*POWER(1+Control!$B$17,9))*Control!$B$26))+(((Control!$B$54*Control!$B$55+Control!$B$56*Control!$B$57*Control!$B$58*Control!$B$59)*POWER(1+Control!$B$17,9))-((Control!$B$56*Control!$B$57*Control!$B$58*Control!$B$59*POWER(1+Control!$B$17,9))*Control!$B$60+(Control!$B$61+Control!$B$62+Control!$B$63)*12*POWER(1+Control!$B$18,9)+((Control!$B$54*Control!$B$55+Control!$B$56*Control!$B$57*Control!$B$58*Control!$B$59)*POWER(1+Control!$B$17,9))*Control!$B$26))+((Control!$B$65*12*POWER(1+Control!$B$17,9))-((Control!$B$66+Control!$B$67+Control!$B$68)*12*POWER(1+Control!$B$18,9)+(Control!$B$65*12*POWER(1+Control!$B$17,9))*Control!$B$26)))*(1-Control!$B$23))-IF(AND(Control!$B$5>0,Control!$B$6="Y",10=Control!$B$39-1),Control!$B$40,0)) | N53: =Control!$B$11*(((((((Control!$B$20*$A$8)*((Control!$B$28+Control!$B$29*(Control!$B$38-2))+(Control!$B$32+Control!$B$33*(Control!$B$38-2))+IF(AND(Control!$B$5>0,Control!$B$6="Y",11>=Control!$B$39),Control!$B$36,0))*POWER(1+Control!$B$17,10))+((((Control!$B$20*$A$8)*Control!$B$38*2+IF(AND(Control!$B$5>0,Control!$B$6="Y",11>=Control!$B$39),(Control!$B$20*$A$8)*2,0))*Control!$B$41)*(Control!$B$42+Control!$B$44)*POWER(1+Control!$B$17,10))+(Control!$B$46*POWER(1+Control!$B$17,10)))-(((Control!$B$20*$A$8)*((Control!$B$28+Control!$B$29*(Control!$B$38-2))+(Control!$B$32+Control!$B$33*(Control!$B$38-2))+IF(AND(Control!$B$5>0,Control!$B$6="Y",11>=Control!$B$39),Control!$B$36,0))*POWER(1+Control!$B$17,10))*Control!$B$52+(((Control!$B$20*$A$8)*Control!$B$38*2+IF(AND(Control!$B$5>0,Control!$B$6="Y",11>=Control!$B$39),(Control!$B$20*$A$8)*2,0))*Control!$B$41)*(Control!$B$43+Control!$B$45)*POWER(1+Control!$B$18,10)+Control!$B$47*POWER(1+Control!$B$18,10)+(Control!$B$48+Control!$B$49+Control!$B$50+Control!$B$51)*12*POWER(1+Control!$B$18,10)+((Control!$B$20*$A$8)*((Control!$B$28+Control!$B$29*(Control!$B$38-2))+(Control!$B$32+Control!$B$33*(Control!$B$38-2))+IF(AND(Control!$B$5>0,Control!$B$6="Y",11>=Control!$B$39),Control!$B$36,0))*POWER(1+Control!$B$17,10))*Control!$B$26))+(((Control!$B$54*Control!$B$55+Control!$B$56*Control!$B$57*Control!$B$58*Control!$B$59)*POWER(1+Control!$B$17,10))-((Control!$B$56*Control!$B$57*Control!$B$58*Control!$B$59*POWER(1+Control!$B$17,10))*Control!$B$60+(Control!$B$61+Control!$B$62+Control!$B$63)*12*POWER(1+Control!$B$18,10)+((Control!$B$54*Control!$B$55+Control!$B$56*Control!$B$57*Control!$B$58*Control!$B$59)*POWER(1+Control!$B$17,10))*Control!$B$26))+((Control!$B$65*12*POWER(1+Control!$B$17,10))-((Control!$B$66+Control!$B$67+Control!$B$68)*12*POWER(1+Control!$B$18,10)+(Control!$B$65*12*POWER(1+Control!$B$17,10))*Control!$B$26)))*(1-Control!$B$23))-IF(AND(Control!$B$5>0,Control!$B$6="Y",11=Control!$B$39-1),Control!$B$40,0)) | O53: =Control!$B$11*(((((((Control!$B$20*$A$8)*((Control!$B$28+Control!$B$29*(Control!$B$38-2))+(Control!$B$32+Control!$B$33*(Control!$B$38-2))+IF(AND(Control!$B$5>0,Control!$B$6="Y",12>=Control!$B$39),Control!$B$36,0))*POWER(1+Control!$B$17,11))+((((Control!$B$20*$A$8)*Control!$B$38*2+IF(AND(Control!$B$5>0,Control!$B$6="Y",12>=Control!$B$39),(Control!$B$20*$A$8)*2,0))*Control!$B$41)*(Control!$B$42+Control!$B$44)*POWER(1+Control!$B$17,11))+(Control!$B$46*POWER(1+Control!$B$17,11)))-(((Control!$B$20*$A$8)*((Control!$B$28+Control!$B$29*(Control!$B$38-2))+(Control!$B$32+Control!$B$33*(Control!$B$38-2))+IF(AND(Control!$B$5>0,Control!$B$6="Y",12>=Control!$B$39),Control!$B$36,0))*POWER(1+Control!$B$17,11))*Control!$B$52+(((Control!$B$20*$A$8)*Control!$B$38*2+IF(AND(Control!$B$5>0,Control!$B$6="Y",12>=Control!$B$39),(Control!$B$20*$A$8)*2,0))*Control!$B$41)*(Control!$B$43+Control!$B$45)*POWER(1+Control!$B$18,11)+Control!$B$47*POWER(1+Control!$B$18,11)+(Control!$B$48+Control!$B$49+Control!$B$50+Control!$B$51)*12*POWER(1+Control!$B$18,11)+((Control!$B$20*$A$8)*((Control!$B$28+Control!$B$29*(Control!$B$38-2))+(Control!$B$32+Control!$B$33*(Control!$B$38-2))+IF(AND(Control!$B$5>0,Control!$B$6="Y",12>=Control!$B$39),Control!$B$36,0))*POWER(1+Control!$B$17,11))*Control!$B$26))+(((Control!$B$54*Control!$B$55+Control!$B$56*Control!$B$57*Control!$B$58*Control!$B$59)*POWER(1+Control!$B$17,11))-((Control!$B$56*Control!$B$57*Control!$B$58*Control!$B$59*POWER(1+Control!$B$17,11))*Control!$B$60+(Control!$B$61+Control!$B$62+Control!$B$63)*12*POWER(1+Control!$B$18,11)+((Control!$B$54*Control!$B$55+Control!$B$56*Control!$B$57*Control!$B$58*Control!$B$59)*POWER(1+Control!$B$17,11))*Control!$B$26))+((Control!$B$65*12*POWER(1+Control!$B$17,11))-((Control!$B$66+Control!$B$67+Control!$B$68)*12*POWER(1+Control!$B$18,11)+(Control!$B$65*12*POWER(1+Control!$B$17,11))*Control!$B$26)))*(1-Control!$B$23))-IF(AND(Control!$B$5>0,Control!$B$6="Y",12=Control!$B$39-1),Control!$B$40,0)) | P53: =Control!$B$11*(((((((Control!$B$20*$A$8)*((Control!$B$28+Control!$B$29*(Control!$B$38-2))+(Control!$B$32+Control!$B$33*(Control!$B$38-2))+IF(AND(Control!$B$5>0,Control!$B$6="Y",13>=Control!$B$39),Control!$B$36,0))*POWER(1+Control!$B$17,12))+((((Control!$B$20*$A$8)*Control!$B$38*2+IF(AND(Control!$B$5>0,Control!$B$6="Y",13>=Control!$B$39),(Control!$B$20*$A$8)*2,0))*Control!$B$41)*(Control!$B$42+Control!$B$44)*POWER(1+Control!$B$17,12))+(Control!$B$46*POWER(1+Control!$B$17,12)))-(((Control!$B$20*$A$8)*((Control!$B$28+Control!$B$29*(Control!$B$38-2))+(Control!$B$32+Control!$B$33*(Control!$B$38-2))+IF(AND(Control!$B$5>0,Control!$B$6="Y",13>=Control!$B$39),Control!$B$36,0))*POWER(1+Control!$B$17,12))*Control!$B$52+(((Control!$B$20*$A$8)*Control!$B$38*2+IF(AND(Control!$B$5>0,Control!$B$6="Y",13>=Control!$B$39),(Control!$B$20*$A$8)*2,0))*Control!$B$41)*(Control!$B$43+Control!$B$45)*POWER(1+Control!$B$18,12)+Control!$B$47*POWER(1+Control!$B$18,12)+(Control!$B$48+Control!$B$49+Control!$B$50+Control!$B$51)*12*POWER(1+Control!$B$18,12)+((Control!$B$20*$A$8)*((Control!$B$28+Control!$B$29*(Control!$B$38-2))+(Control!$B$32+Control!$B$33*(Control!$B$38-2))+IF(AND(Control!$B$5>0,Control!$B$6="Y",13>=Control!$B$39),Control!$B$36,0))*POWER(1+Control!$B$17,12))*Control!$B$26))+(((Control!$B$54*Control!$B$55+Control!$B$56*Control!$B$57*Control!$B$58*Control!$B$59)*POWER(1+Control!$B$17,12))-((Control!$B$56*Control!$B$57*Control!$B$58*Control!$B$59*POWER(1+Control!$B$17,12))*Control!$B$60+(Control!$B$61+Control!$B$62+Control!$B$63)*12*POWER(1+Control!$B$18,12)+((Control!$B$54*Control!$B$55+Control!$B$56*Control!$B$57*Control!$B$58*Control!$B$59)*POWER(1+Control!$B$17,12))*Control!$B$26))+((Control!$B$65*12*POWER(1+Control!$B$17,12))-((Control!$B$66+Control!$B$67+Control!$B$68)*12*POWER(1+Control!$B$18,12)+(Control!$B$65*12*POWER(1+Control!$B$17,12))*Control!$B$26)))*(1-Control!$B$23))-IF(AND(Control!$B$5>0,Control!$B$6="Y",13=Control!$B$39-1),Control!$B$40,0)) | Q53: =Control!$B$11*(((((((Control!$B$20*$A$8)*((Control!$B$28+Control!$B$29*(Control!$B$38-2))+(Control!$B$32+Control!$B$33*(Control!$B$38-2))+IF(AND(Control!$B$5>0,Control!$B$6="Y",14>=Control!$B$39),Control!$B$36,0))*POWER(1+Control!$B$17,13))+((((Control!$B$20*$A$8)*Control!$B$38*2+IF(AND(Control!$B$5>0,Control!$B$6="Y",14>=Control!$B$39),(Control!$B$20*$A$8)*2,0))*Control!$B$41)*(Control!$B$42+Control!$B$44)*POWER(1+Control!$B$17,13))+(Control!$B$46*POWER(1+Control!$B$17,13)))-(((Control!$B$20*$A$8)*((Control!$B$28+Control!$B$29*(Control!$B$38-2))+(Control!$B$32+Control!$B$33*(Control!$B$38-2))+IF(AND(Control!$B$5>0,Control!$B$6="Y",14>=Control!$B$39),Control!$B$36,0))*POWER(1+Control!$B$17,13))*Control!$B$52+(((Control!$B$20*$A$8)*Control!$B$38*2+IF(AND(Control!$B$5>0,Control!$B$6="Y",14>=Control!$B$39),(Control!$B$20*$A$8)*2,0))*Control!$B$41)*(Control!$B$43+Control!$B$45)*POWER(1+Control!$B$18,13)+Control!$B$47*POWER(1+Control!$B$18,13)+(Control!$B$48+Control!$B$49+Control!$B$50+Control!$B$51)*12*POWER(1+Control!$B$18,13)+((Control!$B$20*$A$8)*((Control!$B$28+Control!$B$29*(Control!$B$38-2))+(Control!$B$32+Control!$B$33*(Control!$B$38-2))+IF(AND(Control!$B$5>0,Control!$B$6="Y",14>=Control!$B$39),Control!$B$36,0))*POWER(1+Control!$B$17,13))*Control!$B$26))+(((Control!$B$54*Control!$B$55+Control!$B$56*Control!$B$57*Control!$B$58*Control!$B$59)*POWER(1+Control!$B$17,13))-((Control!$B$56*Control!$B$57*Control!$B$58*Control!$B$59*POWER(1+Control!$B$17,13))*Control!$B$60+(Control!$B$61+Control!$B$62+Control!$B$63)*12*POWER(1+Control!$B$18,13)+((Control!$B$54*Control!$B$55+Control!$B$56*Control!$B$57*Control!$B$58*Control!$B$59)*POWER(1+Control!$B$17,13))*Control!$B$26))+((Control!$B$65*12*POWER(1+Control!$B$17,13))-((Control!$B$66+Control!$B$67+Control!$B$68)*12*POWER(1+Control!$B$18,13)+(Control!$B$65*12*POWER(1+Control!$B$17,13))*Control!$B$26)))*(1-Control!$B$23))-IF(AND(Control!$B$5>0,Control!$B$6="Y",14=Control!$B$39-1),Control!$B$40,0)) | R53: =Control!$B$11*(((((((Control!$B$20*$A$8)*((Control!$B$28+Control!$B$29*(Control!$B$38-2))+(Control!$B$32+Control!$B$33*(Control!$B$38-2))+IF(AND(Control!$B$5>0,Control!$B$6="Y",15>=Control!$B$39),Control!$B$36,0))*POWER(1+Control!$B$17,14))+((((Control!$B$20*$A$8)*Control!$B$38*2+IF(AND(Control!$B$5>0,Control!$B$6="Y",15>=Control!$B$39),(Control!$B$20*$A$8)*2,0))*Control!$B$41)*(Control!$B$42+Control!$B$44)*POWER(1+Control!$B$17,14))+(Control!$B$46*POWER(1+Control!$B$17,14)))-(((Control!$B$20*$A$8)*((Control!$B$28+Control!$B$29*(Control!$B$38-2))+(Control!$B$32+Control!$B$33*(Control!$B$38-2))+IF(AND(Control!$B$5>0,Control!$B$6="Y",15>=Control!$B$39),Control!$B$36,0))*POWER(1+Control!$B$17,14))*Control!$B$52+(((Control!$B$20*$A$8)*Control!$B$38*2+IF(AND(Control!$B$5>0,Control!$B$6="Y",15>=Control!$B$39),(Control!$B$20*$A$8)*2,0))*Control!$B$41)*(Control!$B$43+Control!$B$45)*POWER(1+Control!$B$18,14)+Control!$B$47*POWER(1+Control!$B$18,14)+(Control!$B$48+Control!$B$49+Control!$B$50+Control!$B$51)*12*POWER(1+Control!$B$18,14)+((Control!$B$20*$A$8)*((Control!$B$28+Control!$B$29*(Control!$B$38-2))+(Control!$B$32+Control!$B$33*(Control!$B$38-2))+IF(AND(Control!$B$5>0,Control!$B$6="Y",15>=Control!$B$39),Control!$B$36,0))*POWER(1+Control!$B$17,14))*Control!$B$26))+(((Control!$B$54*Control!$B$55+Control!$B$56*Control!$B$57*Control!$B$58*Control!$B$59)*POWER(1+Control!$B$17,14))-((Control!$B$56*Control!$B$57*Control!$B$58*Control!$B$59*POWER(1+Control!$B$17,14))*Control!$B$60+(Control!$B$61+Control!$B$62+Control!$B$63)*12*POWER(1+Control!$B$18,14)+((Control!$B$54*Control!$B$55+Control!$B$56*Control!$B$57*Control!$B$58*Control!$B$59)*POWER(1+Control!$B$17,14))*Control!$B$26))+((Control!$B$65*12*POWER(1+Control!$B$17,14))-((Control!$B$66+Control!$B$67+Control!$B$68)*12*POWER(1+Control!$B$18,14)+(Control!$B$65*12*POWER(1+Control!$B$17,14))*Control!$B$26)))*(1-Control!$B$23))-IF(AND(Control!$B$5>0,Control!$B$6="Y",15=Control!$B$39-1),Control!$B$40,0)) | S53: =Control!$B$11*(((((((Control!$B$20*$A$8)*((Control!$B$28+Control!$B$29*(Control!$B$38-2))+(Control!$B$32+Control!$B$33*(Control!$B$38-2))+IF(AND(Control!$B$5>0,Control!$B$6="Y",16>=Control!$B$39),Control!$B$36,0))*POWER(1+Control!$B$17,15))+((((Control!$B$20*$A$8)*Control!$B$38*2+IF(AND(Control!$B$5>0,Control!$B$6="Y",16>=Control!$B$39),(Control!$B$20*$A$8)*2,0))*Control!$B$41)*(Control!$B$42+Control!$B$44)*POWER(1+Control!$B$17,15))+(Control!$B$46*POWER(1+Control!$B$17,15)))-(((Control!$B$20*$A$8)*((Control!$B$28+Control!$B$29*(Control!$B$38-2))+(Control!$B$32+Control!$B$33*(Control!$B$38-2))+IF(AND(Control!$B$5>0,Control!$B$6="Y",16>=Control!$B$39),Control!$B$36,0))*POWER(1+Control!$B$17,15))*Control!$B$52+(((Control!$B$20*$A$8)*Control!$B$38*2+IF(AND(Control!$B$5>0,Control!$B$6="Y",16>=Control!$B$39),(Control!$B$20*$A$8)*2,0))*Control!$B$41)*(Control!$B$43+Control!$B$45)*POWER(1+Control!$B$18,15)+Control!$B$47*POWER(1+Control!$B$18,15)+(Control!$B$48+Control!$B$49+Control!$B$50+Control!$B$51)*12*POWER(1+Control!$B$18,15)+((Control!$B$20*$A$8)*((Control!$B$28+Control!$B$29*(Control!$B$38-2))+(Control!$B$32+Control!$B$33*(Control!$B$38-2))+IF(AND(Control!$B$5>0,Control!$B$6="Y",16>=Control!$B$39),Control!$B$36,0))*POWER(1+Control!$B$17,15))*Control!$B$26))+(((Control!$B$54*Control!$B$55+Control!$B$56*Control!$B$57*Control!$B$58*Control!$B$59)*POWER(1+Control!$B$17,15))-((Control!$B$56*Control!$B$57*Control!$B$58*Control!$B$59*POWER(1+Control!$B$17,15))*Control!$B$60+(Control!$B$61+Control!$B$62+Control!$B$63)*12*POWER(1+Control!$B$18,15)+((Control!$B$54*Control!$B$55+Control!$B$56*Control!$B$57*Control!$B$58*Control!$B$59)*POWER(1+Control!$B$17,15))*Control!$B$26))+((Control!$B$65*12*POWER(1+Control!$B$17,15))-((Control!$B$66+Control!$B$67+Control!$B$68)*12*POWER(1+Control!$B$18,15)+(Control!$B$65*12*POWER(1+Control!$B$17,15))*Control!$B$26)))*(1-Control!$B$23))-IF(AND(Control!$B$5>0,Control!$B$6="Y",16=Control!$B$39-1),Control!$B$40,0)) | T53: =Control!$B$11*(((((((Control!$B$20*$A$8)*((Control!$B$28+Control!$B$29*(Control!$B$38-2))+(Control!$B$32+Control!$B$33*(Control!$B$38-2))+IF(AND(Control!$B$5>0,Control!$B$6="Y",17>=Control!$B$39),Control!$B$36,0))*POWER(1+Control!$B$17,16))+((((Control!$B$20*$A$8)*Control!$B$38*2+IF(AND(Control!$B$5>0,Control!$B$6="Y",17>=Control!$B$39),(Control!$B$20*$A$8)*2,0))*Control!$B$41)*(Control!$B$42+Control!$B$44)*POWER(1+Control!$B$17,16))+(Control!$B$46*POWER(1+Control!$B$17,16)))-(((Control!$B$20*$A$8)*((Control!$B$28+Control!$B$29*(Control!$B$38-2))+(Control!$B$32+Control!$B$33*(Control!$B$38-2))+IF(AND(Control!$B$5>0,Control!$B$6="Y",17>=Control!$B$39),Control!$B$36,0))*POWER(1+Control!$B$17,16))*Control!$B$52+(((Control!$B$20*$A$8)*Control!$B$38*2+IF(AND(Control!$B$5>0,Control!$B$6="Y",17>=Control!$B$39),(Control!$B$20*$A$8)*2,0))*Control!$B$41)*(Control!$B$43+Control!$B$45)*POWER(1+Control!$B$18,16)+Control!$B$47*POWER(1+Control!$B$18,16)+(Control!$B$48+Control!$B$49+Control!$B$50+Control!$B$51)*12*POWER(1+Control!$B$18,16)+((Control!$B$20*$A$8)*((Control!$B$28+Control!$B$29*(Control!$B$38-2))+(Control!$B$32+Control!$B$33*(Control!$B$38-2))+IF(AND(Control!$B$5>0,Control!$B$6="Y",17>=Control!$B$39),Control!$B$36,0))*POWER(1+Control!$B$17,16))*Control!$B$26))+(((Control!$B$54*Control!$B$55+Control!$B$56*Control!$B$57*Control!$B$58*Control!$B$59)*POWER(1+Control!$B$17,16))-((Control!$B$56*Control!$B$57*Control!$B$58*Control!$B$59*POWER(1+Control!$B$17,16))*Control!$B$60+(Control!$B$61+Control!$B$62+Control!$B$63)*12*POWER(1+Control!$B$18,16)+((Control!$B$54*Control!$B$55+Control!$B$56*Control!$B$57*Control!$B$58*Control!$B$59)*POWER(1+Control!$B$17,16))*Control!$B$26))+((Control!$B$65*12*POWER(1+Control!$B$17,16))-((Control!$B$66+Control!$B$67+Control!$B$68)*12*POWER(1+Control!$B$18,16)+(Control!$B$65*12*POWER(1+Control!$B$17,16))*Control!$B$26)))*(1-Control!$B$23))-IF(AND(Control!$B$5>0,Control!$B$6="Y",17=Control!$B$39-1),Control!$B$40,0)) | U53: =Control!$B$11*(((((((Control!$B$20*$A$8)*((Control!$B$28+Control!$B$29*(Control!$B$38-2))+(Control!$B$32+Control!$B$33*(Control!$B$38-2))+IF(AND(Control!$B$5>0,Control!$B$6="Y",18>=Control!$B$39),Control!$B$36,0))*POWER(1+Control!$B$17,17))+((((Control!$B$20*$A$8)*Control!$B$38*2+IF(AND(Control!$B$5>0,Control!$B$6="Y",18>=Control!$B$39),(Control!$B$20*$A$8)*2,0))*Control!$B$41)*(Control!$B$42+Control!$B$44)*POWER(1+Control!$B$17,17))+(Control!$B$46*POWER(1+Control!$B$17,17)))-(((Control!$B$20*$A$8)*((Control!$B$28+Control!$B$29*(Control!$B$38-2))+(Control!$B$32+Control!$B$33*(Control!$B$38-2))+IF(AND(Control!$B$5>0,Control!$B$6="Y",18>=Control!$B$39),Control!$B$36,0))*POWER(1+Control!$B$17,17))*Control!$B$52+(((Control!$B$20*$A$8)*Control!$B$38*2+IF(AND(Control!$B$5>0,Control!$B$6="Y",18>=Control!$B$39),(Control!$B$20*$A$8)*2,0))*Control!$B$41)*(Control!$B$43+Control!$B$45)*POWER(1+Control!$B$18,17)+Control!$B$47*POWER(1+Control!$B$18,17)+(Control!$B$48+Control!$B$49+Control!$B$50+Control!$B$51)*12*POWER(1+Control!$B$18,17)+((Control!$B$20*$A$8)*((Control!$B$28+Control!$B$29*(Control!$B$38-2))+(Control!$B$32+Control!$B$33*(Control!$B$38-2))+IF(AND(Control!$B$5>0,Control!$B$6="Y",18>=Control!$B$39),Control!$B$36,0))*POWER(1+Control!$B$17,17))*Control!$B$26))+(((Control!$B$54*Control!$B$55+Control!$B$56*Control!$B$57*Control!$B$58*Control!$B$59)*POWER(1+Control!$B$17,17))-((Control!$B$56*Control!$B$57*Control!$B$58*Control!$B$59*POWER(1+Control!$B$17,17))*Control!$B$60+(Control!$B$61+Control!$B$62+Control!$B$63)*12*POWER(1+Control!$B$18,17)+((Control!$B$54*Control!$B$55+Control!$B$56*Control!$B$57*Control!$B$58*Control!$B$59)*POWER(1+Control!$B$17,17))*Control!$B$26))+((Control!$B$65*12*POWER(1+Control!$B$17,17))-((Control!$B$66+Control!$B$67+Control!$B$68)*12*POWER(1+Control!$B$18,17)+(Control!$B$65*12*POWER(1+Control!$B$17,17))*Control!$B$26)))*(1-Control!$B$23))-IF(AND(Control!$B$5>0,Control!$B$6="Y",18=Control!$B$39-1),Control!$B$40,0)) | V53: =Control!$B$11*(((((((Control!$B$20*$A$8)*((Control!$B$28+Control!$B$29*(Control!$B$38-2))+(Control!$B$32+Control!$B$33*(Control!$B$38-2))+IF(AND(Control!$B$5>0,Control!$B$6="Y",19>=Control!$B$39),Control!$B$36,0))*POWER(1+Control!$B$17,18))+((((Control!$B$20*$A$8)*Control!$B$38*2+IF(AND(Control!$B$5>0,Control!$B$6="Y",19>=Control!$B$39),(Control!$B$20*$A$8)*2,0))*Control!$B$41)*(Control!$B$42+Control!$B$44)*POWER(1+Control!$B$17,18))+(Control!$B$46*POWER(1+Control!$B$17,18)))-(((Control!$B$20*$A$8)*((Control!$B$28+Control!$B$29*(Control!$B$38-2))+(Control!$B$32+Control!$B$33*(Control!$B$38-2))+IF(AND(Control!$B$5>0,Control!$B$6="Y",19>=Control!$B$39),Control!$B$36,0))*POWER(1+Control!$B$17,18))*Control!$B$52+(((Control!$B$20*$A$8)*Control!$B$38*2+IF(AND(Control!$B$5>0,Control!$B$6="Y",19>=Control!$B$39),(Control!$B$20*$A$8)*2,0))*Control!$B$41)*(Control!$B$43+Control!$B$45)*POWER(1+Control!$B$18,18)+Control!$B$47*POWER(1+Control!$B$18,18)+(Control!$B$48+Control!$B$49+Control!$B$50+Control!$B$51)*12*POWER(1+Control!$B$18,18)+((Control!$B$20*$A$8)*((Control!$B$28+Control!$B$29*(Control!$B$38-2))+(Control!$B$32+Control!$B$33*(Control!$B$38-2))+IF(AND(Control!$B$5>0,Control!$B$6="Y",19>=Control!$B$39),Control!$B$36,0))*POWER(1+Control!$B$17,18))*Control!$B$26))+(((Control!$B$54*Control!$B$55+Control!$B$56*Control!$B$57*Control!$B$58*Control!$B$59)*POWER(1+Control!$B$17,18))-((Control!$B$56*Control!$B$57*Control!$B$58*Control!$B$59*POWER(1+Control!$B$17,18))*Control!$B$60+(Control!$B$61+Control!$B$62+Control!$B$63)*12*POWER(1+Control!$B$18,18)+((Control!$B$54*Control!$B$55+Control!$B$56*Control!$B$57*Control!$B$58*Control!$B$59)*POWER(1+Control!$B$17,18))*Control!$B$26))+((Control!$B$65*12*POWER(1+Control!$B$17,18))-((Control!$B$66+Control!$B$67+Control!$B$68)*12*POWER(1+Control!$B$18,18)+(Control!$B$65*12*POWER(1+Control!$B$17,18))*Control!$B$26)))*(1-Control!$B$23))-IF(AND(Control!$B$5>0,Control!$B$6="Y",19=Control!$B$39-1),Control!$B$40,0)) | W53: =Control!$B$11*(((((((Control!$B$20*$A$8)*((Control!$B$28+Control!$B$29*(Control!$B$38-2))+(Control!$B$32+Control!$B$33*(Control!$B$38-2))+IF(AND(Control!$B$5>0,Control!$B$6="Y",20>=Control!$B$39),Control!$B$36,0))*POWER(1+Control!$B$17,19))+((((Control!$B$20*$A$8)*Control!$B$38*2+IF(AND(Control!$B$5>0,Control!$B$6="Y",20>=Control!$B$39),(Control!$B$20*$A$8)*2,0))*Control!$B$41)*(Control!$B$42+Control!$B$44)*POWER(1+Control!$B$17,19))+(Control!$B$46*POWER(1+Control!$B$17,19)))-(((Control!$B$20*$A$8)*((Control!$B$28+Control!$B$29*(Control!$B$38-2))+(Control!$B$32+Control!$B$33*(Control!$B$38-2))+IF(AND(Control!$B$5>0,Control!$B$6="Y",20>=Control!$B$39),Control!$B$36,0))*POWER(1+Control!$B$17,19))*Control!$B$52+(((Control!$B$20*$A$8)*Control!$B$38*2+IF(AND(Control!$B$5>0,Control!$B$6="Y",20>=Control!$B$39),(Control!$B$20*$A$8)*2,0))*Control!$B$41)*(Control!$B$43+Control!$B$45)*POWER(1+Control!$B$18,19)+Control!$B$47*POWER(1+Control!$B$18,19)+(Control!$B$48+Control!$B$49+Control!$B$50+Control!$B$51)*12*POWER(1+Control!$B$18,19)+((Control!$B$20*$A$8)*((Control!$B$28+Control!$B$29*(Control!$B$38-2))+(Control!$B$32+Control!$B$33*(Control!$B$38-2))+IF(AND(Control!$B$5>0,Control!$B$6="Y",20>=Control!$B$39),Control!$B$36,0))*POWER(1+Control!$B$17,19))*Control!$B$26))+(((Control!$B$54*Control!$B$55+Control!$B$56*Control!$B$57*Control!$B$58*Control!$B$59)*POWER(1+Control!$B$17,19))-((Control!$B$56*Control!$B$57*Control!$B$58*Control!$B$59*POWER(1+Control!$B$17,19))*Control!$B$60+(Control!$B$61+Control!$B$62+Control!$B$63)*12*POWER(1+Control!$B$18,19)+((Control!$B$54*Control!$B$55+Control!$B$56*Control!$B$57*Control!$B$58*Control!$B$59)*POWER(1+Control!$B$17,19))*Control!$B$26))+((Control!$B$65*12*POWER(1+Control!$B$17,19))-((Control!$B$66+Control!$B$67+Control!$B$68)*12*POWER(1+Control!$B$18,19)+(Control!$B$65*12*POWER(1+Control!$B$17,19))*Control!$B$26)))*(1-Control!$B$23))-IF(AND(Control!$B$5>0,Control!$B$6="Y",20=Control!$B$39-1),Control!$B$40,0))+Valuation!$F$10*POWER(1+Control!$B$74,20)*(1-Control!$B$75)
A54: [calc] Occupancy 0.7 cum | D54: =D53 | E54: =D54+E53 | F54: =E54+F53 | G54: =F54+G53 | H54: =G54+H53 | I54: =H54+I53 | J54: =I54+J53 | K54: =J54+K53 | L54: =K54+L53 | ... V54: =U54+V53
